Workbook

Sheet JULIO 
C1: RENDICION CAJA CHICA
C2: PLAZA EGAÑA
G3: MES | H3: JULIO
B4: SALDO ANTERIOR | E4: 100000
B5: DEPÓSITO RENDICION ANTERIOR
B6: MONTO ADICIONAL | E6: 0
B7: MONTO A RENDIR | E7: =SUM(E4:E6) -> 100000
B8: RENDIDO | E8: =+G26 -> 97670 | G8: SALDO AL CIERRE | H8: =E7-E8 -> 2330
A10: N° | B10: Fecha | C10: Tipo Documento (boleta venta-boleta honorarios-factura) | D10: N° documento | E10: RUT Titular del documento | F10: Detalle | G10: Total | H10: Código Imputacion (RSM) 130
A11: 1 | B11: 45475 | C11: boleta venta | D11: 234089455 | E11: - | F11: desayuno recepcion de mercaderia | G11: 4380
A12: 2 | B12: 45478 | C12: boleta venta | D12: 48356796 | E12: - | F12: envio telas a talca (visual) | G12: 11993
A13: 3 | B13: 45482 | C13: boleta venta | D13: 46573944 | E13: - | F13: desayuno recepcion de mercaderia | G13: 4270
A14: 4 | B14: 45482 | C14: boleta venta | D14: 743214891 | E14: - | F14: estancos de luz para bodega | G14: 44970
A15: 5 | B15: 45489 | C15: boleta venta | D15: 712480310 | E15: - | F15: desayuno recepcion de mercaderia | G15: 5734
A16: 6 | B16: 45491 | C16: boleta venta | D16: 697436113 | E16: - | F16: papel absorvente | G16: 5543
A17: 7 | B17: 45498 | C17: - | D17: N°28 | E17: - | F17: limpieza de vitrina | G17: 15000
A18: 8 | B18: 45499 | C18: boleta venta | D18: 46582320 | E18: - | F18: desayuno recepcion de mercaderia | G18: 5780
A19: 9
A20: 10
A21: 11
A22: 12
A23: 13
A24: 14
A25: 15
B26: TOTALES | G26: =SUM(G11:G25) -> 97670

Sheet AGOSTO
C1: RENDICION CAJA CHICA
C2: PLAZA EGAÑA
G3: MES | H3: AGOSTO
B4: SALDO ANTERIOR | E4: =+'JULIO '!H8 -> 2330
B5: DEPÓSITO RENDICION ANTERIOR | E5: 97670
B6: MONTO ADICIONAL | E6: 0
B7: MONTO A RENDIR | E7: =SUM(E4:E6) -> 100000
B8: RENDIDO | E8: =+G26 -> 93600 | G8: SALDO AL CIERRE | H8: =E7-E8 -> 6400
A10: N° | B10: Fecha | C10: Tipo Documento (boleta venta-boleta honorarios-factura) | D10: N° documento | E10: RUT Titular del documento | F10: Detalle | G10: Total | H10: Código Imputacion (RSM) 130
A11: 1 | B11: 45503 | C11: boleta venta | D11: 5404406 | F11: desayuno recepcion mercaderia | G11: 3980
A12: 2 | B12: 45513 | C12: boleta venta | D12: 46588713 | F12: desayuno recepcion mercaderia | G12: 4670
A13: 3 | B13: 45509 | C13: boleta venta | D13: 94378 | F13: copia de llaves | G13: 1800
A14: 4 | B14: 45516 | C14: boleta venta | D14: 720725180 | F14: papel absorvente y agua | G14: 5100
A15: 5 | B15: 45505 | C15: boleta venta | D15: 719350079 | F15: recepcion nuevo integrante | G15: 6190
A16: 6 | B16: 45521 | C16: boleta venta | D16: 709336876 | F16: cumpleaños ruben | G16: 7700
A17: 7 | B17: 45521 | C17: boleta venta | D17: 721690830 | F17: cumpleaños ruben | G17: 6990
A18: 8 | B18: 45510 | C18: boleta venta | D18: 46587444 | F18: desayuno recepcion mercaderia | G18: 5780
A19: 9 | B19: 45533 | C19: boleta honorarios | D19: 14162 | F19: limpieza de vitrina | G19: 15000
A20: 10 | B20: 45523 | C20: factura | D20: 117203 | F20: pantalon gabriel x1 | G20: 32990
A21: 11 | B21: 45534 | C21: boleta venta | D21: 725624626 | F21: desayuno recepcion mercaderia | G21: 3400
A22: 12
A23: 13
A24: 14
A25: 15
B26: TOTALES | G26: =SUM(G11:G25) -> 93600

Sheet SEPTIEMBRE
C1: RENDICION CAJA CHICA
C2: PLAZA EGAÑA
G3: MES | H3: SEPTIEMBRE
B4: SALDO ANTERIOR | E4: =+AGOSTO!H8 -> 6400
B5: DEPÓSITO RENDICION ANTERIOR | E5: 93600
B6: MONTO ADICIONAL | E6: 0
B7: MONTO A RENDIR | E7: =SUM(E4:E6) -> 100000
B8: RENDIDO | E8: =+G26 -> 25639 | G8: SALDO AL CIERRE | H8: =E7-E8 -> 74361
A10: N° | B10: Fecha | C10: Tipo Documento (boleta venta-boleta honorarios-factura) | D10: N° documento | E10: RUT Titular del documento | F10: Detalle | G10: Total | H10: Código Imputacion (RSM) 130
A11: 1 | B11: 45564 | C11: boleta honorarios | D11: 14162 | F11: limpieza de vitrina | G11: 15000
A12: 2 | B12: 45545 | C12: boleta | D12: 75367474 | F12: desayuno recepcion mercaderia | G12: 5262
A13: 3 | B13: 45562 | C13: boleta | D13: 50778211 | F13: envio material POP a concepcion | G13: 5377
A14: 4
A15: 5
A16: 6
A17: 7
A18: 8
A19: 9
A20: 10
A21: 11
A22: 12
A23: 13
A24: 14
A25: 15
B26: TOTALES | G26: =SUM(G11:G25) -> 25639

Sheet OCTUBRE
C1: RENDICION CAJA CHICA
C2: PLAZA EGAÑA
G3: MES | H3: OCTUBRE
B4: SALDO ANTERIOR | E4: =+SEPTIEMBRE!H8 -> 74361
B5: DEPÓSITO RENDICION ANTERIOR | E5: 25639
B6: MONTO ADICIONAL | E6: 0
B7: MONTO A RENDIR | E7: =SUM(E4:E6) -> 100000
B8: RENDIDO | E8: =+G26 -> 47340 | G8: SALDO AL CIERRE | H8: =E7-E8 -> 52660
A10: N° | B10: Fecha | C10: Tipo Documento (boleta venta-boleta honorarios-factura) | D10: N° documento | E10: RUT Titular del documento | F10: Detalle | G10: Total | H10: Código Imputacion (RSM) 130
A11: 1 | B11: 45570 | C11: boleta | D11: 731815259 | F11: art. Cumpleaños sebastian. | G11: 18560
A12: 2 | B12: 45572 | C12: boleta | D12: 722498714 | F12: papel absorvente | G12: 3690
A13: 3 | B13: 45573 | C13: boleta | D13: 720838663 | F13: desayuna recepcion llenado | G13: 4500
A14: 4 | B14: 45595 | C14: boleta de honorarios | D14: 14508 | E14: 77227317-7 | F14: limpieza de vidrios y vitrina | G14: 15000
A15: 5 | B15: 45596 | C15: boleta | D15: 734253491 | F15: caramelos halloween | G15: 5590
A16: 6
A17: 7
A18: 8
A19: 9
A20: 10
A21: 11
A22: 12
A23: 13
A24: 14
A25: 15
B26: TOTALES | G26: =SUM(G11:G25) -> 47340

Sheet NOVIEMBRE
C1: RENDICION CAJA CHICA
C2: PLAZA EGAÑA
G3: MES | H3: NOVIEMBRE
B4: SALDO ANTERIOR | E4: =+OCTUBRE!H8 -> 52660
B5: DEPÓSITO RENDICION ANTERIOR | E5: 47340
B6: MONTO ADICIONAL | E6: 0
B7: MONTO A RENDIR | E7: =SUM(E4:E6) -> 100000
B8: RENDIDO | E8: =+G26 -> 44223 | G8: SALDO AL CIERRE | H8: =E7-E8 -> 55777
A10: N° | B10: Fecha | C10: Tipo Documento (boleta venta-boleta honorarios-factura) | D10: N° documento | E10: RUT Titular del documento | F10: Detalle | G10: Total | H10: Código Imputacion (RSM) 130
A11: 1 | B11: 45612 | C11: boleta | D11: 731588899 | F11: desayuno reunion | G11: 6330
A12: 2 | B12: 45625 | C12: boleta | D12: 735381820 | F12: desayuno reunion planificacion diciembre | G12: 16243
A13: 3 | B13: 45625 | C13: boleta | D13: 112087 | F13: cable para pc | G13: 6650
A14: 4 | B14: 45626 | C14: boleta honorarios | D14: 14671 | F14: limpieza vidrios y vitrina | G14: 15000
A15: 5
A16: 6
A17: 7
A18: 8
A19: 9
A20: 10
A21: 11
A22: 12
A23: 13
A24: 14
A25: 15
B26: TOTALES | G26: =SUM(G11:G25) -> 44223

Sheet DICIEMBRE
C1: RENDICION CAJA CHICA
C2: PLAZA EGAÑA
G3: MES | H3: DICIEMBRE
B4: SALDO ANTERIOR | E4: =+NOVIEMBRE!H8 -> 55777
B5: DEPÓSITO RENDICION ANTERIOR | E5: 44223
B6: MONTO ADICIONAL | E6: 0
B7: MONTO A RENDIR | E7: =SUM(E4:E6) -> 100000
B8: RENDIDO | E8: =+G26 -> 64612 | G8: SALDO AL CIERRE | H8: =E7-E8 -> 35388
A10: N° | B10: Fecha | C10: Tipo Documento (boleta venta-boleta honorarios-factura) | D10: N° documento | E10: RUT Titular del documento | F10: Detalle | G10: Total | H10: Código Imputacion (RSM) 130
A11: 1 | B11: 45629 | C11: factura | D11: 4729 | E11: 77227317-7 | F11: mantension extintores | G11: 30583
A12: 2 | B12: 45647 | C12: boleta | D12: 735388267 | F12: desayuno reunion dia pick del mes | G12: 8980
A13: 3 | B13: 45653 | C13: boleta | D13: 735090077 | F13: desayuno reunion navidad egaña | G13: 10049
A14: 4 | B14: 45656 | C14: boleta de honorarios | D14: 14807 | F14: limpieza vidrios y vitrina | G14: 15000
A15: 5
A16: 6
A17: 7
A18: 8
A19: 9
A20: 10
A21: 11
A22: 12
A23: 13
A24: 14
A25: 15
B26: TOTALES | G26: =SUM(G11:G25) -> 64612

Sheet ENERO 2025
C1: RENDICION CAJA CHICA
C2: PLAZA EGAÑA
G3: MES | H3: ENERO
B4: SALDO ANTERIOR | E4: =DICIEMBRE!H8 -> 35388
B5: DEPÓSITO RENDICION ANTERIOR | E5: 64612
B6: MONTO ADICIONAL | E6: 0
B7: MONTO A RENDIR | E7: 100000
B8: RENDIDO | E8: =+G26 -> 35810 | G8: SALDO AL CIERRE | H8: =E7-E8 -> 64190
A10: N° | B10: Fecha | C10: Tipo Documento (boleta venta-boleta honorarios-factura) | D10: N° documento | E10: RUT Titular del documento | F10: Detalle | G10: Total | H10: Código Imputacion (RSM) 130
A11: 1 | B11: 45659 | C11: boleta | D11: 735228627 | F11: bidon de agua | G11: 2050
A12: 2 | B12: 45681 | C12: boleta | D12: 749133266 | F12: cumpleaños Yeison | G12: 16760
A13: 3 | B13: 45686 | C13: boleta honorarios | D13: 14988 | E13: 14580359-4 | F13: limpieza vidrios | G13: 15000
A14: 4 | B14: 45687 | C14: vale por | D14: 30 | F14: movilizacion apoyo vespucio | G14: 2000
A15: 5
A16: 6
A17: 7
A18: 8
A19: 9
A20: 10
A21: 11
A22: 12
A23: 13
A24: 14
A25: 15
B26: TOTALES | G26: =SUM(G11:G25) -> 35810

Sheet FEBRERO 2025
C1: RENDICION CAJA CHICA
C2: PLAZA EGAÑA
G3: MES | H3: FEBRERO
B4: SALDO ANTERIOR | E4: ='ENERO 2025'!H8 -> 64190
B5: DEPÓSITO RENDICION ANTERIOR | E5: 35810
B6: MONTO ADICIONAL | E6: 0
B7: MONTO A RENDIR | E7: 100000
B8: RENDIDO | E8: =+G26 -> 23020 | G8: SALDO AL CIERRE | H8: =E7-E8 -> 76980
A10: N° | B10: Fecha | C10: Tipo Documento (boleta venta-boleta honorarios-factura) | D10: N° documento | E10: RUT Titular del documento | F10: Detalle | G10: Total | H10: Código Imputacion (RSM) 130
A11: 1 | B11: 45696 | C11: boleta | D11: 749619117 | F11: bidon de agua | G11: 2050
A12: 2 | B12: 45706 | C12: boleta | D12: 15509747 | F12: cintas adhesivas | G12: 5970
A13: 3 | B13: 45716 | C13: boleta honorarios | D13: 15176 | E13: 14580359-4 | F13: limpieza vidrios | G13: 15000
A14: 4
A15: 5
A16: 6
A17: 7
A18: 8
A19: 9
A20: 10
A21: 11
A22: 12
A23: 13
A24: 14
A25: 15
B26: TOTALES | G26: =SUM(G11:G25) -> 23020

Sheet  MARZO 2025
C1: RENDICION CAJA CHICA
C2: PLAZA EGAÑA
G3: MES | H3: MARZO
B4: SALDO ANTERIOR | E4: ='FEBRERO 2025'!H8 -> 76980
B5: DEPÓSITO RENDICION ANTERIOR | E5: 23020
B6: MONTO ADICIONAL | E6: 0
B7: MONTO A RENDIR | E7: 100000
B8: RENDIDO | E8: =+G26 -> 37630 | G8: SALDO AL CIERRE | H8: =E7-E8 -> 62370
A10: N° | B10: Fecha | C10: Tipo Documento (boleta venta-boleta honorarios-factura) | D10: N° documento | E10: RUT Titular del documento | F10: Detalle | G10: Total | H10: Código Imputacion (RSM) 130
A11: 1 | B11: 45724 | C11: boleta | D11: 752848804 | F11: celebracion dia de la mujer | G11: 19630
A12: 2 | B12: 45747 | C12: boletas de honorarios | D12: 15344 | F12: limpieza de vidrios | G12: 18000
A13: 3
A14: 4
A15: 5
A16: 6
A17: 7
A18: 8
A19: 9
A20: 10
A21: 11
A22: 12
A23: 13
A24: 14
A25: 15
B26: TOTALES | G26: =SUM(G11:G25) -> 37630

Sheet ABRIL 2025
C1: RENDICION CAJA CHICA
C2: PLAZA EGAÑA
G3: MES | H3: Abril
B4: SALDO ANTERIOR | E4: =' MARZO 2025'!H8 -> 62370
B5: DEPÓSITO RENDICION ANTERIOR | E5: 37630
B6: MONTO ADICIONAL | E6: 0
B7: MONTO A RENDIR | E7: 100000
B8: RENDIDO | E8: =+G26 -> 22000 | G8: SALDO AL CIERRE | H8: =E7-E8 -> 78000
A10: N° | B10: Fecha | C10: Tipo Documento (boleta venta-boleta honorarios-factura) | D10: N° documento | E10: RUT Titular del documento | F10: Detalle | G10: Total | H10: Código Imputacion (RSM) 130
A11: 1 | B11: 45754 | C11: vale por | D11: 31 | F11: cuerda pita | G11: 4000
A12: 2 | B12: 45777 | C12: boleta de honorarios | D12: 15534 | F12: limpieza de vidrios | G12: 18000
A13: 3
A14: 4
A15: 5
A16: 6
A17: 7
A18: 8
A19: 9
A20: 10
A21: 11
A22: 12
A23: 13
A24: 14
A25: 15
B26: TOTALES | G26: =SUM(G11:G25) -> 22000

Sheet MAYO 2025
C1: RENDICION CAJA CHICA
C2: PLAZA EGAÑA
G3: MES | H3: Mayo
B4: SALDO ANTERIOR | E4: ='ABRIL 2025'!H8 -> 78000
B5: DEPÓSITO RENDICION ANTERIOR | E5: 22000
B6: MONTO ADICIONAL | E6: 0
B7: MONTO A RENDIR | E7: 100000
B8: RENDIDO | E8: =+G20 -> 36030 | G8: SALDO AL CIERRE | H8: =E7-E8 -> 63970
A10: N° | B10: Fecha | C10: Tipo Documento (boleta venta-boleta honorarios-factura) | D10: N° documento | E10: RUT Titular del documento | F10: Detalle | G10: Total | H10: Código Imputacion (RSM) 130
A11: 1 | B11: 45779 | C11: boleta | D11: 54987146 | F11: cintas de regalo | G11: 5380
A12: 2 | B12: 45784 | C12: boleta | D12: 778294365 | F12: cinta embalaje y bidon | G12: 5180
A13: 3 | B13: 45787 | C13: boleta | D13: 775136411 | F13: bidon de agua | G13: 1690
A14: 4 | B14: 45790 | C14: boleta | D14: 15961950 | F14: cintas de embalaje | G14: 3980
A15: 5 | B15: 45794 | C15: boleta | D15: 127134 | F15: copia de llave | G15: 1800
A16: 6 | B16: 45807 | C16: boleta de honorarios | D16: 15709 | F16: limpieza vidrios y vitrina | G16: 18000
A17: 7
A18: 8
A19: 9
B20: TOTALES | G20: =SUM(G11:G19) -> 36030

Sheet JUNIO 2025
C1: RENDICION CAJA CHICA
C2: PLAZA EGAÑA
G3: MES | H3: JUNIO
B4: SALDO ANTERIOR | E4: ='MAYO 2025'!H8 -> 63970
B5: DEPÓSITO RENDICION ANTERIOR | E5: 36030
B6: MONTO ADICIONAL | E6: 0
B7: MONTO A RENDIR | E7: 100000
B8: RENDIDO | E8: =+G20 -> 83480 | G8: SALDO AL CIERRE | H8: =E7-E8 -> 16520
A10: N° | B10: Fecha | C10: Tipo Documento (boleta venta-boleta honorarios-factura) | D10: N° documento | E10: RUT Titular del documento | F10: Detalle | G10: Total | H10: Código Imputacion (RSM) 130
A11: 1 | B11: 45813 | C11: boleta | D11: d25060502102 | E11: 77557273-6 | F11: caja organizadora | G11: 6800
A12: 2 | B12: 45810 | C12: boleta | D12: 55269806 | E12: 80478200-1 | F12: cinta de embalaje | G12: 3780
A13: 3 | B13: 45814 | C13: boleta | D13: 789598290 | E13: 96792430-k | F13: equipos estanco para led bodega y sellador | G13: 37970
A14: 4 | B14: 45822 | C14: boleta | D14: 781397730 | E14: 78527210-6 | F14: desayuno reunion equipo | G14: 5840
A15: 5 | B15: 45791 | C15: boleta | D15: 774497570 | E15: 78527210-6 | F15: dibon de agua | G15: 1690
A16: 6 | B16: 45833 | C16: boleta | D16: 54786722 | E16: 96756430-3 | F16: envío material SALE plaza trebol | G16: 9400
A17: 7 | B17: 45837 | C17: boleta de honorarios | D17: 15890 | E17: 14580359-4 | F17: limpieza de vitrina | G17: 18000
A18: 8
A19: 9
B20: TOTALES | G20: =SUM(G11:G19) -> 83480

Sheet JULIO 2025
C1: RENDICION CAJA CHICA
C2: PLAZA EGAÑA
G3: MES | H3: JULIO
B4: SALDO ANTERIOR | E4: ='JUNIO 2025'!H8 -> 16520
B5: DEPÓSITO RENDICION ANTERIOR | E5: 36030
B6: MONTO ADICIONAL | E6: 0
B7: MONTO A RENDIR | E7: 100000
B8: RENDIDO | E8: =+G20 -> 0 | G8: SALDO AL CIERRE | H8: =E7-E8 -> 100000
A10: N° | B10: Fecha | C10: Tipo Documento (boleta venta-boleta honorarios-factura) | D10: N° documento | E10: RUT Titular del documento | F10: Detalle | G10: Total | H10: Código Imputacion (RSM) 130
A11: 1
A12: 2
A13: 3
A14: 4
A15: 5
A16: 6
A17: 7
A18: 8
A19: 9
B20: TOTALES | G20: =SUM(G11:G19) -> 0

Sheet AGOSTO 2025
C1: RENDICION CAJA CHICA
C2: PLAZA EGAÑA
G3: MES | H3: AGOSTO
B4: SALDO ANTERIOR | E4: ='JULIO 2025'!H8 -> 100000
B5: DEPÓSITO RENDICION ANTERIOR | E5: 83480
B6: MONTO ADICIONAL | E6: 0
B7: MONTO A RENDIR | E7: 100000
B8: RENDIDO | E8: =+G20 -> 53630 | G8: SALDO AL CIERRE | H8: =E7-E8 -> 46370
A10: N° | B10: Fecha | C10: Tipo Documento (boleta venta-boleta honorarios-factura) | D10: N° documento | E10: RUT Titular del documento | F10: Detalle | G10: Total | H10: Código Imputacion (RSM) 130
A11: 1 | B11: 45862 | C11: boleta | D11: 25071803028 | F11: dispensador agua | G11: 5990
A12: 2 | B12: 45867 | C12: boleta | D12: 786397742 | F12: limpiavidrios | G12: 3150
A13: 3 | B13: 45868 | C13: boleta | D13: 21786 | F13: bidones de agua | G13: 10500
A14: 4 | B14: 45868 | C14: boleta de honorarios | D14: 16083 | F14: limpieza de vidrios | G14: 18000
A15: 5 | B15: 45879 | C15: boleta | D15: 797086966 | F15: estanco para luces led bodega | G15: 15990
A16: 6
A17: 7
A18: 8
A19: 9
B20: TOTALES | G20: =SUM(G11:G19) -> 53630

Sheet SEPTIEMBRE 2025
C1: RENDICION CAJA CHICA
C2: PLAZA EGAÑA
G3: MES | H3: SEPTIEMBRE
B4: SALDO ANTERIOR | E4: ='AGOSTO 2025'!H8 -> 46370
B5: DEPÓSITO RENDICION ANTERIOR | E5: 53630
B6: MONTO ADICIONAL | E6: 0
B7: MONTO A RENDIR | E7: 100000
B8: RENDIDO | E8: =+G20 -> 67710 | G8: SALDO AL CIERRE | H8: =E7-E8 -> 32290
A10: N° | B10: Fecha | C10: Tipo Documento (boleta venta-boleta honorarios-factura) | D10: N° documento | E10: RUT Titular del documento | F10: Detalle | G10: Total | H10: Código Imputacion (RSM) 130
A11: 1 | B11: 45898 | C11: BOLETA DE HONORARIOS | D11: 16247 | E11: 14580359-4 | F11: limpieza de vitrina y vidrios | G11: 18000
A12: 2 | B12: 45904 | C12: BOLETA | D12: 789722563 | E12: 78627210-6 | F12: papel higienico y absorvente | G12: 4690
A13: 3 | B13: 45906 | C13: boleta | D13: 22212 | E13: 77093957-7 | F13: recarga agua | G13: 10500
A14: 4 | B14: 45916 | C14: boleta | D14: 236719 | F14: empanadas | G14: 16200
A15: 5 | B15: 45916 | C15: vale por | D15: 34 | F15: bebestibles y vasos plasticos | G15: 8320
A16: 6 | B16: 45920 | C16: boleta | D16: 786409160 | E16: 78627210-6 | F16: atr. De limpieza y papel absorvente | G16: 5010
A17: 7 | B17: 45922 | C17: boleta | D17: 16498489 | E17: 92642000-3 | F17: papel carta impresora | G17: 4990
A18: 8
A19: 9
B20: TOTALES | G20: =SUM(G11:G19) -> 67710

Sheet OCTUBRE 2025
C1: RENDICION CAJA CHICA
C2: PLAZA EGAÑA
G3: MES | H3: OCTUBRE
B4: SALDO ANTERIOR | E4: ='SEPTIEMBRE 2025'!H8 -> 32290
B5: DEPÓSITO RENDICION ANTERIOR | E5: 67710
B6: MONTO ADICIONAL | E6: 0
B7: MONTO A RENDIR | E7: 100000
B8: RENDIDO | E8: =+G20 -> 28500 | G8: SALDO AL CIERRE | H8: =E7-E8 -> 71500
A10: N° | B10: Fecha | C10: Tipo Documento (boleta venta-boleta honorarios-factura) | D10: N° documento | E10: RUT Titular del documento | F10: Detalle | G10: Total | H10: Código Imputacion (RSM) 130
A11: 1 | B11: 45951 | C11: BOLETA DE HONORARIOS | D11: 16452 | E11: 14580359-4 | F11: LIMPIEZA DE VIDRIOS Y VITRINA | G11: 18000
A12: 2 | B12: 45951 | C12: NEHUENKO SPA | D12: 22690 | E12: 77093957-7 | F12: RECARGA AGUA | G12: 10500
A13: 3
A14: 4
A15: 5
A16: 6
A17: 7
A18: 8
A19: 9
B20: TOTALES | G20: =SUM(G11:G19) -> 28500

Sheet NOVIEMBRE 2025
C1: RENDICION CAJA CHICA
C2: PLAZA EGAÑA
G3: MES | H3: NOVIEMBRE
B4: SALDO ANTERIOR | E4: ='OCTUBRE 2025'!H8 -> 71500
B5: DEPÓSITO RENDICION ANTERIOR | E5: 28500
B6: MONTO ADICIONAL | E6: 0
B7: MONTO A RENDIR | E7: 100000
B8: RENDIDO | E8: =+G20 -> 49970 | G8: SALDO AL CIERRE | H8: =E7-E8 -> 50030
A10: N° | B10: Fecha | C10: Tipo Documento (boleta venta-boleta honorarios-factura) | D10: N° documento | E10: RUT Titular del documento | F10: Detalle | G10: Total | H10: Código Imputacion (RSM) 130
A11: 1 | B11: 45961 | C11: boleta de honorarios | D11: 16631 | E11: 14580359-4 | F11: limpieza vidrios y vitrina | G11: 18000
A12: 2 | B12: 45965 | C12: boleta | D12: 98800103 | E12: 77398220-1 | F12: tv box | G12: 27990
A13: 3 | B13: 45976 | C13: boleta | D13: d25111506160 | E13: 77557273-6 | F13: bandeja de aluminio | G13: 3980
A14: 4
A15: 5
A16: 6
A17: 7
A18: 8
A19: 9
B20: TOTALES | G20: =SUM(G11:G19) -> 49970

Sheet DICIEMBRE 2025
C1: RENDICION CAJA CHICA
C2: PLAZA EGAÑA
G3: MES | H3: DICIEMBRE
B4: SALDO ANTERIOR | E4: ='NOVIEMBRE 2025'!H8 -> 50030
B5: DEPÓSITO RENDICION ANTERIOR | E5: 49970
B6: MONTO ADICIONAL | E6: 0
B7: MONTO A RENDIR | E7: 100000
B8: RENDIDO | E8: =+G20 -> 46714 | G8: SALDO AL CIERRE | H8: =E7-E8 -> 53286
A10: N° | B10: Fecha | C10: Tipo Documento (boleta venta-boleta honorarios-factura) | D10: N° documento | E10: RUT Titular del documento | F10: Detalle | G10: Total | H10: Código Imputacion (RSM) 130
A11: 1 | B11: 45990 | C11: boleta | D11: 23122 | E11: 77093957-7 | F11: recarga agua | G11: 10500
A12: 2 | B12: 45991 | C12: boleta de honorarios | D12: 16786 | E12: 14580359-4 | F12: limpieza vidrios y vitrina | G12: 18654
A13: 3 | B13: 45992 | C13: boleta | D13: 16849667 | E13: 92642000-3 | F13: cinta de embalaje | G13: 4490
A14: 4 | B14: 45998 | C14: boleta | D14: 766432391 | E14: 78627210-6 | F14: papel absorvente | G14: 4690
A15: 5 | B15: 46011 | C15: boleta | D15: 25122006202 | E15: 77557273-6 | F15: sobres para giftcard | G15: 3000
A16: 6 | B16: 46013 | C16: boleta | D16: 57212203 | E16: 80478200-1 | F16: cintas de regalo | G16: 5380
A17: 7
A18: 8
A19: 9
B20: TOTALES | G20: =SUM(G11:G19) -> 46714

Sheet ENERO 2026
C1: RENDICION CAJA CHICA
C2: PLAZA EGAÑA
G3: MES | H3: ENERO
B4: SALDO ANTERIOR | E4: =+'DICIEMBRE 2025'!H8 -> 53286
B5: DEPÓSITO RENDICION ANTERIOR | E5: 46624
B6: MONTO ADICIONAL | E6: 0
B7: MONTO A RENDIR | E7: =SUM(E4:E6) -> 99910
B8: RENDIDO | E8: =+G18 -> 58308 | G8: SALDO AL CIERRE | H8: =E7-E8 -> 41602
A10: N° | B10: Fecha | C10: Tipo Documento (boleta venta-boleta honorarios-factura) | D10: N° documento | E10: RUT Titular del documento | F10: Detalle | G10: Total | H10: Código Imputacion (RSM) 130
A11: 1 | B11: 46020 | C11: boleta | D11: 57529277 | E11: 96756430-3 | F11: envio calzado a trebol | G11: 24818
A12: 2 | B12: 46028 | C12: boleta | D12: 23495 | E12: 77093957-7 | F12: recarga agua | G12: 10500
A13: 3 | B13: 46031 | C13: boleta | D13: 17088541 | E13: 92642000-3 | F13: resma impresora | G13: 4990
A14: 4 | B14: 46033 | C14: boleta honorarios | D14: 17159 | E14: 14580359-4 | F14: limpieza vidrios y vitrina | G14: 18000
A15: 7
A16: 8
A17: 9
B18: TOTALES | G18: =SUM(G11:G17) -> 58308

Sheet FEBRERO 2026
C1: RENDICION CAJA CHICA
C2: PLAZA EGAÑA
G3: MES | H3: FEBRERO
B4: SALDO ANTERIOR | E4: =+'ENERO 2026'!H8 -> 41602
B5: DEPÓSITO RENDICION ANTERIOR | E5: 58398
B6: MONTO ADICIONAL | E6: 0
B7: MONTO A RENDIR | E7: =SUM(E4:E6) -> 100000
B8: RENDIDO | E8: =+G18 -> 74480 | G8: SALDO AL CIERRE | H8: =E7-E8 -> 25520
A10: N° | B10: Fecha | C10: Tipo Documento (boleta venta-boleta honorarios-factura) | D10: N° documento | E10: RUT Titular del documento | F10: Detalle | G10: Total | H10: Código Imputacion (RSM) 130
A11: 1 | B11: 46052 | C11: boleta de honorarios | D11: 17293 | E11: 14580359-4 | F11: limpieza de vidrios | G11: 18000
A12: 2 | B12: 46058 | C12: boleta | D12: 17242834 | E12: 92642000-3 | F12: cinta de embalaje | G12: 1990
A13: 3 | B13: 46058 | C13: boleta | D13: 814797755 | E13: 78627210-6 | F13: toalla de papel | G13: 2000
A14: 4 | B14: 46061 | C14: boleta | D14: 17264522 | E14: 92642000-3 | F14: cinta de embalaje | G14: 1990
A15: 7 | B15: 46063 | C15: boleta | D15: 23892 | E15: 77093957-7 | F15: recarga agua | G15: 10500
A16: 8 | B16: 46030 | C16: boleta de honorarios | D16: 1420 | E16: 5666822-5 | F16: limpieza fachada, interior y alturas. Diciembre y enero | G16: 40000
A17: 9
B18: TOTALES | G18: =SUM(G11:G17) -> 74480 | H18: .

Sheet MARZO 2026
C1: RENDICION CAJA CHICA
C2: PLAZA EGAÑA
G3: MES | H3: MARZO
B4: SALDO ANTERIOR | E4: =+'FEBRERO 2026'!H8 -> 25520
B5: DEPÓSITO RENDICION ANTERIOR | E5: 74480
B6: MONTO ADICIONAL | E6: 0
B7: MONTO A RENDIR | E7: =SUM(E4:E6) -> 100000
B8: RENDIDO | E8: =+G18 -> 97350 | G8: SALDO AL CIERRE | H8: =E7-E8 -> 2650
A10: N° | B10: Fecha | C10: Tipo Documento (boleta venta-boleta honorarios-factura) | D10: N° documento | E10: RUT Titular del documento | F10: Detalle | G10: Total | H10: Código Imputacion (RSM) 130
A11: 1 | B11: 46081 | C11: BOLETA DE HONORARIOS | D11: 17464 | E11: 14580359-4 | F11: LIMPIEZA DE VITRINA | G11: 18000
A12: 2 | B12: 46084 | C12: BOLETA | D12: 909470 | E12: 77227317-7 | F12: PAGO PATENTE COMERCIAL | G12: 57890
A13: 3 | B13: 46091 | C13: BOLETA | D13: 17412398 | E13: 92642000-3 | F13: RESMA | G13: 4990
A14: 4 | B14: 46100 | C14: BOLETA | D14: 24267 | E14: 77093957-7 | F14: RECARGA AGUA | G14: 10500
A15: 7 | B15: 46104 | C15: BOLETA | D15: 17566085 | E15: 92642000-3 | F15: CINTA EMBALAJE | G15: 3980
A16: 8 | B16: 46106 | C16: BOLETA | D16: 17566434 | E16: 92642000-3 | F16: CINTA ADHESIVA | G16: 1990
A17: 9
B18: TOTALES | G18: =SUM(G11:G17) -> 97350 | H18: .

Sheet ABRIL 2026
C1: RENDICION CAJA CHICA
C2: PLAZA EGAÑA
G3: MES | H3: ABRIL
B4: SALDO ANTERIOR | E4: =+'MARZO 2026'!H8 -> 2650
B5: DEPÓSITO RENDICION ANTERIOR | E5: 97350
B6: MONTO ADICIONAL | E6: 0
B7: MONTO A RENDIR | E7: =SUM(E4:E6) -> 100000
B8: RENDIDO | E8: =+G21 -> 62490 | G8: SALDO AL CIERRE | H8: =E7-E8 -> 37510
A10: N° | B10: Fecha | C10: Tipo Documento (boleta venta-boleta honorarios-factura) | D10: N° documento | E10: RUT Titular del documento | F10: Detalle | G10: Total | H10: Código Imputacion (RSM) 130
A11: 1 | B11: 46112 | C11: BOLETA HONORARIOS | D11: 17662 | E11: 14580359-4 | F11: LIMPIEZA VIDRIOS Y VITRINA | G11: 18000
A12: 2 | B12: 46118 | C12: BOLETA | D12: 17617963 | E12: 92642000-3 | F12: RESMA Y CINTA EMBALAJE | G12: 6980
A13: 3 | B13: 46120 | C13: BOLETA | D13: 817929903 | E13: 78627210-6 | F13: PAPEL ABSORVENTE | G13: 3290
A14: 4 | B14: 46121 | C14: BOLETA | D14: 824556353 | E14: 96792430-K | F14: PITILLA RAFIA | G14: 2780
A15: 5 | B15: 46126 | C15: BOLETA | D15: 24518 | E15: 77093957-7 | F15: RECARGA AGUA | G15: 10500
A16: 6 | B16: 46132 | C16: BOLETA | D16: 59068106 | E16: 96756430-3 | F16: TRASLADO MATERIAL A TALCA Y TREBOL | G16: 11470
A17: 7 | B17: 46133 | C17: BOLETA | D17: 829914370 | E17: 78627210-6 | F17: CINTA EMBALAJE | G17: 3490
A18: 8 | B18: 46135 | C18: BOLETA | D18: 15872002 | E18: 83030600-5 | F18: PILA CONTROL REMOTO CORTINA | G18: 5980
A19: 9
A20: 10
B21: TOTALES | G21: =SUM(G11:G20) -> 62490 | H21: .
