Workbook
Name Balance2005: #REF!
Name Balance2005: #REF!
Name Balance2005: #REF!
Name Balance2005: #REF!
Name cod: #REF!
Name cod: #REF!
Name cod: #REF!
Name cod: #REF!
Name cod: #REF!
Name cod: #REF!
Name cod: #REF!
Name cod: #REF!
Name cod: #REF!
Name cod: #REF!
Name cod: #REF!
Name COSTOS: #REF!
Name COSTOS: #REF!
Name COSTOS: #REF!
Name COSTOS: #REF!
Name datos: #REF!
Name PJ: #REF!
Name PJ: #REF!
Name PJ: #REF!
Name PJ: #REF!
Name sumas: #REF!
Name sumas: #REF!
Name sumas: #REF!
Name sumas: #REF!
Name sumas: #REF!
Name sumas: #REF!
Name sumas: #REF!
Name sumas: #REF!
Name sumas: #REF!
Name sumas: #REF!
Name sumas: #REF!
Name uf: #REF!
Name uf: #REF!
Name uf: #REF!
Name uf: #REF!
Name uf: #REF!
Name uf: #REF!
Name uf: #REF!
Name uf: #REF!
Name uf: #REF!
Name uf: #REF!
Name uf: #REF!

Sheet Carátula
A7: Flexi Chile SpA
A8: Estados Financieros
A9: Al 31 de enero de 2026
E13: Contenidos:
E14: - Balance Clasificado
E15: - Estado de Resultados
E16: - Cuadro Patrimonial
E17: - Análisis y detalle de cuentas Activos y Pasivos
E18: - Agrupación principales cuentas de Resultados
E19: - Balance General

Sheet Balance Clasificado
B1: =+Carátula!A7 -> Flexi Chile SpA
B2: Balance Clasificado
B3: =+Carátula!A9 -> Al 31 de enero de 2026
B6: Tipo Cambio de Cierre $ 895,60 | C6: 865.1 | D6: 46053 | F6: =+D6 -> 46053
B7: ACTIVOS | F7: US$
B9: Activos circulante
B10: Caja y Bancos | D10: =SUMIF('Balance 8 Columnas'!A:O,'Balance Clasificado'!B10,'Balance 8 Columnas'!N:N) -> 892013701 | F10: =SUMIF('Balance 8 Columnas'!A:O,'Balance Clasificado'!B10,'Balance 8 Columnas'!#REF!) -> #REF!
B11: Derechos de arrendamiento | D11: =SUMIF('Balance 8 Columnas'!A:O,'Balance Clasificado'!B11,'Balance 8 Columnas'!N:N) -> 88703455 | F11: =SUMIF('Balance 8 Columnas'!A:O,'Balance Clasificado'!B11,'Balance 8 Columnas'!#REF!) -> #REF!
B12: Clientes | D12: =SUMIF('Balance 8 Columnas'!A:O,'Balance Clasificado'!B12,'Balance 8 Columnas'!N:N) -> 0 | F12: =SUMIF('Balance 8 Columnas'!A:O,'Balance Clasificado'!B12,'Balance 8 Columnas'!#REF!) -> #REF!
B13: Pagos anticipados | D13: =SUMIF('Balance 8 Columnas'!A:O,'Balance Clasificado'!B13,'Balance 8 Columnas'!N:N) -> 32614989 | F13: =SUMIF('Balance 8 Columnas'!A:O,'Balance Clasificado'!B13,'Balance 8 Columnas'!#REF!) -> #REF!
B14: Deudores Diversos | D14: =SUMIF('Balance 8 Columnas'!A:O,'Balance Clasificado'!B14,'Balance 8 Columnas'!N:N) -> 343622261 | F14: =SUMIF('Balance 8 Columnas'!A:O,'Balance Clasificado'!B14,'Balance 8 Columnas'!#REF!) -> #REF!
B15: Inventarios | D15: =SUMIF('Balance 8 Columnas'!A:O,'Balance Clasificado'!B15,'Balance 8 Columnas'!N:N) -> 1824159549 | F15: =SUMIF('Balance 8 Columnas'!A:O,'Balance Clasificado'!B15,'Balance 8 Columnas'!#REF!) -> #REF!
B16: Impuestos a favor | D16: =SUMIF('Balance 8 Columnas'!A:O,'Balance Clasificado'!B16,'Balance 8 Columnas'!N:N) -> 357340940 | F16: =SUMIF('Balance 8 Columnas'!A:O,'Balance Clasificado'!B16,'Balance 8 Columnas'!#REF!) -> #REF!
B17: Activos circulantes totales | D17: =SUM(D10:D16) -> 3538454895 | F17: =SUM(F10:F16) -> #REF!
B19: Activo Fijo
B20: Equipo de tiendas | D20: =SUMIF('Balance 8 Columnas'!A:O,'Balance Clasificado'!B20,'Balance 8 Columnas'!N:N) -> 684577620 | F20: =SUMIF('Balance 8 Columnas'!A:O,'Balance Clasificado'!B20,'Balance 8 Columnas'!#REF!) -> #REF!
B21: Equipo de cómputo | D21: =SUMIF('Balance 8 Columnas'!A:O,'Balance Clasificado'!B21,'Balance 8 Columnas'!N:N) -> 109578639 | F21: =SUMIF('Balance 8 Columnas'!A:O,'Balance Clasificado'!B21,'Balance 8 Columnas'!#REF!) -> #REF!
B22: Depreciación acumulada | D22: =SUMIF('Balance 8 Columnas'!A:O,'Balance Clasificado'!B22,'Balance 8 Columnas'!N:N) -> -247517086 | F22: =SUMIF('Balance 8 Columnas'!A:O,'Balance Clasificado'!B22,'Balance 8 Columnas'!#REF!) -> #REF!
B23: Total de activo fijo | D23: =SUM(D20:D22) -> 546639173 | F23: =SUM(F20:F22) -> #REF!
B25: TOTAL ACTIVOS | D25: =D17+D23 -> 4085094068 | F25: =F17+F23 -> #REF!
B27: PATRIMONIO Y PASIVOS
B28: Pasivos circulante
B29: Proveedores | D29: =-SUMIF('Balance 8 Columnas'!A:O,'Balance Clasificado'!B29,'Balance 8 Columnas'!N:N) -> 18137459 | F29: =-SUMIF('Balance 8 Columnas'!A:O,'Balance Clasificado'!B29,'Balance 8 Columnas'!#REF!) -> #REF!
B30: Acreedores diversos | D30: =-SUMIF('Balance 8 Columnas'!A:O,'Balance Clasificado'!B30,'Balance 8 Columnas'!N:N) -> 4298052 | F30: =-SUMIF('Balance 8 Columnas'!A:O,'Balance Clasificado'!B30,'Balance 8 Columnas'!#REF!) -> #REF!
B31: Impuestos nómina | D31: =-SUMIF('Balance 8 Columnas'!A:O,'Balance Clasificado'!B31,'Balance 8 Columnas'!N:N) -> 9957035 | F31: =-SUMIF('Balance 8 Columnas'!A:O,'Balance Clasificado'!B31,'Balance 8 Columnas'!#REF!) -> #REF!
B32: Cuentas por pagar a empresas realcionadas | D32: =-SUMIF('Balance 8 Columnas'!A:O,'Balance Clasificado'!B32,'Balance 8 Columnas'!N:N) -> 1381573301 | F32: =-SUMIF('Balance 8 Columnas'!A:O,'Balance Clasificado'!B32,'Balance 8 Columnas'!#REF!) -> #REF!
B33: Otros pasivos | D33: =-SUMIF('Balance 8 Columnas'!A:O,'Balance Clasificado'!B33,'Balance 8 Columnas'!N:N) -> 93838855 | F33: =-SUMIF('Balance 8 Columnas'!A:O,'Balance Clasificado'!B33,'Balance 8 Columnas'!#REF!) -> #REF!
B34: IVA por pagar del mes | D34: =-SUMIF('Balance 8 Columnas'!A:O,'Balance Clasificado'!B34,'Balance 8 Columnas'!N:N) -> 958952 | F34: =-SUMIF('Balance 8 Columnas'!A:O,'Balance Clasificado'!B34,'Balance 8 Columnas'!#REF!) -> #REF!
B36: Pasivos circulantes totales | D36: =SUM(D29:D35) -> 1508763654 | F36: =SUM(F29:F35) -> #REF!
B39: Patrimonio
B40: Capital social | D40: =-SUMIF('Balance 8 Columnas'!A:O,'Balance Clasificado'!B40,'Balance 8 Columnas'!N:N) -> 5770668867 | F40: =-SUMIF('Balance 8 Columnas'!A:O,'Balance Clasificado'!B40,'Balance 8 Columnas'!#REF!) -> #REF!
B41: Resultados acumulados | D41: =-SUMIF('Balance 8 Columnas'!A:O,'Balance Clasificado'!B41,'Balance 8 Columnas'!N:N) -> -3142106839 | F41: =-SUMIF('Balance 8 Columnas'!A:O,'Balance Clasificado'!B41,'Balance 8 Columnas'!#REF!)+'Estado de Resultados'!E29 -> #REF!
B42: perdida del periodo | D42: =+'Estado de Resultados'!C29 -> -52231614
B44: Patrimonio total | D44: =SUM(D40:D43) -> 2576330414 | F44: =SUM(F40:F43) -> #REF!
B46: TOTAL DE PATRIMONIO Y PASIVOS | D46: =+D44+D36 -> 4085094068 | F46: =+F44+F36 -> #REF!
D48: =+D46-D25 -> 0 | F48: =+F46-F25 -> #REF!

Sheet Clasificado
B1: FLEXI CHILE SPA
B2: SVS Estado de Situación Financiera Clasificado Final
E3: 44196
B4: Estado de Situación Financiera
B5: Activos | E5: $
B6: Activos corrientes
B7: Efectivo y Equivalentes al Efectivo | E7: =SUMIF('Balance 8 Columnas'!$A$10:$A$113,B7,'Balance 8 Columnas'!$N$10:$N$113) -> 0 | G7: Ver
B8: Activos financieros corrientes | E8: =SUMIF('Balance 8 Columnas'!$A$10:$A$113,B8,'Balance 8 Columnas'!$N$10:$N$113) -> 0 | G8: Ver
B9: Otros Activos No Financieros, Corriente | E9: =SUMIF('Balance 8 Columnas'!$A$10:$A$113,B9,'Balance 8 Columnas'!$N$10:$N$113) -> 0 | G9: Ver
B10: Deudores comerciales y otras cuentas por cobrar corrientes | E10: =SUMIF('Balance 8 Columnas'!$A$10:$A$113,B10,'Balance 8 Columnas'!$N$10:$N$113) -> 0 | G10: Ver
B11: Cuentas por Cobrar a Entidades Relacionadas, Corrientes | E11: =SUMIF('Balance 8 Columnas'!$A$10:$A$113,B11,'Balance 8 Columnas'!$N$10:$N$113) -> 0
B12: Inventarios corrientes | E12: =SUMIF('Balance 8 Columnas'!$A$10:$A$113,B12,'Balance 8 Columnas'!$N$10:$N$113) -> 0
B13: Activos biológicos corrientes | E13: =SUMIF('Balance 8 Columnas'!$A$10:$A$113,B13,'Balance 8 Columnas'!$N$10:$N$113) -> 0
B14: Activos por impuestos corrientes | E14: =SUMIF('Balance 8 Columnas'!$A$10:$A$113,B14,'Balance 8 Columnas'!$N$10:$N$113) -> 0 | G14: Ver
B15: Total de activos corrientes distintos de los activos o grupos de activos para su disposición clasificados como mantenidos para la venta o como mantenidos para distribuir a los propietarios | E15: =SUM(E7:E14) -> 0
B16: Activos no corrientes o grupos de activos para su disposición clasificados como mantenidos para la venta | E16: =SUMIF('Balance 8 Columnas'!$A$10:$A$113,B16,'Balance 8 Columnas'!$N$10:$N$113) -> 0
B17: Activos no corrientes o grupos de activos para su disposición clasificados como mantenidos para distribuir a los propietarios | E17: =SUMIF('Balance 8 Columnas'!$A$10:$A$113,B17,'Balance 8 Columnas'!$N$10:$N$113) -> 0
B18: Activos no corrientes o grupos de activos para su disposición clasificados como mantenidos para la venta o como mantenidos para distribuir a los propietarios | E18: 0
B19: Activos corrientes totales | E19: =SUM(E15:E17) -> 0
B20: Activos no corrientes
B21: Otros activos financieros no corrientes | E21: =SUMIF('Balance 8 Columnas'!$A$10:$A$113,B21,'Balance 8 Columnas'!$N$10:$N$113) -> 0
B22: Otros activos no financieros no corrientes | E22: =SUMIF('Balance 8 Columnas'!$A$10:$A$113,B22,'Balance 8 Columnas'!$N$10:$N$113) -> 0 | G22: Ver
B23: Derechos por cobrar no corrientes | E23: =SUMIF('Balance 8 Columnas'!$A$10:$A$113,B23,'Balance 8 Columnas'!$N$10:$N$113) -> 0
B24: Cuentas por Cobrar a Entidades Relacionadas, No Corriente | E24: =SUMIF('Balance 8 Columnas'!$A$10:$A$113,B24,'Balance 8 Columnas'!$N$10:$N$113) -> 0
B25: Inversiones contabilizadas utilizando el método de la participación | E25: =SUMIF('Balance 8 Columnas'!$A$10:$A$113,B25,'Balance 8 Columnas'!$N$10:$N$113) -> 0
B26: Activos intangibles distintos de la plusvalía | E26: =SUMIF('Balance 8 Columnas'!$A$10:$A$113,B26,'Balance 8 Columnas'!$N$10:$N$113) -> 0
B27: Plusvalía | E27: =SUMIF('Balance 8 Columnas'!$A$10:$A$113,B27,'Balance 8 Columnas'!$N$10:$N$113) -> 0
B28: Inventario no corrientes | E28: =SUMIF('Balance 8 Columnas'!$A$10:$A$113,B28,'Balance 8 Columnas'!$N$10:$N$113) -> 0
B29: Propiedades, Plantas y Equipos | E29: =SUMIF('Balance 8 Columnas'!$A$10:$A$113,B29,'Balance 8 Columnas'!$N$10:$N$113) -> 0 | G29: Ver
B30: Activos biológicos, no corrientes | E30: =SUMIF('Balance 8 Columnas'!$A$10:$A$113,B30,'Balance 8 Columnas'!$N$10:$N$113) -> 0
B31: Propiedad de inversión | E31: =SUMIF('Balance 8 Columnas'!$A$10:$A$113,B31,'Balance 8 Columnas'!$N$10:$N$113) -> 0
B32: Activos por impuestos diferidos | E32: =SUMIF('Balance 8 Columnas'!$A$10:$A$113,B32,'Balance 8 Columnas'!$N$10:$N$113) -> 0
B33: Total de activos no corrientes | E33: =SUM(E21:E32) -> 0
B34: Total de activos | E34: =+E19+E33 -> 0
B36: SVS Estado de Situación Financiera Clasificado
E37: =E3 -> 44196
B38: Estado de Situación Financiera
B39: Patrimonio y pasivos
B40: Pasivos | E40: $
B41: Pasivos corrientes
B42: Pasivos financieros, corrientes | E42: =SUMIF('Balance 8 Columnas'!$A$10:$A$113,B42,'Balance 8 Columnas'!$N$10:$N$113) -> 0
B43: Cuentas por pagar comerciales y otras cuentas por pagar | E43: =SUMIF('Balance 8 Columnas'!$A$10:$A$113,B43,'Balance 8 Columnas'!$N$10:$N$113) -> 0 | G43: Ver
B44: Cuentas por Pagar a Entidades Relacionadas, Corrientes | E44: =SUMIF('Balance 8 Columnas'!$A$10:$A$113,B44,'Balance 8 Columnas'!$N$10:$N$113) -> 0
B45: Otras provisiones a corto plazo | E45: =SUMIF('Balance 8 Columnas'!$A$10:$A$113,B45,'Balance 8 Columnas'!$N$10:$N$113) -> 0
B46: Pasivos por Impuestos corrientes | E46: =SUMIF('Balance 8 Columnas'!$A$10:$A$113,B46,'Balance 8 Columnas'!$N$10:$N$113) -> 0 | G46: Ver
B47: Provisiones corrientes por beneficios a los empleados | E47: =SUMIF('Balance 8 Columnas'!$A$10:$A$113,B47,'Balance 8 Columnas'!$N$10:$N$113) -> 0 | G47: Ver
B48: Otros pasivos no financieros corrientes | E48: =SUMIF('Balance 8 Columnas'!$A$10:$A$113,B48,'Balance 8 Columnas'!$N$10:$N$113) -> 0 | G48: Ver
B49: Total de pasivos corrientes distintos de los pasivos incluidos en grupos de activos para su disposición clasificados como mantenidos para la venta | E49: =SUM(E42:E48) -> 0
B50: Pasivos incluidos en grupos de activos para su disposición clasificados como mantenidos para la venta | E50: =SUMIF('Balance 8 Columnas'!$A$10:$A$113,B50,'Balance 8 Columnas'!$N$10:$N$113) -> 0
B51: Pasivos corrientes totales | E51: =+E49+E50 -> 0
B52: Pasivos no corrientes
B53: Cuentas por pagar comerciales y otras cuentas por pagar no corrientes | E53: =SUMIF('Balance 8 Columnas'!$A$10:$A$113,B53,'Balance 8 Columnas'!$N$10:$N$113) -> 0
B54: Pasivos no corrientes | E54: =SUMIF('Balance 8 Columnas'!$A$10:$A$113,B54,'Balance 8 Columnas'!$N$10:$N$113) -> 0
B55: Cuentas por Pagar a Entidades Relacionadas, no corrientes | E55: =SUMIF('Balance 8 Columnas'!$A$10:$A$113,B55,'Balance 8 Columnas'!$N$10:$N$113) -> 0
B56: Otras provisiones a largo plazo | E56: =SUMIF('Balance 8 Columnas'!$A$10:$A$113,B56,'Balance 8 Columnas'!$N$10:$N$113) -> 0
B57: Pasivo por impuestos diferidos | E57: =SUMIF('Balance 8 Columnas'!$A$10:$A$113,B57,'Balance 8 Columnas'!$N$10:$N$113) -> 0
B58: Provisiones corrientes por beneficios empleados | E58: =SUMIF('Balance 8 Columnas'!$A$10:$A$113,B58,'Balance 8 Columnas'!$N$10:$N$113) -> 0
B59: Otros pasivos no financieros no corrientes | E59: =SUMIF('Balance 8 Columnas'!$A$10:$A$113,B59,'Balance 8 Columnas'!$N$10:$N$113) -> 0
B60: Total de pasivos no corrientes | E60: =SUM(E53:E59) -> 0
B61: Total pasivos | E61: =+E51+E60 -> 0
B62: Patrimonio
B63: Capital emitido | E63: =SUMIF('Balance 8 Columnas'!$A$10:$A$113,B63,'Balance 8 Columnas'!$N$10:$N$113) -> 0 | G63: Ver
B64: Ganancias (pérdidas) acumuladas | E64: =SUMIF('Balance 8 Columnas'!$A$10:$A$113,B64,'Balance 8 Columnas'!$N$10:$N$113) -> 0
B65: Primas de emisión | E65: =SUMIF('Balance 8 Columnas'!$A$10:$A$113,B65,'Balance 8 Columnas'!$N$10:$N$113) -> 0
B66: Acciones propias en cartera | E66: =SUMIF('Balance 8 Columnas'!$A$10:$A$113,B66,'Balance 8 Columnas'!$N$10:$N$113) -> 0
B67: Otras participaciones en el patrimonio | E67: =SUMIF('Balance 8 Columnas'!$A$10:$A$113,B67,'Balance 8 Columnas'!$N$10:$N$113) -> 0
B68: Otras reservas | E68: =SUMIF('Balance 8 Columnas'!$A$10:$A$113,B68,'Balance 8 Columnas'!$N$10:$N$113) -> 0
B69: Patrimonio atribuible a los propietarios de la controladora | E69: =SUM(E63:E68) -> 0
B70: Participaciones no controladoras | E70: 0
B71: Patrimonio total | E71: =SUM(E65:E70) -> 0
B72: Total de patrimonio y pasivos | E72: =+E61+E71 -> 0
E74: =+E72-E34 -> 0 | F74: =+F72-F34 -> 0
B75: (1) Saldo de inicio del periodo anterior cuando presente comparativo en el caso de primera adopción o cambios contables retrospectivos.

Sheet Hoja1

Sheet Estado de Resultados
B1: =+Carátula!A7 -> Flexi Chile SpA
B2: Estado de Resultados
B3: Para el período comprendido entre el 01-01-2026 hasta el 31/01/2026
C6: =+'Balance Clasificado'!D6 -> 46053 | E6: =+C6 -> 46053
C7: $ | E7: US$
B8: Estado de resultados
B9: Ventas Netas | C9: =-SUMIF('Balance 8 Columnas'!A:O,'Estado de Resultados'!B9,'Balance 8 Columnas'!N:N) -> 246614292 | E9: =-SUMIF('Balance 8 Columnas'!A:O,'Estado de Resultados'!B9,'Balance 8 Columnas'!#REF!) -> #REF! | F9: =+E9/$E$9 -> #REF!
B10: Costo estándar de venta | C10: =-SUMIF('Balance 8 Columnas'!A:O,'Estado de Resultados'!B10,'Balance 8 Columnas'!J:J) -> -134839072 | E10: =-SUMIF('Balance 8 Columnas'!A:O,'Estado de Resultados'!B10,'Balance 8 Columnas'!#REF!) -> #REF! | F10: =+E10/$E$9 -> #REF!
B11: Ganancia bruta | C11: =+C9+C10 -> 111775220 | E11: =+E9+E10 -> #REF! | F11: =+E11/$E$9 -> #REF!
B12: Otros ingresos | C12: =-SUMIF('Balance 8 Columnas'!A:O,'Estado de Resultados'!B12,'Balance 8 Columnas'!N:N) -> 3751074 | E12: =-SUMIF('Balance 8 Columnas'!A:O,'Estado de Resultados'!B12,'Balance 8 Columnas'!#REF!) -> #REF!
B13: Resultado por siniestros | C13: =-SUMIF('Balance 8 Columnas'!A:O,'Estado de Resultados'!B13,'Balance 8 Columnas'!N:N) -> 0
B14: Publicidad | C14: =-SUMIF('Balance 8 Columnas'!A:O,'Estado de Resultados'!B14,'Balance 8 Columnas'!N:N) -> -2086868 | E14: =-SUMIF('Balance 8 Columnas'!A:O,'Estado de Resultados'!B14,'Balance 8 Columnas'!#REF!) -> #REF! | F14: =+E14/$E$9 -> #REF!
B15: Gastos de Administracion y Ventas | C15: =-SUMIF('Balance 8 Columnas'!A:O,'Estado de Resultados'!B15,'Balance 8 Columnas'!N:N) -> -109702350 | E15: =-SUMIF('Balance 8 Columnas'!A:O,'Estado de Resultados'!B15,'Balance 8 Columnas'!#REF!) -> #REF! | F15: =+E15/$E$9 -> #REF!
B16: Sueldos | C16: =-SUMIF('Balance 8 Columnas'!A:O,'Estado de Resultados'!B16,'Balance 8 Columnas'!N:N) -> -70008921 | E16: =-SUMIF('Balance 8 Columnas'!A:O,'Estado de Resultados'!B16,'Balance 8 Columnas'!#REF!) -> #REF! | F16: =+E16/$E$9 -> #REF!
B17: Depreciaciones | C17: =-SUMIF('Balance 8 Columnas'!A:O,'Estado de Resultados'!B17,'Balance 8 Columnas'!N:N) -> -8846337 | E17: =-SUMIF('Balance 8 Columnas'!A:O,'Estado de Resultados'!B17,'Balance 8 Columnas'!#REF!) -> #REF! | F17: =+E17/$E$9 -> #REF!
B18: Comisiones bancarias | C18: =-SUMIF('Balance 8 Columnas'!A:O,'Estado de Resultados'!B18,'Balance 8 Columnas'!N:N) -> -502259 | E18: =-SUMIF('Balance 8 Columnas'!A:O,'Estado de Resultados'!B18,'Balance 8 Columnas'!#REF!) -> #REF! | F18: =+E18/$E$9 -> #REF!
B19: Ingresos financieros | C19: =-SUMIF('Balance 8 Columnas'!A:O,'Estado de Resultados'!B19,'Balance 8 Columnas'!N:N) -> 0 | E19: =-SUMIF('Balance 8 Columnas'!A:O,'Estado de Resultados'!B19,'Balance 8 Columnas'!#REF!) -> #REF! | F19: =+E19/$E$9 -> #REF!
B20: Costo financiero | C20: =-SUMIF('Balance 8 Columnas'!A:O,'Estado de Resultados'!B20,'Balance 8 Columnas'!N:N) -> 23388827 | E20: =-SUMIF('Balance 8 Columnas'!A:O,'Estado de Resultados'!B20,'Balance 8 Columnas'!#REF!) -> #REF! | F20: =+E20/$E$9 -> #REF!
B21: Diferencia de cambio | F21: =+E21/$E$9 -> #REF!
B22: Ganancia (pérdida), antes de impuestos | C22: =SUM(C11:C21) -> -52231614 | E22: =SUM(E11:E21) -> #REF! | F22: =+E22/$E$9 -> #REF!
B23: Gasto por impuestos a las ganancias | C23: =SUMIF('Balance 8 Columnas'!A:O,'Estado de Resultados'!B23,'Balance 8 Columnas'!N:N) -> 0 | E23: 0
B25: Ganancia (pérdida) | C25: =SUM(C22:C23) -> -52231614 | E25: =SUM(E22:E23) -> #REF! | F25: =+E25/$E$9 -> #REF!
B26: Ganancia (pérdida), atribuible a
B27: Ganancia (pérdida), atribuible a los propietarios de la controladora | C27: =+C25 -> -52231614 | E27: =+E25 -> #REF! | F27: =+E27/$E$9 -> #REF!
B28: Ganancia (pérdida), atribuible a participaciones no controladoras | C28: 0 | E28: 0
B29: Ganancia (pérdida) | C29: =+C27+C28 -> -52231614 | E29: =+E27+E28 -> #REF! | F29: =+E29/$E$9 -> #REF!

Sheet Balance 8 Columnas
B2: =+Carátula!A7 -> Flexi Chile SpA
B3: Balance General IFRS
B4: =+Carátula!A9 -> Al 31 de enero de 2026
A7: Clasificacion | B7: Numero Cuenta | C7: Nombre Cuenta | D7: Valores Acumulados | F7: Saldos | H7: Inventario | J7: Resultados | N7: Saldos | O7: T/C Cierre
D8: Debitos | E8: Creditos | F8: Deudor | G8: Acreedor | H8: Activo | I8: Pasivo | J8: Perdidas | K8: Ganancias | O8: =+'Balance Clasificado'!C6 -> 865.1
A9: Caja y Bancos | B9: 1.1.01.101 | C9: EFECTIVO EN TRANSITO | D9: 216337650 | E9: 142232595 | F9: 74105055 | G9: 0 | H9: 74105055 | I9: 0 | J9: 0 | K9: 0 | M9: Monetaria | N9: =+D9-E9 -> 74105055 | O9: =N9/$O$8 -> 85660.681
A10: Caja y Bancos | B10: 1.1.01.203 | C10: FONDO FIJO PLAZA EGAÑA | D10: 99910 | E10: 58308 | F10: 41602 | G10: 0 | H10: 41602 | I10: 0 | J10: 0 | K10: 0 | M10: Monetaria | N10: =+D10-E10 -> 41602 | O10: =N10/$O$8 -> 48.089238
A11: Caja y Bancos | B11: 1.1.01.204 | C11: FONDO FIJO VESPUCIO | D11: 85990 | E11: 0 | F11: 85990 | G11: 0 | H11: 85990 | I11: 0 | J11: 0 | K11: 0 | M11: Monetaria | N11: =+D11-E11 -> 85990 | O11: =N11/$O$8 -> 99.398913
A12: Caja y Bancos | B12: 1.1.01.205 | C12: FONDO FIJO TREBOL | D12: 154990 | E12: 152308 | F12: 2682 | G12: 0 | H12: 2682 | I12: 0 | J12: 0 | K12: 0 | M12: Monetaria | N12: =+D12-E12 -> 2682 | O12: =N12/$O$8 -> 3.1002196
A13: Caja y Bancos | B13: 1.1.01.206 | C13: FONDO FIJO COSTANERA CENTER | D13: 100000 | E13: 108130 | F13: 0 | G13: 8130 | H13: 0 | I13: 8130 | J13: 0 | K13: 0 | M13: Monetaria | N13: =+D13-E13 -> -8130 | O13: =N13/$O$8 -> -9.3977575
A14: Caja y Bancos | B14: 1.1.01.207 | C14: FONDO FIJO FLORIDA CENTER | D14: 337628 | E14: 254628 | F14: 83000 | G14: 0 | H14: 83000 | I14: 0 | J14: 0 | K14: 0 | M14: Monetaria | N14: =+D14-E14 -> 83000 | O14: =N14/$O$8 -> 95.942666
A15: Caja y Bancos | B15: 1.1.01.208 | C15: FONDO FIJO SANTIAGO CENTRO | D15: 131290 | E15: 91720 | F15: 39570 | G15: 0 | H15: 39570 | I15: 0 | J15: 0 | K15: 0 | M15: Monetaria | N15: =+D15-E15 -> 39570 | O15: =N15/$O$8 -> 45.740377
A16: Caja y Bancos | B16: 1.1.01.209 | C16: FONDO FIJO CONCEPCION CENTRO | D16: 103980 | E16: 46490 | F16: 57490 | G16: 0 | H16: 57490 | I16: 0 | J16: 0 | K16: 0 | M16: Monetaria | N16: =+D16-E16 -> 57490 | O16: =N16/$O$8 -> 66.454745
A17: Caja y Bancos | B17: 1.1.01.210 | C17: FONDO FIJO TALCA | D17: 103994 | E17: 90688 | F17: 13306 | G17: 0 | H17: 13306 | I17: 0 | J17: 0 | K17: 0 | M17: Monetaria | N17: =+D17-E17 -> 13306 | O17: =N17/$O$8 -> 15.380881
A18: Caja y Bancos | B18: 1.1.01.211 | C18: FONSO FIJO PLAZA NORTE | D18: 128075 | E18: 80955 | F18: 47120 | G18: 0 | H18: 47120 | I18: 0 | J18: 0 | K18: 0 | M18: Monetaria | N18: =+D18-E18 -> 47120 | O18: =N18/$O$8 -> 54.467692
A19: Caja y Bancos | B19: 1.1.01.212 | C19: FONDO FIJO PLAZA OESTE | D19: 135671 | E19: 75671 | F19: 60000 | G19: 0 | H19: 60000 | I19: 0 | J19: 0 | K19: 0 | M19: Monetaria | N19: =+D19-E19 -> 60000 | O19: =N19/$O$8 -> 69.356144
A20: Caja y Bancos | B20: 1.1.01.301 | C20: BANCOS CTA CTE $ | D20: 822199777 | E20: 381616850 | F20: 440582927 | G20: 0 | H20: 440582927 | I20: 0 | J20: 0 | K20: 0 | M20: Monetaria | N20: =+D20-E20 -> 440582927 | O20: =N20/$O$8 -> 509285.55
... A116: Costo financiero | B116: 3.2.13.109 | C116: AJUSTE REDONDEO AUTO | D116: 34 | E116: 0 | F116: 34 | G116: 0 | H116: 0 | I116: 0 | J116: 34 | K116: 0 | M116: NO Monetario | N116: =+D116-E116 -> 34 | O116: =N116/$O$8 -> 0.039301815
B117: Total Acumulado | D117: =SUM(D9:D116) -> 13821361994 | E117: =SUM(E9:E116) -> 13821361994 | F117: =SUM(F9:F116) -> 7806222781 | G117: =SUM(G9:G116) -> 7806222781 | H117: =SUM(H9:H116) -> 7478455448 | I117: =SUM(I9:I116) -> 7530687062 | J117: =SUM(J9:J116) -> 327767333 | K117: =SUM(K9:K116) -> 275535719 | N117: =+D117-E117 -> 0 | O117: =SUM(O9:O116) -> 2.1525032e-10
B118: Resultado del ejercicio | H118: 0 | I118: =+H117-I117 -> -52231614 | J118: =+K117-J117 -> -52231614 | K118: 0 | N118: =SUM(N62:N116) -> 52231614 | O118: =SUM(O62:O116) -> 60376.389
B119: Sumas Iguales | D119: =D117 -> 13821361994 | E119: =E117 -> 13821361994 | F119: =F117 -> 7806222781 | G119: =G117 -> 7806222781 | H119: =SUM(H117:H118) -> 7478455448 | I119: =SUM(I117:I118) -> 7478455448 | J119: =SUM(J117:J118) -> 275535719 | K119: =SUM(K117:K118) -> 275535719
E120: =D119-E119 -> 0
E122: =E120/2 -> 0
E123: =E120*2 -> 0

Sheet EERR Mensual US$
A2: Flexi Chile SpA
A3: Estado de Resultado mensual
A4: =+'Estado de Resultados'!B3 -> Para el período comprendido entre el 01-01-2026 hasta el 31/01/2026
A5: Moneda US$
A8: Numero Cuenta | B8: Nombre Cuenta | C8: 44957 | D8: 44985 | E8: 45016 | F8: 45046 | G8: 45077 | H8: 45107 | I8: 45138 | J8: 45169 | K8: Resultado Periodo
J9: 855.86
C10: USD | D10: USD | E10: USD | F10: USD | G10: USD | H10: USD | I10: USD | J10: USD | K10: USD
A11: 3.1.01.101 | B11: VENTAS CON BOLETA | C11: 0 | D11: 1879.2 | E11: 0 | F11: 0 | G11: 0 | H11: 0 | I11: 283320.34 | J11: ='EERR Mensual $'!#REF!/'EERR Mensual US$'!$J$9 -> #REF! | K11: =SUM(C11:J11) -> #REF!
A12: 3.1.01.102 | B12: VENTAS CON FACTURA | C12: 0 | D12: 0 | E12: 0 | F12: 0 | G12: 0 | H12: 0 | I12: 154.26 | J12: ='EERR Mensual $'!#REF!/'EERR Mensual US$'!$J$9 -> #REF! | K12: =SUM(C12:J12) -> #REF!
A13: 3.1.01.103 | B13: VENTAS CON BOLETA (RPA) | C13: 236876.85 | D13: 181614.1 | E13: 197725.78 | F13: 278768.47 | G13: 325586.65 | H13: 267228.92 | I13: 0 | J13: ='EERR Mensual $'!#REF!/'EERR Mensual US$'!$J$9 -> #REF! | K13: =SUM(C13:J13) -> #REF!
A14: 3.1.01.104 | B14: VENTAS CON FACTURA (RPA) | C14: 37403.03 | D14: 128785.99 | E14: 95545.93 | F14: 70291.04 | G14: 32098.07 | H14: 1370.34 | I14: 0 | J14: ='EERR Mensual $'!#REF!/'EERR Mensual US$'!$J$9 -> #REF! | K14: =SUM(C14:J14) -> #REF!
A15: 3.1.02.101 | B15: COSTO DE VENTAS | C15: -172048.4 | D15: -193242.82 | E15: -174833.04 | F15: -179090.11 | G15: -175480.27 | H15: -132641.24 | I15: -147645.76 | J15: ='EERR Mensual $'!#REF!/'EERR Mensual US$'!$J$9 -> #REF! | K15: =SUM(C15:J15) -> #REF!
A16: 3.1.02.102 | B16: COSTOS OPERATIVOS - FLETES INTERNOS | C16: -5526.8 | D16: -3269.95 | E16: -2476.83 | F16: -4054.64 | G16: -4460.46 | H16: -3747.18 | I16: -2806.37 | J16: ='EERR Mensual $'!#REF!/'EERR Mensual US$'!$J$9 -> #REF! | K16: =SUM(C16:J16) -> #REF!
A17: 3.1.02.103 | B17: CANAL DIGITAL | C17: 0 | D17: -1815.63 | E17: 0 | F17: 0 | G17: -8.84 | H17: 0 | I17: 0 | J17: ='EERR Mensual $'!#REF!/'EERR Mensual US$'!$J$9 -> #REF! | K17: =SUM(C17:J17) -> #REF!
A18: 3.1.02.104 | B18: COMISIÓN - CANAL DIGITAL | C18: -7346.76 | D18: -6770.43 | E18: -6816.94 | F18: -5793.52 | G18: -5837.44 | H18: -5822.39 | I18: -2880.4 | J18: ='EERR Mensual $'!#REF!/'EERR Mensual US$'!$J$9 -> #REF! | K18: =SUM(C18:J18) -> #REF!
A19: 3.1.02.105 | B19: FLETES - CANAL DIGITAL | C19: -1346.95 | D19: -1543.2 | E19: -1141.34 | F19: -1804.89 | G19: -1496.94 | H19: -1560.26 | I19: -1890.16 | J19: ='EERR Mensual $'!#REF!/'EERR Mensual US$'!$J$9 -> #REF! | K19: =SUM(C19:J19) -> #REF!
A20: 3.1.02.108 | B20: SERVICIOS - CANAL DIGITAL | C20: -3921.59 | D20: -6599.82 | E20: -7103.61 | F20: -10158.6 | G20: -7259.92 | H20: -8043.44 | I20: -10487.54 | J20: ='EERR Mensual $'!#REF!/'EERR Mensual US$'!$J$9 -> #REF! | K20: =SUM(C20:J20) -> #REF!
A21: 3.1.02.113 | B21: COSTOS OPERATIVOS - INTERNACIO | C21: 15.11 | D21: -48.72 | E21: 203.13 | F21: 19.37 | G21: -23.38 | H21: 0 | I21: 0 | J21: ='EERR Mensual $'!#REF!/'EERR Mensual US$'!$J$9 -> #REF! | K21: =SUM(C21:J21) -> #REF!
A22: 3.1.05.101 | B22: REMUNERACIONES | C22: -28991.84 | D22: -51892.52 | E22: -29766.33 | F22: -28208.49 | G22: -28491.3 | H22: -29738.91 | I22: -28728.39 | J22: ='EERR Mensual $'!#REF!/'EERR Mensual US$'!$J$9 -> #REF! | K22: =SUM(C22:J22) -> #REF!
... A39: 3.1.05.129 | B39: RE SEMANA CORRIDA | C39: -679.12 | D39: -363.6 | E39: -334.49 | F39: -942.79 | G39: -2139.63 | H39: -984 | I39: -764.59 | J39: ='EERR Mensual $'!#REF!/'EERR Mensual US$'!$J$9 -> #REF! | K39: =SUM(C39:J39) -> #REF!
A40: 3.1.05.130 | B40: RE HORAS EXTRAS DOMINICAL | J40: ='EERR Mensual $'!#REF!/'EERR Mensual US$'!$J$9 -> #REF! | K40: =SUM(C40:J40) -> #REF!
A41: 3.1.05.132 | B41: RE SEGURO DE CESANTIA | C41: -557.26 | D41: -496.18 | E41: -546.09 | F41: -780.92 | G41: -825.81 | H41: -822.45 | I41: -730.57 | J41: ='EERR Mensual $'!#REF!/'EERR Mensual US$'!$J$9 -> #REF! | K41: =SUM(C41:J41) -> #REF!
A42: 3.1.05.133 | B42: RE MUTUAL DE SEGURIDAD | C42: -189.07 | D42: -166.98 | E42: -182.67 | F42: -249.76 | G42: -275.81 | H42: -285.51 | I42: -265.02 | J42: ='EERR Mensual $'!#REF!/'EERR Mensual US$'!$J$9 -> #REF! | K42: =SUM(C42:J42) -> #REF!
A43: 3.1.05.134 | B43: RE SEGURO INVALIDEZ (AFP) | C43: -332.03 | D43: -300.75 | E43: -324.07 | F43: -462.84 | G43: -489.93 | H43: -495.57 | I43: -535.75 | J43: ='EERR Mensual $'!#REF!/'EERR Mensual US$'!$J$9 -> #REF! | K43: =SUM(C43:J43) -> #REF!
A44: 3.1.05.406 | B44: GASTOS DE TELEFONIA MOVIL | C44: 0 | D44: 0 | E44: -50.57 | F44: -132.07 | G44: -347.37 | H44: 197.52 | I44: -326 | J44: ='EERR Mensual $'!#REF!/'EERR Mensual US$'!$J$9 -> #REF! | K44: =SUM(C44:J44) -> #REF!
A45: 3.1.05.818 | B45: LICENCIAS SOTWARE RENTAS | C45: -1029.54 | D45: -659.43 | E45: -1208.25 | F45: -1557.22 | G45: -1705.7 | H45: -1422.98 | I45: -2060.54 | J45: ='EERR Mensual $'!#REF!/'EERR Mensual US$'!$J$9 -> #REF! | K45: =SUM(C45:J45) -> #REF!
A46: 3.1.05.834 | B46: GASTO VENTA CANAL MAYORISTA | C46: 0 | D46: 0 | E46: 0 | F46: 0 | G46: -1029.65 | H46: -4041.18 | I46: 0 | J46: ='EERR Mensual $'!#REF!/'EERR Mensual US$'!$J$9 -> #REF! | K46: =SUM(C46:J46) -> #REF!
A47: 3.1.05.835 | B47: GASTOS CEDIS | C47: 0 | D47: -950.61 | E47: -618.51 | F47: 0 | G47: -960.98 | H47: 0 | I47: 0 | J47: ='EERR Mensual $'!#REF!/'EERR Mensual US$'!$J$9 -> #REF! | K47: =SUM(C47:J47) -> #REF!
A48: 3.1.06.108 | B48: ASIGNACION COLACION | C48: -1578.29 | D48: -1545.87 | E48: -1557.05 | F48: -1490.31 | G48: -1475.63 | H48: -1592.57 | I48: -1477.35 | J48: ='EERR Mensual $'!#REF!/'EERR Mensual US$'!$J$9 -> #REF! | K48: =SUM(C48:J48) -> #REF!
A49: 3.1.06.109 | B49: ASIGNACION MOVILIZACION | C49: -1578.29 | D49: -1545.87 | E49: -1557.05 | F49: -1490.31 | G49: -1475.63 | H49: -1592.57 | I49: -1477.35 | J49: ='EERR Mensual $'!#REF!/'EERR Mensual US$'!$J$9 -> #REF! | K49: =SUM(C49:J49) -> #REF!
A50: 3.1.06.112 | B50: GASTOS DE CAPACITACION | C50: 0 | D50: 0 | E50: 0 | F50: 0 | G50: 0 | H50: 0 | I50: -5865.62 | J50: ='EERR Mensual $'!#REF!/'EERR Mensual US$'!$J$9 -> #REF! | K50: =SUM(C50:J50) -> #REF!
A51: 3.1.06.116 | B51: UNIFORMES | C51: -530.76 | D51: -291.98 | E51: -1719.09 | F51: -2660.05 | G51: -2170.86 | H51: -185.13 | I51: -2440.08 | J51: ='EERR Mensual $'!#REF!/'EERR Mensual US$'!$J$9 -> #REF! | K51: =SUM(C51:J51) -> #REF!
A52: 3.1.06.130 | B52: RE ASIGNACION COLACION | C52: -744.89 | D52: -771.37 | E52: -841.12 | F52: -979.02 | G52: -1097.01 | H52: -1121.49 | I52: -1109.47 | J52: ='EERR Mensual $'!#REF!/'EERR Mensual US$'!$J$9 -> #REF! | K52: =SUM(C52:J52) -> #REF!
... A90: 3.2.13.109 | B90: AJUSTE REDONDEO AUTO | C90: 0 | D90: -0.01 | E90: 0 | F90: 0.03 | G90: 0.03 | H90: -0.21 | I90: -0.34 | J90: ='EERR Mensual $'!#REF!/'EERR Mensual US$'!$J$9 -> #REF! | K90: =SUM(C90:J90) -> #REF!
A91: Resultado del ejercicio mensual | C91: =SUM(C11:C90) -> -86218.13 | D91: =SUM(D11:D90) -> -71469.99 | E91: =SUM(E11:E90) -> -85958.11 | F91: =SUM(F11:F90) -> -15133.3 | G91: =SUM(G11:G90) -> -19700.89 | H91: =SUM(H11:H90) -> -77864.35 | I91: =SUM(I11:I90) -> -68349.73 | J91: =SUM(J11:J90) -> #REF! | K91: =SUM(K11:K90) -> #REF!
K92: =K91+'Balance 8 Columnas'!O118 -> #REF!

Sheet EERR Mensual $
Q1: Sum. Visual'!A1
A2: Flexi Chile SpA
A3: Estado de Resultado mensual
A4: =+'Estado de Resultados'!B3 -> Para el período comprendido entre el 01-01-2026 hasta el 31/01/2026
A5: Moneda $
A8: Numero Cuenta | B8: Nombre Cuenta | C8: 46053 | D8: 46081 | E8: 46112 | F8: 46142 | G8: 46173 | H8: 46203 | I8: 46234 | J8: 46265 | K8: 46295 | L8: 46326 | M8: 46356 | N8: 46387 | O8: Resultado Periodo
C10: $ | D10: $ | E10: $ | F10: $ | G10: $ | H10: $ | I10: $ | J10: $ | K10: $ | L10: $ | M10: $ | N10: $ | O10: $
A11: 3.1.01.103 | B11: VENTAS CON BOLETA (RPA) | C11: 246614292 | O11: =SUM(C11:N11) -> 246614292
A12: 3.1.01.300 | B12: OTROS INGRESOS | C12: 3751074 | O12: =SUM(C12:N12) -> 3751074
A13: 3.1.02.101 | B13: COSTO DE VENTAS | C13: -134839072 | O13: =SUM(C13:N13) -> -134839072 | P13: =C13-D13 -> -134839072
A14: 3.1.02.102 | B14: COSTOS OPERATIVOS - FLETES INTERNOS | C14: -1840455 | O14: =SUM(C14:N14) -> -1840455 | P14: =C14-D14 -> -1840455 | T14: HIDALGO DIC 2.521.008 ENE 2.819.732 FEB 3.040.000
A15: 3.1.02.104 | B15: COMISIÓN - CANAL DIGITAL | C15: -2699824 | O15: =SUM(C15:N15) -> -2699824 | P15: =C15-D15 -> -2699824
A16: 3.1.02.105 | B16: FLETES - CANAL DIGITAL | C16: -800047 | O16: =SUM(C16:N16) -> -800047 | P16: =C16-D16 -> -800047
A17: 3.1.02.108 | B17: SERVICIOS - CANAL DIGITAL | C17: -1976022 | O17: =SUM(C17:N17) -> -1976022 | P17: =C17-D17 -> -1976022
A18: 3.1.02.109 | B18: DESCUENTOS GIFTCARD | C18: -44990 | O18: =SUM(C18:N18) -> -44990 | P18: =C18-D18 -> -44990
A19: 3.1.02.110 | B19: DESCUENTOS CLUB FLEXI | C19: -46507 | O19: =SUM(C19:N19) -> -46507 | P19: =C19-D19 -> -46507
A20: 3.1.05.101 | B20: REMUNERACIONES | C20: -45117151 | O20: =SUM(C20:N20) -> -45117151 | P20: =C21-D20 -> -1730490
A21: 3.1.05.102 | B21: BONOS | C21: -1730490 | O21: =SUM(C21:N21) -> -1730490 | P21: =C22-D21 -> -1655083
A22: 3.1.05.103 | B22: SEGURO DE CESANTIA | C22: -1655083 | O22: =SUM(C22:N22) -> -1655083 | P22: =C23-D22 -> -10584152
A23: 3.1.05.104 | B23: GRATIFICACION | C23: -10584152 | O23: =SUM(C23:N23) -> -10584152 | P23: =C24-D23 -> -4000
A24: 3.1.05.107 | B24: FINIQUITOS | C24: -4000 | O24: =SUM(C24:N24) -> -4000 | P24: =C25-D24 -> -600154
A25: 3.1.05.110 | B25: MUTUAL DE SEGURIDAD | C25: -600154 | O25: =SUM(C25:N25) -> -600154 | P25: =C26-D25 -> -1012481
A26: 3.1.05.111 | B26: SEGURO INVALIDEZ (AFP) | C26: -1012481 | O26: =SUM(C26:N26) -> -1012481 | P26: =C29-D26 -> 0
A27: 3.1.05.112 | B27: CAPITALIZACION INDIVIDUAL AFP | C27: -64495 | O27: =SUM(C27:N27) -> -64495
A28: 3.1.05.113 | B28: EXPECTATIVA DE VIDA | C28: -591718 | O28: =SUM(C28:N28) -> -591718
A29: 3.1.05.114 | B29: HORAS EXTRAS | C29: 0 | O29: =SUM(C29:N29) -> 0 | P29: =C30-D29 -> -756324
A30: 3.1.05.117 | B30: DOMINGOS Y FESTIVOS | C30: -756324 | O30: =SUM(C30:N30) -> -756324 | P30: =C31-D30 -> -1447552
A31: 3.1.05.121 | B31: SEMANA CORRIDA | C31: -1447552 | O31: =SUM(C31:N31) -> -1447552 | P31: =C32-D31 -> -6445321
A32: 3.1.05.122 | B32: COMISION POR VENTA | C32: -6445321 | O32: =SUM(C32:N32) -> -6445321 | P32: =C33-D32 -> -2326500
A33: 3.1.06.108 | B33: ASIGNACION COLACION | C33: -2326500 | O33: =SUM(C33:N33) -> -2326500 | P33: =C34-D33 -> -2326500
A34: 3.1.06.109 | B34: ASIGNACION MOVILIZACION | C34: -2326500 | O34: =SUM(C34:N34) -> -2326500 | P34: =C35-D34 -> 1138389
A35: 3.1.06.116 | B35: UNIFORMES | C35: 1138389 | O35: =SUM(C35:N35) -> 1138389 | P35: =C36-D35 -> -505000
A36: 3.1.06.201 | B36: HONORARIOS PROFESIONALES | C36: -505000 | O36: =SUM(C36:N36) -> -505000 | P36: =C37-D36 -> -3101478
A37: 3.1.06.206 | B37: ASESORIA CONTABLE | C37: -3101478 | O37: =SUM(C37:N37) -> -3101478 | P37: =C38-D37 -> 0
A38: 3.1.06.209 | B38: HONORARIOS POR ASESORIAS INFORMATICAS | C38: 0 | O38: =SUM(C38:N38) -> 0 | P38: =C39-D38 -> -75994402 | R38: enero y feb
A39: 3.1.06.301 | B39: ARRIENDOS | C39: -75994402 | O39: =SUM(C39:N39) -> -75994402 | P39: =C40-D39 -> -3126087
A40: 3.1.06.302 | B40: ARRIENDO DE BODEGAS | C40: -3126087 | O40: =SUM(C40:N40) -> -3126087 | P40: =C41-D40 -> -631049
A41: 3.1.06.305 | B41: GASTOS DIVERSOS | C41: -631049 | O41: =SUM(C41:N41) -> -631049 | P41: =C42-D41 -> 0
A42: 3.1.06.306 | B42: SEGURIDAD INDUSTRIAL | C42: 0 | O42: =SUM(C42:N42) -> 0
A43: 3.1.06.401 | B43: SERVICIOS DE TELECOMUNICACION | C43: -177715 | O43: =SUM(C43:N43) -> -177715 | P43: =C44-D43 -> -131229
A44: 3.1.06.406 | B44: GASTOS DE TELEFONIA MOVIL | C44: -131229 | O44: =SUM(C44:N44) -> -131229 | P44: =C45-D44 -> -839257
A45: 3.1.06.501 | B45: PATENTE COMERCIAL | C45: -839257 | O45: =SUM(C45:N45) -> -839257 | P45: =C47-D45 -> -420710
A46: 3.1.06.504 | B46: IVA IRRECUPERABLE | C46: -1065119 | O46: =SUM(C46:N46) -> -1065119
A47: 3.1.06.505 | B47: MULTAS E INTERESES | C47: -420710 | O47: =SUM(C47:N47) -> -420710 | P47: =C48-D47 -> -741641
A48: 3.1.06.506 | B48: SEGUROS | C48: -741641 | O48: =SUM(C48:N48) -> -741641 | P48: =C49-D48 -> 1
A49: 3.1.06.507 | B49: SERVICIO DE VIGILANCIA | C49: 1 | O49: =SUM(C49:N49) -> 1 | P49: =C50-D49 -> -1105609
A50: 3.1.06.601 | B50: GASTO MANTENCION SUCURSALES | C50: -1105609 | O50: =SUM(C50:N50) -> -1105609 | P50: =C51-D50 -> -642168
A51: 3.1.06.602 | B51: BOLSA IMPRESA | C51: -642168 | O51: =SUM(C51:N51) -> -642168 | P51: =C52-D51 -> 0
A52: 3.1.06.603 | B52: GASTOS DE ALMACENAJE (maniobras) | C52: 0 | O52: =SUM(C52:N52) -> 0
A53: 3.1.06.802 | B53: SUMINISTROS COMPUTACIONALES | C53: 0 | O53: =SUM(C53:N53) -> 0 | P53: =C54-D53 -> -371590
A54: 3.1.06.803 | B54: UTILES DE OFICINA Y PAPELERIA | C54: -371590 | O54: =SUM(C54:N54) -> -371590 | P54: =C56-D54 -> -502259
A55: 3.1.06.805 | B55: GASTOS LEGALES Y NOTARIALES DIRECTOS | C55: 0 | O55: =SUM(C55:N55) -> 0
A56: 3.1.06.806 | B56: COMISIONES Y GASTOS BANCARIOS | C56: -502259 | O56: =SUM(C56:N56) -> -502259 | P56: =C58-D56 -> -597458
A57: 3.1.06.812 | B57: COMISIONES TRANSBANK | C57: -2853756 | O57: =SUM(C57:N57) -> -2853756 | P57: =C58-D57 -> -597458
A58: 3.1.06.813 | B58: COMISIONES GETNET | C58: -597458 | O58: =SUM(C58:N58) -> -597458 | P58: =C59-D58 -> -868786
A59: 3.1.06.817 | B59: GASTOS DE REPRESENTACION | C59: -868786 | O59: =SUM(C59:N59) -> -868786
A60: 3.1.06.818 | B60: LICENCIAS SOTWARE RENTAS | C60: -2919321 | O60: =SUM(C60:N60) -> -2919321 | P60: =C61-D60 -> -268190
A61: 3.1.06.831 | B61: MEMBRESÍAS Y ASOCIACIONES | C61: -268190 | O61: =SUM(C61:N61) -> -268190 | P61: =C62-D61 -> -588258
A62: 3.1.06.837 | B62: MONITOREO COMERCIAL | C62: -588258 | O62: =SUM(C62:N62) -> -588258 | P62: =C63-D62 -> -2086868
A63: 3.1.07.822 | B63: GASTOS DE PUBLICIDAD Y MARKETING | C63: -2086868 | O63: =SUM(C63:N63) -> -2086868 | P63: =C64-D63 -> -1831072
A64: 3.1.07.833 | B64: SUMINISTROS VISUAL | C64: -1831072 | O64: =SUM(C64:N64) -> -1831072 | P64: =C65-D64 -> -8846337
A65: 3.1.08.701 | B65: DEPRECIACION DEL EJERCICIO | C65: -8846337 | O65: =SUM(C65:N65) -> -8846337 | P65: =C67-D65 -> 0
A66: 3.2.08.105 | B66: INTERESES POR PRESTAMO | C66: -19305 | O66: =SUM(C66:N66) -> -19305
A67: 3.2.08.114 | B67: INTERESES DEVENGADOS FONDOS MU | C67: 0 | O67: =SUM(C67:N67) -> 0 | P67: =C68-D67 -> 5791
A68: 3.2.08.116 | B68: INTERES GANADO POR DEPOSITO A PLAZO PESOS | C68: 5791 | O68: =SUM(C68:N68) -> 5791 | P68: =C69-D68 -> 0
A69: 3.2.08.117 | B69: INTERES GANADOS FONDOS MUTUOS | C69: 0 | O69: =SUM(C69:N69) -> 0 | P69: =C70-D69 -> 24026172
A70: 3.2.11.158 | B70: DIFERENCIA DE CAMBIO | C70: 24026172 | O70: =SUM(C70:N70) -> 24026172 | P70: =C71-D70 -> -623797
A71: 3.2.13.101 | B71: CORRECCION MONETARIA ACTIVOS | C71: -623797 | O71: =SUM(C71:N71) -> -623797 | P71: =#REF!-D71 -> #REF!
A72: 3.2.13.109 | B72: AJUSTE REDONDEO AUTO | C72: -34 | O72: =SUM(C72:N72) -> -34 | P72: =C72-D72 -> -34
A73: Resultado del ejercicio mensual | C73: =SUM(C11:C72) -> -52231614 | D73: =SUM(D11:D72) -> 0 | E73: =SUM(E11:E72) -> 0 | F73: =SUM(F11:F72) -> 0 | G73: =SUM(G11:G72) -> 0 | H73: =SUM(H11:H72) -> 0 | I73: =SUM(I11:I72) -> 0 | J73: =SUM(J11:J72) -> 0 | K73: =SUM(K11:K71) -> 0 | L73: =SUM(L11:L71) -> 0 | M73: =SUM(M11:M71) -> 0 | N73: =SUM(N11:N71) -> 0 | O73: =SUM(O11:O72) -> -52231614
O74: =O73-'Balance 8 Columnas'!J118 -> 0

Sheet ER Centro de Costo
D1: 300 | E1: 130 | F1: 140 | G1: 150 | H1: 100 | I1: 2 | J1: 170 | K1: 180 | L1: 185 | M1: 500 | N1: 190 | O1: 195 | P1: 200 | Q1: 210
B2: Estado de Resultado por Centro de Costo
B3: =+'Estado de Resultados'!B3 -> Para el período comprendido entre el 01-01-2026 hasta el 31/01/2026
D5: =+D8/$R$8 -> 0 | E5: =+E8/$R$8 -> 0.13366972 | F5: =+F8/$R$8 -> 0 | G5: =+G8/$R$8 -> 0.093715277 | H5: =+H8/$R$8 -> 0.11146838 | J5: =+J8/$R$8 -> 0.19243443 | K5: =+K8/$R$8 -> 0.085159979 | L5: =+L8/$R$8 -> 0 | M5: =+M8/$R$8 -> 0 | N5: =+N8/$R$8 -> 0.14553252 | O5: =+O8/$R$8 -> 0.068649802 | P5: =+P8/$R$8 -> 0.068109589 | Q5: =+Q8/$R$8 -> 0.10126031
B6: N° CUENTA | C6: NOMBRE CUENTA | D6: CEDIS CHILE | E6: EGAÑA | F6: VESPUCIO | G6: TREBOL | H6: ONLINE | I6: ADMINISTRACION | J6: COSTANERA CENTER | K6: FLORIDA CENTER | L6: CONCEPCION CENTRO | M6: DEPARTAMENTAL | N6: SANTIAGO CENTRO | O6: MAULE TALCA | P6: PLAZA NORTE | Q6: PLAZA OESTE | R6: TOTAL
B8: 3.1.01.101 | C8: VENTAS CON BOLETA | D8: =SUM(D9:D10) -> 0 | E8: =SUM(E9:E10) -> 32964888 | F8: =SUM(F9:F10) -> 0 | G8: =SUM(G9:G10) -> 23111545 | H8: =SUM(H9:H10) -> 27489717 | I8: =SUM(I9:I10) -> 0 | J8: =SUM(J9:J10) -> 47457118 | K8: =SUM(K9:K10) -> 21001684 | ... Q8: =SUM(Q9:Q10) -> 24972259 | R8: =SUM(D8:Q8) -> 2.4661448e+08
C9: ACCESORIOS | E9: 438302.52 | G9: 622984.03 | H9: 59075.63 | J9: 791978.15 | K9: 394328.57 | N9: 439117.65 | O9: 208371.43 | P9: 403824.37 | Q9: 507118.49 | R9: =SUM(E9:Q9) -> 3865100.8
C10: CALZADO | E10: 32526586 | G10: 22488561 | H10: =35615436-8184795 -> 27430641 | J10: 46665139 | K10: 20607355 | N10: 35451308 | O10: 16721664 | P10: 16392987 | Q10: 24465140 | R10: =SUM(E10:Q10) -> 2.4274938e+08
B11: 3.1.02.101 | C11: COSTO DE VENTAS | E11: -17793331 | F11: 0 | G11: -11944357 | H11: -17445854 | I11: 0 | J11: -25211212 | K11: -11190542 | L11: 0 | N11: -19343670 | O11: -9135162 | P11: -9119820 | Q11: -13655123 | R11: =SUM(D11:Q11) -> -134839071
B12: Resultado por Centro de Beneficio | D12: =+D8+D11 -> 0 | E12: =+E8+E11 -> 15171557 | F12: =+F8+F11 -> 0 | G12: =+G8+G11 -> 11167188 | H12: =+H8+H11 -> 10043863 | I12: =+I8+I11 -> 0 | J12: =+J8+J11 -> 22245906 | K12: =+K8+K11 -> 9811142 | ... R12: =+R8+R11 -> 1.1177541e+08 | S12: OK
B14: N° CUENTA | C14: NOMBRE CUENTA | D14: CEDIS CHILE | E14: EGAÑA | F14: VESPUCIO | G14: TREBOL | H14: ONLINE | I14: ADMINISTRACION | J14: COSTANERA CENTER | K14: FLORIDA CENTER | L14: CONCEPCION CENTRO | M14: DEPARTAMENTAL | N14: SANTIAGO CENTRO | O14: MAULE TALCA | P14: PLAZA NORTE | Q14: PLAZA OESTE | R14: TOTAL
B16: 3.1.01.300 | C16: OTROS INGRESOS | D16: 0 | E16: 0 | F16: 0 | G16: 0 | H16: 3751074 | I16: 0 | J16: 0 | K16: 0 | L16: 0 | M16: 0 | N16: 0 | O16: 0 | P16: 0 | Q16: 0 | R16: =SUM(D16:Q16) -> 3751074
B17: 3.1.02.102 | C17: COSTOS OPERATIVOS - FLETES INTERNOS | D17: -2164695 | E17: 21780 | F17: 0 | G17: 21780 | H17: 150000 | I17: 0 | J17: 21780 | K17: 21780 | L17: 0 | M17: 0 | N17: 21780 | O17: 21780 | P17: 21780 | Q17: 21780 | R17: =SUM(D17:Q17) -> -1840455
B18: 3.1.02.104 | C18: COMISIÓN - CANAL DIGITAL | D18: 0 | E18: 0 | F18: 0 | G18: 0 | H18: -3004368 | I18: 0 | J18: 0 | K18: 0 | L18: 0 | M18: 304544 | N18: 0 | O18: 0 | P18: 0 | Q18: 0 | R18: =SUM(D18:Q18) -> -2699824
B19: 3.1.02.105 | C19: FLETES - CANAL DIGITAL | D19: 0 | E19: 0 | F19: 0 | G19: 0 | H19: 2066127 | I19: 0 | J19: 0 | K19: 0 | L19: 0 | M19: -2866174 | N19: 0 | O19: 0 | P19: 0 | Q19: 0 | R19: =SUM(D19:Q19) -> -800047
B20: 3.1.02.108 | C20: SERVICIOS - CANAL DIGITAL | D20: 0 | E20: 0 | F20: 0 | G20: 0 | H20: -129245 | I20: 0 | J20: 0 | K20: 0 | L20: 0 | M20: -1846777 | N20: 0 | O20: 0 | P20: 0 | Q20: 0 | R20: =SUM(D20:Q20) -> -1976022
B21: 3.1.02.109 | C21: DESCUENTOS GIFTCARD | D21: 0 | E21: 0 | F21: 0 | G21: 0 | H21: 0 | I21: 0 | J21: 0 | K21: 0 | L21: 0 | M21: 0 | N21: -44990 | O21: 0 | P21: 0 | Q21: 0 | R21: =SUM(D21:Q21) -> -44990
B22: 3.1.02.110 | C22: DESCUENTOS CLUB FLEXI | D22: 0 | E22: 0 | F22: 0 | G22: 0 | H22: 0 | I22: 0 | J22: -14372 | K22: -27334 | L22: 0 | M22: 0 | N22: -4801 | O22: 0 | P22: 0 | Q22: 0 | R22: =SUM(D22:Q22) -> -46507
B23: 3.1.05.101 | C23: REMUNERACIONES | D23: 0 | E23: -5471370 | F23: 0 | G23: -5105142 | H23: -3360231 | I23: -589781 | J23: -6163578 | K23: -4432782 | L23: 0 | M23: -1429576 | N23: -5819291 | O23: -3991543 | P23: -4129167 | Q23: -4624690 | R23: =SUM(D23:Q23) -> -45117151
B24: 3.1.05.102 | C24: BONOS | D24: 0 | E24: -273846 | F24: 0 | G24: -183785 | H24: -127312 | I24: 0 | J24: -295071 | K24: -167527 | L24: 0 | M24: 0 | N24: -668574 | O24: -17293 | P24: 805918 | Q24: -803000 | R24: =SUM(D24:Q24) -> -1730490
B25: 3.1.05.103 | C25: SEGURO DE CESANTIA | D25: 0 | E25: -190943 | F25: 0 | G25: -203449 | H25: -92175 | I25: -44143 | J25: -226386 | K25: -163670 | L25: 0 | M25: -34952 | N25: -219642 | O25: -149355 | P25: -149071 | Q25: -181297 | R25: =SUM(D25:Q25) -> -1655083
B26: 3.1.05.104 | C26: GRATIFICACION | D26: 0 | E26: -1260847 | F26: 0 | G26: -1345486 | H26: -460102 | I26: -215308 | J26: -1419780 | K26: -1136975 | L26: 0 | M26: -147415 | N26: -1338001 | O26: -1000642 | P26: -1039174 | Q26: -1220422 | R26: =SUM(D26:Q26) -> -10584152
B27: 3.1.05.107 | C27: FINIQUITOS | D27: 0 | E27: 0 | F27: 0 | G27: 0 | H27: 0 | I27: -4000 | J27: 0 | K27: 0 | L27: 0 | M27: 0 | N27: 0 | O27: 0 | P27: 0 | Q27: 0 | R27: =SUM(D27:Q27) -> -4000
... B69: 3.2.08.105 | C69: INTERESES POR PRESTAMO | D69: 0 | E69: 0 | F69: 0 | G69: 0 | H69: 0 | I69: 0 | J69: -8446 | K69: 0 | L69: 0 | M69: 0 | N69: 0 | O69: 0 | P69: -4101 | Q69: -6758 | R69: =SUM(D69:Q69) -> -19305
B70: 3.2.08.114 | C70: INTERESES DEVENGADOS FONDOS MU | D70: 0 | E70: 0 | F70: 0 | G70: 0 | H70: 0 | I70: 0 | J70: 0 | K70: 0 | L70: 0 | M70: 0 | N70: 0 | O70: 0 | R70: =SUM(D70:Q70) -> 0
B71: 3.2.08.116 | C71: INTERES GANADO POR DEPOSITO A PLAZO PESOS | D71: 0 | E71: 0 | F71: 0 | G71: 0 | H71: 0 | I71: 5791 | J71: 0 | K71: 0 | L71: 0 | M71: 0 | N71: 0 | O71: 0 | P71: 0 | Q71: 0 | R71: =SUM(D71:Q71) -> 5791
B72: 3.2.08.117 | C72: INTERES GANADO FONDOS MUTUOS | D72: 0 | E72: 0 | F72: 0 | G72: 0 | H72: 0 | I72: 0 | J72: 0 | K72: 0 | L72: 0 | M72: 0 | N72: 0 | O72: 0 | R72: =SUM(D72:Q72) -> 0
B73: 3.2.11.158 | C73: DIFERENCIA DE CAMBIO | H73: 0 | I73: 24026172 | M73: 0 | R73: =SUM(D73:Q73) -> 24026172
B74: 3.2.13.101 | C74: CORRECCION MONETARIA ACTIVOS | D74: 0 | E74: 0 | F74: 0 | G74: 0 | H74: 0 | I74: -623797 | J74: 0 | K74: 0 | L74: 0 | M74: 0 | N74: 0 | O74: 0 | P74: 0 | Q74: 0 | R74: =SUM(D74:Q74) -> -623797
B75: 3.2.13.109 | C75: AJUSTE REDONDEO AUTO | D75: 0 | E75: 0 | F75: 0 | G75: 0 | H75: 0 | I75: -34 | J75: 0 | K75: 0 | L75: 0 | M75: 0 | N75: 0 | O75: 0 | P75: 0 | Q75: 0 | R75: =SUM(D75:Q75) -> -34
B76: Resultado por Centro de Costo | D76: =SUM(D16:D75) -> -8834134 | E76: =SUM(E16:E75) -> -18557806 | F76: =SUM(F16:F75) -> -11619 | G76: =SUM(G16:G75) -> -17972450 | H76: =SUM(H16:H75) -> -5369377 | I76: =SUM(I16:I75) -> 11379261 | J76: =SUM(J16:J75) -> -32106886 | K76: =SUM(K16:K75) -> -19456181 | ... Q76: =SUM(Q16:Q75) -> -18312604 | R76: =SUM(D76:Q76) -> -164006834
B78: Resultado por Centro de Costo | D78: =D12+D76 -> -8834134 | E78: =E12+E76 -> -3386248.8 | F78: =F12+F76 -> -11619 | G78: =G12+G76 -> -6805262.5 | H78: =H12+H76 -> 4674485.6 | I78: =I12+I76 -> 11379261 | J78: =J12+J76 -> -9860980.4 | K78: =K12+K76 -> -9645039 | ... R78: =R12+R76 -> -52231423
R80: =+R78-'Balance 8 Columnas'!J118 -> 191.17647
B83: Distribución Remuneraciones | C83: 36260981 | D83: 0 | E83: 3466729 | F83: 3249093.5 | G83: 3569959.2 | H83: 6640432.4 | I83: 0 | J83: 4695061 | K83: 1699384.3 | L83: 1699384.3 | M83: 9529728.4 | R83: =+$C$83*R5 -> 0
A84: 3105101 | B84: REMUNERACIONES | C84: 33549150 | E84: 3207464.6 | F84: 3006105.2 | G84: 3302974.6 | H84: 6143817.9 | I84: 0 | J84: 4343934 | K84: 1572293.4 | L84: 1572293.4 | M84: 8817033.6
A85: 3105102 | B85: BONOS | C85: -1359336 | E85: -129959.24 | F85: -121800.61 | G85: -133829.09 | H85: -248933.66 | I85: 0 | J85: -176006.42 | K85: -63705.786 | L85: -63705.786 | M85: -357246.34
A86: 3105103 | B86: SEGURO DE CESANTIA | C86: 414120 | E86: 39591.919 | F86: 37106.404 | G86: 40770.864 | H86: 75837.327 | I86: 0 | J86: 53620.134 | K86: 19407.888 | L86: 19407.888 | M86: 108834.65
A87: 3105104 | B87: GRATIFICACION | C87: 1436130 | E87: 137301.13 | F87: 128681.59 | G87: 141389.6 | H87: 262996.86 | I87: 0 | J87: 185949.69 | K87: 67304.766 | L87: 67304.766 | M87: 377428.53
A88: 3105107 | B88: FINIQUITOS | C88: 634303 | E88: 60642.502 | F88: 56835.466 | G88: 62448.279 | H88: 116159.19 | I88: 0 | J88: 82129.364 | K88: 29726.846 | L88: 29726.846 | M88: 166700.82
A89: 3105108 | B89: ASIGNACION COLACION | C89: 608000 | E89: 58127.806 | F89: 54478.637 | G89: 59858.701 | H89: 111342.35 | I89: 0 | J89: 78723.659 | K89: 28494.146 | L89: 28494.146 | M89: 159788.14
A90: 3105109 | B90: ASIGNACION MOVILIZACION | C90: 608000 | E90: 58127.806 | F90: 54478.637 | G90: 59858.701 | H90: 111342.35 | I90: 0 | J90: 78723.659 | K90: 28494.146 | L90: 28494.146 | M90: 159788.14
A91: 3105110 | B91: MUTUAL DE SEGURIDAD | C91: 122247 | E91: 11687.418 | F91: 10953.701 | G91: 12035.438 | H91: 22386.955 | I91: 0 | J91: 15828.505 | K91: 5729.151 | L91: 5729.151 | M91: 32127.666
A92: 3105111 | B92: SEGURO INVALIDEZ (AFP) | C92: 243178 | E92: 23249.019 | F92: 21789.484 | G92: 23941.314 | H92: 44532.912 | I92: 0 | J92: 31486.615 | K92: 11396.627 | L92: 11396.627 | M92: 63909.476
A93: 3105116 | B93: UNIFORMES | C93: 0 | E93: 0 | F93: 0 | G93: 0 | H93: 0 | I93: 0 | J93: 0 | K93: 0 | L93: 0 | M93: 0
A94: 3105118 | B94: ATENCIONES AL PERSONAL | C94: 0 | E94: 0 | F94: 0 | G94: 0 | H94: 0 | I94: 0 | J94: 0 | K94: 0 | L94: 0 | M94: 0
A95: 3105119 | B95: VACACIONES | C95: 5189 | E95: 496.09405 | F95: 464.95008 | G95: 510.86644 | H95: 950.2557 | I95: 0 | J95: 671.87018 | K95: 243.18441 | L95: 243.18441 | M95: 1363.7182

Sheet ER Centro de Costo aperturado
D1: 300 | E1: 130 | F1: 140 | G1: 150 | H1: 100 | I1: 2 | J1: 170 | K1: 180 | L1: 185 | M1: 500 | N1: 190 | O1: 195 | P1: 200 | Q1: 210
B2: Estado de Resultado por Centro de Costo
B3: =+'Estado de Resultados'!B3 -> Para el período comprendido entre el 01-01-2026 hasta el 31/01/2026
C5: FLEXI | D5: =+D8/$R$8 -> 0 | E5: =+E8/$R$8 -> 0.13267171 | F5: =+F8/$R$8 -> 0 | G5: =+G8/$R$8 -> 0.092921499 | H5: =+H8/$R$8 -> 0.11890004 | J5: =+J8/$R$8 -> 0.18393545 | K5: =+K8/$R$8 -> 0.088426071 | L5: =+L8/$R$8 -> 0 | M5: =+M8/$R$8 -> 0 | N5: =+N8/$R$8 -> 0.14955484 | O5: =+O8/$R$8 -> 0.070423486 | P5: =+P8/$R$8 -> 0.067144825 | Q5: =+Q8/$R$8 -> 0.096022088
B6: N° CUENTA | C6: NOMBRE CUENTA | D6: CEDIS CHILE | E6: EGAÑA | F6: VESPUCIO | G6: TREBOL | H6: ONLINE | I6: ADMINISTRACION | J6: COSTANERA CENTER | K6: FLORIDA CENTER | L6: CONCEPCION CENTRO | M6: DEPARTAMENTAL | N6: SANTIAGO CENTRO | O6: MAULE TALCA | P6: PLAZA NORTE | Q6: PLAZA OESTE | R6: TOTAL
B8: 3.1.01.101 | C8: VENTAS CON BOLETA | D8: =SUM(D9:D10) -> 0 | E8: =SUM(E9:E10) -> 29741079 | F8: =SUM(F9:F10) -> 0 | G8: =SUM(G9:G10) -> 20830255 | H8: =SUM(H9:H10) -> 26653877 | I8: =SUM(I9:I10) -> 0 | J8: =SUM(J9:J10) -> 41232894 | K8: =SUM(K9:K10) -> 19822513 | M8: =SUM(M9:M10) -> 0 | N8: =SUM(N9:N10) -> 33525777 | O8: =SUM(O9:O10) -> 15786866 | P8: =SUM(P9:P10) -> 15051887 | Q8: =SUM(Q9:Q10) -> 21525316 | R8: =SUM(D8:Q8) -> 2.2417046e+08
C9: ACCESORIOS | E9: 438302.52 | G9: 622984.03 | H9: 59075.63 | J9: 791978.15 | K9: 394328.57 | N9: 439117.65 | O9: 208371.43 | P9: 403824.37 | Q9: 507118.49 | R9: =SUM(E9:Q9) -> 3865100.8
C10: CALZADO | E10: 29302776 | G10: 20207271 | H10: 26594801 | J10: 40440916 | K10: 19428185 | N10: 33086660 | O10: 15578494 | P10: 14648062 | Q10: 21018197 | R10: =SUM(E10:Q10) -> 2.2030536e+08
B11: 3.1.02.101 | C11: COSTO DE VENTAS | E11: -16286827 | F11: 0 | G11: -10948521 | H11: -17063296 | J11: -22321825 | K11: -10656695 | N11: -18278478 | O11: -8650021 | P11: -8315284 | Q11: -12089897 | R11: =SUM(D11:Q11) -> -124610844
B12: Resultado por Centro de Beneficio | D12: =+D8+D11 -> 0 | E12: =+E8+E11 -> 13454252 | F12: =+F8+F11 -> 0 | G12: =+G8+G11 -> 9881734.5 | H12: =+H8+H11 -> 9590580.6 | I12: =+I8+I11 -> 0 | J12: =+J8+J11 -> 18911069 | K12: =+K8+K11 -> 9165818.4 | M12: =+M8+M11 -> 0 | N12: =+N8+N11 -> 15247299 | O12: =+O8+O11 -> 7136844.5 | P12: =+P8+P11 -> 6736602.6 | Q12: =+Q8+Q11 -> 9435419 | R12: =+R8+R11 -> 99559620 | S12: OK
C14: TAMARIS | D14: =+D17/$R$17 -> 0 | E14: =+E17/$R$17 -> 0.14363779 | F14: =+F17/$R$17 -> 0 | G14: =+G17/$R$17 -> 0.10164352 | H14: =+H17/$R$17 -> 0.037241118 | J14: =+J17/$R$17 -> 0.27732215 | K14: =+K17/$R$17 -> 0.052538301 | L14: =+L17/$R$17 -> 0 | M14: =+M17/$R$17 -> 0 | N14: =+N17/$R$17 -> 0.10535764 | O14: =+O17/$R$17 -> 0.050934272 | P14: =+P17/$R$17 -> 0.077745631 | Q14: =+Q17/$R$17 -> 0.15357958
B15: N° CUENTA | C15: NOMBRE CUENTA | D15: CEDIS CHILE | E15: EGAÑA | F15: VESPUCIO | G15: TREBOL | H15: ONLINE | I15: ADMINISTRACION | J15: COSTANERA CENTER | K15: FLORIDA CENTER | L15: CONCEPCION CENTRO | M15: DEPARTAMENTAL | N15: SANTIAGO CENTRO | O15: MAULE TALCA | P15: PLAZA NORTE | Q15: PLAZA OESTE | R15: TOTAL
B17: 3.1.01.101 | C17: VENTAS CON BOLETA | D17: =SUM(D18:D19) -> 0 | E17: =SUM(E18:E19) -> 3223809.2 | F17: =SUM(F18:F19) -> 0 | G17: =SUM(G18:G19) -> 2281289.1 | H17: =SUM(H18:H19) -> 835840.34 | I17: =SUM(I18:I19) -> 0 | J17: =SUM(J18:J19) -> 6224223.5 | K17: =SUM(K18:K19) -> 1179170.6 | M17: =SUM(M18:M19) -> 0 | N17: =SUM(N18:N19) -> 2364648.7 | O17: =SUM(O18:O19) -> 1143169.7 | P17: =SUM(P18:P19) -> 1744924.4 | Q17: =SUM(Q18:Q19) -> 3446942.9 | R17: =SUM(D17:Q17) -> 22444018
C18: ACCESORIOS | R18: =SUM(E18:Q18) -> 0
C19: CALZADO | E19: 3223809.2 | F19: 0 | G19: 2281289.1 | H19: 835840.34 | J19: 6224223.5 | K19: 1179170.6 | N19: 2364648.7 | O19: 1143169.7 | P19: 1744924.4 | Q19: 3446942.9 | R19: =SUM(E19:Q19) -> 22444018
B20: 3.1.02.101 | C20: COSTO DE VENTAS | E20: -1506504 | F20: 0 | G20: -995836 | H20: -382558 | J20: -2889387 | K20: -533847 | N20: -1065192 | O20: -485141 | P20: -804536 | Q20: -1565226 | R20: =SUM(D20:Q20) -> -10228227
B21: Resultado por Centro de Beneficio | D21: =+D17+D20 -> 0 | E21: =+E17+E20 -> 1717305.2 | F21: =+F17+F20 -> 0 | G21: =+G17+G20 -> 1285453.1 | H21: =+H17+H20 -> 453282.34 | I21: =+I17+I20 -> 0 | J21: =+J17+J20 -> 3334836.5 | K21: =+K17+K20 -> 645323.59 | M21: =+M17+M20 -> 0 | N21: =+N17+N20 -> 1299456.7 | O21: =+O17+O20 -> 658028.75 | P21: =+P17+P20 -> 940388.37 | Q21: =+Q17+Q20 -> 1881716.9 | R21: =+R17+R20 -> 12215791 | S21: OK
B23: N° CUENTA | C23: NOMBRE CUENTA | D23: CEDIS CHILE | E23: EGAÑA | F23: VESPUCIO | G23: TREBOL | H23: ONLINE | I23: ADMINISTRACION | J23: COSTANERA CENTER | K23: FLORIDA CENTER | L23: CONCEPCION CENTRO | M23: DEPARTAMENTAL | N23: SANTIAGO CENTRO | O23: MAULE TALCA | P23: PLAZA NORTE | Q23: PLAZA OESTE | R23: TOTAL
B25: 3.1.01.300 | C25: OTROS INGRESOS | D25: 0 | E25: 0 | F25: 0 | G25: 0 | H25: 3751074 | I25: 0 | J25: 0 | K25: 0 | L25: 0 | M25: 0 | N25: 0 | O25: 0 | P25: 0 | Q25: 0 | R25: =SUM(D25:Q25) -> 3751074
B26: 3.1.02.102 | C26: COSTOS OPERATIVOS - FLETES INTERNOS | D26: -2164695 | E26: 21780 | F26: 0 | G26: 21780 | H26: 150000 | I26: 0 | J26: 21780 | K26: 21780 | L26: 0 | M26: 0 | N26: 21780 | O26: 21780 | P26: 21780 | Q26: 21780 | R26: =SUM(D26:Q26) -> -1840455
B27: 3.1.02.104 | C27: COMISIÓN - CANAL DIGITAL | D27: 0 | E27: 0 | F27: 0 | G27: 0 | H27: -3004368 | I27: 0 | J27: 0 | K27: 0 | L27: 0 | M27: 304544 | N27: 0 | O27: 0 | P27: 0 | Q27: 0 | R27: =SUM(D27:Q27) -> -2699824
B28: 3.1.02.105 | C28: FLETES - CANAL DIGITAL | D28: 0 | E28: 0 | F28: 0 | G28: 0 | H28: 2066127 | I28: 0 | J28: 0 | K28: 0 | L28: 0 | M28: -2866174 | N28: 0 | O28: 0 | P28: 0 | Q28: 0 | R28: =SUM(D28:Q28) -> -800047
B29: 3.1.02.108 | C29: SERVICIOS - CANAL DIGITAL | D29: 0 | E29: 0 | F29: 0 | G29: 0 | H29: -129245 | I29: 0 | J29: 0 | K29: 0 | L29: 0 | M29: -1846777 | N29: 0 | O29: 0 | P29: 0 | Q29: 0 | R29: =SUM(D29:Q29) -> -1976022
B30: 3.1.02.109 | C30: DESCUENTOS GIFTCARD | D30: 0 | E30: 0 | F30: 0 | G30: 0 | H30: 0 | I30: 0 | J30: 0 | K30: 0 | L30: 0 | M30: 0 | N30: -44990 | O30: 0 | P30: 0 | Q30: 0 | R30: =SUM(D30:Q30) -> -44990
B31: 3.1.02.110 | C31: DESCUENTOS CLUB FLEXI | D31: 0 | E31: 0 | F31: 0 | G31: 0 | H31: 0 | I31: 0 | J31: -14372 | K31: -27334 | L31: 0 | M31: 0 | N31: -4801 | O31: 0 | P31: 0 | Q31: 0 | R31: =SUM(D31:Q31) -> -46507
B32: 3.1.05.101 | C32: REMUNERACIONES | D32: 0 | E32: -5471370 | F32: 0 | G32: -5105142 | H32: -3360231 | I32: -589781 | J32: -6163578 | K32: -4432782 | L32: 0 | M32: -1429576 | N32: -5819291 | O32: -3991543 | P32: -4129167 | Q32: -4624690 | R32: =SUM(D32:Q32) -> -45117151
B33: 3.1.05.102 | C33: BONOS | D33: 0 | E33: -273846 | F33: 0 | G33: -183785 | H33: -127312 | I33: 0 | J33: -295071 | K33: -167527 | L33: 0 | M33: 0 | N33: -668574 | O33: -17293 | P33: 805918 | Q33: -803000 | R33: =SUM(D33:Q33) -> -1730490
B34: 3.1.05.103 | C34: SEGURO DE CESANTIA | D34: 0 | E34: -190943 | F34: 0 | G34: -203449 | H34: -92175 | I34: -44143 | J34: -226386 | K34: -163670 | L34: 0 | M34: -34952 | N34: -219642 | O34: -149355 | P34: -149071 | Q34: -181297 | R34: =SUM(D34:Q34) -> -1655083
B35: 3.1.05.104 | C35: GRATIFICACION | D35: 0 | E35: -1260847 | F35: 0 | G35: -1345486 | H35: -460102 | I35: -215308 | J35: -1419780 | K35: -1136975 | L35: 0 | M35: -147415 | N35: -1338001 | O35: -1000642 | P35: -1039174 | Q35: -1220422 | R35: =SUM(D35:Q35) -> -10584152
B36: 3.1.05.107 | C36: FINIQUITOS | D36: 0 | E36: 0 | F36: 0 | G36: 0 | H36: 0 | I36: -4000 | J36: 0 | K36: 0 | L36: 0 | M36: 0 | N36: 0 | O36: 0 | P36: 0 | Q36: 0 | R36: =SUM(D36:Q36) -> -4000
... B78: 3.2.08.105 | C78: INTERESES POR PRESTAMO | D78: 0 | E78: 0 | F78: 0 | G78: 0 | H78: 0 | I78: 0 | J78: -8446 | K78: 0 | L78: 0 | M78: 0 | N78: 0 | O78: 0 | P78: -4101 | Q78: -6758 | R78: =SUM(D78:Q78) -> -19305
B79: 3.2.08.114 | C79: INTERESES DEVENGADOS FONDOS MU | D79: 0 | E79: 0 | F79: 0 | G79: 0 | H79: 0 | I79: 0 | J79: 0 | K79: 0 | L79: 0 | M79: 0 | N79: 0 | O79: 0 | R79: =SUM(D79:Q79) -> 0
B80: 3.2.08.116 | C80: INTERES GANADO POR DEPOSITO A PLAZO PESOS | D80: 0 | E80: 0 | F80: 0 | G80: 0 | H80: 0 | I80: 5791 | J80: 0 | K80: 0 | L80: 0 | M80: 0 | N80: 0 | O80: 0 | P80: 0 | Q80: 0 | R80: =SUM(D80:Q80) -> 5791
B81: 3.2.08.117 | C81: INTERES GANADO FONDOS MUTUOS | D81: 0 | E81: 0 | F81: 0 | G81: 0 | H81: 0 | I81: 0 | J81: 0 | K81: 0 | L81: 0 | M81: 0 | N81: 0 | O81: 0 | R81: =SUM(D81:Q81) -> 0
B82: 3.2.11.158 | C82: DIFERENCIA DE CAMBIO | H82: 0 | I82: 24026172 | M82: 0 | R82: =SUM(D82:Q82) -> 24026172
B83: 3.2.13.101 | C83: CORRECCION MONETARIA ACTIVOS | D83: 0 | E83: 0 | F83: 0 | G83: 0 | H83: 0 | I83: -623797 | J83: 0 | K83: 0 | L83: 0 | M83: 0 | N83: 0 | O83: 0 | P83: 0 | Q83: 0 | R83: =SUM(D83:Q83) -> -623797
B84: 3.2.13.109 | C84: AJUSTE REDONDEO AUTO | D84: 0 | E84: 0 | F84: 0 | G84: 0 | H84: 0 | I84: -34 | J84: 0 | K84: 0 | L84: 0 | M84: 0 | N84: 0 | O84: 0 | P84: 0 | Q84: 0 | R84: =SUM(D84:Q84) -> -34
B85: Resultado por Centro de Costo | D85: =SUM(D25:D84) -> -8834134 | E85: =SUM(E25:E84) -> -18557806 | F85: =SUM(F25:F84) -> -11619 | G85: =SUM(G25:G84) -> -17972450 | H85: =SUM(H25:H84) -> -5369377 | I85: =SUM(I25:I84) -> 11379261 | J85: =SUM(J25:J84) -> -32106886 | K85: =SUM(K25:K84) -> -19456181 | ... Q85: =SUM(Q25:Q84) -> -18312604 | R85: =SUM(D85:Q85) -> -164006834
B87: Resultado por Centro de Costo | D87: =D21+D85+D12 -> -8834134 | E87: =E21+E85+E12 -> -3386248.8 | F87: =F21+F85+F12 -> -11619 | G87: =G21+G85+G12 -> -6805262.5 | H87: =H21+H85+H12 -> 4674486 | I87: =I21+I85+I12 -> 11379261 | J87: =J21+J85+J12 -> -9860980.4 | K87: =K21+K85+K12 -> -9645039 | ... R87: =R21+R85+R12 -> -52231422
R89: =+R87-'Balance 8 Columnas'!J118 -> 191.5126
B92: Distribución Remuneraciones | C92: 36260981 | D92: 0 | E92: 3466729 | F92: 3249093.5 | G92: 3569959.2 | H92: 6640432.4 | I92: 0 | J92: 4695061 | K92: 1699384.3 | M92: 9529728.4 | R92: =+$C$92*R14 -> 0
A93: 3105101 | B93: REMUNERACIONES | C93: 33549150 | E93: 3207464.6 | F93: 3006105.2 | G93: 3302974.6 | H93: 6143817.9 | I93: 0 | J93: 4343934 | K93: 1572293.4 | M93: 8817033.6
A94: 3105102 | B94: BONOS | C94: -1359336 | E94: -129959.24 | F94: -121800.61 | G94: -133829.09 | H94: -248933.66 | I94: 0 | J94: -176006.42 | K94: -63705.786 | M94: -357246.34
A95: 3105103 | B95: SEGURO DE CESANTIA | C95: 414120 | E95: 39591.919 | F95: 37106.404 | G95: 40770.864 | H95: 75837.327 | I95: 0 | J95: 53620.134 | K95: 19407.888 | M95: 108834.65
A96: 3105104 | B96: GRATIFICACION | C96: 1436130 | E96: 137301.13 | F96: 128681.59 | G96: 141389.6 | H96: 262996.86 | I96: 0 | J96: 185949.69 | K96: 67304.766 | M96: 377428.53
A97: 3105107 | B97: FINIQUITOS | C97: 634303 | E97: 60642.502 | F97: 56835.466 | G97: 62448.279 | H97: 116159.19 | I97: 0 | J97: 82129.364 | K97: 29726.846 | M97: 166700.82
A98: 3105108 | B98: ASIGNACION COLACION | C98: 608000 | E98: 58127.806 | F98: 54478.637 | G98: 59858.701 | H98: 111342.35 | I98: 0 | J98: 78723.659 | K98: 28494.146 | M98: 159788.14
A99: 3105109 | B99: ASIGNACION MOVILIZACION | C99: 608000 | E99: 58127.806 | F99: 54478.637 | G99: 59858.701 | H99: 111342.35 | I99: 0 | J99: 78723.659 | K99: 28494.146 | M99: 159788.14
A100: 3105110 | B100: MUTUAL DE SEGURIDAD | C100: 122247 | E100: 11687.418 | F100: 10953.701 | G100: 12035.438 | H100: 22386.955 | I100: 0 | J100: 15828.505 | K100: 5729.151 | M100: 32127.666
A101: 3105111 | B101: SEGURO INVALIDEZ (AFP) | C101: 243178 | E101: 23249.019 | F101: 21789.484 | G101: 23941.314 | H101: 44532.912 | I101: 0 | J101: 31486.615 | K101: 11396.627 | M101: 63909.476
A102: 3105116 | B102: UNIFORMES | C102: 0 | E102: 0 | F102: 0 | G102: 0 | H102: 0 | I102: 0 | J102: 0 | K102: 0 | M102: 0
A103: 3105118 | B103: ATENCIONES AL PERSONAL | C103: 0 | E103: 0 | F103: 0 | G103: 0 | H103: 0 | I103: 0 | J103: 0 | K103: 0 | M103: 0
A104: 3105119 | B104: VACACIONES | C104: 5189 | E104: 496.09405 | F104: 464.95008 | G104: 510.86644 | H104: 950.2557 | I104: 0 | J104: 671.87018 | K104: 243.18441 | M104: 1363.7182

Sheet Patrimonio
B1: Flexi Chile Spa
B2: Cuadro Patromonial
B3: =+'Balance 8 Columnas'!B4:K4 -> Al 31 de enero de 2026
B5: PATRIMONIO
B6: Movimientos de patrimonio durante el ejercicio 2026 - Moneda Local $
B7: Detalle | C7: Capital | D7: Aportes por Capitalizar | E7: Aportes por Enterar | F7: Resultados Acumulados | G7: Retiros | H7: Resultado del Periodo | I7: Totales
B10: Saldos al 31/12/2025 | C10: 4547054500 | D10: 0 | E10: 0 | F10: -2294052799 | G10: 0 | H10: -848054041 | I10: =SUM(C10:H10) -> 1404947660
B11: Distribución resultado ejercicio anterior | D11: 0 | F11: =+H10 -> -848054041 | G11: 0 | H11: =-H10 -> 848054041 | I11: =SUM(C11:H11) -> 0
B12: Aporte Capital 02-01-2025 | C12: 1223614367 | I12: =SUM(C12:H12) -> 1223614367
B13: Resultado del período | D13: 0 | F13: 0 | H13: =+-'Balance 8 Columnas'!N118 -> -52231614 | I13: =SUM(C13:H13) -> -52231614
B14: Saldos | C14: =ROUND(SUM(C10:C13),0) -> 5770668867 | D14: =ROUND(SUM(D10:D13),0) -> 0 | E14: =ROUND(SUM(E10:E13),0) -> 0 | F14: =ROUND(SUM(F10:F13),0) -> -3142106840 | G14: =ROUND(SUM(G10:G13),0) -> 0 | H14: =ROUND(SUM(H10:H13),0) -> -52231614 | I14: =ROUND(SUM(I10:I13),0) -> 2576330413
C16: =C14+'Balance 8 Columnas'!N60 -> 0 | F16: =+F14+'Balance 8 Columnas'!N61 -> -1
B17: Movimientos de patrimonio durante el ejercicio 2025 - Moneda Dólar
B18: Detalle | C18: Capital | D18: Aportes por Capitalizar | E18: Aportes por Enterar | F18: Resultados Acumulados | G18: Retiros | H18: Resultado del Periodo | I18: Totales
B21: Saldos al 31/12/2025 USD 5.075.000 | C21: 5075000 | D21: 0 | E21: 0 | F21: -2544044 | G21: 0 | H21: -907553 | I21: =SUM(C21:H21) -> 1623403
B22: Distribución resultado ejercicio anterior | D22: 0 | F22: =+H21 -> -907553 | G22: 0 | H22: =-H21 -> 907553 | I22: =SUM(C22:H22) -> 0
B23: Aporte Capital 02-01-2025 | C23: 1348885.4 | I23: =SUM(C23:H23) -> 1348885.4
B24: Resultado del período | D24: 0 | F24: 0 | H24: =H13/865.1 -> -60376.389 | I24: =SUM(C24:H24) -> -60376.389
B25: Saldos | C25: =ROUND(SUM(C21:C24),0) -> 6423885 | D25: =ROUND(SUM(D21:D24),0) -> 0 | E25: =ROUND(SUM(E21:E24),0) -> 0 | F25: =ROUND(SUM(F21:F24),0) -> -3451597 | G25: =ROUND(SUM(G21:G24),0) -> 0 | H25: =ROUND(SUM(H21:H24),0) -> -60376 | I25: =ROUND(SUM(I21:I24),0) -> 2911912
B29: Socios | C29: acciones | D29: % | F29: Monto USD | H29: Monto CLP
B30: Grupo Calzado Flexi, S.A.P.I de C.V | C30: 100 | D30: 2.08 | F30: 100000 | H30: 75000000
B31: Flexi Retail International, S.L., | C31: 4697 | D31: 97.92 | F31: 6323885 | H31: =5770668867-75000000 -> 5695668867
B32: Totales | C32: =SUM(C30:C31) -> 4797 | D32: =SUM(D30:D31) -> 100 | E32: =SUM(E30:E31) -> 0 | F32: =SUM(F30:F31) -> 6423885 | G32: =SUM(G30:G31) -> 0 | H32: =SUM(H30:H31) -> 5770668867

Sheet Cajas y Bancos
A1: Balance 8 Columnas'!A1 | B1: Flexi Chile Spa | I1: =+C12-'Balance Clasificado'!D10 -> 0.40250707
B2: Análisis y Detalle de Cuentas de Cajas y Bancos
B3: =+Patrimonio!B3 -> Al 31 de enero de 2026
F4: Volver
B5: CAJAS Y BANCOS - Agrupación:
B6: Cuentas | C6: Monto MN $
B7: Efectivo en transito | C7: =+E19 -> 74105055
B8: Fondos Fijos | C8: =+F33 -> 422630
B9: Bancos Cuenta Corriente $ | C9: =F52 -> 440582927
B10: Bancos Cuenta Corriente USD$ | C10: =+'Balance 8 Columnas'!H21 -> 371961813
B11: Deposito a Plazo | C11: =+H77 -> 4941276.4
B12: Total Cajas y Bancos | C12: =SUM(C7:C11) -> 8.920137e+08
B14: CAJAS Y BANCOS - Detalle:
B16: EFECTIVO EN TRANSITO
B17: Nombre Cuenta | C17: Nombre Titular | E17: Importe MN
B18: Efectivo en transito | C18: periodo de cierre | E18: 74105055
C19: Total | E19: =+E18 -> 74105055 | F19: ok
B21: Fondos Fijos
B22: Fecha | C22: Detalle | F22: Valor Actual
B23: 46053 | C23: Fondo Fijo Plaza Egaña | F23: =53286+46624-58308 -> 41602 | G23: OK
B24: =+B23 -> 46053 | C24: Fondo Fijo Vespucio | F24: 85990 | G24: OK
B25: =+B24 -> 46053 | C25: Fondo Fijo Trebol | F25: 2682 | G25: OK
B26: =+B25 -> 46053 | C26: Fondo Fijo Costanera Center | F26: -8130 | G26: OK
B27: =+B26 -> 46053 | C27: Fondo Fijo Florida Center | F27: 83000 | G27: OK
B28: =+B27 -> 46053 | C28: Fondo Fijo Santiago Centro | F28: 39570 | G28: OK
B29: =+B27 -> 46053 | C29: Fondo Fijo Concepcion Centro | F29: 57490 | G29: OK
B30: =+B27 -> 46053 | C30: Fondo Fijo Talca | F30: 13306 | G30: OK
B31: =+B27 -> 46053 | C31: Fondo Fijo Plaza Norte | F31: 47120 | G31: OK
B32: =+B28 -> 46053 | C32: Fondo Fijo Plaza Oeste | F32: 60000 | G32: OK
B33: Saldo Según Balance | F33: =SUM(F23:F32) -> 422630 | G33: ok
B36: Banco Santander
B38: Saldo Según Cartola Bancaria | F38: 440582927 | G38: OK
B39: Banco Santander Pesos - Cta. Cte. 0-000-7776441-0
B40: Cheques Girados y No cobrados
B41: Fecha Emisión | C41: Numero Cheque | D41: Detalle | F41: Valor
D44: Total Cheques no cobrados | F44: =SUM(E42:E43)*-1 -> 0
C46: Saldo según Conciliación | F46: =SUM(F38:F45) -> 440582927 | G46: ok
C48: Saldo según balance | F48: =+'Balance 8 Columnas'!H20 -> 440582927
C50: Control | F50: =+F46-F48 -> 0
B52: Total Banco santander | F52: =+F48 -> 440582927 | G52: OK
B54: Banco Santander Dolar - Cta. Cte. 0-051-0048375-2
B55: Saldo Según Cartola Bancaria | F55: 429963.95
B56: Tipo de cambio al cierre | F56: =+'Balance 8 Columnas'!O8 -> 865.1
B57: Saldo en pesos | F57: =F55*F56 -> 3.7196181e+08 | G57: ok
B58: Cheques Girados y No cobrados | F58: =408613612-F57 -> 36651799
B59: Fecha Emisión | C59: Numero Cheque | D59: Detalle | F59: Valor
D62: Total Cheques no cobrados | F62: =SUM(E60:E61)*-1 -> 0
C64: Saldo según Conciliación | F64: =+F57-F62 -> 3.7196181e+08
C66: Saldo según balance | F66: =+'Balance 8 Columnas'!H21 -> 371961813
C68: Control | F68: =+F64-F66 -> 0.14500004
B70: Total Banco santander | F70: =+F66 -> 371961813 | G70: =3948882-F68 -> 3948881.9
B73: DEPOSITO A PLAZO
B74: DETALLE | C74: Fecha | D74: Valor de | E74: Tasa | F74: Plazo | G74: Int. Devengados | H74: Valor
D75: Inversión | H75: Actual
B76: DEPOSITO A PLAZO SANTANDER | C76: 46045 | D76: 4938639.5 | E76: 0.0021333 | F76: 8 | G76: 2633.8999 | H76: 4941273.4
B77: Saldo Según Balance | D77: =SUM(D76:D76) -> 4938639.5 | H77: =SUM(H76:H76)+3 -> 4941276.4 | I77: ok

Sheet Otros Act no Fin
B1: Flexi Chile Spa | G1: =+C8-'Balance Clasificado'!D11 -> -88703455
B2: Análisis y Detalle de Otros Activos No Financieros, Corriente
B3: =+'Cajas y Bancos'!B3 -> Al 31 de enero de 2026
B5: Otros Activos No Financieros, Corriente - Agrupación
B6: Cuentas | C6: Monto MN $
B7: GARANTIAS OTORGADAS | C7: 0
B8: TOTAL ACTIVOS FINANCIEROS CORRIENTES | C8: =SUM(C7:C7) -> 0
B10: Otros Activos No Financieros, Corriente - Detalle
B12: GARANTIAS OTORGADAS
B13: DETALLE | C13: Fecha | D13: Valor Actual
B14: BOLETA DE GARANTIA - Plaza Egaña | C14: 44176 | D14: 13164563
B15: BOLETA DE GARANTIA - Plaza el Trebol | C15: 44176 | D15: 11854972
B16: BOLETA DE GARANTIA - Plaza Vespucio | C16: 44176 | D16: 10592505
B17: BOLETA DE GARANTIA - Arauco Maipu | C17: 44176 | D17: 10250999
B18: BOLETA DE GARANTIA - Plaza Los Dominicos | C18: 44176 | D18: 2264005
B19: BOLETA DE GARANTIA - Costanera Center | C19: 44392 | D19: 22306718
B20: BOLETA DE GARANTIA - Costanera Center | C20: 44392 | D20: 9814956
B21: Saldo Según Balance | D21: =SUM(D14:D20) -> 80248718

Sheet Derechos de arrendamiento
A1: Balance 8 Columnas'!A1 | B1: Flexi Chile Spa | H1: =+C9-'Balance Clasificado'!D11 -> 0
B2: Análisis y Detalle de Derechos de arrendamiento
B3: =+Carátula!A9 -> Al 31 de enero de 2026
B5: Derechos de arrendamiento - Agrupación
B6: Cuentas | C6: Monto MN $
B7: GASTOS PAGADOS POR ANTICIPADO | C7: =+D331 -> 31375083
B8: GARANTIAS ARRIENDO | C8: =$D$344 -> 57328372
B9: TOTAL Derechos de arrendamiento | C9: =SUM(C7:C8) -> 88703455
B11: Derechos de arrendamiento - Detalle
B13: GASTOS PAGADOS POR ANTICIPADO
B14: DETALLE | D14: Valor Actual
B15: VMM COSTANERA CENTER | D15: 16213165
B16: VMM COSTANERA CENTER | C16: 44473 | D16: 5765894
B17: *01.10.2021-01.10.2021-Recargo VMM Costanera Center | C17: 44505 | D17: 16437082
B18: *01.11.2021-01.11.2021-Recargo VMM Florida Center | C18: 44501 | D18: 10941199
B19: *01.10.2021-01.10.2021-Fondo Inicial Pub Costanera Center | C19: 44516 | D19: 7583329
B20: *01.11.2021-01.11.2021-Fondo Inicial Pub Florida Center | C20: 44516 | D20: 3883398
B21: Amortización VMN Costanera Center 1/60 | C21: 44500 | D21: =-(D15+D16)/60 -> -366317.65
B22: Amortización VMN Costanera Center 2/60 | C22: 44530 | D22: =-(D16+D17+D15+D19)/60 -> -766657.83
B23: Amortización VMN Florida Center 1/60 | C23: 44530 | D23: =-(D18+D20)/60 -> -247076.62
B24: Recargo VMM Florida Center | C24: 44561 | D24: 11088922
B25: *01.12.2021-01.12.2021-Fondo Inicial Pub Florida Center | C25: 44561 | D25: 3911925
B26: *01.12.2021-01.12.2021-Aporte Mensual PU Florida Center | C26: 44561 | D26: 193748
B27: Amortización VMN Costanera Center 3/60 | C27: 44530 | D27: -766657.83
B28: Amortización VMN Florida Center 2/60 | C28: 44530 | D28: =-SUM(D18,D20,D24,D25,D26)/60 -> -500319.87
B29: Amortización VMN Costanera Center 4/60 | C29: 44592 | D29: -766658
B30: Amortización VMN Florida Center 3/60 | C30: 44592 | D30: -500319
B31: *04.01.2022-04.01.2022-Recargo VMM Florida Center | C31: 44599 | D31: =11256790-2047063 -> 9209727
B32: *04.01.2022-04.01.2022-Fondo Inicial Pub Florida Center | C32: 44599 | D32: =3971145-195032 -> 3776113
B33: Amortización VMN Costanera Center 5/60 | C33: 44620 | D33: -766658
B34: Amortización VMN Florida Center 4/60 | C34: 44620 | D34: =-500319.866666667+((-D31+D32)/60) -> -590880.1
B35: Amortización VMN Costanera Center 6/60 | C35: 44651 | D35: -766657.83
B36: Amortización VMN Florida Center 5/60 | C36: 44651 | D36: -590880
B37: Amortización VMN Costanera Center 7/60 | C37: 44681 | D37: -766657.83
B38: Amortización VMN Florida Center 6/60 | C38: 44681 | D38: -590880
B39: Amortización VMN Costanera Center 8/60 | C39: 44712 | D39: -766657.83
B40: Amortización VMN Florida Center 7/60 | C40: 44712 | D40: -590880
B41: Amortización VMN Costanera Center 9/60 | C41: 44742 | D41: -766657.83
B42: Amortización VMN Florida Center 8/60 | C42: 44742 | D42: -590880
B43: Amortización VMN Costanera Center 10/60 | C43: 44773 | D43: -766657.83
B44: Amortización VMN Florida Center 9/60 | C44: 44773 | D44: -590880
B45: Amortización VMN Costanera Center 11/60 | C45: 44804 | D45: -766657.83
B46: Amortización VMN Florida Center 10/60 | C46: 44804 | D46: -590880
... B66: Amortización VMN Florida Center 18/60 | C66: 45046 | D66: -590879
B67: Amortización VMN Concepcion Centro 1/60 | C67: 45046 | D67: =-SUM(D61:D64)/60 -> -134480.82
B68: Amortización VMN Costanera Center 20/60 | C68: 45077 | D68: -766657
B69: Amortización VMN Florida Center 19/60 | C69: 45077 | D69: -590879
B70: Amortización VMN Concepcion Centro 2/60 | C70: 45077 | D70: -134481
B71: Amortización VMN Costanera Center 21/60 | C71: 45107 | D71: -766657
B72: Amortización VMN Florida Center 20/60 | C72: 45107 | D72: -590879
B73: Amortización VMN Concepcion Centro 3/60 | C73: 45107 | D73: -134481
B74: Amortización VMN Costanera Center 22/60 | C74: 45138 | D74: -766657
B75: Amortización VMN Florida Center 21/60 | C75: 45138 | D75: -590879
B76: Amortización VMN Concepcion Centro 4/60 | C76: 45138 | D76: -134481
B77: Amortización VMN Costanera Center 23/60 | C77: 45169 | D77: -766657
B78: Amortización VMN Florida Center 22/60 | C78: 45169 | D78: -590879
B79: Amortización VMN Concepcion Centro 5/60 | C79: 45169 | D79: -134481
... B127: Amortización VMN Concepcion Centro 21/60 | C127: 45657 | D127: -134481
B128: Saldo Según Balance | D128: =SUM(D15:D127) -> 42821461
B130: DETALLE | D130: Valor Actual
B131: Saldo Inicial | C131: 46022 | D131: 42821461
B132: Amortización VMN Costanera Center 40/60 | C132: 45688 | D132: -766657
B133: Amortización VMN Florida Center 39/60 | C133: 45688 | D133: -590879
B134: Amortización VMN Concepcion Centro 22/60 | C134: 45688 | D134: -134481
B135: Amortización VMN Costanera Center 41/60 | C135: 45716 | D135: -766657
B136: Amortización VMN Florida Center 40/60 | C136: 45716 | D136: -590879
B137: Amortización VMN Concepcion Centro 23/60 | C137: 45716 | D137: -134481
B138: Amortización VMN Costanera Center 42/60 | C138: 45747 | D138: -766657
B139: Amortización VMN Florida Center 41/60 | C139: 45747 | D139: -590879
B140: Amortización VMN Concepcion Centro 24/60 | C140: 45747 | D140: -134481
B141: Amortización VMN Costanera Center 43/60 | C141: 45777 | D141: -766657
B142: Amortización VMN Florida Center 42/60 | C142: 45777 | D142: -590879
... B170: Amortización VMN Concepcion Centro 60/60 | C170: 46053 | D170: -3630987
B172: Bolsas impresas | C172: 45987 | D172: =2407200-13600 -> 2393600
B173: Amortización bolsas impresas 1/12 (locales, mayorista y online) | C173: 45991 | D173: -199467
B174: Amortización bolsas impresas 2/12 (locales, mayorista y online) | C174: 46022 | D174: -199467
B175: Amortización bolsas impresas 3/12 (locales, mayorista y online) | C175: 46053 | D175: -199467
B177: Bolsas impresas | C177: 46038 | D177: 5312409
B178: Amortización bolsas impresas 1/12 (locales, mayorista y online) | C178: 46053 | D178: -442701
B180: Seguros HDI Resp C. | C180: 46053
B181: Amortización SEGURO Resp. C. Cuota 1/12 Cedis | C181: 46053
B182: Amortización SEGURO Resp. C. Cuota 1/12 Plaza Egaña | C182: 46053
B183: Amortización SEGURO Resp. C. Cuota 1/12 Plaza Vespucio | C183: 46053
B184: Amortización SEGURO Resp. C. Cuota 1/12 Trebol | C184: 46053
B185: Amortización SEGURO Resp. C. Cuota 1/12 Costanera Center | C185: 46053
B186: Amortización SEGURO Resp. C. Cuota 1/12 Florida Center | C186: 46053
B187: Amortización SEGURO Resp. C. Cuota 1/12 Estado | C187: 46053
B188: Amortización SEGURO Resp. C. Cuota 1/12 Talca | C188: 46053
B189: Amortización SEGURO Resp. C. Cuota 1/12 Plaza Norte | C189: 46053
B190: Amortización SEGURO Resp. C. Cuota 1/12 Plaza Oeste | C190: 46053
B193: Seguros HDI | C193: 45747 | D193: =9225744-542936-721849 -> 7960959
B194: Amortización SEGURO Cuota 1/12 Cedis | C194: 45747 | D194: -226385
B195: Amortización SEGURO Cuota 1/12 Plaza Egaña | C195: 45747 | D195: -47536
B196: Amortización SEGURO Cuota 1/12 Plaza Vespucio | C196: 45747 | D196: -42728
B197: Amortización SEGURO Cuota 1/12 Trebol | C197: 45747 | D197: -46439
B198: Amortización SEGURO Cuota 1/12 Costanera Center | C198: 45747 | D198: -44696
B199: Amortización SEGURO Cuota 1/12 Florida Center | C199: 45747 | D199: -40307
B200: Amortización SEGURO Cuota 1/12 Estado | C200: 45747 | D200: -44599
B201: Amortización SEGURO Cuota 1/12 Concepcion Centro | C201: 45747 | D201: -35499
B202: Amortización SEGURO Cuota 1/12 Talca | C202: 45747 | D202: -41685
...

Sheet Deudores Diversos
A1: Balance 8 Columnas'!A1 | B1: Flexi Chile Spa | H1: =+D16-'Balance Clasificado'!D14 -> 0
B2: Análisis y Detalle de Deudores Diversos
B3: =+Carátula!A9 -> Al 31 de enero de 2026
B6: DEUDORES DIVERSOS - Agrupación:
B7: Cuentas | D7: Monto
B8: 1104102 | C8: CLIENTES BOLETAS | D8: =+E23 -> -3158489
B9: 1104105 | C9: TRANSBANK POR COBRAR TC | D9: =+E28 -> 54573495
B10: 1104106 | C10: TRANSBANK POR COBRAR TD | D10: =+E32 -> 71836904
B11: 1104108 | C11: GIFTCARD | D11: =+E38 -> 480400
B12: 1104109 | C12: ECOMMERCE | D12: =+E43 -> 201859659
B13: 1104112 | C13: GETNET TC | D13: =+E48 -> 9764312
B14: 1104113 | C14: GETNET TD | D14: =+E53 -> 1531859
B15: 1104200 | C15: CUENTA POR COBRAR | D15: =+E60 -> 6734121
B16: TOTAL Deudores Diversos | D16: =SUM(D8:D15) -> 343622261
B18: DEUDORES DEUDORES DIVERSOS - Detalle:
B20: CLIENTES BOLETAS
B21: Nombre Cuenta | C21: Detalle/Fecha | E21: Importe MN
B22: Clientes Boletas | C22: Saldo al cierre | E22: -3158489
B23: CLIENTES BOLETAS Total | E23: =+E22 -> -3158489 | F23: ok
B25: TRANSBANK POR COBRAR TC
B26: Nombre Cuenta | C26: Detalle | E26: Importe MN
B27: TRANSBANK POR COBRAR TC | C27: al cierre | E27: 54573495
C28: Total | E28: =SUM(E27:E27) -> 54573495 | F28: ok
B30: TRANSBANK POR COBRAR TD
B31: Nombre Cuenta | C31: Nombre Titular | E31: Importe MN
B32: TRANSBANK POR COBRAR TD | C32: periodo cierre | E32: 71836904
C33: Total | E33: =+E32 -> 71836904 | F33: ok
B35: GIFTCARD
B36: Nombre Cuenta | C36: Detalle | E36: Importe MN
B37: Giftcard | C37: periodo Cierre | E37: 480400
C38: Total | E38: =SUM(E37:E37) -> 480400 | F38: ok
B40: ECOMMERCE
B41: Nombre Cuenta | C41: Detalle | E41: Importe MN
B42: Ecommerce | C42: periodo Cierre | E42: 201859659
C43: Total | E43: =SUM(E42:E42) -> 201859659 | F43: ok
B45: GETNET TC
B46: Nombre Cuenta | C46: Detalle | E46: Importe MN
B47: Tarjeta de credito | C47: periodo Cierre | E47: 9764312
C48: Total | E48: =SUM(E47:E47) -> 9764312 | F48: ok
B50: GETNET TD
B51: Nombre Cuenta | C51: Detalle | E51: Importe MN
B52: Tarjeta Debito / Prepago | C52: periodo Cierre | E52: 1531859
C53: Total | E53: =SUM(E52:E52) -> 1531859 | F53: ok
B55: CUENTAS POR COBRAR
B56: Nombre Cuenta | C56: Detalle | E56: Importe MN
B57: Juan Ataya | C57: Caso Juan Araya 5 cuotas 53.2 uf septiembre 2023 | E57: 18697201
B58: Juan Ataya | C58: Abono en mercado Libre marzo 2024 | E58: -10000000
B59: Juan Ataya | C59: primera cuota 53.2 uf marzo 2024 | E59: -1963080
E60: =SUM(E57:E59) -> 6734121 | F60: ok
J61: MERCADO LIBRE
H62: 53.2 UF PAGARE | J62: 5 CUOTAS
H63: BUSCRA CUOTA PAGADA

Sheet Pagos Anticipados
A1: Balance 8 Columnas'!A1 | B1: Flexi Chile Spa | H1: =+D13-'Balance Clasificado'!D13 -> 0
B2: Análisis y Detalle de Pagos Anticipados
B3: =+Carátula!A9 -> Al 31 de enero de 2026
B6: PAGOS ANTICIPADOS - Agrupación:
B7: Cuentas | D7: Monto
B8: 1104104 | C8: FONDOS POR RENDIR | D8: =+E26 -> 934351
B9: 1105302 | C9: ANTICIPOS SUELDOS | D9: =+E31 -> 0
B10: 1105403 | C10: ANTICIPO PROVEEDORES | D10: =+E47 -> 30795995
B11: 1105404 | C11: ANTICIPO HONORARIOS | D11: =+E52 -> 0
B12: 1105405 | C12: ANTICIPO AGENCIA DE ADUANAS | D12: =+E62 -> 884643
B13: TOTAL Pagos Anticipados | D13: =SUM(D8:D12) -> 32614989
B15: PAGOS ANTICIPADOS - Detalle:
B17: FONDOS POR RENDIR
B18: RUT | C18: Titular | D18: Fecha | E18: Importe MN
B19: 12.242.596-7 | C19: Raul | D19: 46053 | E19: =879186+141858-10400-868786 -> 141858
B20: 13.104.274-4 | C20: Fondo a Rendir Luis Castillo | D20: 45835 | E20: 25880
B21: 15.589.025-8 | C21: TABLET costanera | D21: 46001 | E21: 152990
B22: 16.089.318-4 | C22: FONDO A RENDIR sept | D22: 45930 | E22: =105349+212770+2787-54215+80000 -> 346691
B23: 16.089.318-5 | C23: FONDO A RENDIR NOV | D23: 45991 | E23: =295141+2311 -> 297452
B24: 16.783.966-6 | C24: PAGO FACTURA | D24: 46053 | E24: -56912
B25: 16.783.966-6 | C25: FXR CEDIS ENE26 | D25: 46053 | E25: =-119468+145860 -> 26392
B26: Fondos por Rendir Total | E26: =SUM(E19:E25) -> 934351 | F26: ok
B28: ANTICIPOS SUELDOS
B29: RUT | C29: Titular | D29: Fecha | E29: Importe MN
B31: Anticipo Honorarios Total | E31: =SUM(E30:E30) -> 0 | F31: ok
B33: ANTICIPO PROVEEDORES
B34: RUT | C34: Titular | D34: Fecha | E34: Importe MN
B35: 760965189 | C35: Arte Impreso | D35: 46050 | E35: 386750
B36: 172573584 | C36: ABRAHAM PINO factura solicitada | D36: 45499 | E36: 399839 | F36: =E36/1.19 -> 335999.16 | G36: factura solicitadafacturas seran emitidas en febrero
B37: 109805203 | C37: BAP CONSTRUCTORA | D37: 45638 | E37: 20192013 | F37: =E37/1.19 -> 16968078 | G37: factura solicitadafacturas seran emitidas en febrero
B38: 109805203 | C38: BAP CONSTRUCTORA | D38: 45729 | E38: 4275000 | G38: factura solicitadafacturas seran emitidas en febrero
B39: 108532246 | C39: Carlos Arredondo | D39: 46053 | E39: 189486
B40: 775451475 | C40: COCO DISEÃ‘O SPA | D40: 45947 | E40: =7217168-4023891 -> 3193277 | G40: factura solicitadafacturas seran emitidas en febrero
B41: 968056905 | C41: CoSco Shiping | D41: 46053 | E41: 65450
B42: 992250003 | C42: Chub Seguros | D42: 46053 | E42: =286324 -> 286324
B43: 775706945 | C43: energia y servicios limite 21 | D43: 46050 | E43: 1317343
B44: 121704536 | C44: FRANCISCO JAVIER JASCURA GUERRA | D44: 45968 | E44: =630703-250000 -> 380703 | G44: saldo se deposita en febrero
B45: 937370008 | C45: GTD MANQUEHUE S.A. | D45: 45868 | E45: 109810 | G45: Factura solicitada
B47: Anticipo Proveedores Total | E47: =SUM(E35:E46) -> 30795995 | F47: ok
B49: ANTICIPO HONORARIOS
B50: RUT | C50: Titular | D50: Fecha | E50: Importe MN
B52: Anticipo Honorarios Total | E52: =SUM(E51:E51) -> 0 | F52: ok
B54: ANTICIPO AGENCIA DE ADUANAS
B55: 10.853.224-6 | C55: Saldo a favor agencia 85486 F57267 | D55: 46052 | E55: =8683566-9377634 -> -694068
B56: 10.853.224-6 | C56: Saldo a favor Flexi 85542 F57239 | D56: 46052 | E56: =24099445-23682186 -> 417259
B57: 10.853.224-6 | C57: Saldo a favor Flexi 85560 F57258 | D57: 46052 | E57: =18231074-18106273 -> 124801
B58: 10.853.224-6 | C58: Saldo a favor Flexi 85723 F57313 | D58: 46052 | E58: =6691439-6104081 -> 587358
B59: 10.853.224-6 | C59: Saldo a favor Flexi 85910 F57269 | D59: 46052 | E59: =24524841-24086465 -> 438376
B60: 10.853.224-6 | C60: Saldo a favor Flexi 86086 F57238 | D60: 46052 | E60: =3565952-3555035 -> 10917
B62: Anticipo Agente de Aduaba Total | E62: =SUM(E55:E61) -> 884643 | F62: ok

Sheet Inventarios
A1: Balance 8 Columnas'!A1 | B1: Flexi Chile Spa | J1: =+C9-'Balance Clasificado'!D15 -> -2.2492628
B2: Análisis y Detalle de Cuentas Inventarios
B3: =+'Deudores Diversos'!B3:F3 -> Al 31 de enero de 2026
B5: INVENTARIOS - Agrupación
B6: Cuentas | C6: Monto MN $
B7: EXISTENCIAS NACIONALES | C7: =+D41+I41 -> 1608492119
B8: MERCADERÍA EN TRÁNSITO | C8: =+I1882 -> 2.1566743e+08
B9: TOTAL Inventarios | C9: =SUM(C7:C8) -> 1.8241595e+09
B11: INVENTARIOS - Detalle
B13: EXISTENCIAS NACIONALES FLEXI | G13: EXISTENCIAS NACIONALES TAMARIS
B14: Tipo de Producto | C14: Sucursal | D14: Costo Valorizado | E14: Stock | G14: Tipo de Producto | H14: Sucursal | I14: Costo Valorizado | J14: Stock
B15: ACCESORIO | C15: Total | D15: =SUM(D16:D26) -> 16184834 | E15: =SUM(E16:E26) -> 4654 | F15: =+D15+I15 -> 16184834 | G15: ACCESORIO | H15: Total | I15: =SUM(I16:I26) -> 0 | J15: =SUM(J16:J26) -> 0 | K15: =+E15+J15 -> 4654
C16: FLEXI ECOMMERCE | D16: 534 | E16: -2 | H16: FLEXI ECOMMERCE | I16: 0 | J16: 0
C17: FLEXI PLAZA EGANA | D17: 818076 | E17: 192 | H17: FLEXI PLAZA EGANA | I17: 0 | J17: 0
C18: FLEXI PLAZA VESPUCIO | D18: 11975 | E18: 12 | H18: FLEXI PLAZA VESPUCIO | I18: 0 | J18: 0
C19: FLEXI EL TREBOL | D19: 659932 | E19: 137 | H19: FLEXI EL TREBOL | I19: 0 | J19: 0
C20: FLEXI COSTANERA CENTER | D20: 1012610 | E20: 191 | H20: FLEXI COSTANERA CENTER | I20: 0 | J20: 0
C21: FLEXI FLORIDA CENTER | D21: 940489 | E21: 183 | H21: FLEXI FLORIDA CENTER | I21: 0 | J21: 0
C22: FLEXI ESTADO | D22: 1113035 | E22: 309 | H22: FLEXI ESTADO | I22: 0 | J22: 0
C23: FLEXI TALCA | D23: 1081232 | E23: 389 | H23: FLEXI TALCA | I23: 0 | J23: 0
C24: FLEXI PLAZA NORTE | D24: 993136 | E24: 315 | H24: FLEXI PLAZA NORTE | I24: 0 | J24: 0
C25: FLEXI PLAZA OESTE | D25: 658208 | E25: 141 | H25: FLEXI PLAZA OESTE | I25: 0 | J25: 0
C26: BODEGA CENTRAL | D26: 8895607 | E26: 2787 | H26: BODEGA CENTRAL | I26: 0 | J26: 0
B27: CALZADO | C27: Total | D27: =SUM(D28:D39) -> 1415676636 | E27: =SUM(E28:E39) -> 56281 | F27: =+D27+I27 -> 1592307285 | G27: CALZADO | H27: Total | I27: =SUM(I28:I39) -> 176630649 | J27: =SUM(J28:J39) -> 6855 | K27: =+E27+J27 -> 63136
C28: FLEXI ECOMMERCE | D28: =1178946+210996 -> 1389942 | E28: =45+5 -> 50 | H28: FLEXI ECOMMERCE | I28: 0 | J28: 0
C29: FLEXI PLAZA EGANA | D29: =55999974+2481553 -> 58481527 | E29: =2329+62 -> 2391 | H29: FLEXI PLAZA EGANA | I29: 13722176 | J29: 525
C30: FLEXI PLAZA VESPUCIO | D30: -26685 | E30: -1 | H30: FLEXI PLAZA VESPUCIO | I30: 0 | J30: 0
C31: FLEXI EL TREBOL | D31: =58663551+2283236 -> 60946787 | E31: =2443+57 -> 2500 | H31: FLEXI EL TREBOL | I31: 11634984 | J31: 452
C32: FLEXI COSTANERA CENTER | D32: =49733848+1784661 -> 51518509 | E32: =2057+45 -> 2102 | H32: FLEXI COSTANERA CENTER | I32: 12225594 | J32: 472
C33: FLEXI FLORIDA CENTER | D33: 37155879 | E33: 1563 | H33: FLEXI FLORIDA CENTER | I33: 5466014 | J33: 216
C34: FLEXI BARROS ARANA | D34: 149892 | E34: 4 | H34: FLEXI BARROS ARANA | I34: 0 | J34: 0
C35: FLEXI ESTADO | D35: =46787856+323196+995465 -> 48106517 | E35: =1977+12+25 -> 2014 | H35: FLEXI ESTADO | I35: 7349559 | J35: 295
C36: FLEXI TALCA | D36: 46770973 | E36: 1971 | H36: FLEXI TALCA | I36: 5389663 | J36: 207
C37: FLEXI PLAZA NORTE | D37: 40986099 | E37: 1703 | H37: FLEXI PLAZA NORTE | I37: 7149372 | J37: 277
C38: FLEXI PLAZA OESTE | D38: 36689443 | E38: 1540 | H38: FLEXI PLAZA OESTE | I38: 12402944 | J38: 474
C39: BODEGA CENTRAL | D39: =980026016+4+53481733 -> 1033507753 | E39: =39149+4+1291 -> 40444 | H39: BODEGA CENTRAL | I39: 101290343 | J39: 3937
B40: CONTABILIDAD | C40: Total | D40: 0 | G40: CONTABILIDAD | H40: Total | I40: 0
B41: Total general | D41: =+D15+D27+D40 -> 1431861470 | E41: =+E15+E27+E40 -> 60935 | F41: =+D41+I41 -> 1608492119 | G41: Total general | I41: =+I15+I27+I40 -> 176630649 | J41: =+J15+J27+J40 -> 6855 | K41: =+E41+J41 -> 67790
D42: 996402817
D43: =D41-D42 -> 435458653 | E43: =D43/803.3 -> 542087.21
B44: Unidades Vendidas Flexi | D44: =D43/790.47 -> 550885.74
D46: ene | E46: Total general
B47: Tipo de Producto / Servicio | C47: Sucursal
B48: CALZADO | C48: FLEXI ECOMMERCE | D48: =907-220+2 -> 689 | E48: =SUM(D48:D48) -> 689 | G48: BODEGA DEPARTAMENTAL (Mayorista)
C49: FLEXI PLAZA EGANA | D49: 682 | E49: =SUM(D49:D49) -> 682 | G49: FLEXI ARAUCO MAIPU
C50: FLEXI PLAZA VESPUCIO | D50: 0 | E50: =SUM(D50:D50) -> 0 | G50: FLEXI BARROS ARANA
C51: FLEXI EL TREBOL | D51: 459 | E51: =SUM(D51:D51) -> 459 | G51: FLEXI COSTANERA CENTER
C52: FLEXI COSTANERA CENTER | D52: 940 | E52: =SUM(D52:D52) -> 940 | G52: FLEXI ECOMMERCE (Casa matriz)
C53: FLEXI FLORIDA CENTER | D53: 442 | E53: =SUM(D53:D53) -> 442 | G53: FLEXI EL TREBOL
C54: FLEXI ESTADO | D54: 783 | E54: =SUM(D54:D54) -> 783 | G54: FLEXI FLORIDA CENTER
C55: FLEXI TALCA | D55: 359 | E55: =SUM(D55:D55) -> 359 | G55: FLEXI PLAZA EGANA
C56: FLEXI PLAZA NORTE | D56: 352 | E56: =SUM(D56:D56) -> 352 | G56: FLEXI PLAZA NORTE
C57: FLEXI PLAZA OESTE | D57: 489 | E57: =SUM(D57:D57) -> 489
C58: BODEGA CENTRAL MAYORISTA | D58: 0 | E58: =SUM(D58:D58) -> 0 | G58: FLEXI PLAZA LOS DOMINICOS
C59: BODEGA CENTRAL Notas de credito | D59: 0 | E59: =SUM(D59:D59) -> 0 | G59: FLEXI PLAZA LOS DOMINICOS
B60: Total CALZADO | D60: =SUM(D48:D59) -> 5195 | E60: =SUM(E48:E59) -> 5195
B61: ACCESORIO | C61: FLEXI ECOMMERCE | D61: 14 | E61: =SUM(D61:D61) -> 14 | G61: BODEGA DEPARTAMENTAL (Mayorista)
C62: FLEXI PLAZA EGANA | D62: 93 | E62: =SUM(D62:D62) -> 93 | G62: FLEXI ARAUCO MAIPU
C63: FLEXI PLAZA VESPUCIO | D63: 0 | E63: =SUM(D63:D63) -> 0 | G63: FLEXI BARROS ARANA
C64: FLEXI EL TREBOL | D64: 115 | E64: =SUM(D64:D64) -> 115 | G64: FLEXI COSTANERA CENTER
C65: FLEXI COSTANERA CENTER | D65: 140 | E65: =SUM(D65:D65) -> 140 | G65: FLEXI ECOMMERCE (Casa matriz)
C66: FLEXI FLORIDA CENTER | D66: 65 | E66: =SUM(D66:D66) -> 65 | G66: FLEXI EL TREBOL
C67: FLEXI ESTADO | D67: 93 | E67: =SUM(D67:D67) -> 93 | G67: FLEXI FLORIDA CENTER
C68: FLEXI TALCA | D68: 61 | E68: =SUM(D68:D68) -> 61 | G68: FLEXI PLAZA EGANA
C69: FLEXI PLAZA NORTE | D69: 216 | E69: =SUM(D69:D69) -> 216 | G69: FLEXI PLAZA NORTE
C70: FLEXI PLAZA OESTE | D70: 92 | E70: =SUM(D70:D70) -> 92
B71: Total ACCESORIO | D71: =SUM(D61:D70) -> 889 | E71: =SUM(E61:E70) -> 889
B72: Total general | D72: =+D60+D71 -> 6084 | E72: =+E60+E71 -> 6084 | F72: ok
B74: Unidades Vendidas Tamaris | D74: =D73/790.47 -> 0
D76: ene | E76: Total general
B77: Tipo de Producto / Servicio | C77: Sucursal
B78: CALZADO | C78: FLEXI ECOMMERCE | D78: =16-1 -> 15 | E78: =SUM(D78:D78) -> 15 | G78: BODEGA DEPARTAMENTAL (Mayorista)
C79: FLEXI PLAZA EGANA | D79: 61 | E79: =SUM(D79:D79) -> 61 | G79: FLEXI ARAUCO MAIPU
C80: FLEXI PLAZA VESPUCIO | D80: 0 | E80: =SUM(D80:D80) -> 0 | G80: FLEXI BARROS ARANA
C81: FLEXI EL TREBOL | D81: 39 | E81: =SUM(D81:D81) -> 39 | G81: FLEXI COSTANERA CENTER
C82: FLEXI COSTANERA CENTER | D82: 114 | E82: =SUM(D82:D82) -> 114 | G82: FLEXI ECOMMERCE (Casa matriz)
C83: FLEXI FLORIDA CENTER | D83: 22 | E83: =SUM(D83:D83) -> 22 | G83: FLEXI EL TREBOL
C84: FLEXI ESTADO | D84: 43 | E84: =SUM(D84:D84) -> 43 | G84: FLEXI FLORIDA CENTER
C85: FLEXI TALCA | D85: 19 | E85: =SUM(D85:D85) -> 19 | G85: FLEXI PLAZA EGANA
C86: FLEXI PLAZA NORTE | D86: 31 | E86: =SUM(D86:D86) -> 31 | G86: FLEXI PLAZA NORTE
C87: FLEXI PLAZA OESTE | D87: 64 | E87: =SUM(D87:D87) -> 64
C88: BODEGA CENTRAL MAYORISTA | E88: =SUM(D88:D88) -> 0 | G88: FLEXI PLAZA LOS DOMINICOS
C89: BODEGA CENTRAL Notas de credito | D89: 0 | E89: =SUM(D89:D89) -> 0 | G89: FLEXI PLAZA LOS DOMINICOS
B90: Total CALZADO | D90: =SUM(D78:D89) -> 408 | E90: =SUM(E78:E89) -> 408 | F90: ok
B92: MERCADERÍA EN TRÁNSITO
B93: FECHA | C93: DESCRIPCIÓN | D93: Monto MN | E93: US$ | F93: Valor US$ | G93: US$ cierre | H93: Diferencia de Cambio | I93: Valor al cierre
B94: 44895 | C94: Mercaderia no internada pendiente nota de credito | D94: =F94*E94 -> 6633325.4 | E94: 860.03 | F94: 7712.9 | G94: 865.1 | H94: =+I94-D94 -> 39104.403 | I94: =+F94*G94 -> 6672429.8
B95: 44897 | C95: Invoice A5737302 Distribuidora Flexi | D95: =F95*E95 -> 604166 | E95: 885.77 | F95: 682.08 | G95: =+G94 -> 865.1 | H95: =+I95-D95 -> -14098.594 | I95: =+F95*G95 -> 590067.41
B96: 44897 | C96: Invoice A5737303 Distribuidora Flexi | D96: =F96*E96 -> 755207.5 | E96: 885.77 | F96: 852.6 | G96: =+G95 -> 865.1 | H96: =+I96-D96 -> -17623.242 | I96: =+F96*G96 -> 737584.26
B97: 44897 | C97: Invoice A5737304 Distribuidora Flexi | D97: =F97*E97 -> 755207.5 | E97: 885.77 | F97: 852.6 | G97: =+G96 -> 865.1 | H97: =+I97-D97 -> -17623.242 | I97: =+F97*G97 -> 737584.26
B98: 44897 | C98: Invoice A5737305 Distribuidora Flexi | D98: =F98*E98 -> 755207.5 | E98: 885.77 | F98: 852.6 | G98: =+G97 -> 865.1 | H98: =+I98-D98 -> -17623.242 | I98: =+F98*G98 -> 737584.26
B99: 44897 | C99: Invoice A5737306 Distribuidora Flexi | D99: =F99*E99 -> 906249 | E99: 885.77 | F99: 1023.12 | G99: =+G98 -> 865.1 | H99: =+I99-D99 -> -21147.89 | I99: =+F99*G99 -> 885101.11
B100: 44897 | C100: Invoice A5737307 Distribuidora Flexi | D100: =F100*E100 -> 604166 | E100: 885.77 | F100: 682.08 | G100: =+G99 -> 865.1 | H100: =+I100-D100 -> -14098.594 | I100: =+F100*G100 -> 590067.41
B101: 44897 | C101: Invoice A5737308 Distribuidora Flexi | D101: =F101*E101 -> 755207.5 | E101: 885.77 | F101: 852.6 | G101: =+G100 -> 865.1 | H101: =+I101-D101 -> -17623.242 | I101: =+F101*G101 -> 737584.26
B102: 44897 | C102: Invoice A5737309 Distribuidora Flexi | D102: =F102*E102 -> 2059362.1 | E102: 885.77 | F102: 2324.94 | G102: =+G101 -> 865.1 | H102: =+I102-D102 -> -48056.51 | I102: =+F102*G102 -> 2011305.6
B103: 44897 | C103: Invoice A5737310 Distribuidora Flexi | D103: =F103*E103 -> 2792602.5 | E103: 885.77 | F103: 3152.74 | G103: =+G102 -> 865.1 | H103: =+I103-D103 -> -65167.136 | I103: =+F103*G103 -> 2727435.4
B104: 44897 | C104: Invoice A5737311 Distribuidora Flexi | D104: =F104*E104 -> 2792602.5 | E104: 885.77 | F104: 3152.74 | G104: =+G103 -> 865.1 | H104: =+I104-D104 -> -65167.136 | I104: =+F104*G104 -> 2727435.4
B105: 44897 | C105: Invoice A5737312 Distribuidora Flexi | D105: =F105*E105 -> 2792602.5 | E105: 885.77 | F105: 3152.74 | G105: =+G104 -> 865.1 | H105: =+I105-D105 -> -65167.136 | I105: =+F105*G105 -> 2727435.4
B106: 44897 | C106: Invoice A5737313 Distribuidora Flexi | D106: =F106*E106 -> 3683775.7 | E106: 885.77 | F106: 4158.84 | G106: =+G105 -> 865.1 | H106: =+I106-D106 -> -85963.223 | I106: =+F106*G106 -> 3597812.5
... B135: 44925 | C135: Invoice B246139 Distribuidora Flexi | D135: =F135*E135 -> 4208986.1 | E135: 859.51 | F135: 4896.96 | G135: =+G134 -> 865.1 | H135: =+I135-D135 -> 27374.006 | I135: =+F135*G135 -> 4236360.1
...

Sheet Impuestos a favor
A1: Balance 8 Columnas'!A1 | B1: Flexi Chile Spa | G1: =+C10-'Balance Clasificado'!D16 -> 0
B2: Análisis y Detalle de Cuentas Impuestos a favor
B3: =+'Deudores Diversos'!B3:F3 -> Al 31 de enero de 2026
B5: IMPUESTOS A FAVOR
B6: Cuentas | C6: Monto MN $
B7: IMPUESTOS POR RECUPERAR | C7: =+D18 -> 0
B8: =+B21 -> PAGOS PROVISIONALES MENSUALES | C8: =+D25 -> 0
B9: REMANENTE CREDITO FISCAL | C9: =+D32 -> 357340940
B10: TOTAL Impuestos a favor | C10: =SUM(C7:C9) -> 357340940
B12: IMPUESTOS A FAVOR - Detalle:
B14: IMPUESTOS POR RECUPERAR
B15: Detalle | C15: Fecha | D15: Monto
D16: Inicial
B17: Pagos Provisionales Año 2020 | C17: 44316 | D17: 0 | J17: 830761 | K17: 0.016 | L17: =+J17*K17 -> 13292.176
B18: Saldo Según Balance | D18: =SUM(D17:D17) -> 0
B21: PAGOS PROVISIONALES MENSUALES
B22: Detalle | C22: Fecha | D22: Valor
D23: Actual | J23: 3663217 | K23: 0.042 | L23: =+J23*K23 -> 153855.11 | M23: =+J23+L23 -> 3817072.1
B24: PPM Acumulado 31-12-2021 | C24: 44561 | D24: 0
B25: Saldo Según Balance | D25: =SUM(D24:D24) -> 0
M27: =SUM(M23:M26) -> 3817072.1
B28: REMANENTE CREDITO FISCAL | M28: =+D25-M27 -> -3817072.1
B29: Detalle | C29: Fecha | D29: Valor
D30: Actual
B31: Remanente Acumulado al cierre | C31: 46053 | D31: =310909957+47044410-623797+10370 -> 357340940
B32: Saldo Según Balance | D32: =SUM(D31:D31) -> 357340940
B35: MES | C35: Rem Anterior | D35: reajuste | E35: ICF/IDF | F35: Saldo Reman | G35: original declarado | H35: diferencia
B36: SEPTIEMBRE | C36: 149161767 | D36: 148025 | E36: 25435951 | F36: =+C36+D36+E36 -> 174745743 | G36: 150640363 | H36: =F36-G36 -> 24105380
B37: OCTUBRE | C37: =+F36 -> 174745743 | D37: 1224207 | E37: -19717971 | F37: =+C37+D37+E37 -> 156251979 | G37: 131977880 | H37: =F37-G37 -> 24274099
B38: NOVIEMBRE | C38: =+F37 -> 156251979 | D38: 625140 | E38: 13721314 | F38: =+C38+D38+E38 -> 170598433 | G38: 146227177 | H38: =F38-G38 -> 24371256
B39: DICIEMBRE | C39: =+F38 -> 170598433 | D39: 1195203 | E39: -30438016 | F39: =+C39+D39+E39 -> 141355620 | G39: 116813579 | H39: =F39-G39 -> 24542041
B40: ENERO | C40: =+F39 -> 141355620 | D40: -706326 | E40: -1950318 | F40: =+C40+D40+E40 -> 138698976 | G40: 114279521 | H40: =F40-G40 -> 24419455
B41: FEBRERO | C41: =+F40 -> 138698976 | D41: 970111 | E41: -22391101 | F41: =+C41+D41+E41 -> 117277986 | G41: 92687746 | H41: =F41-G41 -> 24590240
B42: MARZO | C42: =+F41 -> 117277986 | D42: 704042 | E42: 45526742 | F42: =+C42+D42+E42 -> 163508770 | G42: 138770897 | H42: =F42-G42 -> 24737873
B43: ABRIL | C43: =+F42 -> 163508770 | D43: 654996 | E43: 70699134 | F43: =+C43+D43+E43 -> 234862900 | G43: 210025972 | H43: =F43-G43 -> 24836928
B44: MAYO | C44: =+F43 -> 234862900 | D44: 1173791 | E44: 32712848 | F44: =+C44+D44+E44 -> 268749539 | G44: 243788509 | H44: =F44-G44 -> 24961030
B45: JUNIO | C45: =+F44 -> 268749539 | D45: -298458 | E45: -17683028 | F45: =+C45+D45+E45 -> 250768053 | G45: 225834728 | H45: =F45-G45 -> 24933325
D84: INTERES DEVENGADO FONDO MUTUO SECURITY

Sheet Activo fijo
A1: Balance 8 Columnas'!A1 | B1: Flexi Chile Spa | M1: =+C12-'Balance Clasificado'!D23 -> 1.2266656
B2: Análisis y Detalle Activos Fijos
B3: =+Carátula!A9 -> Al 31 de enero de 2026
B5: Activos Fijos
B6: Cuentas | C6: Monto MN $
B7: MUEBLES, UTILES Y OTROS | C7: =+F148 -> 656828984
B8: EQUIPOS COMPUTACIONALES | C8: =+F237 -> 109578639
B9: ACTIVO EN CONSTRUCCION | C9: =+D244 -> 27748636
B10: DEPREC. ACUM. MUEBLRES, UTILES Y OTROS | C10: =+-K148 -> -2.108308e+08
B11: DEPREC. ACUM. EQUIPOS COMPUTACIONALES | C11: =+-K237 -> -36686283
B12: TOTAL Activos Fijos | C12: =SUM(C7:C11) -> 5.4663917e+08
B14: MUEBLES, UTILES Y OTROS
B15: Detalle | C15: Centro de Costo | D15: Fecha | E15: Vida | F15: Valor | G15: Dep. Acum. | H15: Total Acum. | I15: Meses | J15: Depreciación | K15: Total | L15: Total
E16: útil | F16: Inicio | G16: Inicial | H16: Inicial | I16: a Dep. | J16: Ejercicio | K16: Dep. Acum.
B17: Fact. 47 Imp. Export. Globus 1 Caja Metalica | C17: CEDIS | D17: 44151 | E17: 23 | F17: 11000 | G17: 7988.1695 | H17: 3011.8305 | I17: 1 | J17: 130.94915 | K17: 8119.1186 | L17: 2880.8814
B18: Fact. 47 Imp. Export. Globus 1 Escala Metalica | C18: CEDIS | D18: 44151 | E18: 23 | F18: 11000 | G18: 7988.1084 | H18: 3011.8916 | I18: 1 | J18: 130.95181 | K18: 8119.0602 | L18: 2880.9398
B19: Fact. 47 Imp. Export. Globus 1 Aspiradora | C19: CEDIS | D19: 44151 | E19: 23 | F19: 23000 | G19: 16702.288 | H19: 6297.7119 | I19: 1 | J19: 273.81356 | K19: 16976.102 | L19: 6023.8983
B20: Fact. 47 Imp. Export. Globus 7 Puff | C20: CEDIS | D20: 44151 | E20: 23 | F20: 35000 | G20: 25416.759 | H20: 9583.241 | I20: 1 | J20: 416.66265 | K20: 25833.422 | L20: 9166.5783
B21: Fact. 47 Imp. Export. Globus 1 Escala Metalica | C21: EGAÑA | D21: 44151 | E21: 23 | F21: 11000 | G21: 7988.1084 | H21: 3011.8916 | I21: 1 | J21: 130.95181 | K21: 8119.0602 | L21: 2880.9398
B22: Fact. 47 Imp. Export. Globus 1 Caja Metalica | C22: EGAÑA | D22: 44151 | E22: 23 | F22: 11000 | G22: 7988.1084 | H22: 3011.8916 | I22: 1 | J22: 130.95181 | K22: 8119.0602 | L22: 2880.9398
B23: Fact. 47 Imp. Export. Globus 1 Aspiradora | C23: EGAÑA | D23: 44151 | E23: 23 | F23: 23000 | G23: 16702.288 | H23: 6297.7119 | I23: 1 | J23: 273.81356 | K23: 16976.102 | L23: 6023.8983
B24: Fact. 47 Imp. Export. Globus 1 Piso Metalico | C24: EGAÑA | D24: 44151 | E24: 23 | F24: 11000 | G24: 7988.1084 | H24: 3011.8916 | I24: 1 | J24: 130.95181 | K24: 8119.0602 | L24: 2880.9398
B25: Fact. 47 Imp. Export. Globus 1 Silla | C25: EGAÑA | D25: 44151 | E25: 23 | F25: 11000 | G25: 7988.1084 | H25: 3011.8916 | I25: 1 | J25: 130.95181 | K25: 8119.0602 | L25: 2880.9398
B26: Fact. 47 Imp. Export. Globus 1 Mesa Plastica | C26: EGAÑA | D26: 44151 | E26: 23 | F26: 11000 | G26: 7988.1084 | H26: 3011.8916 | I26: 1 | J26: 130.95181 | K26: 8119.0602 | L26: 2880.9398
B27: Fact. 47 Imp. Export. Globus 1 Silla | C27: EGAÑA | D27: 44151 | E27: 23 | F27: 11000 | G27: 7988.1084 | H27: 3011.8916 | I27: 1 | J27: 130.95181 | K27: 8119.0602 | L27: 2880.9398
B28: Fact. 47 Imp. Export. Globus 7 Puff | C28: EGAÑA | D28: 44151 | E28: 23 | F28: 35000 | G28: 25416.759 | H28: 9583.241 | I28: 1 | J28: 416.66265 | K28: 25833.422 | L28: 9166.5783
... B76: BAP OBRAS CIVILIE saldo (construccion Local Centro Santiago y centro concepciÃ³n.) F/142 | C76: STGO CENTRO | D76: 45078 | E76: 54 | F76: 18461300 | G76: 6593321.4 | H76: 11867979 | I76: 1 | J76: 219777.38 | K76: 6813098.8 | L76: 11648201
B77: BAP OBRAS CIVILIE saldo (construccion Local Centro Santiago y centro concepciÃ³n.) F/142 | C77: CONCEPCION CENTRO | D77: 45078 | E77: 54 | F77: 15104700 | G77: 5394535.7 | H77: 9710164.3 | I77: 1 | J77: 179817.86 | K77: 5574353.6 | L77: 9530346.4 | S77: =ROUND(P77,0) -> 0
B78: COCO DISEÑO Honorarios proyecto de (Arquitectura Flexi Santiago Centro) CAPEX ESTADO F35 | C78: STGO CENTRO | D78: 45084 | E78: 54 | F78: 3680000 | G78: 1314285.7 | H78: 2365714.3 | I78: 1 | J78: 43809.524 | K78: 1358095.2 | L78: 2321904.8 | S78: =ROUND(P78,0) -> 0
B79: COCO DISEÑO Honorarios proyecto de (Arquitectura Flexi Santiago Centro) CAPEX ESTADO F36 | C79: CONCEPCION CENTRO | D79: 45084 | E79: 54 | F79: 2490000 | G79: 889285.71 | H79: 1600714.3 | I79: 1 | J79: 29642.857 | K79: 918928.57 | L79: 1571071.4 | S79: =ROUND(P79,0) -> 0
B80: BAP OBRAS CIVILES SPA F146 asientos (confecciÃ³n de asientos local costanera center | C80: COSTANERA CENTER | D80: 45117 | E80: 55 | F80: 1650000 | G80: 569642.86 | H80: 1080357.1 | I80: 1 | J80: 19642.857 | K80: 589285.71 | L80: 1060714.3 | S80: =ROUND(P80,0) -> 0
B81: BAP OBRAS CIVILES SPA F150 motor (cambio de motor cortina estado) | C81: STGO CENTRO | D81: 45119 | E81: 55 | F81: 970000 | G81: 334880.95 | H81: 635119.05 | I81: 1 | J81: 11547.619 | K81: 346428.57 | L81: 623571.43 | S81: =ROUND(P81,0) -> 0
B82: COCO DISEÑO F42 | C82: ADMINISTRACION | D82: 45236 | E82: 58 | F82: 2176890 | G82: 673799.29 | H82: 1503090.7 | I82: 1 | J82: 25915.357 | K82: 699714.64 | L82: 1477175.4 | S82: =ROUND(P82,0) -> 0
B83: COCO DISEÑO F43 | C83: ADMINISTRACION | D83: 45273 | E83: 59 | F83: 2461890 | G83: 732705.36 | H83: 1729184.6 | I83: 1 | J83: 29308.214 | K83: 762013.57 | L83: 1699876.4 | S83: =ROUND(P83,0) -> 0
B84: COCO DISEÑO F44 | C84: ADMINISTRACION | D84: 45273 | E84: 59 | F84: 200000 | G84: 59523.81 | H84: 140476.19 | I84: 1 | J84: 2380.9524 | K84: 61904.762 | L84: 138095.24 | S84: =ROUND(P84,0) -> 0
B85: COMERCIALIZADORA AVYMAQ SPA F/2251 MESAS PLEGABLES REINSTALACION CEDIS | C85: CEDIS | D85: 45351 | E85: 62 | F85: 163866 | G85: 42917.286 | H85: 120948.71 | I85: 1 | J85: 1950.7857 | K85: 44868.071 | L85: 118997.93 | S85: =ROUND(P85,0) -> 0
B86: ZAMBON Y ZAMBON F9132 50% Infraestructura Cedis 2.0 (Rack Pallet-Altillo) | C86: CEDIS | D86: 45356 | E86: 63 | F86: 4917500 | G86: 1229375 | H86: 3688125 | I86: 1 | J86: 58541.667 | K86: 1287916.7 | L86: 3629583.3 | S86: =ROUND(P86,0) -> 0
B87: ZAMBON Y ZAMBON F9133 50% Infraestructura Cedis 2.0 (Rack Pallet-Altillo) | C87: CEDIS | D87: 45356 | E87: 63 | F87: 16254832 | G87: 4063708 | H87: 12191124 | I87: 1 | J87: 193509.9 | K87: 4257217.9 | L87: 11997614 | S87: =ROUND(P87,0) -> 0
B88: ZAMBON Y ZAMBON FAC. NRO.9190 saldo Infraestructura Cedis Zona Racks | C88: CEDIS | D88: 45387 | E88: 64 | F88: 4917500 | G88: 1170833.3 | H88: 3746666.7 | I88: 1 | J88: 58541.667 | K88: 1229375 | L88: 3688125
B89: COCO DISEÑO FAC. NRO.46 50% Soporte tecnico y administrativo proyecto Tienda Talca | C89: TALCA | D89: 45390 | E89: 64 | F89: 1437500 | G89: 342261.9 | H89: 1095238.1 | I89: 1 | J89: 17113.095 | K89: 359375 | L89: 1078125
B90: BAP OBRAS CIVILES FAC. NRO.186 1er Anticipo Obras Tienda Mall Plaza Maule | C90: TALCA | D90: 45400 | E90: 64 | F90: 23680234 | G90: 5638151 | H90: 18042083 | I90: 1 | J90: 281907.55 | K90: 5920058.5 | L90: 17760176
B91: ESTRUCTURAS Y MONTAJES RAUL V. FAC. NRO.84 SALDO Carros Ecommerce-Mesones de trabajo | C91: CEDIS | D91: 45400 | E91: 64 | F91: 2760000 | G91: 657142.86 | H91: 2102857.1 | I91: 1 | J91: 32857.143 | K91: 690000 | L91: 2070000
B92: ZAMBON Y ZAMBON FAC. NRO.9219 Saldo final Infraestructura Cedis Zona Altillo | C92: CEDIS | D92: 45401 | E92: 64 | F92: 16254831 | G92: 3870197.9 | H92: 12384633 | I92: 1 | J92: 193509.89 | K92: 4063707.8 | L92: 12191123
B93: GRUPO DERZA SPA FAC. NRO.430 50% Anticipo Sistema Electrico General | C93: CEDIS | D93: 45407 | E93: 65 | F93: 4901838 | G93: 1108749.1 | H93: 3793088.9 | I93: 1 | J93: 58355.214 | K93: 1167104.3 | L93: 3734733.7
B94: KREATINA SPA FAC. NRO.2359 Implementacion redes--datos- camaras Talca | C94: TALCA | D94: 45411 | E94: 65 | F94: 3301750 | G94: 746824.4 | H94: 2554925.6 | I94: 1 | J94: 39306.548 | K94: 786130.95 | L94: 2515619
B95: BAP OBRAS CIVILES SPA FAC. NRO.187 2do anticipo construcion oficina Cedis | C95: CEDIS | D95: 45418 | E95: 65 | F95: 3800000 | G95: 859523.81 | H95: 2940476.2 | I95: 1 | J95: 45238.095 | K95: 904761.9 | L95: 2895238.1
B96: BAP OBRAS CIVILES SPA FAC. NRO.188 saldo tienda Talca | C96: TALCA | D96: 45418 | E96: 65 | F96: 13651000 | G96: 3087726.2 | H96: 10563274 | I96: 1 | J96: 162511.9 | K96: 3250238.1 | L96: 10400762
B97: BAP OBRAS CIVILES SPA FAC. NRO.190 2do anticipo construcion oficina Cedis | C97: CEDIS | D97: 45425 | E97: 65 | F97: 3800000 | G97: 859523.81 | H97: 2940476.2 | I97: 1 | J97: 45238.095 | K97: 904761.9 | L97: 2895238.1
B98: ACCIONA FACILITY FAC. NRO.1200 Mantencion Electrica y Muebles Trebol Concepcion | C98: TREBOL | D98: 45429 | E98: 65 | F98: 109116 | G98: 24681 | H98: 84435 | I98: 1 | J98: 1299 | K98: 25980 | L98: 83136
B99: ACCIONA FACILITY FAC. NRO.1201 Mantencion Electrica y Muebles Trebol Concepcion | C99: TREBOL | D99: 45429 | E99: 65 | F99: 624616 | G99: 141282.19 | H99: 483333.81 | I99: 1 | J99: 7435.9048 | K99: 148718.1 | L99: 475897.9
... B118: BAP OBRAS CIVILES F212 | C118: OESTE | D118: 45615 | E118: 71 | F118: 17962185 | G118: 2779862 | H118: 15182323 | I118: 1 | J118: 213835.54 | K118: 2993697.5 | L118: 14968488
B119: BAP OBRAS CIVILES SPA F215 | C119: STGO CENTRO | D119: 45640 | E119: 72 | F119: 850 | G119: 121.42857 | H119: 728.57143 | I119: 1 | J119: 10.119048 | K119: 131.54762 | L119: 718.45238 | N119: 0
B120: BAP OBRAS CIVILES SPA F216 | C120: NORTE | D120: 45640 | E120: 72 | F120: 120000 | G120: 17142.857 | H120: 102857.14 | I120: 1 | J120: 1428.5714 | K120: 18571.429 | L120: 101428.57 | N120: 0
B121: COCO DISEÑO FAC. 56 | C121: OESTE | D121: 45642 | E121: 72 | F121: 1487500 | G121: 212500 | H121: 1275000 | I121: 1 | J121: 17708.333 | K121: 230208.33 | L121: 1257291.7
B122: BAP OBRAS CIVILES SPA F218 | C122: NORTE | D122: 45678 | E122: 73 | F122: 32331933 | G122: 4233943.6 | H122: 28097989 | I122: 1 | J122: 384903.96 | K122: 4618847.6 | L122: 27713085
B123: BAP OBRAS CIVILES SPA F219 | C123: TALCA | D123: 45678 | E123: 73 | F123: 6106218 | G123: 799623.79 | H123: 5306594.2 | I123: 1 | J123: 72693.071 | K123: 872316.86 | L123: 5233901.1 | N123: 0
B124: PANORAMICA3D SPA, TARIMAS VITRINAS | C124: EGAÑA | D124: 45698 | E124: 74 | F124: 98000 | G124: 11666.667 | H124: 86333.333 | I124: 1 | J124: 1166.6667 | K124: 12833.333 | L124: 85166.667
B125: PANORAMICA3D SPA, TARIMAS VITRINAS | C125: CEDIS | D125: 45698 | E125: 74 | F125: 98000 | G125: 11666.667 | H125: 86333.333 | I125: 1 | J125: 1166.6667 | K125: 12833.333 | L125: 85166.667
B126: PANORAMICA3D SPA, TARIMAS VITRINAS | C126: TREBOL | D126: 45698 | E126: 74 | F126: 98000 | G126: 11666.667 | H126: 86333.333 | I126: 1 | J126: 1166.6667 | K126: 12833.333 | L126: 85166.667
B127: PANORAMICA3D SPA, TARIMAS VITRINAS | C127: COSTANERA CENTER | D127: 45698 | E127: 74 | F127: 98000 | G127: 11666.667 | H127: 86333.333 | I127: 1 | J127: 1166.6667 | K127: 12833.333 | L127: 85166.667
B128: PANORAMICA3D SPA, TARIMAS VITRINAS | C128: FLORIDA CENTER | D128: 45698 | E128: 74 | F128: 98000 | G128: 11666.667 | H128: 86333.333 | I128: 1 | J128: 1166.6667 | K128: 12833.333 | L128: 85166.667
B129: PANORAMICA3D SPA, TARIMAS VITRINAS | C129: CONCEPCION CENTRO | D129: 45698 | E129: 74 | F129: 98000 | G129: 11666.667 | H129: 86333.333 | I129: 1 | J129: 1166.6667 | K129: 12833.333 | L129: 85166.667
B130: PANORAMICA3D SPA, TARIMAS VITRINAS | C130: STGO CENTRO | D130: 45698 | E130: 74 | F130: 98000 | G130: 11666.667 | H130: 86333.333 | I130: 1 | J130: 1166.6667 | K130: 12833.333 | L130: 85166.667
B131: PANORAMICA3D SPA, TARIMAS VITRINAS | C131: TALCA | D131: 45698 | E131: 74 | F131: 98000 | G131: 11666.667 | H131: 86333.333 | I131: 1 | J131: 1166.6667 | K131: 12833.333 | L131: 85166.667
B132: PANORAMICA3D SPA, TARIMAS VITRINAS | C132: NORTE | D132: 45698 | E132: 74 | F132: 98000 | G132: 11666.667 | H132: 86333.333 | I132: 1 | J132: 1166.6667 | K132: 12833.333 | L132: 85166.667
B133: PANORAMICA3D SPA, TARIMAS VITRINAS | C133: OESTE | D133: 45698 | E133: 74 | F133: 98000 | G133: 11666.667 | H133: 86333.333 | I133: 1 | J133: 1166.6667 | K133: 12833.333 | L133: 85166.667
B134: BAP OBRAS CIVILES SPA F227 OESTE | C134: OESTE | D134: 45723 | E134: 75 | F134: 1159000 | G134: 124178.57 | H134: 1034821.4 | I134: 1 | J134: 13797.619 | K134: 137976.19 | L134: 1021023.8
B135: BAP OBRAS CIVILES SPA F228 | C135: STGO CENTRO | D135: 45723 | E135: 75 | F135: 850000 | G135: 91071.429 | H135: 758928.57 | I135: 1 | J135: 10119.048 | K135: 101190.48 | L135: 748809.52
... B145: METALPLASTIC SPA F1352 soporte grafica | C145: STGO CENTRO | D145: 46006 | E145: 84 | F145: 120000 | G145: 0 | H145: 120000 | I145: 1 | J145: 1428.5714 | K145: 1428.5714 | L145: 118571.43
B146: CHIC DESIGN SPA F662 CONSTRUCCION | D146: 46029 | E146: 84 | F146: 36505040 | G146: 0 | H146: 36505040 | I146: 0 | J146: 0 | K146: 0 | L146: 36505040
B147: COCO DISEÃ‘O SPA F91 PROYECTO ARQUITECTURA | D147: 46040 | E147: 84 | F147: 1252736 | G147: 0 | H147: 1252736 | I147: 0 | J147: 0 | K147: 0 | L147: 1252736
B148: Total Muebles y Otros | F148: =SUM(F17:F147) -> 656828984 | G148: =SUM(G17:G147) -> 2.0346091e+08 | H148: =SUM(H17:H147) -> 4.5336808e+08 | J148: =SUM(J17:J147) -> 7369895.4 | K148: =SUM(K17:K147) -> 2.108308e+08 | L148: =SUM(L17:L147) -> 4.4599818e+08
B151: EQUIPOS COMPUTACIONALES
B152: Detalle | C152: Centro de Costo | D152: Fecha | E152: Vida | F152: Valor | G152: Dep. Acum. | H152: Total Acum. | I152: Meses | J152: Depreciación | K152: Total | L152: Total
E153: útil | F153: Inicio | G153: Inicial | H153: Inicial | I153: a Dep. | J153: Ejercicio | K153: Dep. Acum.
B154: Notebook RG HP Spectre | C154: ADMINISTRACION | D154: 44236 | E154: 25 | F154: 840348 | G154: 590240.18 | H154: 250107.82 | I154: 1 | J154: 10004.313 | K154: 600244.49 | L154: 240103.51
B155: Fact. 47 Imp. Export. Globus 1 Impresora Hp | C155: CEDIS | D155: 44151 | E155: 11 | F155: 23010 | G155: 19492.899 | H155: 3517.1006 | I155: 1 | J155: 319.73642 | K155: 19812.636 | L155: 3197.3642
B156: Fact. 47 Imp. Export. Globus 1 Impresora Termica | C156: CEDIS | D156: 44151 | E156: 11 | F156: 40010 | G156: 33895.815 | H156: 6114.1851 | I156: 1 | J156: 555.83501 | K156: 34451.65 | L156: 5558.3501
B157: Fact. 47 Imp. Export. Globus 1 Televisor Samsug | C157: CEDIS | D157: 44151 | E157: 11 | F157: 120010 | G157: 101673.58 | H157: 18336.425 | I157: 1 | J157: 1666.9477 | K157: 103340.52 | L157: 16669.477
B158: Fact. 47 Imp. Export. Globus 1 Computador Hp | C158: CEDIS | D158: 44151 | E158: 11 | F158: 220010 | G158: 186395.81 | H158: 33614.185 | I158: 1 | J158: 3055.835 | K158: 189451.65 | L158: 30558.35
B159: Fact. 47 Imp. Export. Globus 1 Computador Hp | C159: EGAÑA | D159: 44151 | E159: 11 | F159: 220010 | G159: 186395.81 | H159: 33614.185 | I159: 1 | J159: 3055.835 | K159: 189451.65 | L159: 30558.35
B160: Fact. 47 Imp. Export. Globus 1 Impresora Hp | C160: EGAÑA | D160: 44151 | E160: 11 | F160: 23010 | G160: 19492.899 | H160: 3517.1006 | I160: 1 | J160: 319.73642 | K160: 19812.636 | L160: 3197.3642
B161: Fact. 47 Imp. Export. Globus 1 Equipo De Musica | C161: EGAÑA | D161: 44151 | E161: 11 | F161: 50010 | G161: 42367.899 | H161: 7642.1006 | I161: 1 | J161: 694.73642 | K161: 43062.636 | L161: 6947.3642
B162: Fact. 47 Imp. Export. Globus 1 Impresora Termica | C162: EGAÑA | D162: 44151 | E162: 11 | F162: 40010 | G162: 33895.815 | H162: 6114.1851 | I162: 1 | J162: 555.83501 | K162: 34451.65 | L162: 5558.3501
B163: Fact. 47 Imp. Export. Globus 1 Lector Cod Barra | C163: EGAÑA | D163: 44151 | E163: 11 | F163: 35010 | G163: 29659.618 | H163: 5350.3823 | I163: 1 | J163: 486.39839 | K163: 30146.016 | L163: 4863.9839
B164: Fact. 47 Imp. Export. Globus 1 Computador Hp | C164: CEDIS | D164: 44151 | E164: 11 | F164: 220010 | G164: 186395.81 | H164: 33614.185 | I164: 1 | J164: 3055.835 | K164: 189451.65 | L164: 30558.35
B165: Fact. 47 Imp. Export. Globus 1 Impresora Hp | C165: CEDIS | D165: 44151 | E165: 11 | F165: 23010 | G165: 19492.899 | H165: 3517.1006 | I165: 1 | J165: 319.73642 | K165: 19812.636 | L165: 3197.3642
... B227: KREATINA SPA F2614 | C227: OESTE | D227: 45635 | E227: 72 | F227: 1902887 | G227: 271841 | H227: 1631046 | I227: 1 | J227: 22653.417 | K227: 294494.42 | L227: 1608392.6
B228: CHANNELS MEDIA F13168 | C228: OESTE | D228: 45639 | E228: 60 | F228: 204891 | G228: 34148.5 | H228: 170742.5 | I228: 1 | J228: 2845.7083 | K228: 36994.208 | L228: 167896.79 | N228: 0
B229: CHANNELS MEDIA F13169 | C229: OESTE | D229: 45639 | E229: 60 | F229: 3813894 | G229: 635649 | H229: 3178245 | I229: 1 | J229: 52970.75 | K229: 688619.75 | L229: 3125274.2 | N229: 0
B230: IMP Y EXP DE PRODUCTOS TEC. F119765 LECTOR DVD | C230: OESTE | D230: 45751 | E230: 28 | F230: 133172 | G230: 29593.778 | H230: 103578.22 | I230: 1 | J230: 3699.2222 | K230: 33293 | L230: 99879 | N230: 0
B231: ADAN ENRIQUE LOPEZ GALLARDO F497 ROUTER | C231: CEDIS | D231: 45763 | E231: 28 | F231: 117480 | G231: 26106.667 | H231: 91373.333 | I231: 1 | J231: 3263.3333 | K231: 29370 | L231: 88110
B232: ADAN ENRIQUE LOPEZ GALLARDO F496 ROUTER | C232: FLORIDA CENTER | D232: 45763 | E232: 28 | F232: 58740 | G232: 13053.333 | H232: 45686.667 | I232: 1 | J232: 1631.6667 | K232: 14685 | L232: 44055
B233: ADAN ENRIQUE LOPEZ GALLARDO F499 ROUTER | C233: CEDIS | D233: 45783 | E233: 29 | F233: 58740 | G233: 11421.667 | H233: 47318.333 | I233: 1 | J233: 1631.6667 | K233: 13053.333 | L233: 45686.667
B234: KREATINA SPA F2942 | C234: CEDIS | D234: 45964 | E234: 35 | F234: 1935870 | G234: 53774.167 | H234: 1882095.8 | I234: 1 | J234: 53774.167 | K234: 107548.33 | L234: 1828321.7
B235: CHANNELS MEDIA S.A. F13408 | D235: 46041 | E235: 36 | F235: 5187174 | G235: 0 | H235: 5187174 | I235: 0 | J235: 0 | K235: 0 | L235: 5187174
B237: Total Equipos Computacionales | F237: =SUM(F154:F236) -> 109578639 | G237: =SUM(G154:G236) -> 35209840 | H237: =SUM(H154:H236) -> 74368799 | J237: =SUM(J154:J236) -> 1476443 | K237: =SUM(K154:K236) -> 36686283 | L237: =SUM(L154:L236) -> 72892356
B240: ACTIVO EN CONSTRUCCION
B241: DETALLE | C241: Fecha | D241: Valor
B242: PROVISION ANTCIIOS BAP CONSTRUCTORA PLAZA OESTE | C242: PROVISION ANTCIIOS BAP CONSTRUCTORA PLAZA OESTE | D242: =41881933-16806723 -> 25075210
...

Sheet Acreedores diversos (prestamo)
A1: Balance 8 Columnas'!A1 | B1: Flexi Chile Spa | J1: =C8+'Cuentas por pagar EERR'!D9-'Balance Clasificado'!D32 -> 1.7449999
B2: Análisis y Detalle de Acreedores Diversos
B3: =+Carátula!A9 -> Al 31 de enero de 2026
B5: ACREEDORES DIVERSOS - Agrupación
B6: Cuentas | C6: Monto MN $
B7: PRESTAMOS NO BANCARIOS MONTO A PAGAR U$S | C7: =+H51 -> 1.4666872e+08
B8: TOTAL Acreedores Diversos | C8: =SUM(C7:C7) -> 1.4666872e+08
B10: PRESTAMOS NO BANCARIOS MONTO A PAGAR U$S
B11: DETALLE | C11: Monto Historico | D11: US$ | E11: Valor US$ | F11: US$ cierre | G11: Diferencia de Cambio | H11: Valor al cierre
B12: Intereses Ptmo. 11-2020 F3573 pesos mexicanos 12942.80 | C12: 546720.16 | D12: 844.69 | E12: 647.24 | F12: =+'Cajas y Bancos'!F56 -> 865.1 | G12: =+H12-C12 -> 13207.162 | H12: =+E12*F12 -> 559927.32
B13: Intereses Ptmo. 12-2020 F3574 pesos mexicanos 22819.40 | C13: 963920.18 | D13: 844.69 | E13: 1141.15 | F13: =+F12 -> 865.1 | G13: =+H13-C13 -> 23288.688 | H13: =+E13*F13 -> 987208.87
B14: Intereses Ptmo. 01-2021 F4081 | C14: =+D14*E14 -> 1055381 | D14: 844.69 | E14: 1249.43 | F14: =+F13 -> 865.1 | G14: =+H14-C14 -> 25500.866 | H14: =+E14*F14 -> 1080881.9
B15: Intereses Ptmo. 02-2021 F4082 | C15: =+D15*E15 -> 956239.76 | D15: 844.69 | E15: 1132.06 | F15: =+F14 -> 865.1 | G15: =+H15-C15 -> 23105.345 | H15: =+E15*F15 -> 979345.11
B16: Intereses Ptmo. 03-2021 F4083 | C16: =+D16*E16 -> 1082039.4 | D16: 844.69 | E16: 1280.99 | F16: =+F15 -> 865.1 | G16: =+H16-C16 -> 26145.006 | H16: =+E16*F16 -> 1108184.4
B17: Intereses Ptmo. 04-2021 F4084 | C17: =+D17*E17 -> 1034162.4 | D17: 844.69 | E17: 1224.31 | F17: =+F16 -> 865.1 | G17: =+H17-C17 -> 24988.167 | H17: =+E17*F17 -> 1059150.6
B18: Intereses Ptmo. 05-2021 F4085 | C18: =+D18*E18 -> 1033495.1 | D18: 844.69 | E18: 1223.52 | F18: =+F17 -> 865.1 | G18: =+H18-C18 -> 24972.043 | H18: =+E18*F18 -> 1058467.2
B19: Intereses Ptmo. 06-2021 F4086 | C19: =+D19*E19 -> 1005966.7 | D19: 844.69 | E19: 1190.93 | F19: =+F18 -> 865.1 | G19: =+H19-C19 -> 24306.881 | H19: =+E19*F19 -> 1030273.5
B20: Intereses Ptmo. 07-2021 F4087 | C20: =+D20*E20 -> 1279865.8 | D20: 844.69 | E20: 1515.19 | F20: =+F19 -> 865.1 | G20: =+H20-C20 -> 30925.028 | H20: =+E20*F20 -> 1310790.9
B21: Grupo Flexi de León, S A P I de C V F4088 NTERESES AL 31/08/2021 | C21: =+D21*E21 -> 1344814.1 | D21: 844.69 | E21: 1592.08 | F21: =+F20 -> 865.1 | G21: =+H21-C21 -> 32494.353 | H21: =+E21*F21 -> 1377308.4
B22: Intereses Ptmo. 09-2021 F3983 | C22: =+D22*E22 -> 1419357.9 | D22: 844.69 | E22: 1680.33 | F22: =+F21 -> 865.1 | G22: =+H22-C22 -> 34295.535 | H22: =+E22*F22 -> 1453653.5
B23: Intereses Ptmo. 10-2021 F4018 | C23: =+D23*E23 -> 3278132.1 | D23: 844.69 | E23: 3880.87 | F23: =+F22 -> 865.1 | G23: =+H23-C23 -> 79208.557 | H23: =+E23*F23 -> 3357340.6
B24: Intereses Ptmo. 11-2021 F4089 | C24: =+D24*E24 -> 3194947 | D24: 844.69 | E24: 3782.39 | F24: =+F23 -> 865.1 | G24: =+H24-C24 -> 77198.58 | H24: =+E24*F24 -> 3272145.6
B25: Intereses Ptmo. 12-2021 F4128 | C25: =+D25*E25 -> 3693119.8 | D25: 844.69 | E25: =4335.31+36.85 -> 4372.16 | F25: =+F24 -> 865.1 | G25: =+H25-C25 -> 89235.786 | H25: =+E25*F25 -> 3782355.6
B26: Intereses Ptmo. 01-2022 F4209 | C26: 3476066 | D26: 804.2 | E26: 4322.39 | F26: =+F25 -> 865.1 | G26: =+H26-C26 -> 263233.59 | H26: =+E26*F26 -> 3739299.6
B27: Intereses Ptmo. 02-2022 F4257 | C27: =+D27*E27 -> 3219541.7 | D27: 806.03 | E27: 3994.32 | F27: =+F26 -> 865.1 | G27: =+H27-C27 -> 235944.48 | H27: =+E27*F27 -> 3455486.2
B28: Intereses Ptmo. 03-2022 F4313 | C28: 3859137.7 | D28: 807.88 | E28: 4776.87 | F28: =+F27 -> 865.1 | G28: =+H28-C28 -> 273332.5 | H28: =+E28*F28 -> 4132470.2
B29: Intereses Ptmo. 04-2022 F4362 | C29: 4027299 | D29: 867.87 | E29: 4640.44 | F29: =+F28 -> 865.1 | G29: =+H29-C29 -> -12854.356 | H29: =+E29*F29 -> 4014444.6
B30: Intereses Ptmo. 05-2022 F4404 | C30: 4292901.5 | D30: 817.99 | E30: 5248.11 | F30: =+F29 -> 865.1 | G30: =+H30-C30 -> 247238.46 | H30: =+E30*F30 -> 4540140
B31: Intereses Ptmo. 06-2022 F4451 | C31: 4662776 | D31: 972.66 | E31: 4793.84 | F31: =+F30 -> 865.1 | G31: =+H31-C31 -> -515625.02 | H31: =+E31*F31 -> 4147151
B32: Intereses Ptmo. 07-2022 F4519 Grupo Flexi de León S.A.P.I de CV | C32: =E32*D32 -> 4750887.7 | D32: 903.91 | E32: 5255.93 | F32: =+F31 -> 865.1 | G32: =+H32-C32 -> -203982.64 | H32: =+E32*F32 -> 4546905
B33: Intereses Ptmo. 08-2022 F4607 Grupo Flexi de León S.A.P.I de CV | C33: =E33*D33 -> 5271510.1 | D33: 910.27 | E33: 5791.15 | F33: =+F32 -> 865.1 | G33: =+H33-C33 -> -261586.25 | H33: =+E33*F33 -> 5009923.9
B34: Intereses Ptmo. 09-2022 F4663 Grupo Flexi de León S.A.P.I de CV | C34: =E34*D34 -> 5272973.1 | D34: 943.92 | E34: 5586.25 | F34: =+F33 -> 865.1 | G34: =+H34-C34 -> -440308.22 | H34: =+E34*F34 -> 4832664.9
B35: Intereses Ptmo. 10-2022 F4727 Grupo Flexi de León S.A.P.I de CV | C35: =E35*D35 -> 5876644.2 | D35: 932.37 | E35: 6302.91 | F35: =+F32 -> 865.1 | G35: =+H35-C35 -> -423996.76 | H35: =+E35*F35 -> 5452647.4
B36: Intereses Ptmo. 11-2022 F4778 Grupo Flexi de León S.A.P.I de CV | C36: =E36*D36-1 -> 5414209.7 | D36: 884.74 | E36: 6119.55 | F36: =+F33 -> 865.1 | G36: =+H36-C36 -> -120186.96 | H36: =+E36*F36 -> 5294022.7
B37: Intereses Ptmo. 12-2022 F4834 Grupo Flexi de León S.A.P.I de CV | C37: =E37*D37 -> 5568722.3 | D37: 859.51 | E37: 6478.95 | F37: =+F34 -> 865.1 | G37: =+H37-C37 -> 36217.331 | H37: =+E37*F37 -> 5604939.6
B38: Intereses Ptmo. 01-2023 F4917 Grupo Flexi de León S.A.P.I de CV | C38: =E38*D38 -> 5285112.2 | D38: 793.19 | E38: 6663.11 | F38: =+F34 -> 865.1 | G38: =+H38-C38 -> 479144.24 | H38: =+E38*F38 -> 5764256.5
B39: Intereses Ptmo. 02-2023 F4985 Grupo Flexi de León S.A.P.I de CV | C39: =E39*D39 -> 5038995.3 | D39: 802.88 | E39: 6276.15 | F39: =+F34 -> 865.1 | G39: =+H39-C39 -> 390502.05 | H39: =+E39*F39 -> 5429497.4
B40: Intereses Ptmo. 03-2023 F5083 Grupo Flexi de León S.A.P.I de CV | C40: =E40*D40 -> 5617611.5 | D40: 821.49 | E40: 6838.32 | F40: =+F34 -> 865.1 | G40: =+H40-C40 -> 298219.14 | H40: =+E40*F40 -> 5915830.6
B41: Intereses Ptmo. 04-2023 F5147 Grupo Flexi de León S.A.P.I de CV | C41: =E41*D41 -> 5369347.1 | D41: 793.43 | E41: 6767.26 | F41: =+F34 -> 865.1 | G41: =+H41-C41 -> 485009.52 | H41: =+E41*F41 -> 5854356.6
B42: Intereses Ptmo. 05-2023 F5216 Grupo Flexi de León S.A.P.I de CV | C42: =E42*D42 -> 5636806.9 | D42: 797.74 | E42: 7065.97 | F42: =+F34 -> 865.1 | G42: =+H42-C42 -> 475963.74 | H42: =+E42*F42 -> 6112770.6
B43: Intereses Ptmo. 06-2023 F5300 Grupo Flexi de León S.A.P.I de CV | C43: =E43*D43 -> 5424079.8 | D43: 797.87 | E43: 6798.2 | F43: =+F34 -> 865.1 | G43: =+H43-C43 -> 457042.99 | H43: =+E43*F43 -> 5881122.8
B44: Intereses Ptmo. 07-2023 F5390 Grupo Flexi de León S.A.P.I de CV | C44: 5728445 | D44: =C44/E44 -> 840.69002 | E44: 6813.98 | F44: =+F34 -> 865.1 | G44: =+H44-C44 -> 166329.1 | H44: =+E44*F44 -> 5894774.1
B45: Intereses Ptmo. 08-2023 F5464 Grupo Flexi de León S.A.P.I de CV | C45: 5730266 | D45: =C45/E45 -> 872.92002 | E45: 6564.48 | F45: =+F34 -> 865.1 | G45: =+H45-C45 -> -51334.352 | H45: =+E45*F45 -> 5678931.6
B46: Intereses Ptmo. 09-2023 F5553 Grupo Flexi de León S.A.P.I de CV | C46: 5576966.5 | D46: =C46/E46 -> 912.42 | E46: 6112.28 | F46: =+F34 -> 865.1 | G46: =+H46-C46 -> -289233.09 | H46: =+E46*F46 -> 5287733.4
B47: Intereses Ptmo. 10-2023 F5624 Grupo Flexi de León S.A.P.I de CV | C47: 6066516 | D47: =C47/E47 -> 886.28004 | E47: 6844.92 | F47: =+F33 -> 865.1 | G47: =+H47-C47 -> -144975.71 | H47: =+E47*F47 -> 5921540.3
B48: Intereses Ptmo. 11-2023 F5708 Grupo Flexi de León S.A.P.I de CV | C48: 6032326.3 | D48: 874.42 | E48: 6898.66 | F48: =+F34 -> 865.1 | G48: =+H48-C48 -> -64295.511 | H48: =+E48*F48 -> 5968030.8
B49: Intereses Ptmo. 12-2023 F5760 Grupo Flexi de León S.A.P.I de CV | C49: 6027534.5 | D49: 874.42 | E49: 6893.18 | F49: =+F35 -> 865.1 | G49: =+H49-C49 -> -64244.438 | H49: =+E49*F49 -> 5963290
B50: Bonificación intereses Diciembre 2023 N-65 USD220.25 | C50: -219470 | D50: =C50/E50 -> 996.45857 | E50: -220.25 | F50: =+F36 -> 865.1 | G50: =+H50-C50 -> 28931.725 | H50: =+E50*F50 -> -190538.27
B51: Saldo Según Balance | C51: =SUM(C12:C50) -> 1.4489537e+08 | E51: =SUM(E12:E50) -> 169539.62 | G51: =SUM(G12:G50) -> 1773357.6 | H51: =SUM(H12:H50)-3 -> 1.4666872e+08 | I51: OK
H52: 153794472
E53: =+E51+'Cuentas por pagar EERR'!F325+'Cuentas por pagar EERR'!F328+'Cuentas por pagar EERR'!F16 -> 1596511 | H53: =H51-H52 -> -7125749.7 | I53: dif

Sheet Acreedores Diversos
A1: Balance 8 Columnas'!A1 | B1: Flexi Chile Spa | I1: =+C10-'Balance Clasificado'!D30 -> 0
B2: Análisis y Detalle de Acreedores Diversos
B3: =+'Activo fijo'!B3:G3 -> Al 31 de enero de 2026
B6: ACREEDORES DIVERSOS - Agrupación
B7: Cuentas | C7: Monto MN $
B8: CUENTAS POR PAGAR | C8: =+D17 -> 4868888
B9: TARJETA CREDITO CLP | C9: =+D23 -> -570836
B10: TOTAL Acreedores Diversos | C10: =SUM(C8:C9) -> 4298052
B12: ACREEDORES DIVERSOS - Detalle
B14: CUENTAS POR PAGAR BANCO SANTANDER (Boletas en garantia)
B15: Detalle | C15: Fecha | D15: Valor
B16: Banco Santander (Boleta garantia) | C16: 46053 | D16: 4868888
B17: Total del mes | D17: =SUM(D16:D16) -> 4868888 | E17: ok
B19: TARJETA CREDITO CLP
B20: Detalle | C20: Fecha | D20: Valor
B21: TDC diciembre | C21: 46022 | D21: =3345848-2405680-2095615 -> -1155447
B22: TDC enero | C22: 46036 | D22: =-3498892+4083503 -> 584611
B23: Total del mes | D23: =SUM(D21:D22) -> -570836 | E23: ok

Sheet Cuentas por pagar EERR
A1: Balance 8 Columnas'!A1 | B1: Flexi Chile Spa | N1: =D9+'Acreedores diversos (prestamo)'!C8-'Balance Clasificado'!D32 -> 1.7449999
B2: Análisis y Detalle de Cuentas por pagar a entidades relacionadas
B3: =+Carátula!A9 -> Al 31 de enero de 2026
B6: CUENTAS POR PAGAR A ENTIDADES RELACIONADAS - Agrupación
B7: Cuentas | D7: Monto MN $
B8: PROVEEDORES US$ | D8: =+I339 -> 1.2349046e+09
B9: TOTAL Cuentas por pagar a entidades relacionadas | D9: =SUM(D8:D8) -> 1.2349046e+09
B11: CUENTAS POR PAGAR A ENTIDADES RELACIONADAS - Detalle
G12: 899.44
B13: PROVEEDORES US$
B14: Fecha | C14: Detalle | D14: Monto MN | E14: US$ | F14: Valor US$ | G14: US$ cierre | H14: Diferencia de Cambio | I14: Valor al cierre
B15: 45218 | C15: Invoice Q-00323445 Distribuidora QLI SAPI de CV | D15: 71227.96 | E15: 937.21 | F15: 76 | G15: 865.1 | H15: =+I15-D15 -> -5480.36 | I15: =+F15*G15 -> 65747.6 | J15: =+I15 -> 65747.6 | K15: 907.13 | L15: =K15*F15 -> 68941.88 | M15: =I15-L15 -> -3194.28
C16: Total Quirelli Mexico | D16: =SUM(D15:D15) -> 71227.96 | F16: =SUM(F15:F15) -> 76 | H16: =SUM(H15:H15) -> -5480.36 | I16: =SUM(I15:I15) -> 65747.6 | J16: =SUM(J15:J15) -> 65747.6 | L16: =SUM(L15:L15) -> 68941.88 | M16: =I16-L16 -> -3194.28 | N16: dif,cambio
B18: 44861 | C18: Invoice A5651549 Distribuidora Flexi | D18: 2860772.6 | E18: 953 | F18: 3001.86 | G18: 865.1 | H18: =+I18-D18 -> -263863.49 | I18: =+F18*G18 -> 2596909.1 | J18: =+I18 -> 2596909.1 | K18: 907.13 | L18: =K18*F18 -> 2723077.3 | M18: =I18-L18 -> -126168.18
B19: 45197 | C19: Invoice A-06219967 Distribuidora Flexi SA de CV | D19: 1327982.2 | E19: 904.62 | F19: 1468 | G19: =+G18 -> 865.1 | H19: =+I19-D19 -> -58015.36 | I19: =+F19*G19 -> 1269966.8 | J19: =+I19 -> 1269966.8 | K19: =+K18 -> 907.13 | L19: =K19*F19 -> 1331666.8 | M19: =I19-L19 -> -61700.04
B20: 45254 | C20: invoice A-06279448Distribuidora Flexi SA de CV TC871.38 | D20: 1158935.4 | E20: 871.38 | F20: 1330 | G20: =+G19 -> 865.1 | H20: =+I20-D20 -> -8352.4 | I20: =+F20*G20 -> 1150583 | J20: =SUM(I20:I20) -> 1150583 | K20: =+K19 -> 907.13 | L20: =K20*F20 -> 1206482.9 | M20: =I20-L20 -> -55899.9
B21: 45274 | C21: Invoice A-06294382 Distribuidora Flexi SA de CV tc876.77 | D21: 1166104.1 | E21: 876.77 | F21: 1330 | G21: =+G20 -> 865.1 | H21: =+I21-D21 -> -15521.1 | I21: =+F21*G21 -> 1150583 | J21: =SUM(I21:I21) -> 1150583 | K21: =+K20 -> 907.13 | L21: =K21*F21 -> 1206482.9 | M21: =I21-L21 -> -55899.9
B22: 45310 | C22: Invoice A-06307260 Distribuidora Flexi SA de CV tc918.62 | D22: =F22*E22 -> 1221764.6 | E22: 918.62 | F22: 1330 | G22: =+G21 -> 865.1 | H22: =+I22-D22 -> -71181.6 | I22: =+F22*G22 -> 1150583 | J22: =SUM(I22:I22) -> 1150583 | K22: =+K21 -> 907.13 | L22: =K22*F22 -> 1206482.9 | M22: =I22-L22 -> -55899.9
B23: 45513 | C23: Diferencia cobranza | D23: =F23*E23 -> -158078.41 | E23: 996.46 | F23: -158.64 | G23: =+G22 -> 865.1 | H23: =+I23-D23 -> 20838.95 | I23: =+F23*G23 -> -137239.46 | J23: =+I23 -> -137239.46 | K23: =+K22 -> 907.13 | L23: =K23*F23 -> -143907.1 | M23: =I23-L23 -> 6667.6392
B24: 45700 | C24: Invoice A-06610153Distribuidora Flexi S de CV USD 1260 TC 961.89 | D24: 1211981.4 | E24: 961.89 | F24: 1260 | G24: =+G23 -> 865.1 | H24: =+I24-D24 -> -121955.4 | I24: =+F24*G24 -> 1090026 | J24: =+I24 -> 1090026 | K24: =+K23 -> 907.13 | L24: =K24*F24 -> 1142983.8 | M24: =I24-L24 -> -52957.8
B25: 45728 | C25: Invoice A-06646504 Distribuidora Flexi S de CV USD 15785 TC 937.45 | D25: 14797648 | E25: 937.45 | F25: 15785 | G25: =+G24 -> 865.1 | H25: =+I25-D25 -> -1142044.8 | I25: =+F25*G25 -> 13655604 | K25: =+K24 -> 907.13 | L25: =K25*F25 -> 14319047 | M25: =I25-L25 -> -663443.55
B26: 45728 | C26: Invoice A-06646514 Distribuidora Flexi S de CV USD 3163.2 TC 937.45 | D26: 2965341.8 | E26: 937.45 | F26: 3163.2 | G26: =+G25 -> 865.1 | H26: =+I26-D26 -> -228857.52 | I26: =+F26*G26 -> 2736484.3 | K26: =+K25 -> 907.13 | L26: =K26*F26 -> 2869433.6 | M26: =I26-L26 -> -132949.3
B27: 45728 | C27: Invoice A-06646518 Distribuidora Flexi S de CV USD 1787.2 TC 937.45 | D27: 1675410.6 | E27: 937.45 | F27: 1787.2 | G27: =+G26 -> 865.1 | H27: =+I27-D27 -> -129303.92 | I27: =+F27*G27 -> 1546106.7 | K27: =+K26 -> 907.13 | L27: =K27*F27 -> 1621222.7 | M27: =I27-L27 -> -75116.016
B28: 45728 | C28: Invoice A-06646519 Distribuidora Flexi S de CV USD 3204 TC 937.45 | D28: 3003589.8 | E28: 937.45 | F28: 3204 | G28: =+G27 -> 865.1 | H28: =+I28-D28 -> -231809.4 | I28: =+F28*G28 -> 2771780.4 | K28: =+K27 -> 907.13 | L28: =K28*F28 -> 2906444.5 | M28: =I28-L28 -> -134664.12
B29: 45728 | C29: Invoice A-06646520 Distribuidora Flexi S de CV USD 1787.2 TC 937.45 | D29: 1675410.6 | E29: 937.45 | F29: 1787.2 | G29: =+G28 -> 865.1 | H29: =+I29-D29 -> -129303.92 | I29: =+F29*G29 -> 1546106.7 | K29: =+K28 -> 907.13 | L29: =K29*F29 -> 1621222.7 | M29: =I29-L29 -> -75116.016
B30: 45728 | C30: Invoice A-06646521 Distribuidora Flexi S de CV USD 3204 TC 937.45 | D30: 3003589.8 | E30: 937.45 | F30: 3204 | G30: =+G29 -> 865.1 | H30: =+I30-D30 -> -231809.4 | I30: =+F30*G30 -> 2771780.4 | K30: =+K29 -> 907.13 | L30: =K30*F30 -> 2906444.5 | M30: =I30-L30 -> -134664.12
B31: 45728 | C31: Invoice A-06646523 Distribuidora Flexi S de CV USD 3204 TC 937.45 | D31: 3003589.8 | E31: 937.45 | F31: 3204 | G31: =+G30 -> 865.1 | H31: =+I31-D31 -> -231809.4 | I31: =+F31*G31 -> 2771780.4 | K31: =+K30 -> 907.13 | L31: =K31*F31 -> 2906444.5 | M31: =I31-L31 -> -134664.12
B32: 45728 | C32: Invoice A-06646524 Distribuidora Flexi S de CV USD 1414.1 TC 937.45 | D32: 1325648 | E32: 937.45 | F32: 1414.1 | G32: =+G31 -> 865.1 | H32: =+I32-D32 -> -102310.14 | I32: =+F32*G32 -> 1223337.9 | K32: =+K31 -> 907.13 | L32: =K32*F32 -> 1282772.5 | M32: =I32-L32 -> -59434.623
B33: 45728 | C33: Invoice A-06646525 Distribuidora Flexi S de CV USD 3204 TC 937.45 | D33: 3003589.8 | E33: 937.45 | F33: 3204 | G33: =+G32 -> 865.1 | H33: =+I33-D33 -> -231809.4 | I33: =+F33*G33 -> 2771780.4 | K33: =+K32 -> 907.13 | L33: =K33*F33 -> 2906444.5 | M33: =I33-L33 -> -134664.12
B34: 45728 | C34: Invoice A-06646527 Distribuidora Flexi S de CV USD 1414.1 TC 937.45 | D34: 1325648 | E34: 937.45 | F34: 1414.1 | G34: =+G33 -> 865.1 | H34: =+I34-D34 -> -102310.14 | I34: =+F34*G34 -> 1223337.9 | K34: =+K33 -> 907.13 | L34: =K34*F34 -> 1282772.5 | M34: =I34-L34 -> -59434.623
B35: 45728 | C35: Invoice A-06646528 Distribuidora Flexi S de CV USD 3204 TC 937.45 | D35: 3003589.8 | E35: 937.45 | F35: 3204 | G35: =+G34 -> 865.1 | H35: =+I35-D35 -> -231809.4 | I35: =+F35*G35 -> 2771780.4 | K35: =+K34 -> 907.13 | L35: =K35*F35 -> 2906444.5 | M35: =I35-L35 -> -134664.12
B36: 45728 | C36: Invoice A-06646529 Distribuidora Flexi S de CV USD 863.4 TC 937.45 | D36: 809394.33 | E36: 937.45 | F36: 863.4 | G36: =+G35 -> 865.1 | H36: =+I36-D36 -> -62466.99 | I36: =+F36*G36 -> 746927.34 | K36: =+K35 -> 907.13 | L36: =K36*F36 -> 783216.04 | M36: =I36-L36 -> -36288.702
... B71: 45726 | C71: Invoice A-06644716 Distribuidora Flexi S de CV USD 1260 TC 928.25 | D71: 1169595 | E71: 928.25 | F71: 1260 | G71: =+G70 -> 865.1 | H71: =+I71-D71 -> -79569 | I71: =+F71*G71 -> 1090026 | K71: =+K70 -> 907.13 | L71: =K71*F71 -> 1142983.8 | M71: =I71-L71 -> -52957.8
B72: 45747 | C72: Invoice A-06671425 Distribuidora Flexi S de CV USD 1260 TC 946.1 | D72: 1192086 | E72: 946.1 | F72: 1260 | G72: =+G71 -> 865.1 | H72: =+I72-D72 -> -102060 | I72: =+F72*G72 -> 1090026 | J72: =SUM(I25:I72) -> 2.4079258e+08 | K72: =+K71 -> 907.13 | L72: =K72*F72 -> 1142983.8 | M72: =I72-L72 -> -52957.8
B73: 45768 | C73: Invoice A-06686288 Distribuidora Flexi S de CV USD 2280 TC968.71 | D73: =F73*E73 -> 2208658.8 | E73: 968.71 | F73: 2280 | G73: =+G72 -> 865.1 | H73: =+I73-D73 -> -236230.8 | I73: =+F73*G73 -> 1972428 | K73: =+K72 -> 907.13 | L73: =K73*F73 -> 2068256.4 | M73: =I73-L73 -> -95828.4
B74: 45751 | C74: Invoice A-06675516 Distribuidora Flexi S de CV USD 216.9 TC946.59 | D74: =F74*E74 -> 205315.37 | E74: 946.59 | F74: 216.9 | G74: =+G73 -> 865.1 | H74: =+I74-D74 -> -17675.181 | I74: =+F74*G74 -> 187640.19 | K74: =+K73 -> 907.13 | L74: =K74*F74 -> 196756.5 | M74: =I74-L74 -> -9116.307
B75: 45751 | C75: Invoice A-06675517 Distribuidora Flexi S de CV USD 751.2 TC946.59 | D75: =F75*E75 -> 711078.41 | E75: 946.59 | F75: 751.2 | G75: =+G74 -> 865.1 | H75: =+I75-D75 -> -61215.288 | I75: =+F75*G75 -> 649863.12 | K75: =+K74 -> 907.13 | L75: =K75*F75 -> 681436.06 | M75: =I75-L75 -> -31572.936
B76: 45751 | C76: Invoice A-06675518 Distribuidora Flexi S de CV USD 190.5 TC946.59 | D76: =F76*E76 -> 180325.4 | E76: 946.59 | F76: 190.5 | G76: =+G75 -> 865.1 | H76: =+I76-D76 -> -15523.845 | I76: =+F76*G76 -> 164801.55 | K76: =+K75 -> 907.13 | L76: =K76*F76 -> 172808.26 | M76: =I76-L76 -> -8006.715
B77: 45751 | C77: Invoice A-06675519 Distribuidora Flexi S de CV USD 2164.2 TC946.59 | D77: =F77*E77 -> 2048610.1 | E77: 946.59 | F77: 2164.2 | G77: =+G76 -> 865.1 | H77: =+I77-D77 -> -176360.66 | I77: =+F77*G77 -> 1872249.4 | K77: =+K76 -> 907.13 | L77: =K77*F77 -> 1963210.7 | M77: =I77-L77 -> -90961.326
B78: 45756 | C78: Invoice A-06680430 Distribuidora Flexi S de CV USD 8618.4 TC939.89 | D78: =F78*E78 -> 8100348 | E78: 939.89 | F78: 8618.4 | G78: =+G77 -> 865.1 | H78: =+I78-D78 -> -644570.14 | I78: =+F78*G78 -> 7455777.8 | J78: =SUM(I73:I78) -> 12302760 | K78: =+K77 -> 907.13 | L78: =K78*F78 -> 7818009.2 | M78: =I78-L78 -> -362231.35
B79: 45797 | C79: Invoice A-06713146 Distribuidora Flexi S de CV USD 1260 TC936.69 | D79: =F79*E79 -> 1180229.4 | E79: 936.69 | F79: 1260 | G79: =+G78 -> 865.1 | H79: =+I79-D79 -> -90203.4 | I79: =+F79*G79 -> 1090026 | K79: =+K78 -> 907.13 | L79: =K79*F79 -> 1142983.8 | M79: =I79-L79 -> -52957.8
B80: 45783 | C80: Invoice A-06702164 Distribuidora Flexi S de CV USD 264 TC940.18 | D80: =F80*E80 -> 248207.52 | E80: 940.18 | F80: 264 | G80: =+G79 -> 865.1 | H80: =+I80-D80 -> -19821.12 | I80: =+F80*G80 -> 228386.4 | K80: =+K79 -> 907.13 | L80: =K80*F80 -> 239482.32 | M80: =I80-L80 -> -11095.92
B81: 45783 | C81: Invoice A-06702165 Distribuidora Flexi S de CV USD 652 TC940.18 | D81: =F81*E81 -> 612997.36 | E81: 940.18 | F81: 652 | G81: =+G80 -> 865.1 | H81: =+I81-D81 -> -48952.16 | I81: =+F81*G81 -> 564045.2 | K81: =+K80 -> 907.13 | L81: =K81*F81 -> 591448.76 | M81: =I81-L81 -> -27403.56
B82: 45783 | C82: Invoice A-06702166 Distribuidora Flexi S de CV USD 264 TC940.18 | D82: =F82*E82 -> 248207.52 | E82: 940.18 | F82: 264 | G82: =+G81 -> 865.1 | H82: =+I82-D82 -> -19821.12 | I82: =+F82*G82 -> 228386.4 | K82: =+K81 -> 907.13 | L82: =K82*F82 -> 239482.32 | M82: =I82-L82 -> -11095.92
B83: 45783 | C83: Invoice A-06702167 Distribuidora Flexi S de CV USD 652 TC940.18 | D83: =F83*E83 -> 612997.36 | E83: 940.18 | F83: 652 | G83: =+G82 -> 865.1 | H83: =+I83-D83 -> -48952.16 | I83: =+F83*G83 -> 564045.2 | K83: =+K82 -> 907.13 | L83: =K83*F83 -> 591448.76 | M83: =I83-L83 -> -27403.56
B84: 45783 | C84: Invoice A-06702168 Distribuidora Flexi S de CV USD 1072.5 TC940.18 | D84: =F84*E84 -> 1008343 | E84: 940.18 | F84: 1072.5 | G84: =+G83 -> 865.1 | H84: =+I84-D84 -> -80523.3 | I84: =+F84*G84 -> 927819.75 | K84: =+K83 -> 907.13 | L84: =K84*F84 -> 972896.93 | M84: =I84-L84 -> -45077.175
B85: 45783 | C85: Invoice A-06702169 Distribuidora Flexi S de CV USD 9867.3 TC940.18 | D85: =F85*E85 -> 9277038.1 | E85: 940.18 | F85: 9867.3 | G85: =+G84 -> 865.1 | H85: =+I85-D85 -> -740836.88 | I85: =+F85*G85 -> 8536201.2 | K85: =+K84 -> 907.13 | L85: =K85*F85 -> 8950923.8 | M85: =I85-L85 -> -414722.62
B86: 45783 | C86: Invoice A-06702170 Distribuidora Flexi S de CV USD 5430 TC940.18 | D86: =F86*E86 -> 5105177.4 | E86: 940.18 | F86: 5430 | G86: =+G85 -> 865.1 | H86: =+I86-D86 -> -407684.4 | I86: =+F86*G86 -> 4697493 | K86: =+K85 -> 907.13 | L86: =K86*F86 -> 4925715.9 | M86: =I86-L86 -> -228222.9
B87: 45783 | C87: Invoice A-06702171 Distribuidora Flexi S de CV USD 4881 TC940.18 | D87: =F87*E87 -> 4589018.6 | E87: 940.18 | F87: 4881 | G87: =+G86 -> 865.1 | H87: =+I87-D87 -> -366465.48 | I87: =+F87*G87 -> 4222553.1 | K87: =+K86 -> 907.13 | L87: =K87*F87 -> 4427701.5 | M87: =I87-L87 -> -205148.43
B88: 45783 | C88: Invoice A-06702172 Distribuidora Flexi S de CV USD 2050.2 TC940.18 | D88: =F88*E88 -> 1927557 | E88: 940.18 | F88: 2050.2 | G88: =+G87 -> 865.1 | H88: =+I88-D88 -> -153929.02 | I88: =+F88*G88 -> 1773628 | K88: =+K87 -> 907.13 | L88: =K88*F88 -> 1859797.9 | M88: =I88-L88 -> -86169.906
B89: 45783 | C89: Invoice A-06702173 Distribuidora Flexi S de CV USD 1188 TC940.18 | D89: =F89*E89 -> 1116933.8 | E89: 940.18 | F89: 1188 | G89: =+G88 -> 865.1 | H89: =+I89-D89 -> -89195.04 | I89: =+F89*G89 -> 1027738.8 | K89: =+K88 -> 907.13 | L89: =K89*F89 -> 1077670.4 | M89: =I89-L89 -> -49931.64
B90: 45783 | C90: Invoice A-06702174 Distribuidora Flexi S de CV USD 3912 TC940.18 | D90: =F90*E90 -> 3677984.2 | E90: 940.18 | F90: 3912 | G90: =+G89 -> 865.1 | H90: =+I90-D90 -> -293712.96 | I90: =+F90*G90 -> 3384271.2 | K90: =+K89 -> 907.13 | L90: =K90*F90 -> 3548692.6 | M90: =I90-L90 -> -164421.36
... B134: 45783 | C134: Invoice A-06702218 Distribuidora Flexi S de CV USD 1777 TC940.18 | D134: =F134*E134 -> 1670699.9 | E134: 940.18 | F134: 1777 | G134: =+G133 -> 865.1 | H134: =+I134-D134 -> -133417.16 | I134: =+F134*G134 -> 1537282.7 | K134: =+K133 -> 907.13 | L134: =K134*F134 -> 1611970 | M134: =I134-L134 -> -74687.31
B135: 45793 | C135: Invoice A-06712019 Distribuidora Flexi S de CV USD 11542 TC940.25 | D135: =F135*E135 -> 10852366 | E135: 940.25 | F135: 11542 | G135: =+G134 -> 865.1 | H135: =+I135-D135 -> -867381.3 | I135: =+F135*G135 -> 9984984.2 | J135: =SUM(I79:I135) -> 1.3479478e+08 | K135: =+K134 -> 907.13 | L135: =K135*F135 -> 10470094 | M135: =I135-L135 -> -485110.26
B136: 45817 | C136: Invoice A-06731287 Distribuidora Flexi de CV USD2145 TC933.91 | D136: =F136*E136 -> 2003236.9 | E136: 933.91 | F136: 2145 | G136: =+G135 -> 865.1 | H136: =+I136-D136 -> -147597.45 | I136: =+F136*G136 -> 1855639.5 | K136: =+K135 -> 907.13 | L136: =K136*F136 -> 1945793.9 | M136: =I136-L136 -> -90154.35
B137: 45812 | C137: Invoice A-06726892 Distribuidora Flexi de CV USD3494.4 TC941.53 | D137: =F137*E137 -> 3290082.4 | E137: 941.53 | F137: 3494.4 | G137: =+G136 -> 865.1 | H137: =+I137-D137 -> -267076.99 | I137: =+F137*G137 -> 3023005.4 | K137: =+K136 -> 907.13 | L137: =K137*F137 -> 3169875.1 | M137: =I137-L137 -> -146869.63
B138: 45812 | C138: Invoice A-06727101 Distribuidora Flexi de CV USD28781.6 TC941.53 | D138: =F138*E138 -> 27098740 | E138: 941.53 | F138: 28781.6 | G138: =+G137 -> 865.1 | H138: =+I138-D138 -> -2199777.7 | I138: =+F138*G138 -> 24898962 | K138: =+K137 -> 907.13 | L138: =K138*F138 -> 26108653 | M138: =I138-L138 -> -1209690.6
B139: 45824 | C139: Invoice A-06737954 Distribuidora Flexi de CV USD4032 TC937.78 | D139: =F139*E139 -> 3781129 | E139: 937.78 | F139: 4032 | G139: =+G138 -> 865.1 | H139: =+I139-D139 -> -293045.76 | I139: =+F139*G139 -> 3488083.2 | K139: =+K138 -> 907.13 | L139: =K139*F139 -> 3657548.2 | M139: =I139-L139 -> -169464.96
B140: 45831 | C140: Invoice A-06745447 Distribuidora Flexi de CV USD10232 TC947.03 | D140: =F140*E140 -> 9690011 | E140: 947.03 | F140: 10232 | G140: =+G139 -> 865.1 | H140: =+I140-D140 -> -838307.76 | I140: =+F140*G140 -> 8851703.2 | K140: =+K139 -> 907.13 | L140: =K140*F140 -> 9281754.2 | M140: =I140-L140 -> -430050.96
B141: 45833 | C141: Invoice A-06747530 Distribuidora Flexi de CV USD302.5 TC937.89 | D141: =F141*E141 -> 283711.72 | E141: 937.89 | F141: 302.5 | G141: =+G140 -> 865.1 | H141: =+I141-D141 -> -22018.975 | I141: =+F141*G141 -> 261692.75 | K141: =+K140 -> 907.13 | L141: =K141*F141 -> 274406.83 | M141: =I141-L141 -> -12714.075
B142: 45833 | C142: Invoice A-06747531 Distribuidora Flexi de CV USD174 TC937.89 | D142: =F142*E142 -> 163192.86 | E142: 937.89 | F142: 174 | G142: =+G141 -> 865.1 | H142: =+I142-D142 -> -12665.46 | I142: =+F142*G142 -> 150527.4 | J142: =SUM(I136:I142) -> 42529614 | K142: =+K141 -> 907.13 | L142: =K142*F142 -> 157840.62 | M142: =I142-L142 -> -7313.22
B143: 45845 | C143: Invoice A-06759294 Distribuidora Flexi de CV USD 9016 TC932.34 | D143: =F143*E143 -> 8405977.4 | E143: 932.34 | F143: 9016 | G143: =+G142 -> 865.1 | H143: =+I143-D143 -> -606235.84 | I143: =+F143*G143 -> 7799741.6 | K143: =+K142 -> 907.13 | L143: =K143*F143 -> 8178684.1 | M143: =I143-L143 -> -378942.48
B144: 45845 | C144: Invoice A-06759329 Distribuidora Flexi de CV USD 1056 TC932.34 | D144: =F144*E144 -> 984551.04 | E144: 932.34 | F144: 1056 | G144: =+G143 -> 865.1 | H144: =+I144-D144 -> -71005.44 | I144: =+F144*G144 -> 913545.6 | K144: =+K143 -> 907.13 | L144: =K144*F144 -> 957929.28 | M144: =I144-L144 -> -44383.68
B145: 45845 | C145: Invoice A-06759330 Distribuidora Flexi de CV USD 30060.4 TC932.34 | D145: =F145*E145 -> 28026513 | E145: 932.34 | F145: 30060.4 | G145: =+G144 -> 865.1 | H145: =+I145-D145 -> -2021261.3 | I145: =+F145*G145 -> 26005252 | K145: =+K144 -> 907.13 | L145: =K145*F145 -> 27268691 | M145: =I145-L145 -> -1263438.6
B146: 45845 | C146: Invoice A-06759331 Distribuidora Flexi de CV USD 8772 TC932.34 | D146: =F146*E146 -> 8178486.5 | E146: 932.34 | F146: 8772 | G146: =+G145 -> 865.1 | H146: =+I146-D146 -> -589829.28 | I146: =+F146*G146 -> 7588657.2 | K146: =+K145 -> 907.13 | L146: =K146*F146 -> 7957344.4 | M146: =I146-L146 -> -368687.16
B147: 45845 | C147: Invoice A-06759469 Distribuidora Flexi de CV USD 46080 TC932.34 | D147: =F147*E147 -> 42962227 | E147: 932.34 | F147: 46080 | G147: =+G146 -> 865.1 | H147: =+I147-D147 -> -3098419.2 | I147: =+F147*G147 -> 39863808 | K147: =+K146 -> 907.13 | L147: =K147*F147 -> 41800550 | M147: =I147-L147 -> -1936742.4
B148: 45845 | C148: Invoice A-06759470 Distribuidora Flexi de CV USD 53840 TC932.34 | D148: =F148*E148 -> 50197186 | E148: 932.34 | F148: 53840 | G148: =+G147 -> 865.1 | H148: =+I148-D148 -> -3620201.6 | I148: =+F148*G148 -> 46576984 | K148: =+K147 -> 907.13 | L148: =K148*F148 -> 48839879 | M148: =I148-L148 -> -2262895.2
B149: 45849 | C149: Invoice A-06763930 Distribuidora Flexi de CV USD 1163.8 TC950.43 | D149: =F149*E149 -> 1106110.4 | E149: 950.43 | F149: 1163.8 | G149: =+G148 -> 865.1 | H149: =+I149-D149 -> -99307.054 | I149: =+F149*G149 -> 1006803.4 | K149: =+K148 -> 907.13 | L149: =K149*F149 -> 1055717.9 | M149: =I149-L149 -> -48914.514
B150: 45849 | C150: Invoice A-06763931 Distribuidora Flexi de CV USD 1028.8 TC950.43 | D150: =F150*E150 -> 977802.38 | E150: 950.43 | F150: 1028.8 | G150: =+G149 -> 865.1 | H150: =+I150-D150 -> -87787.504 | I150: =+F150*G150 -> 890014.88 | K150: =+K149 -> 907.13 | L150: =K150*F150 -> 933255.34 | M150: =I150-L150 -> -43240.464
B151: 45849 | C151: Invoice A-06763932 Distribuidora Flexi de CV USD 3023.5 TC950.43 | D151: =F151*E151 -> 2873625.1 | E151: 950.43 | F151: 3023.5 | G151: =+G150 -> 865.1 | H151: =+I151-D151 -> -257995.25 | I151: =+F151*G151 -> 2615629.9 | K151: =+K150 -> 907.13 | L151: =K151*F151 -> 2742707.6 | M151: =I151-L151 -> -127077.71
B152: 45849 | C152: Invoice A-06763933 Distribuidora Flexi de CV USD 7411.5 TC950.43 | D152: =F152*E152 -> 7044111.9 | E152: 950.43 | F152: 7411.5 | G152: =+G151 -> 865.1 | H152: =+I152-D152 -> -632423.29 | I152: =+F152*G152 -> 6411688.7 | K152: =+K151 -> 907.13 | L152: =K152*F152 -> 6723194 | M152: =I152-L152 -> -311505.34
B153: 45849 | C153: Invoice A-06763934 Distribuidora Flexi de CV USD 6600 TC950.43 | D153: =F153*E153 -> 6272838 | E153: 950.43 | F153: 6600 | G153: =+G152 -> 865.1 | H153: =+I153-D153 -> -563178 | I153: =+F153*G153 -> 5709660 | K153: =+K152 -> 907.13 | L153: =K153*F153 -> 5987058 | M153: =I153-L153 -> -277398
B154: 45849 | C154: Invoice A-06763935 Distribuidora Flexi de CV USD 164.1 TC950.43 | D154: =F154*E154 -> 155965.56 | E154: 950.43 | F154: 164.1 | G154: =+G153 -> 865.1 | H154: =+I154-D154 -> -14002.653 | I154: =+F154*G154 -> 141962.91 | K154: =+K153 -> 907.13 | L154: =K154*F154 -> 148860.03 | M154: =I154-L154 -> -6897.123
... B189: 45849 | C189: Invoice A-06763989 Distribuidora Flexi de CV USD 2443 TC950.43 | D189: =F189*E189 -> 2321900.5 | E189: 950.43 | F189: 2443 | G189: =+G188 -> 865.1 | H189: =+I189-D189 -> -208461.19 | I189: =+F189*G189 -> 2113439.3 | K189: =+K188 -> 907.13 | L189: =K189*F189 -> 2216118.6 | M189: =I189-L189 -> -102679.29
B190: 45849 | C190: Invoice A-06763990 Distribuidora Flexi de CV USD 6600 TC950.43 | D190: =F190*E190 -> 6272838 | E190: 950.43 | F190: 6600 | G190: =+G189 -> 865.1 | H190: =+I190-D190 -> -563178 | I190: =+F190*G190 -> 5709660 | J190: =SUM(I143:I190) -> 2.6043325e+08 | K190: =+K189 -> 907.13 | L190: =K190*F190 -> 5987058 | M190: =I190-L190 -> -277398
B191: 45873 | C191: Invoice A-06787498 Distribuidora Flexi SA de CV USD1311TC 967.48 | D191: =F191*E191 -> 1268366.3 | E191: 967.48 | F191: 1311 | G191: =+G190 -> 865.1 | H191: =+I191-D191 -> -134220.18 | I191: =+F191*G191 -> 1134146.1 | K191: =+K190 -> 907.13 | L191: =K191*F191 -> 1189247.4 | M191: =I191-L191 -> -55101.33
B192: 45884 | C192: Invoice A-06800369 Distribuidora Flexi SA de CV USD7296TC 952.37 | D192: =F192*E192 -> 6948491.5 | E192: 952.37 | F192: 7296 | G192: =+G191 -> 865.1 | H192: =+I192-D192 -> -636721.92 | I192: =+F192*G192 -> 6311769.6 | K192: =+K191 -> 907.13 | L192: =K192*F192 -> 6618420.5 | M192: =I192-L192 -> -306650.88
B193: 45884 | C193: Invoice A-06800370 Distribuidora Flexi SA de CV USD194TC 952.37 | D193: =F193*E193 -> 184759.78 | E193: 952.37 | F193: 194 | G193: =+G192 -> 865.1 | H193: =+I193-D193 -> -16930.38 | I193: =+F193*G193 -> 167829.4 | K193: =+K192 -> 907.13 | L193: =K193*F193 -> 175983.22 | M193: =I193-L193 -> -8153.82
B194: 45887 | C194: Invoice A-06801359 Distribuidora Flexi SA de CV USD979TC 961.84 | D194: =F194*E194 -> 941641.36 | E194: 961.84 | F194: 979 | G194: =+G193 -> 865.1 | H194: =+I194-D194 -> -94708.46 | I194: =+F194*G194 -> 846932.9 | K194: =+K193 -> 907.13 | L194: =K194*F194 -> 888080.27 | M194: =I194-L194 -> -41147.37
B195: 45887 | C195: Invoice A-06801360 Distribuidora Flexi SA de CV USD11969.5TC 961.84 | D195: =F195*E195 -> 11512744 | E195: 961.84 | F195: 11969.5 | G195: =+G194 -> 865.1 | H195: =+I195-D195 -> -1157929.4 | I195: =+F195*G195 -> 10354814 | K195: =+K194 -> 907.13 | L195: =K195*F195 -> 10857893 | M195: =I195-L195 -> -503078.08
B196: 45887 | C196: Invoice A-06801361 Distribuidora Flexi SA de CV USD1029.5TC 961.84 | D196: =F196*E196 -> 990214.28 | E196: 961.84 | F196: 1029.5 | G196: =+G195 -> 865.1 | H196: =+I196-D196 -> -99593.83 | I196: =+F196*G196 -> 890620.45 | K196: =+K195 -> 907.13 | L196: =K196*F196 -> 933890.33 | M196: =I196-L196 -> -43269.885
B197: 45887 | C197: Invoice A-06801362 Distribuidora Flexi SA de CV USD12194.5TC 961.84 | D197: =F197*E197 -> 11729158 | E197: 961.84 | F197: 12194.5 | G197: =+G196 -> 865.1 | H197: =+I197-D197 -> -1179695.9 | I197: =+F197*G197 -> 10549462 | K197: =+K196 -> 907.13 | L197: =K197*F197 -> 11061997 | M197: =I197-L197 -> -512534.83
B198: 45887 | C198: Invoice A-06801363 Distribuidora Flexi SA de CV USD1515TC 961.84 | D198: =F198*E198 -> 1457187.6 | E198: 961.84 | F198: 1515 | G198: =+G197 -> 865.1 | H198: =+I198-D198 -> -146561.1 | I198: =+F198*G198 -> 1310626.5 | K198: =+K197 -> 907.13 | L198: =K198*F198 -> 1374301.9 | M198: =I198-L198 -> -63675.45
B199: 45887 | C199: Invoice A-06801364 Distribuidora Flexi SA de CV USD812.5TC 961.84 | D199: =F199*E199 -> 781495 | E199: 961.84 | F199: 812.5 | G199: =+G198 -> 865.1 | H199: =+I199-D199 -> -78601.25 | I199: =+F199*G199 -> 702893.75 | K199: =+K198 -> 907.13 | L199: =K199*F199 -> 737043.12 | M199: =I199-L199 -> -34149.375
B200: 45887 | C200: Invoice A-06801365 Distribuidora Flexi SA de CV USD10162TC 961.84 | D200: =F200*E200 -> 9774218.1 | E200: 961.84 | F200: 10162 | G200: =+G199 -> 865.1 | H200: =+I200-D200 -> -983071.88 | I200: =+F200*G200 -> 8791146.2 | K200: =+K199 -> 907.13 | L200: =K200*F200 -> 9218255.1 | M200: =I200-L200 -> -427108.86
B201: 45887 | C201: Invoice A-06801366 Distribuidora Flexi SA de CV USD1029.5TC 961.84 | D201: =F201*E201 -> 990214.28 | E201: 961.84 | F201: 1029.5 | G201: =+G200 -> 865.1 | H201: =+I201-D201 -> -99593.83 | I201: =+F201*G201 -> 890620.45 | K201: =+K200 -> 907.13 | L201: =K201*F201 -> 933890.33 | M201: =I201-L201 -> -43269.885
B202: 45887 | C202: Invoice A-06801367 Distribuidora Flexi SA de CV USD11944.5TC 961.84 | D202: =F202*E202 -> 11488698 | E202: 961.84 | F202: 11944.5 | G202: =+G201 -> 865.1 | H202: =+I202-D202 -> -1155510.9 | I202: =+F202*G202 -> 10333187 | K202: =+K201 -> 907.13 | L202: =K202*F202 -> 10835214 | M202: =I202-L202 -> -502027.33
... B228: 45887 | C228: Invoice A-06801393 Distribuidora Flexi SA de CV USD812.5TC 961.84 | D228: =F228*E228 -> 781495 | E228: 961.84 | F228: 812.5 | G228: =+G227 -> 865.1 | H228: =+I228-D228 -> -78601.25 | I228: =+F228*G228 -> 702893.75 | K228: =+K227 -> 907.13 | L228: =K228*F228 -> 737043.12 | M228: =I228-L228 -> -34149.375
B229: 45887 | C229: Invoice A-06801394 Distribuidora Flexi SA de CV USD750TC 961.84 | D229: =F229*E229 -> 721380 | E229: 961.84 | F229: 750 | G229: =+G228 -> 865.1 | H229: =+I229-D229 -> -72555 | I229: =+F229*G229 -> 648825 | J229: =SUM(I191:I229) -> 1.1371653e+08 | K229: =+K228 -> 907.13 | L229: =K229*F229 -> 680347.5 | M229: =I229-L229 -> -31522.5
B230: 45902 | C230: Invoice A-06815818Distribuidora Flexi SA de CV USD 1260TC 968.35 | D230: =F230*E230 -> 1220121 | E230: 968.35 | F230: 1260 | G230: =+G229 -> 865.1 | H230: =+I230-D230 -> -130095 | I230: =+F230*G230 -> 1090026 | K230: =+K229 -> 907.13 | L230: =K230*F230 -> 1142983.8 | M230: =I230-L230 -> -52957.8
B231: 45909 | C231: Invoice A-06821179Distribuidora Flexi SA de CV USD 820TC 967.07 | D231: =F231*E231 -> 792997.4 | E231: 967.07 | F231: 820 | G231: =+G230 -> 865.1 | H231: =+I231-D231 -> -83615.4 | I231: =+F231*G231 -> 709382 | K231: =+K230 -> 907.13 | L231: =K231*F231 -> 743846.6 | M231: =I231-L231 -> -34464.6
B232: 45909 | C232: Invoice A-06821180Distribuidora Flexi SA de CV USD 2047.3TC 967.07 | D232: =F232*E232 -> 1979882.4 | E232: 967.07 | F232: 2047.3 | G232: =+G231 -> 865.1 | H232: =+I232-D232 -> -208763.18 | I232: =+F232*G232 -> 1771119.2 | K232: =+K231 -> 907.13 | L232: =K232*F232 -> 1857167.2 | M232: =I232-L232 -> -86048.019
B233: 45909 | C233: Invoice A-06821181Distribuidora Flexi SA de CV USD 820TC 967.07 | D233: =F233*E233 -> 792997.4 | E233: 967.07 | F233: 820 | G233: =+G232 -> 865.1 | H233: =+I233-D233 -> -83615.4 | I233: =+F233*G233 -> 709382 | K233: =+K232 -> 907.13 | L233: =K233*F233 -> 743846.6 | M233: =I233-L233 -> -34464.6
B234: 45909 | C234: Invoice A-06821182Distribuidora Flexi SA de CV USD 546TC 967.07 | D234: =F234*E234 -> 528020.22 | E234: 967.07 | F234: 546 | G234: =+G233 -> 865.1 | H234: =+I234-D234 -> -55675.62 | I234: =+F234*G234 -> 472344.6 | K234: =+K233 -> 907.13 | L234: =K234*F234 -> 495292.98 | M234: =I234-L234 -> -22948.38
B235: 45909 | C235: Invoice A-06821183Distribuidora Flexi SA de CV USD 820TC 967.07 | D235: =F235*E235 -> 792997.4 | E235: 967.07 | F235: 820 | G235: =+G234 -> 865.1 | H235: =+I235-D235 -> -83615.4 | I235: =+F235*G235 -> 709382 | K235: =+K234 -> 907.13 | L235: =K235*F235 -> 743846.6 | M235: =I235-L235 -> -34464.6
B236: 45909 | C236: Invoice A-06821184Distribuidora Flexi SA de CV USD 546TC 967.07 | D236: =F236*E236 -> 528020.22 | E236: 967.07 | F236: 546 | G236: =+G235 -> 865.1 | H236: =+I236-D236 -> -55675.62 | I236: =+F236*G236 -> 472344.6 | K236: =+K235 -> 907.13 | L236: =K236*F236 -> 495292.98 | M236: =I236-L236 -> -22948.38
B237: 45909 | C237: Invoice A-06821185Distribuidora Flexi SA de CV USD 1536TC 967.07 | D237: =F237*E237 -> 1485419.5 | E237: 967.07 | F237: 1536 | G237: =+G236 -> 865.1 | H237: =+I237-D237 -> -156625.92 | I237: =+F237*G237 -> 1328793.6 | K237: =+K236 -> 907.13 | L237: =K237*F237 -> 1393351.7 | M237: =I237-L237 -> -64558.08
B238: 45909 | C238: Invoice A-06821186Distribuidora Flexi SA de CV USD 136.5TC 967.07 | D238: =F238*E238 -> 132005.05 | E238: 967.07 | F238: 136.5 | G238: =+G237 -> 865.1 | H238: =+I238-D238 -> -13918.905 | I238: =+F238*G238 -> 118086.15 | K238: =+K237 -> 907.13 | L238: =K238*F238 -> 123823.24 | M238: =I238-L238 -> -5737.095
B239: 45909 | C239: Invoice A-06821187Distribuidora Flexi SA de CV USD 814TC 967.07 | D239: =F239*E239 -> 787194.98 | E239: 967.07 | F239: 814 | G239: =+G238 -> 865.1 | H239: =+I239-D239 -> -83003.58 | I239: =+F239*G239 -> 704191.4 | K239: =+K238 -> 907.13 | L239: =K239*F239 -> 738403.82 | M239: =I239-L239 -> -34212.42
B240: 45909 | C240: Invoice A-06821188Distribuidora Flexi SA de CV USD 546TC 967.07 | D240: =F240*E240 -> 528020.22 | E240: 967.07 | F240: 546 | G240: =+G239 -> 865.1 | H240: =+I240-D240 -> -55675.62 | I240: =+F240*G240 -> 472344.6 | K240: =+K239 -> 907.13 | L240: =K240*F240 -> 495292.98 | M240: =I240-L240 -> -22948.38
...

Sheet Proveedores
A1: Balance 8 Columnas'!A1 | B1: Flexi Chile Spa | J1: =+C12-'Balance Clasificado'!D29 -> -8
B2: Análisis y Detalle de Proveedores
B3: =+'Activo fijo'!B3:G3 -> Al 31 de enero de 2026
B6: PROVEEDORES - Agrupación
B7: Cuentas | C7: Monto MN $
B8: PROVEEDORES | C8: =+F35 -> 16326038
B9: ANTICIPO CLIENTES | C9: =+F40 -> 0
B10: HONORARIOS POR PAGAR | C10: =+F54 -> 1548293
B11: ACREEDORES VARIOS | C11: =+F59 -> 263120
B12: TOTAL Proveedores | C12: =SUM(C8:C11) -> 18137451
B14: PROVEEDORES - Detalle
B16: PROVEEDORES
B17: Nombre Titular | C17: Titular | D17: Nro Doc. | E17: fec_doc | F17: Importe MN Total
B18: ADVICOM COMPUTACION LIMITADA | C18: 780738200 | D18: 3631 | E18: 46029 | F18: 1813674
B19: AGENCIA DE ADUANA | C19: 108532246 | D19: NC2485 | E19: 46022 | F19: 6
B20: CHANNELS MEDIA S.A. | C20: 764244400 | D20: 13408 | E20: 46041 | F20: 6172737
B21: COMERCIALIZADORA AYL SPA | C21: 778200945 | D21: 50 | E21: 45947 | F21: 251985
B22: ECU WORLDWIDE (CHILE) S.A | C22: 785564707 | D22: 129639 | E22: 46049 | F22: 948346
B23: ENVIAME LATAM SPA | C23: 766695086 | D23: 62938 | E23: 46003 | F23: =3258013-3093825 -> 164188
B24: LATAMFIT CHILE SPA | C24: 769767401 | D24: 16947 | E24: 46022 | F24: 315744
B25: MARIA ISABEL SANTANA MOLINA | C25: 97844895 | D25: 441 | E25: 46020 | F25: =30000+284410 -> 314410
B26: NEURALIS SPA | C26: 771577679 | D26: 4521 | E26: 45777 | F26: 107100 | H26: factura pagada, se necesita repaldo
B27: NIKEMATECH SPA | C27: 77423523k | D27: 8396 | E27: 45995 | F27: 9810
B28: NUEVOS DESARROLLOS S.A. | C28: 768823308 | D28: 203616 | E28: 45491 | F28: 3094348 | H28: factura impaga
B29: PLAZA MAULE | C29: 969219301 | D29: 47645 | E29: 46036 | F29: 2428965
B30: PLAZA VALPARAÃ­SO S.A. | C30: 766779409 | D30: 10258-5180-NC3195 | E30: 45903 | F30: =11787+6157742-5517187-609595 -> 42747 | H30: no tengo pago de esto
B31: RVR CLIMATIZACION LIMITADA | C31: 768355940 | D31: 304 | E31: 46036 | F31: 380752
B32: SANTANDER | C32: 97036000K | D32: 54315967 | E32: 46052 | F32: 37762
B33: TELEFONICA CHILE S.A. | C33: 906350009 | D33: 53531819 | E33: 45870 | F33: -113536 | H33: saldo a favor
B34: VS CARGO SPA | C34: 776610313 | D34: 211 | E34: 46044 | F34: 357000
B35: Grand Total | F35: =SUM(F18:F34) -> 16326038 | G35: ok | I35: =H35-F35 -> -16326038
B37: ANTICIPO CLIENTES
B38: Nombre Titular | C38: RUT | D38: Nro Doc. | E38: fec_doc | F38: Importe MN Total
B40: Grand Total | F40: =SUM(F39:F39) -> 0 | G40: ok
B42: HONORARIOS POR PAGAR
B43: Nombre Titular | C43: RUT | D43: Nro Doc. | E43: fec_doc | F43: Importe MN Total
B44: ALVARO GONZALEZ SALINAS | C44: 74118046 | D44: 185687-512-513 | E44: 27-04-2025 | F44: 480000 | H44: valor se debe a rsm tax and legal
B45: ANGELO MEDINA | C45: 14580359-6 | D45: 16082-16246-16819-17056-17293 | E45: 31-01-2026 | F45: =20000+20000+20000+18000+18000 -> 96000
B46: Coonservador de Bienes Riaices | C46: 60306045-8 | D46: 14884779-15012219 | E46: 26-11-2025 | F46: =2300+266700 -> 269000
B47: FERNANDO OLGUEA | C47: 21321577-9 | D47: 3553 | E47: 24-12-2025 | F47: 20000
B48: JUAN ANTONIO MELO SAAVEDRA | C48: 56668225 | D48: 1324-1390-94-1420-25 | E48: 31-01-2026 | F48: =40000+40000+40000+40000+40000 -> 200000
B49: JUAN JESUS ARRIAGADA GONZALEZ | C49: 89920584 | D49: 5469 | E49: 30-12-2025 | F49: 15000
B50: JESHUA ANNIR | C50: 21795374-K | D50: 1 | E50: 29-10-2025 | F50: 76950
B51: MARIA LASCAR MERINO | C51: 8215914-2 | D51: 218653 | E51: 14-11-2025 | F51: 69000
B52: Lorena Quintanilla | C52: 144733045 | D52: 122008 | E52: 12-01-2026 | F52: 5000
B53: Jorge Venegas | C53: 14046459-7 | D53: 185 | E53: 20-01-2026 | F53: 317343
B54: Grand Total | F54: =SUM(F44:F53) -> 1548293 | G54: ok
B56: ACREEDORES VARIOS
B57: Nombre Titular | C57: RUT | D57: Nro Doc. | E57: fec_doc | F57: Importe MN Total
B58: Latam fit | C58: 76.976.740-1 | E58: 31-01-2026 | F58: 263120
B59: Grand Total | F59: =SUM(F58:F58) -> 263120 | G59: ok

Sheet Impuestos nómina
A1: Balance 8 Columnas'!A1 | B1: Flexi Chile Spa | G1: =+C9-'Balance Clasificado'!D31 -> 0
B2: Análisis y Detalle de Impuestos nómina
B3: =+'Activo fijo'!B3:G3 -> Al 31 de enero de 2026
B6: IMPUESTOS NÓMINA - Agrupación
B7: Cuentas | C7: Monto MN $
B8: PREVIRED POR PAGAR | C8: =+D17 -> 9957035
B9: TOTAL Impuestos nómina | C9: =SUM(C8:C8) -> 9957035 | J9: 60000 | L9: hxp
K10: 527740 | L10: fxr
B11: IMPUESTOS NÓMINA - Detalle | K11: 1199754 | L11: sxp
J12: =430000+1340000+6000 -> 1776000 | L12: acre
B13: PREVIRED POR PAGAR | J13: =10601190-10500427 -> 100763 | K13: 345951 | L13: prev
B14: Detalle | C14: Fecha | D14: Valor | J14: =11542154-11406776 -> 135378 | L14: sxp
B15: Pago Imposiciones abril (duplicado)/sin devolucion aun | C15: 45057 | D15: -6951819 | J15: =SUM(J9:J14) -> 2072141 | K15: =SUM(K10:K14) -> 2073445 | L15: sxp
B16: Centralizacion Imposiciones del mes | C16: 46053 | D16: 16908855 | K16: =J15-K15 -> -1304
B17: Saldo Según Balance | D17: =SUM(D15:D16)-1 -> 9957035

Sheet Otros Pasivos
A1: Balance 8 Columnas'!A1 | B1: Flexi Chile Spa | G1: =+D10-'Balance Clasificado'!D33 -> 0
B2: Análisis y Detalle de Otros pasivos
B3: =+Carátula!A9 -> Al 31 de enero de 2026
B5: OTROS PASIVOS - Agrupación:
B6: Cuentas | D6: Monto MN $
B7: PROVISIONES VARIAS | D7: =+E47 -> 79712038
B8: SUELDOS POR PAGAR | D8: =+D65 -> 14126817
B9: FINIQUITOS POR PAGAR | D9: =+D71 -> 0
B10: TOTAL Otros pasivos | D10: =SUM(D7:D9) -> 93838855
B12: OTROS PASIVOS - Detalle:
B14: PROVISIONES VARIAS
B15: Fecha | C15: DETALLE | D15: RUT | E15: Valor
B16: 46022 | C16: PROVISION OSRCAR HIDALGO | D16: 5.618.113-k | E16: 4000000
B17: 46053 | C17: PROVISION AGENCIA DE ADUANA | D17: 10.853.224-6 | E17: 159232
B18: 45657 | C18: PROVISION ANTCIPOS BAP CONSTRUCTORA PLAZA OESTE | D18: 10.980.520-3 | E18: =41881933-16806723 -> 25075210 | G18: factura parcial emitida/ febrero emision final
B19: 46022 | C19: PROVISION FRANCISCO JASCURA | D19: 12.170.453-6 | E19: 530019
B20: 46022 | C20: PROVISION RENDICION RGB CIERRE BARROS ARANA | D20: 12.242.596-7 | E20: 879186
B21: 46022 | C21: PROVISION RENDICION RGB PUBLICIDAD ESTADO | D21: 12.242.596-7 | E21: 3307156
B22: 46022 | C22: PROVISION RENDICION E. MARCHANT CIERRE ARANA | D22: 16.089.318-4 | E22: 250000
B23: 46022 | C23: PROVISION RENDICION E. MARCHANT | D23: 16.089.318-4 | E23: 844113
B24: 45657 | C24: PROVISION ABRAHAM PINO (espejos talca) | D24: 17.257.358-4 | E24: 335999 | G24: factura solicitada sin respuesta
B25: 46022 | C25: PROVISION ARTE IMPRESO ant prov | D25: 76.096.518-9 | E25: 325000
B26: 46053 | C26: PROVISION JACH TECHNOLOGY | D26: 76.110.436-5 | E26: 588258
B27: 46022 | C27: PROVISION RENTOKILL | D27: 76.360.903-0 | E27: 104665
B28: 46053 | C28: PROVISION RENTOKILL | D28: 76.360.903-0 | E28: 104803
B29: 46053 | C29: PROVISION VTEX | D29: 76.376.315-3 | E29: 1097655
B30: 46053 | C30: PROVISION LATAMFIT | D30: 76.976.740-1 | E30: 315744
B31: 46022 | C31: PROVISION LABBE | D31: 77.227.317-7 | E31: =8000000-5072199-1716000 -> 1211801
B32: 46022 | C32: PROVISION MKT DIC | D32: 77.227.317-7 | E32: 11392785
B33: 46053 | C33: PROVISION PATENTES | D33: 77.227.317-7 | E33: =408370+57384+69714+69714+269237+331316+41773+25545 -> 1273053
B34: 46022 | C34: PROVISION UNIIFORMES REGALIAS | D34: 77.227.317-7 | E34: 18619324
B35: 46022 | C35: PROVISION COCO DISEÑO ANT PROV | D35: 77.545.147-5 | E35: 2673426
B36: 46022 | C36: PROVISION ENRGA LIMITE 21 | D36: 77.570.694-5 | E36: 4000000
B37: 46053 | C37: PROVISION ME CONECTO SPA | D37: 78.124.998-K | E37: 500000
B38: 46053 | C38: PROVISION WOM S.A. | D38: 78.921.690-8 | E38: 131229
B39: 46053 | C39: PROVISION CENCOSUD RETAIL | D39: 81.201.000-K | E39: 539421
B40: 46022 | C40: PROVISION GTD JULIO ANT P | D40: 93.737.000-8 | E40: 192277
B41: 46022 | C41: PROVISION TRANSBANK FACTURA | D41: 96.689.310-9 | E41: =1653696-798427 -> 855269
B42: 46053 | C42: PROVISION COSCO SHIPPING | D42: 96.805.690-5 | E42: 55000
B43: 46022 | C43: PROVISION GASTOS COMUNES BANCO CHILE | D43: 97.004.000-5 | E43: 197372
B44: 46053 | C44: PROVISION TDC GASTOS ENE FACTURADO FEB | D44: 97.036.000-k | E44: 1379880
B45: 46053 | C45: PROVISION CHUBB SEGUROS C | D45: 99.225.000-3 | E45: =309353+240608 -> 549961
B46: 46053 | C46: PROVISION AJUSTE BONO MAL CALCULADO | D46: 77.227.317-7 | E46: -1775800
B47: Saldo Según Balance | E47: =SUM(E16:E46) -> 79712038 | F47: ok
B50: SUELDOS POR PAGAR
B51: Detalle | C51: Fecha | D51: Valor
B52: 45961 | C52: Saldo sueldos | D52: =9059772-141393-8658231 -> 260148
B53: 46053 | C53: Saldo sueldos | D53: 13505
B54: 46053 | C54: SUELDOS VESPUCIO | D54: 13506
B55: 46053 | C55: SUELDOS EGAÑA | D55: 1741504
B56: 46053 | C56: SUELDOS TREBOL | D56: 2229165
B57: 46053 | C57: SUELDOS COSTANERA | D57: 2320870
B58: 46053 | C58: SUELDOS FLORIDA CENTER | D58: 1270111
B59: 46053 | C59: SUELDOS ESTADO | D59: 2462517
B60: 46053 | C60: SUELDOS BARROS ARANA | D60: =88236+274865 -> 363101
B61: 46053 | C61: SUELDOS TALCA | D61: 841502
B62: 46053 | C62: SUELDOS PLAZA NORTE | D62: 725839
B63: 46053 | C63: SUELDOS PLAZA OESTE | D63: 1785049
B64: 46053 | C64: SUELDOS ASMINISTRACION | D64: 100000
B65: Saldo Según Balance | D65: =SUM(D52:D64) -> 14126817 | E65: ok
B68: =+B9 -> FINIQUITOS POR PAGAR
B69: Fecha | C69: DETALLE | D69: Valor
B71: Saldo Según Balance | D71: =SUM(D70:D70) -> 0

Sheet IVA por pagar del mes
A1: Balance 8 Columnas'!A1 | B1: Flexi Chile Spa | F1: =+C8-'Balance Clasificado'!D34 -> 0
B2: Análisis y Detalle de Iva por pagar del mes
B3: =+Carátula!A9 -> Al 31 de enero de 2026
B5: Pasivos por Impuestos corrientes
B6: Cuentas | C6: Monto MN $
B7: IMPUESTOS POR PAGAR F29 | C7: =$D$13 -> 958952
B8: TOTAL Iva por pagar del mes | C8: =SUM(C7:C7) -> 958952
B10: IMPUESTOS POR PAGAR F29
B11: DETALLE | D11: Valor Actual
B12: IMPUESTO POR PAGAR del mes | D12: 958952
B13: Saldo Según Balance | D13: =SUM(D12:D12) -> 958952

Sheet Publicidad y Mark
A1: Balance 8 Columnas'!A1 | B1: Flexi Chile Spa | J1: =E11-'Balance 8 Columnas'!J109 -> 0 | K1: Patrimonio!A1
B2: Análisis y Detalle de Cuentas Gastos de Publicidad y Marketing
B3: =+'Deudores Diversos'!B3:F3 -> Al 31 de enero de 2026
B5: GASTOS DE PUBLICIDAD Y MARKETING
B6: Titular | C6: Descripcion | D6: Fecha | E6: Monto MN $
B7: SOFIA JORQUERA | C7: BH 187 | D7: 46036 | E7: 88496
B8: JANICE CACERES | C8: BH 2 | D8: 46044 | E8: 40000
B9: HELLO CONTENT SPA | C9: BH 87 | D9: 46053 | E9: 245000
B10: TDC ENERO | C10: TDC | D10: 46053 | E10: =1159217+581644-27489 -> 1713372
B11: TOTAL GASTOS DE PUBLICIDAD Y MARKETING | E11: =SUM(E7:E10) -> 2086868

Sheet Sum. Visual
A1: Balance 8 Columnas'!A1 | B1: Flexi Chile Spa
B2: Análisis y Detalle de Cuentas suministros Visual | G2: =E13-'Balance 8 Columnas'!N110 -> -2 | I2: Balance 8 Columnas'!A1
B3: =+'Deudores Diversos'!B3:F3 -> Al 31 de enero de 2026
B5: SUMINISTROS VISUAL
B6: Titular | C6: Descripcion | D6: Fecha | E6: Monto MN $
B7: GETTY IMAGES | C7: F 62646 | D7: 46053 | E7: 23100
B8: LA VITRINERIA | C8: F 2911 | D8: 46053 | E8: 1415500
B9: ARTE IMPRESO LIMITADA | C9: F 5335 | D9: 46053 | E9: 26000
B10: LA VITRINERIA | C10: F 2924 | D10: 46053 | E10: 63900
B11: VISUAL | C11: ENERO | D11: 46053 | E11: =199703+41000 -> 240703
B12: TDC ENERO | C12: TDC | D12: 46053 | E12: 61869
B13: TOTAL SUMINISTROS VISUAL | E13: =SUM(E7:E12)-2 -> 1831070

Sheet Finiquitos
A1: F | B1: Flexi Chile Spa
B2: Análisis y Detalle de Cuentas suministros Visual | G2: =E8-'Balance 8 Columnas'!N75 -> 0 | I2: Balance 8 Columnas'!A1
B3: =+'Deudores Diversos'!B3:F3 -> Al 31 de enero de 2026
B5: FINIQUITOS
B6: Titular | C6: Descripcion | D6: Fecha | E6: Monto MN $
C7: Diferencia con provsion dicimbre | D7: 46038 | E7: 4000
B8: TOTAL SUMINISTROS VISUAL | E8: =SUM(E7:E7) -> 4000
