Workbook

Sheet Balanza ok
B2: Cuenta Mexico | C2: Texto | D2: Cuenta Chile
A3: ok | B3: 111100 | C3: FONDOS FIJOS | D3: 1.1.01.201 | E3: FONDO FIJO LOS DOMINICOS
B4: 111100 | C4: FONDOS FIJOS | D4: 1.1.01.202 | E4: FONDO FIJO MAIPU
B5: 111100 | C5: FONDOS FIJOS | D5: 1.1.01.203 | E5: FONDO FIJO PLAZA EGAÑA
B6: 111100 | C6: FONDOS FIJOS | D6: 1.1.01.204 | E6: FONDO FIJO VESPUCIO
B7: 111100 | C7: FONDOS FIJOS | D7: 1.1.01.205 | E7: FONDO FIJO TREBOL
B8: 111100 | C8: FONDOS FIJOS | D8: 1.1.01.206 | E8: FONDO FIJO COSTANERA CENTER
B9: 111100 | C9: FONDOS FIJOS | D9: 1.1.01.207 | E9: FONDO FIJO FLORIDA CENTER
B10: 111100 | C10: FONDOS FIJOS | D10: 1.1.01.208 | E10: FONDO FIJO SANTIAGO CENTRO
B11: 111100 | C11: FONDOS FIJOS | D11: 1.1.01.209 | E11: FONDO FIJO CONCEPCION CENTRO
B12: 111100 | C12: FONDOS FIJOS | D12: 1.1.01.210 | E12: FONDO FIJO TALCA
B13: 111100 | C13: FONDOS FIJOS | D13: 1.1.01.211 | E13: FONDO FIJO PLAZA NORTE
B14: 111100 | C14: FONDOS FIJOS | D14: 1.1.01.212 | E14: FONDO FIJO PLAZA OESTE
A15: ok | B15: 112093 | C15: SANTANDER CHILE ( 89 ) SALDO | D15: 1.1.01.301 | E15: BANCOS CTA CTE $
A16: ok | B16: 112094 | C16: SANTANDER ( 89 ) INVERSION | D16: 1.1.02.106 | E16: DEPOSITO A PLAZO CORREDORA
B17: 112094 | C17: SANTANDER ( 89 ) INVERSION | D17: 1.1.01.501 | E17: INVERSION FONDO MUTUO
B18: 112095 | C18: SANTANDER ( 89 ) USD | D18: 1.1.01.502 | E18: INVERIOSN FONDO MUTUO USD
A19: ok | B19: 112095 | C19: SANTANDER ( 89 ) USD | D19: 1.1.01.302 | E19: BANCOS CTA CTE US$
A20: ok | B20: 113100 | C20: CLIENTES | D20: 1.1.04.102 | E20: CLIENTES BOLETAS | F20: Sin factura
B21: 111100 | C21: DEUDORES DIVERSOS | D21: 1.1.04.101 | E21: CLIENTES NACIONALES | F21: Con factura
B22: 113103 | C22: CLIENTES PARTES RELACIONADAS
B23: 115000 | C23: DOCUMENTOS POR COBRAR
B24: 111100 | C24: DEUDORES DIVERSOS | D24: 1.1.01.101 | E24: EFECTIVO EN TRANSITO
B25: 115010 | C25: DEUDORES DIVERSOS | D25: 1.1.04.105 | E25: TRANSBANK POR COBRAR TC
A26: ok | B26: 115010 | C26: DEUDORES DIVERSOS | D26: 1.1.04.106 | E26: TRANSBANK POR COBRAR TD
B27: 115010 | C27: DEUDORES DIVERSOS | D27: 1.1.04.112 | E27: GETNET TC
B28: 115010 | C28: DEUDORES DIVERSOS | D28: 1.1.04.113 | E28: GETNET TD/ PREPAGO
B29: 115010 | C29: DEUDORES DIVERSOS | D29: 1.1.04.108 | E29: GIFTCARD
B30: 115010 | C30: DEUDORES DIVERSOS | D30: 1.1.04.109 | E30: ECOMMERCE
B31: 115010 | C31: DEUDORES DIVERSOS | D31: 1.1.04.200 | E31: CUENTAS POR COBRAR
B32: 115010 | C32: DEUDORES DIVERSOS | D32: 1.1.04.201 | E32: CUENTAS POR COBRAR USD
B33: 115010 | C33: DEUDORES DIVERSOS | D33: 1.1.04.300 | E33: PROVISION INGRESOS | F33: (para pago publicidad recibido en enero)
B34: 115025 | C34: RESERVA CUENTAS INCOBRABLES DEUDORES
B35: 115026 | C35: RETENCIONES POR COBRAR
B36: 115050 | C36: ANTICIPOS PARA VIATICOS
B37: 115061 | C37: ANTICIPOS PROVEEDORES | D37: 1.1.04.104 | E37: FONDOS POR RENDIR
B38: 115060 | C38: ANTICIPOS EMPLEADOS | D38: 1.1.05.302 | E38: ANTICIPOS SUELDOS
A39: ok | B39: 115055 | C39: ANTICIPOS PARA GASTOS | D39: 1.1.05.405 | E39: ANTICIPO AGENCIA DE ADUANAS
A40: OK | B40: 115061 | C40: ANTICIPOS PROVEEDORES | D40: 1.1.05.403 | E40: ANTICIPO PROVEEDORES
A41: ok | B41: 115055 | C41: ANTICIPOS PARA GASTOS | D41: 1.1.05.404 | E41: ANTICIPO HONORARIOS
A42: ok | B42: 115070 | C42: INTERCOMPAÑIAS CUENTAS X COBRAR
A43: ok | B43: 115071 | C43: INTERCOMPAÑIAS CUENTAS X COBRAR EXTRANJERO
B44: 115082 | C44: IVA A FAVOR | D44: 1.1.09.103 | E44: REMANENTE IVA CREDITO FISCAL
B45: 115087 | C45: IVA A FAVOR COMPENSABLE
A46: Ok | B46: 115091 | C46: ANTICIPO IMPUESTO SOBRE LA RENTA | D46: 1.1.09.201 | E46: PAGOS PROVISIONALES MENSUALES
B47: 115093 | C47: ISR RETENIDO DE BANCOS
A48: ok | B48: 115102 | C48: IVA ACREDITABLE
B49: 115099 | C49: IVA ACREDITABLE DE COMISIONES BANCARIAS
B50: 115095 | C50: IVA ACREDITABLE EFECTIVAMENTE PAGADO | D50: 1.1.09.101 | E50: IVA CREDITO FISCAL (COMPRAS) | F50: 115095 | G50: IVA ACREDITABLE EFECTIVAMENTE PAGADO
B51: 115103 | C51: IVA DIFERIDO POR RETENCIONES
A52: ok | B52: 115100 | C52: IVA NO ACREDITABLE
B53: 115108 | C53: IVA ACREDITABLE EFECTIVAMENTE PAGADO IMPORTACIONES
B54: 115111 | C54: PAGOS ANTICIPADOS SEGUROS
B55: 115081 | C55: ISR A FAVOR | E55: IMPUESTOS POR RECUPERAR
B56: 116010 | C56: INVENTARIO DE MATERIA PRIMA
B57: 116030 | C57: INVENTARIO DE PRODUCCION EN PROCESO
B58: 116050 | C58: INVENTARIO DE PRODUCTO TERMINADO | D58: 1.1.06.401 | E58: EXISTENCIAS NACIONALES
B59: 116050 | C59: INVENTARIO DE PRODUCTO TERMINADO | D59: 1.1.06.402 | E59: EXISTENCIAS SINIESTRADAS
A60: ok | B60: 116060 | C60: INVENTARIO DE REFACCIONES
B61: 116067 | C61: INVENTARIO DE ACCESORIOS
B62: 116068 | C62: INVENTARIO DE MATERIAL PARA TIENDA
B63: 116069 | C63: REVALUACION DE INVENTARIOS MP
B64: 116072 | C64: INVENTARIO EN TRANSITO | D64: 1.1.06.801 | E64: MERCADERIA EN TRANSITO
B65: 116072 | C65: INVENTARIO EN TRANSITO | D65: 1.1.06.802 | E65: MERCADERIA EN TRANSITO USD
A66: ok | B66: 116081 | C66: RESERVA PARA OBSOLESCENCIA DE MATERIA PRIMA
A67: ok | B67: 116083 | C67: RESERVA PARA OBSOLESC DE INVENTARIOS PRODUCTO TERM
B68: 167010 | C68: ISR DIFERIDO X COBRAR
B69: 116950 | C69: INVENTARIO DE PRODUCTO TERMINADO AJUSTE A PROMEDIO
B70: 116970 | C70: ANTICIPOS A PROVEEDORES
B71: 118200 | C71: INTERCIAS CUENTAS POR COBRAR EMPLEADOS
B72: 118615 | C72: CUENTA CORRIENTE GRUPO FLEXI
B73: 141000 | C73: ACTIVO FIJO VALOR ORIGINAL
B74: 141010 | C74: TERRENOS, DERECHOS SIMILARES SOBRE TERRENOS
B75: 141020 | C75: EDIFICIOS
B76: 141040 | C76: EQUIPO DE TRANSPORTE
B77: 141050 | C77: EQUIPO DE TRANSPORTE DE CARGA
B78: 141070 | C78: MOBILIARIO Y EQUIPO DE COMPUTO | D78: 1.2.02.402 | E78: EQUIPOS COMPUTACIONALES
B79: 141070 | C79: MOBILIARIO Y EQUIPO DE COMPUTO | D79: 1.2.02.404 | E79: EQUIPOS COMPUTAC SINIESTRADOS
A80: ok | B80: 141080 | C80: MOBILIARIO Y EQUIPO DE OFICINA | D80: 1.2.02.401 | E80: MUEBLES, UTILES Y OTROS
B81: 141080 | C81: MOBILIARIO Y EQUIPO DE OFICINA | D81: 1.2.02.403 | E81: MUEBLES, UTILES O SINIESTRADOS
B82: 141080 | C82: MOBILIARIO Y EQUIPO DE OFICINA | F82: se crea para la provision de facturas de BAP provisionadas
A83: ok | B83: 141085 | C83: OTROS ACTIVOS MUEBLES Y ENSERES
B84: 141090 | C84: MOBILIARIO Y EQUIPO DE COMEDOR
B85: 141100 | C85: EQUIPO DE SEGURIDAD
B86: 141140 | C86: EQUIPO DE TIENDA
B87: 141170 | C87: GASTOS DE ORGANIZACION
B88: 141180 | C88: GASTOS DE INSTALACION
B89: 141190 | C89: MEJORAS A LOCALES ARRENDADOS
B90: 170013 | C90: DEPOSITO DE GARANTIA | D90: 1.2.02.101 | E90: GARANTIAS DE ARRIENDO
B91: 141195 | C91: DERECHOS DE ARRENDAMIENTO | D91: 1.1.03.201 | E91: GASTOS PAGADOS POR ANTICIPADO
A92: ok | B92: 141200 | C92: PATENTES Y MARCAS
B93: 141210 | C93: LICENCIAS DE SOFTWARE
B94: 141900 | C94: OTROS ACTIVOS FIJOS
B95: 142000 | C95: DEPRECIACION ACUMULADA HISTORICA
B96: 142020 | C96: DEPRECIACION ACUMULADA EDIFICIOS
B97: 142040 | C97: DEPRECIACION ACUMULADA EQUIPO DE TRANSPORTE
B98: 142050 | C98: DEPRECIACION ACUMULADA TRANSPORTE DE CARGA
B99: 142080 | C99: DEPRECIACION ACUMULADA EQUIPO DE COMPUTO | D99: 1.2.02.904 | E99: DEPRECIACION ACUMULADA MUEBLES Y UTILES
B100: 142070 | C100: DEPRECIACION ACUMULADA EQUIPO DE COMPUTO | D100: 1.2.02.905 | E100: DEPRECIACION ACUMULADA EQUIPOS COMPUTACIONALES
A101: ok | B101: 142085 | C101: DEPRECIACION ACUMULADA OTROS ACTMUEBLES Y ENSERES
...

Sheet BCE
D2: Flexi Chile SpA
D3: Al 30 de abril de 2026
A5: MEX | B5: CHILE | C5: MEX
A7: Nombre Cuenta | B7: Clasificacion | C7: Numero Cuenta | D7: Numero Cuenta | E7: Nombre Cuenta | F7: Valores Acumulados | H7: Saldos | J7: Inventario | L7: Resultados | P7: Saldos | Q7: T/C Cierre | R7: Transacioanal | S7: Saldo (R) | U7: Saldos CLP sumados | V7: Dif
F8: Debitos | G8: Creditos | H8: Deudor | I8: Acreedor | J8: Activo | K8: Pasivo | L8: Perdidas | M8: Ganancias | Q8: 903.05
A9: FONDOS FIJOS | B9: Caja y Bancos | C9: 111100 | D9: 1.1.01.101 | E9: EFECTIVO EN TRANSITO | F9: 270743555 | G9: 186333119 | H9: 84410436 | I9: 0 | J9: 84410436 | K9: 0 | L9: 0 | M9: 0 | O9: Monetaria | P9: =+J9-K9+L9-M9 -> 84410436 | Q9: =P9/$Q$8 -> 93472.605 | X9: 1.1.01.101 | Y9: =EXACT(X9,D9) -> TRUE
A10: FONDOS FIJOS | B10: Caja y Bancos | C10: 111100 | D10: 1.1.01.203 | E10: FONDO FIJO PLAZA EGAÑA | F10: 330048 | G10: 292628 | H10: 37420 | I10: 0 | J10: 37420 | K10: 0 | L10: 0 | M10: 0 | O10: Monetaria | P10: =+J10-K10+L10-M10 -> 37420 | Q10: =P10/$Q$8 -> 41.437351 | V10: =U10-P10 -> -37420 | X10: 1.1.01.203 | Y10: =EXACT(X10,D10) -> TRUE
A11: FONDOS FIJOS | B11: Caja y Bancos | C11: 111100 | D11: 1.1.01.204 | E11: FONDO FIJO VESPUCIO | F11: 140340 | G11: 267114 | H11: 0 | I11: 126774 | J11: 0 | K11: 126774 | L11: 0 | M11: 0 | O11: Monetaria | P11: =+J11-K11+L11-M11 -> -126774 | Q11: =P11/$Q$8 -> -140.38425 | V11: =U11-P11 -> 126774 | X11: 1.1.01.204 | Y11: =EXACT(X11,D11) -> TRUE
A12: FONDOS FIJOS | B12: Caja y Bancos | C12: 111100 | D12: 1.1.01.205 | E12: FONDO FIJO TREBOL | F12: 385201 | G12: 352851 | H12: 32350 | I12: 0 | J12: 32350 | K12: 0 | L12: 0 | M12: 0 | O12: Monetaria | P12: =+J12-K12+L12-M12 -> 32350 | Q12: =P12/$Q$8 -> 35.823044 | V12: =U12-P12 -> -32350 | X12: 1.1.01.205 | Y12: =EXACT(X12,D12) -> TRUE
A13: FONDOS FIJOS | B13: Caja y Bancos | C13: 111100 | D13: 1.1.01.206 | E13: FONDO FIJO COSTANERA CENTER | F13: 352120 | G13: 307150 | H13: 44970 | I13: 0 | J13: 44970 | K13: 0 | L13: 0 | M13: 0 | O13: Monetaria | P13: =+J13-K13+L13-M13 -> 44970 | Q13: =P13/$Q$8 -> 49.797907 | V13: =U13-P13 -> -44970 | X13: 1.1.01.206 | Y13: =EXACT(X13,D13) -> TRUE
A14: FONDOS FIJOS | B14: Caja y Bancos | C14: 111100 | D14: 1.1.01.207 | E14: FONDO FIJO FLORIDA CENTER | F14: 407078 | G14: 374218 | H14: 32860 | I14: 0 | J14: 32860 | K14: 0 | L14: 0 | M14: 0 | O14: Monetaria | P14: =+J14-K14+L14-M14 -> 32860 | Q14: =P14/$Q$8 -> 36.387797 | V14: =U14-P14 -> -32860 | X14: 1.1.01.207 | Y14: =EXACT(X14,D14) -> TRUE
A15: FONDOS FIJOS | B15: Caja y Bancos | C15: 111100 | D15: 1.1.01.208 | E15: FONDO FIJO SANTIAGO CENTRO | F15: 215730 | G15: 204370 | H15: 11360 | I15: 0 | J15: 11360 | K15: 0 | L15: 0 | M15: 0 | O15: Monetaria | P15: =+J15-K15+L15-M15 -> 11360 | Q15: =P15/$Q$8 -> 12.579591 | V15: =U15-P15 -> -11360 | X15: 1.1.01.208 | Y15: =EXACT(X15,D15) -> TRUE
A16: FONDOS FIJOS | B16: Caja y Bancos | C16: 111100 | D16: 1.1.01.209 | E16: FONDO FIJO CONCEPCION CENTRO | F16: 103980 | G16: 103980 | H16: 0 | I16: 0 | J16: 0 | K16: 0 | L16: 0 | M16: 0 | O16: Monetaria | P16: =+J16-K16+L16-M16 -> 0 | Q16: =P16/$Q$8 -> 0 | V16: =U16-P16 -> 0 | X16: 1.1.01.209 | Y16: =EXACT(X16,D16) -> TRUE
A17: FONDOS FIJOS | B17: Caja y Bancos | C17: 111100 | D17: 1.1.01.210 | E17: FONDO FIJO TALCA | F17: 389445 | G17: 351423 | H17: 38022 | I17: 0 | J17: 38022 | K17: 0 | L17: 0 | M17: 0 | O17: Monetaria | P17: =+J17-K17+L17-M17 -> 38022 | Q17: =P17/$Q$8 -> 42.103981 | V17: =U17-P17 -> -38022 | X17: 1.1.01.210 | Y17: =EXACT(X17,D17) -> TRUE
A18: FONDOS FIJOS | B18: Caja y Bancos | C18: 111100 | D18: 1.1.01.211 | E18: FONSO FIJO PLAZA NORTE | F18: 262035 | G18: 225915 | H18: 36120 | I18: 0 | J18: 36120 | K18: 0 | L18: 0 | M18: 0 | O18: Monetaria | P18: =+J18-K18+L18-M18 -> 36120 | Q18: =P18/$Q$8 -> 39.997785 | X18: 1.1.01.211 | Y18: =EXACT(X18,D18) -> TRUE
A19: FONDOS FIJOS | B19: Caja y Bancos | C19: 111100 | D19: 1.1.01.212 | E19: FONDO FIJO PLAZA OESTE | F19: 279193 | G19: 237595 | H19: 41598 | I19: 0 | J19: 41598 | K19: 0 | L19: 0 | M19: 0 | O19: Monetaria | P19: =+J19-K19+L19-M19 -> 41598 | Q19: =P19/$Q$8 -> 46.063895 | X19: 1.1.01.212 | Y19: =EXACT(X19,D19) -> TRUE
A20: SANTANDER CHILE | B20: Caja y Bancos | C20: 112093 | D20: 1.1.01.301 | E20: BANCOS CTA CTE $ | F20: 1674610704 | G20: 1460796887 | H20: 213813817 | I20: 0 | J20: 213813817 | K20: 0 | L20: 0 | M20: 0 | O20: Monetaria | P20: =+J20-K20+L20-M20 -> 213813817 | Q20: =P20/$Q$8 -> 236768.53 | V20: =U20-P20 -> -213813817 | X20: 1.1.01.301 | Y20: =EXACT(X20,D20) -> TRUE
A21: SANTANDER CH USD | B21: Caja y Bancos | C21: 112095 | D21: 1.1.01.302 | E21: BANCOS CTA CTE US$ | F21: 1448479616 | G21: 1434002975 | H21: 14476641 | I21: 0 | J21: 14476641 | K21: 0 | L21: 0 | M21: 0 | O21: Monetaria | P21: =+J21-K21+L21-M21 -> 14476641 | Q21: =P21/$Q$8 -> 16030.83 | V21: =U21-P21 -> -14476641 | X21: 1.1.01.302 | Y21: =EXACT(X21,D21) -> TRUE
A22: SANTANDER CH INV | B22: Caja y Bancos | C22: 112094 | D22: 1.1.01.501 | E22: INVERSION FONDO MUTUO | F22: 302389138 | G22: 0 | H22: 302389138 | I22: 0 | J22: 302389138 | K22: 0 | L22: 0 | M22: 0 | O22: Monetaria | P22: =+J22-K22+L22-M22 -> 302389138 | Q22: =P22/$Q$8 -> 334853.15 | V22: =U22-P22 -> -302389138 | X22: 1.1.01.501 | Y22: =EXACT(X22,D22) -> TRUE
A23: SANTANDER CH INV | B23: Caja y Bancos | C23: 112094 | D23: 1.1.01.502 | E23: INVERIOSN FONDO MUTUO USD | F23: 324679550 | G23: 144084902 | H23: 180594648 | I23: 0 | J23: 180594648 | K23: 0 | L23: 0 | M23: 0 | O23: Monetaria | P23: =+J23-K23+L23-M23 -> 180594648 | Q23: =P23/$Q$8 -> 199983 | V23: =U23-P23 -> -180594648 | X23: 1.1.01.502 | Y23: =EXACT(X23,D23) -> TRUE
A24: SANTANDER CH INV | B24: Caja y Bancos | C24: 112094 | D24: 1.1.02.106 | E24: DEPOSITO A PLAZO CORREDORA | F24: 4970977 | G24: 0 | H24: 4970977 | I24: 0 | J24: 4970977 | K24: 0 | L24: 0 | M24: 0 | O24: Monetaria | P24: =+J24-K24+L24-M24 -> 4970977 | Q24: =P24/$Q$8 -> 5504.6531 | V24: =U24-P24 -> -4970977 | X24: 1.1.02.106 | Y24: =EXACT(X24,D24) -> TRUE
A25: DEPOSITOS GARANTIA | B25: Derechos de arrendamiento | C25: 170013 | D25: 1.1.03.201 | E25: GASTOS PAGADOS POR ANTICIPADO | F25: 54550224 | G25: 26359837 | H25: 28190387 | I25: 0 | J25: 28190387 | K25: 0 | L25: 0 | M25: 0 | O25: Monetaria | P25: =+J25-K25+L25-M25 -> 28190387 | Q25: =P25/$Q$8 -> 31216.862 | V25: =U25-P25 -> -28190387 | X25: 1.1.03.201 | Y25: =EXACT(X25,D25) -> TRUE
A26: DEUDORES DIVERSOS | B26: Deudores Diversos | C26: 115010 | D26: 1.1.04.102 | E26: CLIENTES BOLETAS | F26: 1254176241 | G26: 1254176241 | H26: 0 | I26: 0 | J26: 0 | K26: 0 | L26: 0 | M26: 0 | O26: Monetaria | P26: =+J26-K26+L26-M26 -> 0 | Q26: =P26/$Q$8 -> 0 | V26: =U26-P26 -> 0 | X26: 1.1.04.102 | Y26: =EXACT(X26,D26) -> TRUE
A27: ANTICIPOS PROVEEDORE | B27: Pagos anticipados | C27: 115061 | D27: 1.1.04.104 | E27: FONDOS POR RENDIR | F27: 11021221 | G27: 8392663 | H27: 2628558 | I27: 0 | J27: 2628558 | K27: 0 | L27: 0 | M27: 0 | O27: Monetaria | P27: =+J27-K27+L27-M27 -> 2628558 | Q27: =P27/$Q$8 -> 2910.7558 | V27: =U27-P27 -> -2628558 | X27: 1.1.04.104 | Y27: =EXACT(X27,D27) -> TRUE
A28: DEUDORES DIVERSOS | B28: Deudores Diversos | C28: 115010 | D28: 1.1.04.105 | E28: TRANSBANK POR COBRAR TC | F28: 675298550 | G28: 675836139 | H28: 0 | I28: 537589 | J28: 0 | K28: 537589 | L28: 0 | M28: 0 | O28: Monetaria | P28: =+J28-K28+L28-M28 -> -537589 | Q28: =P28/$Q$8 -> -595.30369 | V28: =U28-P28 -> 537589 | X28: 1.1.04.105 | Y28: =EXACT(X28,D28) -> TRUE
A29: DEUDORES DIVERSOS | B29: Deudores Diversos | C29: 115010 | D29: 1.1.04.106 | E29: TRANSBANK POR COBRAR TD | F29: 732267924 | G29: 692327810 | H29: 39940114 | I29: 0 | J29: 39940114 | K29: 0 | L29: 0 | M29: 0 | O29: Monetaria | P29: =+J29-K29+L29-M29 -> 39940114 | Q29: =P29/$Q$8 -> 44228.021 | V29: =U29-P29 -> -39940114 | X29: 1.1.04.106 | Y29: =EXACT(X29,D29) -> TRUE
A30: DEUDORES DIVERSOS | B30: Deudores Diversos | C30: 115010 | D30: 1.1.04.108 | E30: GIFTCARD | F30: 585390 | G30: 104990 | H30: 480400 | I30: 0 | J30: 480400 | K30: 0 | L30: 0 | M30: 0 | O30: Monetaria | P30: =+J30-K30+L30-M30 -> 480400 | Q30: =P30/$Q$8 -> 531.97497 | V30: =U30-P30 -> -480400 | X30: 1.1.04.108 | Y30: =EXACT(X30,D30) -> TRUE
A31: DEUDORES DIVERSOS | B31: Deudores Diversos | C31: 115010 | D31: 1.1.04.109 | E31: ECOMMERCE | F31: 1371322273 | G31: 1083308831 | H31: 288013442 | I31: 0 | J31: 288013442 | K31: 0 | L31: 0 | M31: 0 | O31: Monetaria | P31: =+J31-K31+L31-M31 -> 288013442 | Q31: =P31/$Q$8 -> 318934.1 | V31: =U31-P31 -> -288013442 | X31: 1.1.04.109 | Y31: =EXACT(X31,D31) -> TRUE
... A33: DEUDORES DIVERSOS | B33: Deudores Diversos | C33: 115010 | D33: 1.1.04.113 | E33: GETNET TD/ PREPAGO | F33: 89987722 | G33: 88445522 | H33: 1542200 | I33: 0 | J33: 1542200 | K33: 0 | L33: 0 | M33: 0 | O33: Monetaria | P33: =+J33-K33+L33-M33 -> 1542200 | Q33: =P33/$Q$8 -> 1707.7681 | V33: =U33-P33 -> -1542200 | X33: 1.1.04.113 | Y33: =EXACT(X33,D33) -> TRUE
A34: DEUDORES DIVERSOS | B34: Deudores Diversos | C34: 115010 | D34: 1.1.04.200 | E34: CUENTAS POR COBRAR | F34: 6734121 | G34: 0 | H34: 6734121 | I34: 0 | J34: 6734121 | K34: 0 | L34: 0 | M34: 0 | O34: Monetaria | P34: =+J34-K34+L34-M34 -> 6734121 | Q34: =P34/$Q$8 -> 7457.0854 | X34: 1.1.04.200 | Y34: =EXACT(X34,D34) -> TRUE
A35: ANTICIPOS PROVEEDORE | B35: Pagos anticipados | C35: 115061 | D35: 1.1.05.403 | E35: ANTICIPO PROVEEDORES | F35: 288303448 | G35: 54409745 | H35: 233893703 | I35: 0 | J35: 233893703 | K35: 0 | L35: 0 | M35: 0 | O35: Monetaria | P35: =+J35-K35+L35-M35 -> 233893703 | Q35: =P35/$Q$8 -> 259004.16 | V35: =U35-P35 -> -233893703 | X35: 1.1.05.403 | Y35: =EXACT(X35,D35) -> TRUE
A36: ANTICIPOS PROVEEDORE | B36: Pagos anticipados | C36: 115061 | D36: 1.1.05.404 | E36: ANTICIPO HONORARIOS | F36: 100000 | G36: 20000 | H36: 80000 | I36: 0 | J36: 80000 | K36: 0 | L36: 0 | M36: 0 | O36: Monetaria | P36: =+J36-K36+L36-M36 -> 80000 | Q36: =P36/$Q$8 -> 88.588672 | V36: =U36-P36 -> -80000 | X36: 1.1.05.404 | Y36: =EXACT(X36,D36) -> TRUE
A37: ANTICIPOS PARA GASTOS | B37: Pagos anticipados | C37: 115055 | D37: 1.1.05.405 | E37: ANTICIPO AGENCIA DE ADUANAS | F37: 183281799 | G37: 181910308 | H37: 1371491 | I37: 0 | J37: 1371491 | K37: 0 | L37: 0 | M37: 0 | O37: Monetaria | P37: =+J37-K37+L37-M37 -> 1371491 | Q37: =P37/$Q$8 -> 1518.7321 | V37: =U37-P37 -> -1371491 | X37: 1.1.05.405 | Y37: =EXACT(X37,D37) -> TRUE
A38: INV PROD TERMINADO | B38: Inventarios | C38: 116050 | D38: 1.1.06.401 | E38: EXISTENCIAS NACIONALES | F38: 2012343198 | G38: 534509537 | H38: 1477833661 | I38: 0 | J38: 1477833661 | K38: 0 | L38: 0 | M38: 0 | O38: NO Monetario | P38: =+J38-K38+L38-M38 -> 1477833661 | Q38: =P38/$Q$8 -> 1636491.5 | V38: =U38-P38 -> -1477833661 | X38: 1.1.06.401 | Y38: =EXACT(X38,D38) -> TRUE
A39: INVENTARIO TRANSITO | B39: Inventarios | C39: 116072 | D39: 1.1.06.801 | E39: MERCADERIA EN TRANSITO | F39: 35497364 | G39: 35497364 | H39: 0 | I39: 0 | J39: 0 | K39: 0 | L39: 0 | M39: 0 | O39: Monetaria | P39: =+J39-K39+L39-M39 -> 0 | Q39: =P39/$Q$8 -> 0 | V39: =U39-P39 -> 0 | X39: 1.1.06.801 | Y39: =EXACT(X39,D39) -> TRUE
A40: INVENTARIO TRANSITO | B40: Inventarios | C40: 116072 | D40: 1.1.06.802 | E40: MERCADERIA EN TRANSITO USD | F40: 835086075 | G40: 561260345 | H40: 273825730 | I40: 0 | J40: 273825730 | K40: 0 | L40: 0 | M40: 0 | O40: Monetaria | P40: =+J40-K40+L40-M40 -> 273825730 | Q40: =P40/$Q$8 -> 303223.22 | V40: =U40-P40 -> -273825730 | X40: 1.1.06.802 | Y40: =EXACT(X40,D40) -> TRUE
A41: IVA A FAVOR | B41: Impuestos a favor | C41: 115082 | D41: 1.1.09.101 | E41: IVA CREDITO FISCAL (COMPRAS) | F41: 262722387 | G41: 262722387 | H41: 0 | I41: 0 | J41: 0 | K41: 0 | L41: 0 | M41: 0 | O41: Monetaria | P41: =+J41-K41+L41-M41 -> 0 | Q41: =P41/$Q$8 -> 0 | V41: =U41-P41 -> 0 | X41: 1.1.09.101 | Y41: =EXACT(X41,D41) -> TRUE
A42: IVA A FAVOR | B42: Impuestos a favor | C42: 115082 | D42: 1.1.09.103 | E42: REMANENTE IVA CREDITO FISCAL | F42: 456135707 | G42: 99687425 | H42: 356448282 | I42: 0 | J42: 356448282 | K42: 0 | L42: 0 | M42: 0 | O42: Monetaria | P42: =+J42-K42+L42-M42 -> 356448282 | Q42: =P42/$Q$8 -> 394716 | V42: =U42-P42 -> -356448282 | X42: 1.1.09.103 | Y42: =EXACT(X42,D42) -> TRUE
A43: DERECHOS ARRENDAMIEN | B43: Derechos de arrendamiento | C43: 141195 | D43: 1.2.02.101 | E43: GARANTIAS DE ARRIENDO | F43: 83146237 | G43: 25817865 | H43: 57328372 | I43: 0 | J43: 57328372 | K43: 0 | L43: 0 | M43: 0 | O43: Monetaria | P43: =+J43-K43+L43-M43 -> 57328372 | Q43: =P43/$Q$8 -> 63483.054 | V43: =U43-P43 -> -57328372 | X43: 1.2.02.101 | Y43: =EXACT(X43,D43) -> TRUE
A44: MOB Y EQ OFNA | B44: Equipo de tiendas | C44: 141080 | D44: 1.2.02.401 | E44: MUEBLES, UTILES Y OTROS | F44: 749360787 | G44: 0 | H44: 749360787 | I44: 0 | J44: 749360787 | K44: 0 | L44: 0 | M44: 0 | O44: NO Monetario | P44: =+J44-K44+L44-M44 -> 749360787 | Q44: =P44/$Q$8 -> 829810.96 | V44: =U44-P44 -> -749360787 | X44: 1.2.02.401 | Y44: =EXACT(X44,D44) -> TRUE
A45: MOB Y EQ COMPUTO | B45: Equipo de cómputo | C45: 141070 | D45: 1.2.02.402 | E45: EQUIPOS COMPUTACIONALES | F45: 117850669 | G45: 5187174 | H45: 112663495 | I45: 0 | J45: 112663495 | K45: 0 | L45: 0 | M45: 0 | O45: NO Monetario | P45: =+J45-K45+L45-M45 -> 112663495 | Q45: =P45/$Q$8 -> 124758.87 | V45: =U45-P45 -> -112663495 | X45: 1.2.02.402 | Y45: =EXACT(X45,D45) -> TRUE
A46: ACT FIJO CONTRUCCION | B46: Equipo de tiendas | C46: 145000 | D46: 1.2.02.405 | E46: ACTIVO EN CONSTRUCCION | F46: 27748636 | G46: 27748636 | H46: 0 | I46: 0 | J46: 0 | K46: 0 | L46: 0 | M46: 0 | O46: NO Monetario | P46: =+J46-K46+L46-M46 -> 0 | Q46: =P46/$Q$8 -> 0 | V46: =U46-P46 -> 0 | X46: 1.2.02.405 | Y46: =EXACT(X46,D46) -> TRUE
... A65: VTAS CALZ NAL MENUD | B65: Ventas Netas | C65: 510020 | D65: 3.1.01.103 | E65: VENTAS CON BOLETA (RPA) | F65: 56869595 | G65: 1023709546 | H65: 0 | I65: 966839951 | J65: 0 | K65: 0 | L65: 0 | M65: 966839951 | O65: NO Monetario | P65: =+J65-K65+L65-M65 -> -966839951 | Q65: =P65/$Q$8 -> -1070638.3 | V65: =U65-P65 -> 966839951 | X65: 3.1.01.103 | Y65: =EXACT(X65,D65) -> TRUE
A66: INGRESOS OTROS PRODUCTOS | B66: Otros ingresos | C66: 570500 | D66: 3.1.01.300 | E66: OTROS INGRESOS | F66: 0 | G66: 10765435 | H66: 0 | I66: 10765435 | J66: 0 | K66: 0 | L66: 0 | M66: 10765435 | O66: NO Monetario | P66: =+J66-K66+L66-M66 -> -10765435 | Q66: =P66/$Q$8 -> -11921.195 | X66: 3.1.01.300 | Y66: =EXACT(X66,D66) -> TRUE
A67: CTO ESTANDAR VTAS | B67: Costo estándar de venta | C67: 610000 | D67: 3.1.02.101 | E67: COSTO DE VENTAS | F67: 521764218 | G67: 20105868 | H67: 501658350 | I67: 0 | J67: 0 | K67: 0 | L67: 501658350 | M67: 0 | O67: NO Monetario | P67: =+J67-K67+L67-M67 -> 501658350 | Q67: =P67/$Q$8 -> 555515.59 | V67: =U67-P67 -> -501658350 | X67: 3.1.02.101 | Y67: =EXACT(X67,D67) -> TRUE
A68: FLETES SOBRE VTA | B68: Gastos de Administracion y Ventas | C68: 708130 | D68: 3.1.02.102 | E68: COSTOS OPERATIVOS - FLETES INTERNOS | F68: 20343976 | G68: 8527680 | H68: 11816296 | I68: 0 | J68: 0 | K68: 0 | L68: 11816296 | M68: 0 | O68: NO Monetario | P68: =+J68-K68+L68-M68 -> 11816296 | Q68: =P68/$Q$8 -> 13084.875 | V68: =U68-P68 -> -11816296 | X68: 3.1.02.102 | Y68: =EXACT(X68,D68) -> TRUE
A69: COMISIONES VENTAS | B69: Gastos de Administracion y Ventas | C69: 701013 | D69: 3.1.02.104 | E69: COMISIÓN - CANAL DIGITAL | F69: 19865543 | G69: 7920152 | H69: 11945391 | I69: 0 | J69: 0 | K69: 0 | L69: 11945391 | M69: 0 | O69: NO Monetario | P69: =+J69-K69+L69-M69 -> 11945391 | Q69: =P69/$Q$8 -> 13227.829 | V69: =U69-P69 -> -11945391 | X69: 3.1.02.104 | Y69: =EXACT(X69,D69) -> TRUE
A70: FLETES SOBRE VTA | B70: Gastos de Administracion y Ventas | C70: 708130 | D70: 3.1.02.105 | E70: FLETES - CANAL DIGITAL | F70: 27818810 | G70: 10588880 | H70: 17229930 | I70: 0 | J70: 0 | K70: 0 | L70: 17229930 | M70: 0 | O70: NO Monetario | P70: =+J70-K70+L70-M70 -> 17229930 | Q70: =P70/$Q$8 -> 19079.708 | V70: =U70-P70 -> -17229930 | X70: 3.1.02.105 | Y70: =EXACT(X70,D70) -> TRUE
A71: MEDIOS DIGITAL | B71: Gastos de Administracion y Ventas | C71: 709226 | D71: 3.1.02.108 | E71: SERVICIOS - CANAL DIGITAL | F71: 8731382 | G71: 249954 | H71: 8481428 | I71: 0 | J71: 0 | K71: 0 | L71: 8481428 | M71: 0 | O71: NO Monetario | P71: =+J71-K71+L71-M71 -> 8481428 | Q71: =P71/$Q$8 -> 9391.9805 | V71: =U71-P71 -> -8481428 | X71: 3.1.02.108 | Y71: =EXACT(X71,D71) -> TRUE
A72: OTROS GASTOS | B72: Gastos de Administracion y Ventas | C72: 730789 | D72: 3.1.02.109 | E72: DESCUENTOS GIFTCARD | F72: 104990 | G72: 0 | H72: 104990 | I72: 0 | J72: 0 | K72: 0 | L72: 104990 | M72: 0 | O72: NO Monetario | P72: =+J72-K72+L72-M72 -> 104990 | Q72: =P72/$Q$8 -> 116.26156 | X72: 3.1.02.109 | Y72: =EXACT(X72,D72) -> TRUE
A73: OTROS GASTOS | B73: Gastos de Administracion y Ventas | C73: 730789 | D73: 3.1.02.110 | E73: DESCUENTOS CLUB FLEXI | F73: 178274 | G73: 0 | H73: 178274 | I73: 0 | J73: 0 | K73: 0 | L73: 178274 | M73: 0 | O73: NO Monetario | P73: =+J73-K73+L73-M73 -> 178274 | Q73: =P73/$Q$8 -> 197.41321 | X73: 3.1.02.110 | Y73: =EXACT(X73,D73) -> TRUE
A74: SUELDOS | B74: Sueldos | C74: 701011 | D74: 3.1.05.101 | E74: REMUNERACIONES | F74: 245413637 | G74: 72355238 | H74: 173058399 | I74: 0 | J74: 0 | K74: 0 | L74: 173058399 | M74: 0 | O74: NO Monetario | P74: =+J74-K74+L74-M74 -> 173058399 | Q74: =P74/$Q$8 -> 191637.67 | V74: =U74-P74 -> -173058399 | X74: 3.1.05.101 | Y74: =EXACT(X74,D74) -> TRUE
A75: GRATIFICACIONES | B75: Sueldos | C75: 701025 | D75: 3.1.05.102 | E75: BONOS | F75: 7431815 | G75: 1795800 | H75: 5636015 | I75: 0 | J75: 0 | K75: 0 | L75: 5636015 | M75: 0 | O75: NO Monetario | P75: =+J75-K75+L75-M75 -> 5636015 | Q75: =P75/$Q$8 -> 6241.0885 | V75: =U75-P75 -> -5636015 | X75: 3.1.05.102 | Y75: =EXACT(X75,D75) -> TRUE
A76: CESANTIA Y VEJEZ | B76: Sueldos | C76: 702059 | D76: 3.1.05.103 | E76: SEGURO DE CESANTIA | F76: 8007119 | G76: 1858975 | H76: 6148144 | I76: 0 | J76: 0 | K76: 0 | L76: 6148144 | M76: 0 | O76: NO Monetario | P76: =+J76-K76+L76-M76 -> 6148144 | Q76: =P76/$Q$8 -> 6808.1989 | V76: =U76-P76 -> -6148144 | X76: 3.1.05.103 | Y76: =EXACT(X76,D76) -> TRUE
A77: GRATIFICACIONES | B77: Sueldos | C77: 701025 | D77: 3.1.05.104 | E77: GRATIFICACION | F77: 48413067 | G77: 8103026 | H77: 40310041 | I77: 0 | J77: 0 | K77: 0 | L77: 40310041 | M77: 0 | O77: NO Monetario | P77: =+J77-K77+L77-M77 -> 40310041 | Q77: =P77/$Q$8 -> 44637.662 | V77: =U77-P77 -> -40310041 | X77: 3.1.05.104 | Y77: =EXACT(X77,D77) -> TRUE
A78: INDEMNIZACIONES | B78: Sueldos | C78: 701026 | D78: 3.1.05.107 | E78: FINIQUITOS | F78: 2825656 | G78: 0 | H78: 2825656 | I78: 0 | J78: 0 | K78: 0 | L78: 2825656 | M78: 0 | O78: NO Monetario | P78: =+J78-K78+L78-M78 -> 2825656 | Q78: =P78/$Q$8 -> 3129.0139 | V78: =U78-P78 -> -2825656 | X78: 3.1.05.107 | Y78: =EXACT(X78,D78) -> TRUE
A79: I.M.S.S | B79: Sueldos | C79: 702051 | D79: 3.1.05.110 | E79: MUTUAL DE SEGURIDAD | F79: 2883601 | G79: 643555 | H79: 2240046 | I79: 0 | J79: 0 | K79: 0 | L79: 2240046 | M79: 0 | O79: NO Monetario | P79: =+J79-K79+L79-M79 -> 2240046 | Q79: =P79/$Q$8 -> 2480.5337 | V79: =U79-P79 -> -2240046 | X79: 3.1.05.110 | Y79: =EXACT(X79,D79) -> TRUE
A80: AHORRO P/EL RETIRO | B80: Sueldos | C80: 702052 | D80: 3.1.05.111 | E80: SEGURO INVALIDEZ (AFP) | F80: 4910778 | G80: 1095399 | H80: 3815379 | I80: 0 | J80: 0 | K80: 0 | L80: 3815379 | M80: 0 | O80: NO Monetario | P80: =+J80-K80+L80-M80 -> 3815379 | Q80: =P80/$Q$8 -> 4224.992 | V80: =U80-P80 -> -3815379 | X80: 3.1.05.111 | Y80: =EXACT(X80,D80) -> TRUE
A81: AHORRO P/EL RETIRO | B81: Sueldos | C81: 702052 | D81: 3.1.05.112 | E81: CAPITALIZACION INDIVIDUAL AFP | F81: 309915 | G81: 69168 | H81: 240747 | I81: 0 | J81: 0 | K81: 0 | L81: 240747 | M81: 0 | O81: NO Monetario | P81: =+J81-K81+L81-M81 -> 240747 | Q81: =P81/$Q$8 -> 266.59321 | V81: =U81-P81 -> -240747 | X81: 3.1.05.112 | Y81: =EXACT(X81,D81) -> TRUE
A82: AHORRO P/EL RETIRO | B82: Sueldos | C82: 702052 | D82: 3.1.05.113 | E82: EXPECTATIVA DE VIDA | F82: 2833244 | G82: 632259 | H82: 2200985 | I82: 0 | J82: 0 | K82: 0 | L82: 2200985 | M82: 0 | O82: NO Monetario | P82: =+J82-K82+L82-M82 -> 2200985 | Q82: =P82/$Q$8 -> 2437.2792 | V82: =U82-P82 -> -2200985 | X82: 3.1.05.113 | Y82: =EXACT(X82,D82) -> TRUE
A83: DIA FESTIVO LABORADO | B83: Sueldos | C83: 701028 | D83: 3.1.05.117 | E83: DOMINGOS Y FESTIVOS | F83: 5410005 | G83: 7718 | H83: 5402287 | I83: 0 | J83: 0 | K83: 0 | L83: 5402287 | M83: 0 | O83: NO Monetario | P83: =+J83-K83+L83-M83 -> 5402287 | Q83: =P83/$Q$8 -> 5982.2679 | V83: =U83-P83 -> -5402287 | X83: 3.1.05.117 | Y83: =EXACT(X83,D83) -> TRUE
A84: DIA FESTIVO NO LABORADO | B84: Sueldos | C84: 701009 | D84: 3.1.05.121 | E84: SEMANA CORRIDA | F84: 5672845 | G84: 80923 | H84: 5591922 | I84: 0 | J84: 0 | K84: 0 | L84: 5591922 | M84: 0 | O84: NO Monetario | P84: =+J84-K84+L84-M84 -> 5591922 | Q84: =P84/$Q$8 -> 6192.2618 | V84: =U84-P84 -> -5591922 | X84: 3.1.05.121 | Y84: =EXACT(X84,D84) -> TRUE
A85: COMISIONES VENTAS | B85: Sueldos | C85: 701013 | D85: 3.1.05.122 | E85: COMISION POR VENTA | F85: 23649973 | G85: 360252 | H85: 23289721 | I85: 0 | J85: 0 | K85: 0 | L85: 23289721 | M85: 0 | O85: NO Monetario | P85: =+J85-K85+L85-M85 -> 23289721 | Q85: =P85/$Q$8 -> 25790.068 | V85: =U85-P85 -> -23289721 | X85: 3.1.05.122 | Y85: =EXACT(X85,D85) -> TRUE
... A94: RENTA DEL EDIFICIO | B94: Gastos de Administracion y Ventas | C94: 707121 | D94: 3.1.06.302 | E94: ARRIENDO DE BODEGAS | F94: 12437499 | G94: 0 | H94: 12437499 | I94: 0 | J94: 0 | K94: 0 | L94: 12437499 | M94: 0 | O94: NO Monetario | P94: =+J94-K94+L94-M94 -> 12437499 | Q94: =P94/$Q$8 -> 13772.769 | V94: =U94-P94 -> -12437499 | X94: 3.1.06.302 | Y94: =EXACT(X94,D94) -> TRUE
A95: GASTOS DIVERSOS | B95: Gastos de Administracion y Ventas | C95: 730765 | D95: 3.1.06.305 | E95: GASTOS DIVERSOS | F95: 4853316 | G95: 2479746 | H95: 2373570 | I95: 0 | J95: 0 | K95: 0 | L95: 2373570 | M95: 0 | O95: NO Monetario | P95: =+J95-K95+L95-M95 -> 2373570 | Q95: =P95/$Q$8 -> 2628.3927 | X95: 3.1.06.305 | Y95: =EXACT(X95,D95) -> TRUE
A96: GASTOS DIVERSOS | B96: Gastos de Administracion y Ventas | C96: 730765 | D96: 3.1.06.306 | E96: SEGURIDAD INDUSTRIAL | F96: 234000 | G96: 0 | H96: 234000 | I96: 0 | J96: 0 | K96: 0 | L96: 234000 | M96: 0 | O96: NO Monetario | P96: =+J96-K96+L96-M96 -> 234000 | Q96: =P96/$Q$8 -> 259.12186 | X96: 3.1.06.306 | Y96: =EXACT(X96,D96) -> TRUE
A97: GASTOS DIVERSOS | B97: Gastos de Administracion y Ventas | C97: 730765 | D97: 3.1.06.307 | E97: GASTOS FUERA DE PLANIFICACION | F97: 900000 | G97: 1395860 | H97: 0 | I97: 495860 | J97: 0 | K97: 0 | L97: 0 | M97: 495860 | O97: NO Monetario | P97: =+J97-K97+L97-M97 -> -495860 | Q97: =P97/$Q$8 -> -549.09473 | X97: 3.1.06.307 | Y97: =EXACT(X97,D97) -> TRUE
A98: TELEFONO E INTERNET | B98: Gastos de Administracion y Ventas | C98: 711353 | D98: 3.1.06.401 | E98: SERVICIOS DE TELECOMUNICACION | F98: 3520523 | G98: 1011068 | H98: 2509455 | I98: 0 | J98: 0 | K98: 0 | L98: 2509455 | M98: 0 | O98: NO Monetario | P98: =+J98-K98+L98-M98 -> 2509455 | Q98: =P98/$Q$8 -> 2778.8661 | V98: =U98-P98 -> -2509455 | X98: 3.1.06.401 | Y98: =EXACT(X98,D98) -> TRUE
A99: TELEFONO E INTERNET | B99: Gastos de Administracion y Ventas | C99: 711353 | D99: 3.1.06.406 | E99: GASTOS DE TELEFONIA MOVIL | F99: 538900 | G99: 13123 | H99: 525777 | I99: 0 | J99: 0 | K99: 0 | L99: 525777 | M99: 0 | O99: NO Monetario | P99: =+J99-K99+L99-M99 -> 525777 | Q99: =P99/$Q$8 -> 582.22358 | V99: =U99-P99 -> -525777 | X99: 3.1.06.406 | Y99: =EXACT(X99,D99) -> TRUE
A100: OTROS IMP Y DCHOS | B100: Gastos de Administracion y Ventas | C100: 730779 | D100: 3.1.06.501 | E100: PATENTE COMERCIAL | F100: 3398921 | G100: 41856 | H100: 3357065 | I100: 0 | J100: 0 | K100: 0 | L100: 3357065 | M100: 0 | O100: NO Monetario | P100: =+J100-K100+L100-M100 -> 3357065 | Q100: =P100/$Q$8 -> 3717.4741 | V100: =U100-P100 -> -3357065 | X100: 3.1.06.501 | Y100: =EXACT(X100,D100) -> TRUE
D101: 3.1.06.504 | E101: IVA IRRECUPERABLE | F101: 1065119 | G101: 0 | H101: 1065119 | I101: 0 | J101: 0 | K101: 0 | L101: 1065119 | M101: 0 | O101: NO Monetario | P101: =+J101-K101+L101-M101 -> 1065119 | Q101: =P101/$Q$8 -> 1179.4685 | X101: 3.1.06.504 | Y101: =EXACT(X101,D101) -> TRUE
A102: RECARGOS | B102: Gastos de Administracion y Ventas | C102: 730764 | D102: 3.1.06.505 | E102: MULTAS E INTERESES | F102: 421448 | G102: 0 | H102: 421448 | I102: 0 | J102: 0 | K102: 0 | L102: 421448 | M102: 0 | O102: NO Monetario | P102: =+J102-K102+L102-M102 -> 421448 | Q102: =P102/$Q$8 -> 466.69398 | X102: 3.1.06.505 | Y102: =EXACT(X102,D102) -> TRUE
A103: SEGUROS | B103: Gastos de Administracion y Ventas | C103: 730787 | D103: 3.1.06.506 | E103: SEGUROS | F103: 2622763 | G103: 112463 | H103: 2510300 | I103: 0 | J103: 0 | K103: 0 | L103: 2510300 | M103: 0 | O103: NO Monetario | P103: =+J103-K103+L103-M103 -> 2510300 | Q103: =P103/$Q$8 -> 2779.8018 | X103: 3.1.06.506 | Y103: =EXACT(X103,D103) -> TRUE
A104: SERVICIO VIGILANCIA | B104: Gastos de Administracion y Ventas | C104: 730788 | D104: 3.1.06.507 | E104: SERVICIO DE VIGILANCIA | F104: 243778 | G104: 61187 | H104: 182591 | I104: 0 | J104: 0 | K104: 0 | L104: 182591 | M104: 0 | O104: NO Monetario | P104: =+J104-K104+L104-M104 -> 182591 | Q104: =P104/$Q$8 -> 202.19368 | X104: 3.1.06.507 | Y104: =EXACT(X104,D104) -> TRUE
A105: MTTO DEL EDIFICIO | B105: Gastos de Administracion y Ventas | C105: 710303 | D105: 3.1.06.601 | E105: GASTO MANTENCION SUCURSALES | F105: 10148319 | G105: 6788199 | H105: 3360120 | I105: 0 | J105: 0 | K105: 0 | L105: 3360120 | M105: 0 | O105: NO Monetario | P105: =+J105-K105+L105-M105 -> 3360120 | Q105: =P105/$Q$8 -> 3720.8571 | V105: =U105-P105 -> -3360120 | X105: 3.1.06.601 | Y105: =EXACT(X105,D105) -> TRUE
A106: BOLSA IMPRESA | B106: Gastos de Administracion y Ventas | C106: 709222 | D106: 3.1.06.602 | E106: BOLSA IMPRESA | F106: 2588619 | G106: 19947 | H106: 2568672 | I106: 0 | J106: 0 | K106: 0 | L106: 2568672 | M106: 0 | O106: NO Monetario | P106: =+J106-K106+L106-M106 -> 2568672 | Q106: =P106/$Q$8 -> 2844.4405 | X106: 3.1.06.602 | Y106: =EXACT(X106,D106) -> TRUE
A107: PAP Y ART DE OFNA | B107: Gastos de Administracion y Ventas | C107: 715391 | D107: 3.1.06.802 | E107: SUMINISTROS COMPUTACIONALES | F107: 295630 | G107: 0 | H107: 295630 | I107: 0 | J107: 0 | K107: 0 | L107: 295630 | M107: 0 | O107: NO Monetario | P107: =+J107-K107+L107-M107 -> 295630 | Q107: =P107/$Q$8 -> 327.36836 | V107: =U107-P107 -> -295630 | X107: 3.1.06.802 | Y107: =EXACT(X107,D107) -> TRUE
A108: PAP Y ART DE OFNA | B108: Gastos de Administracion y Ventas | C108: 715391 | D108: 3.1.06.803 | E108: UTILES DE OFICINA Y PAPELERIA | F108: 1389959 | G108: 3890 | H108: 1386069 | I108: 0 | J108: 0 | K108: 0 | L108: 1386069 | M108: 0 | O108: NO Monetario | P108: =+J108-K108+L108-M108 -> 1386069 | Q108: =P108/$Q$8 -> 1534.8751 | V108: =U108-P108 -> -1386069 | X108: 3.1.06.803 | Y108: =EXACT(X108,D108) -> TRUE
A109: GF GASTOS BANCARIOS | B109: Comisiones bancarias | C109: 810040 | D109: 3.1.06.806 | E109: COMISIONES Y GASTOS BANCARIOS | F109: 1560534 | G109: 101644 | H109: 1458890 | I109: 0 | J109: 0 | K109: 0 | L109: 1458890 | M109: 0 | O109: NO Monetario | P109: =+J109-K109+L109-M109 -> 1458890 | Q109: =P109/$Q$8 -> 1615.5141 | V109: =U109-P109 -> -1458890 | X109: 3.1.06.806 | Y109: =EXACT(X109,D109) -> TRUE
A110: CARGO POR SERVICIO | B110: Gastos de Administracion y Ventas | C110: 717604 | D110: 3.1.06.812 | E110: COMISIONES TRANSBANK | F110: 10594035 | G110: 133467 | H110: 10460568 | I110: 0 | J110: 0 | K110: 0 | L110: 10460568 | M110: 0 | O110: NO Monetario | P110: =+J110-K110+L110-M110 -> 10460568 | Q110: =P110/$Q$8 -> 11583.598 | V110: =U110-P110 -> -10460568 | X110: 3.1.06.812 | Y110: =EXACT(X110,D110) -> TRUE
A111: CARGO POR SERVICIO | B111: Gastos de Administracion y Ventas | C111: 717604 | D111: 3.1.06.813 | E111: COMISIONES GETNET | F111: 2443895 | G111: 0 | H111: 2443895 | I111: 0 | J111: 0 | K111: 0 | L111: 2443895 | M111: 0 | O111: NO Monetario | P111: =+J111-K111+L111-M111 -> 2443895 | Q111: =P111/$Q$8 -> 2706.2676 | V111: =U111-P111 -> -2443895 | X111: 3.1.06.813 | Y111: =EXACT(X111,D111) -> TRUE
A112: VIATICOS CONSULTORES | B112: Gastos de Administracion y Ventas | C112: 706113 | D112: 3.1.06.817 | E112: GASTOS DE REPRESENTACION | F112: 1133557 | G112: 0 | H112: 1133557 | I112: 0 | J112: 0 | K112: 0 | L112: 1133557 | M112: 0 | O112: NO Monetario | P112: =+J112-K112+L112-M112 -> 1133557 | Q112: =P112/$Q$8 -> 1255.2539 | X112: 3.1.06.817 | Y112: =EXACT(X112,D112) -> TRUE
A113: LICENCIAS SOFTWARE | B113: Gastos de Administracion y Ventas | C113: 721752 | D113: 3.1.06.818 | E113: LICENCIAS SOTWARE RENTAS | F113: 11326287 | G113: 587504 | H113: 10738783 | I113: 0 | J113: 0 | K113: 0 | L113: 10738783 | M113: 0 | O113: NO Monetario | P113: =+J113-K113+L113-M113 -> 10738783 | Q113: =P113/$Q$8 -> 11891.682 | V113: =U113-P113 -> -10738783 | X113: 3.1.06.818 | Y113: =EXACT(X113,D113) -> TRUE
A114: CUOTAS Y SUSCRIP | B114: Gastos de Administracion y Ventas | C114: 730786 | D114: 3.1.06.831 | E114: MEMBRESÍAS Y ASOCIACIONES | F114: 537122 | G114: 0 | H114: 537122 | I114: 0 | J114: 0 | K114: 0 | L114: 537122 | M114: 0 | O114: NO Monetario | P114: =+J114-K114+L114-M114 -> 537122 | Q114: =P114/$Q$8 -> 594.78656 | V114: =U114-P114 -> -537122 | X114: 3.1.06.831 | Y114: =EXACT(X114,D114) -> TRUE
A115: MONITOREO COMERCIAL | B115: Gastos de Administracion y Ventas | C115: 709225 | D115: 3.1.06.837 | E115: MONITOREO COMERCIAL | F115: 4258452 | G115: 2094675 | H115: 2163777 | I115: 0 | J115: 0 | K115: 0 | L115: 2163777 | M115: 0 | O115: NO Monetario | P115: =+J115-K115+L115-M115 -> 2163777 | Q115: =P115/$Q$8 -> 2396.0766 | V115: =U115-P115 -> -2163777 | X115: 3.1.06.837 | Y115: =EXACT(X115,D115) -> TRUE
A116: MONITOREO COMERCIAL | B116: Publicidad | C116: 709205 | D116: 3.1.07.822 | E116: GASTOS DE PUBLICIDAD Y MARKETING | F116: 11460348 | G116: 459174 | H116: 11001174 | I116: 0 | J116: 0 | K116: 0 | L116: 11001174 | M116: 0 | O116: NO Monetario | P116: =+J116-K116+L116-M116 -> 11001174 | Q116: =P116/$Q$8 -> 12182.242 | V116: =U116-P116 -> -11001174 | X116: 3.1.07.822 | Y116: =EXACT(X116,D116) -> TRUE
A117: MATERIAL POP INTERNA | B117: Gastos de Administracion y Ventas | C117: 709224 | D117: 3.1.07.833 | E117: SUMINISTROS VISUAL | F117: 13441550 | G117: 6853996 | H117: 6587554 | I117: 0 | J117: 0 | K117: 0 | L117: 6587554 | M117: 0 | O117: NO Monetario | P117: =+J117-K117+L117-M117 -> 6587554 | Q117: =P117/$Q$8 -> 7294.7832 | V117: =U117-P117 -> -6587554 | X117: 3.1.07.833 | Y117: =EXACT(X117,D117) -> TRUE
A118: DEPR EQUIPO COMPUTO | B118: Depreciaciones | C118: 740814 | D118: 3.1.08.701 | E118: DEPRECIACION DEL EJERCICIO | F118: 37936648 | G118: 0 | H118: 37936648 | I118: 0 | J118: 0 | K118: 0 | L118: 37936648 | M118: 0 | O118: NO Monetario | P118: =+J118-K118+L118-M118 -> 37936648 | Q118: =P118/$Q$8 -> 42009.466 | V118: =U118-P118 -> -37936648 | X118: 3.1.08.701 | Y118: =EXACT(X118,D118) -> TRUE
A119: DEPR MUEBLES-ENSERES | C119: 740818 | F119: 0 | G119: 0 | H119: 0 | I119: 0 | J119: 0 | K119: 0 | L119: 0 | M119: 0 | O119: NO Monetario | P119: =+J119-K119+L119-M119 -> 0 | Q119: =P119/$Q$8 -> 0 | Y119: =EXACT(X119,D119) -> TRUE
A120: PRODUCTO FINANCIERO INTS X INVERSION | B120: Costo financiero | C120: 820010 | D120: 3.2.08.105 | E120: INTERESES POR PRESTAMO | F120: 77281 | G120: 0 | H120: 77281 | I120: 0 | J120: 0 | K120: 0 | L120: 77281 | M120: 0 | O120: NO Monetario | P120: =+J120-K120+L120-M120 -> 77281 | Q120: =P120/$Q$8 -> 85.577764 | V120: =U120-P120 -> -77281 | X120: 3.2.08.105 | Y120: =EXACT(X120,D120) -> TRUE
D121: 3.2.08.114 | E121: INTERESES DEVENGADOS FONDOS MU | F121: 105657 | G121: 3801270 | H121: 0 | I121: 3695613 | J121: 0 | K121: 0 | L121: 0 | M121: 3695613 | O121: NO Monetario | P121: =+J121-K121+L121-M121 -> -3695613 | Q121: =P121/$Q$8 -> -4092.3681 | X121: 3.2.08.114 | Y121: =EXACT(X121,D121) -> TRUE
A122: PRODUCTO FINANCIERO INTS X INVERSION | B122: Costo financiero | C122: 820010 | D122: 3.2.08.116 | E122: INTERES GANADO POR DEPOSITO A PLAZO PESOS | F122: 0 | G122: 35492 | H122: 0 | I122: 35492 | J122: 0 | K122: 0 | L122: 0 | M122: 35492 | O122: NO Monetario | P122: =+J122-K122+L122-M122 -> -35492 | Q122: =P122/$Q$8 -> -39.302364 | V122: =U122-P122 -> 35492 | X122: 3.2.08.116 | Y122: =EXACT(X122,D122) -> TRUE
A123: PRODUCTO FINANCIERO INTS X INVERSION | B123: Costo financiero | C123: 820010 | D123: 3.2.08.117 | E123: INTERES GANADO FONDOS MUTUOS | F123: 0 | G123: 775274 | H123: 0 | I123: 775274 | J123: 0 | K123: 0 | L123: 0 | M123: 775274 | O123: NO Monetario | P123: =+J123-K123+L123-M123 -> -775274 | Q123: =P123/$Q$8 -> -858.50617 | V123: =U123-P123 -> 775274 | X123: 3.2.08.117 | Y123: =EXACT(X123,D123) -> TRUE
A124: PRODUCTO FINANCIERO UTILIDAD CAMBIOS | B124: Costo financiero | C124: 820060 | D124: 3.2.11.158 | E124: DIFERENCIA DE CAMBIO | F124: 199410323 | G124: 188575345 | H124: 10834978 | I124: 0 | J124: 0 | K124: 0 | L124: 10834978 | M124: 0 | O124: NO Monetario | P124: =+J124-K124+L124-M124 -> 10834978 | Q124: =P124/$Q$8 -> 11998.204 | V124: =U124-P124 -> -10834978 | X124: 3.2.11.158 | Y124: =EXACT(X124,D124) -> TRUE
A125: GF PERDIDA (V M EXT) | B125: Costo financiero | C125: 810080 | D125: 3.2.13.101 | E125: CORRECCION MONETARIA ACTIVOS | F125: 1746970 | G125: 6262362 | H125: 0 | I125: 4515392 | J125: 0 | K125: 0 | L125: 0 | M125: 4515392 | O125: NO Monetario | P125: =+J125-K125+L125-M125 -> -4515392 | Q125: =P125/$Q$8 -> -5000.1572 | X125: 3.2.13.101 | Y125: =EXACT(X125,D125) -> TRUE
A126: DIFER POR REDONDEOS | B126: Costo financiero | C126: 810099 | D126: 3.2.13.109 | E126: AJUSTE REDONDEO AUTO | F126: 1352 | G126: 3 | H126: 1349 | I126: 0 | J126: 0 | K126: 0 | L126: 1349 | M126: 0 | O126: NO Monetario | P126: =+J126-K126+L126-M126 -> 1349 | Q126: =P126/$Q$8 -> 1.4938265 | V126: =U126-P126 -> -1349 | X126: 3.2.13.109 | Y126: =EXACT(X126,D126) -> TRUE
D129: Total Acumulado | F129: =SUM(F9:F126) -> 20837246768 | G129: =SUM(G9:G126) -> 20837246768 | H129: =SUM(H9:H126) -> 8854952726 | I129: =SUM(I9:I126) -> 8854952726 | J129: =SUM(J9:J126) -> 7590346978 | K129: =SUM(K9:K126) -> 7867829709 | L129: =SUM(L9:L126) -> 1264605748 | M129: =SUM(M9:M126) -> 987123017 | P129: =SUM(P9:P126) -> 0 | Q129: =SUM(Q9:Q126) -> -1.0091983e-09 | R129: =SUM(R10:R65) -> 0 | S129: =SUM(S10:S65) -> 0 | U129: =SUM(U10:U65) -> 0
D130: Resultado del ejercicio | J130: 0 | K130: =+J129-K129 -> -277482731 | L130: =+M129-L129 -> -277482731 | M130: 0 | P130: =SUM(P65:P128) -> 277482731 | Q130: =SUM(Q65:Q128) -> 307272.83 | R130: =SUM(R67:R127) -> 0 | S130: =SUM(S67:S127) -> 0 | U130: =SUM(U67:U127) -> 0
D131: Sumas Iguales | F131: =SUM(F129:F130) -> 20837246768 | G131: =SUM(G129:G130) -> 20837246768 | H131: =SUM(H129:H130) -> 8854952726 | I131: =SUM(I129:I130) -> 8854952726 | J131: =SUM(J129:J130) -> 7590346978 | K131: =SUM(K129:K130) -> 7590346978 | L131: =SUM(L129:L130) -> 987123017 | M131: =SUM(M129:M130) -> 987123017

Sheet Balance
C1: Valor | D1: Cuenta México | E1: Registro SAP | F1: 903.05 | H1: Monetarias | I1: TC cierre | J1: No monetarias | K1: TC Historico transaccional
A2: 1.1.01.101 | B2: EFECTIVO EN TRANSITO | C2: =VLOOKUP(A2,BCE!$D$9:$P$131,13) -> 84410436 | D2: =SUMIF('Balanza ok'!D:D,A2,'Balanza ok'!B:B) -> 111100 | E2: 40 | F2: =C2/$F$1 -> 93472.605
A3: 1.1.01.203 | B3: FONDO FIJO PLAZA EGAÑA | C3: =VLOOKUP(A3,BCE!$D$9:$P$131,13) -> 37420 | D3: =SUMIF('Balanza ok'!D:D,A3,'Balanza ok'!B:B) -> 111100 | E3: 40 | F3: =C3/$F$1 -> 41.437351
A4: 1.1.01.204 | B4: FONDO FIJO VESPUCIO | C4: =VLOOKUP(A4,BCE!$D$9:$P$131,13) -> -126774 | D4: =SUMIF('Balanza ok'!D:D,A4,'Balanza ok'!B:B) -> 111100 | E4: 50 | F4: =C4/$F$1 -> -140.38425
A5: 1.1.01.205 | B5: FONDO FIJO TREBOL | C5: =VLOOKUP(A5,BCE!$D$9:$P$131,13) -> 32350 | D5: =SUMIF('Balanza ok'!D:D,A5,'Balanza ok'!B:B) -> 111100 | E5: 40 | F5: =C5/$F$1 -> 35.823044
A6: 1.1.01.206 | B6: FONDO FIJO COSTANERA CENTER | C6: =VLOOKUP(A6,BCE!$D$9:$P$131,13) -> 44970 | D6: =SUMIF('Balanza ok'!D:D,A6,'Balanza ok'!B:B) -> 111100 | E6: 40 | F6: =C6/$F$1 -> 49.797907
A7: 1.1.01.207 | B7: FONDO FIJO FLORIDA CENTER | C7: =VLOOKUP(A7,BCE!$D$9:$P$131,13) -> 32860 | D7: =SUMIF('Balanza ok'!D:D,A7,'Balanza ok'!B:B) -> 111100 | E7: 40 | F7: =C7/$F$1 -> 36.387797
A8: 1.1.01.208 | B8: FONDO FIJO SANTIAGO CENTRO | C8: =VLOOKUP(A8,BCE!$D$9:$P$131,13) -> 11360 | D8: =SUMIF('Balanza ok'!D:D,A8,'Balanza ok'!B:B) -> 111100 | E8: 40 | F8: =C8/$F$1 -> 12.579591
A9: 1.1.01.209 | B9: FONDO FIJO CONCEPCION CENTRO | C9: =VLOOKUP(A9,BCE!$D$9:$P$131,13) -> 0 | D9: =SUMIF('Balanza ok'!D:D,A9,'Balanza ok'!B:B) -> 111100 | E9: 40 | F9: =C9/$F$1 -> 0
A10: 1.1.01.210 | B10: FONDO FIJO TALCA | C10: =VLOOKUP(A10,BCE!$D$9:$P$131,13) -> 38022 | D10: =SUMIF('Balanza ok'!D:D,A10,'Balanza ok'!B:B) -> 111100 | E10: 40 | F10: =C10/$F$1 -> 42.103981
A11: 1.1.01.211 | B11: FONDO FIJO PLAZA NORTE | C11: =VLOOKUP(A11,BCE!$D$9:$P$131,13) -> 36120 | D11: =SUMIF('Balanza ok'!D:D,A11,'Balanza ok'!B:B) -> 111100 | E11: 40 | F11: =C11/$F$1 -> 39.997785
A12: 1.1.01.212 | B12: FONDO FIJO PLAZA OESTE | C12: =VLOOKUP(A12,BCE!$D$9:$P$131,13) -> 41598 | D12: =SUMIF('Balanza ok'!D:D,A12,'Balanza ok'!B:B) -> 111100 | E12: 40 | F12: =C12/$F$1 -> 46.063895
A13: 1.1.01.301 | B13: BANCOS CTA CTE $ | C13: =VLOOKUP(A13,BCE!$D$9:$P$131,13) -> 213813817 | D13: =SUMIF('Balanza ok'!D:D,A13,'Balanza ok'!B:B) -> 112093 | E13: 40 | F13: =C13/$F$1 -> 236768.53
... A41: 1.2.02.905 | B41: DEPRECIACION ACUMULADA EQUIPOS COMPUTACIONALES | C41: =VLOOKUP(A41,BCE!$D$9:$P$131,13) -> -41292706 | D41: =SUMIF('Balanza ok'!D:D,A41,'Balanza ok'!B:B) -> 142070 | E41: 50 | F41: =C41/$F$1 -> -45725.825
A42: 2.1.01.203 | B42: PRESTAMOS NO BANCARIOS MONTO A | C42: =VLOOKUP(A42,BCE!$D$9:$P$131,13) -> -153102751 | D42: =SUMIF('Balanza ok'!D:D,A42,'Balanza ok'!B:B) -> 224000 | E42: 50 | F42: =C42/$F$1 -> -169539.62 | G42: S17 | H42: Grupo Flexi de León S.A.P.I de CV
A43: 2.1.01.204 | B43: CUENTAS POR PAGAR | C43: =VLOOKUP(A43,BCE!$D$9:$P$131,13) -> -3101856 | D43: =SUMIF('Balanza ok'!D:D,A43,'Balanza ok'!B:B) -> 224000 | E43: 50 | F43: =C43/$F$1 -> -3434.8663
A44: 2.1.01.601 | B44: TARJETA CREDITO CLP | C44: =VLOOKUP(A44,BCE!$D$9:$P$131,13) -> 0 | D44: =SUMIF('Balanza ok'!D:D,A44,'Balanza ok'!B:B) -> 224000 | E44: 50 | F44: =C44/$F$1 -> 0
A45: 2.1.02.102 | B45: PROVEEDORES US$ | C45: =VLOOKUP(A45,BCE!$D$9:$P$131,13) -> -1542217800 | D45: =SUMIF('Balanza ok'!D:D,A45,'Balanza ok'!B:B) -> 210020 | E45: 50 | F45: =C45/$F$1 -> -1707787.8 | G45: S07 y S87 | H45: Alyc-Distrib Flexi - Qli
A46: 2.1.02.103 | B46: PROVEEDORES $ | C46: =VLOOKUP(A46,BCE!$D$9:$P$131,13) -> -16895791 | D46: =SUMIF('Balanza ok'!D:D,A46,'Balanza ok'!B:B) -> 210010 | E46: 50 | F46: =C46/$F$1 -> -18709.696
A47: 2.1.02.401 | B47: HONORARIOS POR PAGAR | C47: =VLOOKUP(A47,BCE!$D$9:$P$131,13) -> -2728385 | D47: =SUMIF('Balanza ok'!D:D,A47,'Balanza ok'!B:B) -> 210030 | E47: 50 | F47: =C47/$F$1 -> -3021.3
A48: 2.1.02.503 | B48: PREVIRED POR PAGAR | C48: =VLOOKUP(A48,BCE!$D$9:$P$131,13) -> -9447850 | D48: =SUMIF('Balanza ok'!D:D,A48,'Balanza ok'!B:B) -> 226030 | E48: 50 | F48: =C48/$F$1 -> -10462.156
A49: 2.1.02.604 | B49: ACREEDORES VARIOS | C49: =VLOOKUP(A49,BCE!$D$9:$P$131,13) -> -31127797 | D49: =SUMIF('Balanza ok'!D:D,A49,'Balanza ok'!B:B) -> 228050 | E49: 50 | F49: =C49/$F$1 -> -34469.627
A50: 2.1.02.605 | B50: PROVISIONES VARIAS | C50: =VLOOKUP(A50,BCE!$D$9:$P$131,13) -> -45893120 | D50: =SUMIF('Balanza ok'!D:D,A50,'Balanza ok'!B:B) -> 228050 | E50: 50 | F50: =C50/$F$1 -> -50820.132
A51: 2.1.05.101 | B51: IMPUESTO ÚNICO TRABAJADORES | C51: =VLOOKUP(A51,BCE!$D$9:$P$131,13) -> 0 | D51: =SUMIF('Balanza ok'!D:D,A51,'Balanza ok'!B:B) -> 227010 | E51: 50 | F51: =C51/$F$1 -> 0
A52: 2.1.05.102 | B52: RETENCION DE HONORARIOS | C52: =VLOOKUP(A52,BCE!$D$9:$P$131,13) -> 0 | D52: =SUMIF('Balanza ok'!D:D,A52,'Balanza ok'!B:B) -> 227050 | E52: 50 | F52: =C52/$F$1 -> 0
A53: 2.1.05.103 | B53: IVA DEBITO FISCAL (VENTAS) | C53: =VLOOKUP(A53,BCE!$D$9:$P$131,13) -> 0 | D53: =SUMIF('Balanza ok'!D:D,A53,'Balanza ok'!B:B) -> 226050 | E53: 50 | F53: =C53/$F$1 -> 0
A54: 2.1.05.106 | B54: IMPUESTO POR PAGAR FORM. 29 | C54: =VLOOKUP(A54,BCE!$D$9:$P$131,13) -> -3873394 | D54: =SUMIF('Balanza ok'!D:D,A54,'Balanza ok'!B:B) -> 226060 | E54: 50 | F54: =C54/$F$1 -> -4289.2354
A55: 2.1.06.103 | B55: SUELDOS POR PAGAR | C55: =VLOOKUP(A55,BCE!$D$9:$P$131,13) -> -11500335 | D55: =SUMIF('Balanza ok'!D:D,A55,'Balanza ok'!B:B) -> 228011 | E55: 50 | F55: =C55/$F$1 -> -12734.993
A56: 2.3.01.101 | B56: CAPITAL | C56: =VLOOKUP(A56,BCE!$D$9:$P$131,13) -> -5770668867 | D56: =SUMIF('Balanza ok'!D:D,A56,'Balanza ok'!B:B) -> 310100 | E56: 50 | F56: =C56/$F$1 -> -6390198.6
A57: 2.3.02.101 | B57: RESULTADOS ACUMULADOS | C57: =VLOOKUP(A57,BCE!$D$9:$P$131,13) -> 3154549713 | D57: =SUMIF('Balanza ok'!D:D,A57,'Balanza ok'!B:B) -> 340100 | E57: 40 | F57: =C57/$F$1 -> 3493217.1
C59: =SUM(C2:C58) -> -277482731 | F59: =C59/$F$1 -> -307272.83
C60: =EXACT(C59,BCE!L130) -> TRUE

Sheet Resultados
C1: HMARKETPLAZ | E1: HEGAÑA | F1: HVESPUCIO | G1: TREBOL | H1: HONLINE | J1: HCOSTANERA | K1: HFLORIDA | L1: HDEPARTAME | M1: HSANTIAGO CENTRO | N1: HMAULE TALCA | R1: Valor transaccional | S1: Tipo de cambio transaccional | U1: HDOMINICOS | V1: HMAIPU | W1: HEGAÑA | X1: HVESPUCIO | Y1: HTREBOL | Z1: HONLINE | AA1: HDEPARTAME | AB1: HCOSTANERA | AC1: HFLORIDA | AD1: HDEPARTAME | AE1: HSANTIAGO | AF1: HCONCEPCIO | AG1: HMAULETALC | AH1: HNORTE | AI1: HOESTE
C2: FLEXI
A3: Cuenta México | B3: N° CUENTA | C3: NOMBRE CUENTA | D3: CEDIS CHILE | E3: EGAÑA | F3: VESPUCIO | G3: TREBOL | H3: ONLINE | I3: ADMINISTRACION | J3: COSTANERA CENTER | K3: FLORIDA CENTER | L3: DEPARTAMENTALES | M3: SANTIAGO CENTRO | N3: TALCA | O3: PLAZA NORTE | P3: PLAZA OESTE | Q3: TOTAL | T3: CEDIS CHILE | U3: DOMINICOS | V3: MAIPU | W3: EGAÑA | X3: VESPUCIO | Y3: TREBOL | Z3: ONLINE | AA3: ADMINISTRACION | AB3: COSTANERA CENTER | AC3: FLORIDA CENTER | AD3: DEPARTAMENTALES | AE3: SANTIAGO CENTRO | AF3: CONCEPCION CENTRO | AG3: TALCA | AH3: PLAZA NORTE | AI3: PLAZA OESTE | AJ3: TOTAL
A5: =SUMIF('Balanza ok'!D:D,B5,'Balanza ok'!B:B) -> 0 | B5: 3.1.01.101 | C5: VENTAS CON BOLETA | D5: =SUM(D6:D7) -> 0 | E5: =SUM(E6:E7) -> 98849734 | F5: =SUM(F6:F7) -> 23271304 | G5: =SUM(G6:G7) -> 68376719 | H5: =SUM(H6:H7) -> 128312918 | I5: =SUM(I6:I7) -> 0 | J5: =SUM(J6:J7) -> 1.3888742e+08 | K5: =SUM(K6:K7) -> 57892370 | ... Q5: =SUM(Q6:Q7) -> 7.8920614e+08 | R5: =Q5/S5 -> 873934.04 | S5: 903.05 | T5: =IFERROR((D5/#REF!),0) -> 0 | V5: =+V6+V7 -> 0 | W5: =+W6+W7 -> 109462.08 | X5: =+X6+X7 -> 25769.674 | Y5: =+Y6+Y7 -> 75717.534 | Z5: =+Z6+Z7 -> 142088.39 | AA5: =+AA6+AA7 -> 0 | AB5: =+AB6+AB7 -> 153798.15 | AC5: =+AC6+AC7 -> 64107.602 | ... AJ5: =+AJ6+AJ7 -> 873934.04 | AK5: =+AJ5 -> 873934.04
A6: 510060 | B6: ACC | C6: ACCESORIOS | E6: 1460319.3 | F6: 176722.69 | G6: 1900809.2 | H6: 267353 | J6: 3361368.1 | K6: 1122858.8 | M6: 1530563.9 | N6: 770665.55 | O6: 1330168.9 | P6: 1282000.8 | Q6: =SUM(D6:P6) -> 13202830 | R6: =Q6/S6 -> 14620.265 | S6: =+S5 -> 903.05 | T6: =IFERROR((D6/$S$5),0) -> 0 | U6: =IFERROR((#REF!/$S$5),0) -> 0 | V6: =IFERROR((#REF!/$S$5),0) -> 0 | W6: =IFERROR((E6/$S$5),0) -> 1617.0969 | X6: =IFERROR((F6/$S$5),0) -> 195.69535 | Y6: =IFERROR((G6/$S$5),0) -> 2104.8771 | Z6: =IFERROR((H6/$S$5),0) -> 296.05559 | AA6: =IFERROR((I6/$S$5),0) -> 0 | AB6: =IFERROR((J6/$S$5),0) -> 3722.2392 | AC6: =IFERROR((K6/$S$5),0) -> 1243.4071 | AD6: =IFERROR((L6/$S$5),0) -> 0 | AE6: =IFERROR((M6/$S$5),0) -> 1694.8827 | AF6: =IFERROR((#REF!/$S$5),0) -> 0 | AG6: =IFERROR((N6/$S$5),0) -> 853.40296 | AH6: =IFERROR((O6/$S$5),0) -> 1472.9737 | AI6: =IFERROR((P6/$S$5),0) -> 1419.6344 | AJ6: =SUM(T6:AI6) -> 14620.265
A7: 510020 | B7: CAL | C7: CALZADO | E7: 97389415 | F7: 23094582 | G7: 66475910 | H7: 128045565 | J7: 1.3552605e+08 | K7: 56769511 | M7: 1.0555948e+08 | N7: 51282706 | O7: 46624103 | P7: 65235983 | Q7: =SUM(D7:P7) -> 7.7600331e+08 | R7: =Q7/S7 -> 859313.78 | S7: =+S6 -> 903.05 | T7: =IFERROR((D7/$S$5),0) -> 0 | U7: =IFERROR((#REF!/$S$5),0) -> 0 | V7: =IFERROR((#REF!/$S$5),0) -> 0 | W7: =IFERROR((E7/$S$5),0) -> 107844.99 | X7: =IFERROR((F7/$S$5),0) -> 25573.979 | Y7: =IFERROR((G7/$S$5),0) -> 73612.657 | Z7: =IFERROR((H7/$S$5),0) -> 141792.33 | AA7: =IFERROR((I7/$S$5),0) -> 0 | AB7: =IFERROR((J7/$S$5),0) -> 150075.91 | AC7: =IFERROR((K7/$S$5),0) -> 62864.195 | AD7: =IFERROR((L7/$S$5),0) -> 0 | AE7: =IFERROR((M7/$S$5),0) -> 116892.18 | AF7: =IFERROR((#REF!/$S$5),0) -> 0 | AG7: =IFERROR((N7/$S$5),0) -> 56788.335 | AH7: =IFERROR((O7/$S$5),0) -> 51629.591 | AI7: =IFERROR((P7/$S$5),0) -> 72239.614 | AJ7: =SUM(T7:AI7) -> 859313.78
A8: =SUMIF('Balanza ok'!D:D,B8,'Balanza ok'!B:B) -> 610000 | B8: 3.1.02.101 | C8: COSTO DE VENTAS | E8: -52077833 | F8: -11212926 | G8: -33973126 | H8: -83073137 | J8: -73387032 | K8: -29634483 | M8: -56640704 | N8: -27289574 | O8: -24878624 | P8: -34956397 | Q8: =SUM(D8:P8) -> -427123836 | R8: =Q8/S8 -> -472979.17 | S8: =+S7 -> 903.05 | T8: =IFERROR((D8/$S$8),0) -> 0 | U8: =IFERROR((#REF!/$S$8),0) -> 0 | V8: =IFERROR((#REF!/$S$8),0) -> 0 | W8: =IFERROR((E8/$S$8),0) -> -57668.826 | X8: =IFERROR((F8/$S$8),0) -> -12416.728 | Y8: =IFERROR((G8/$S$8),0) -> -37620.426 | Z8: =IFERROR((H8/$S$8),0) -> -91991.736 | AA8: =IFERROR((I8/$S$8),0) -> 0 | AB8: =IFERROR((J8/$S$8),0) -> -81265.746 | AC8: =IFERROR((K8/$S$8),0) -> -32815.994 | AD8: =IFERROR((L8/$S$8),0) -> 0 | AE8: =IFERROR((M8/$S$8),0) -> -62721.559 | AF8: =IFERROR((#REF!/$S$8),0) -> 0 | AG8: =IFERROR((N8/$S$8),0) -> -30219.339 | AH8: =IFERROR((O8/$S$8),0) -> -27549.553 | AI8: =IFERROR((P8/$S$8),0) -> -38709.26 | AJ8: =SUM(T8:AI8) -> -472979.17 | AK8: =+AJ8 -> -472979.17
B9: Resultado por Centro de Beneficio | D9: =+D5+D8 -> 0 | E9: =+E5+E8 -> 46771901 | F9: =+F5+F8 -> 12058378 | G9: =+G5+G8 -> 34403593 | H9: =+H5+H8 -> 45239781 | I9: =+I5+I8 -> 0 | J9: =+J5+J8 -> 65500388 | K9: =+K5+K8 -> 28257887 | ... R9: =+R5+R8 -> 400954.88 | T9: =SUM(T6:T8) -> 0 | U9: =SUM(U6:U8) -> 0 | V9: =SUM(V6:V8) -> 0 | W9: =SUM(W6:W8) -> 51793.257 | X9: =SUM(X6:X8) -> 13352.946 | Y9: =SUM(Y6:Y8) -> 38097.108 | Z9: =SUM(Z6:Z8) -> 50096.651 | AA9: =SUM(AA6:AA8) -> 0 | ... AJ9: =SUM(AJ6:AJ8) -> 400954.88 | AK9: =SUM(AK5:AK8) -> 400954.88
AD10: C89004570 | AE10: C89004630 | AF10: C89004620 | AG10: C89004640 | AH10: C89004660 | AI10: C89004650
C11: TAMARIS
A12: Cuenta México | B12: N° CUENTA | C12: NOMBRE CUENTA | D12: CEDIS CHILE | E12: EGAÑA | F12: VESPUCIO | G12: TREBOL | H12: ONLINE | I12: ADMINISTRACION | J12: COSTANERA CENTER | K12: FLORIDA CENTER | L12: DEPARTAMENTALES | M12: SANTIAGO CENTRO | N12: TALCA | O12: PLAZA NORTE | P12: PLAZA OESTE | Q12: TOTAL | T12: CEDIS CHILE | U12: DOMINICOS | V12: MAIPU | W12: EGAÑA | X12: VESPUCIO | Y12: TREBOL | Z12: ONLINE | AA12: ADMINISTRACION | AB12: COSTANERA CENTER | AC12: FLORIDA CENTER | AD12: DEPARTAMENTALES | AE12: SANTIAGO CENTRO | AF12: CONCEPCION CENTRO | AG12: TALCA | AH12: PLAZA NORTE | AI12: PLAZA OESTE | AJ12: TOTAL
A14: =SUMIF('Balanza ok'!D:D,B14,'Balanza ok'!B:B) -> 0 | B14: 3.1.01.101 | C14: VENTAS CON BOLETA | D14: =SUM(D15:D16) -> 0 | E14: =SUM(E15:E16) -> 20188230 | F14: =SUM(F15:F16) -> 9144942.9 | G14: =SUM(G15:G16) -> 18738756 | H14: =SUM(H15:H16) -> 4629941.2 | I14: =SUM(I15:I16) -> 0 | J14: =SUM(J15:J16) -> 47691077 | K14: =SUM(K15:K16) -> 10781589 | ... Q14: =SUM(Q15:Q16) -> 1.7763436e+08 | R14: =Q14/S14 -> 203847.05 | S14: 871.41 | T14: =IFERROR((D14/#REF!),0) -> 0 | V14: =+V15+V16 -> 0 | W14: =+W15+W16 -> 22355.606 | X14: =+X15+X16 -> 10126.729 | Y14: =+Y15+Y16 -> 20750.519 | Z14: =+Z15+Z16 -> 5127.0042 | AA14: =+AA15+AA16 -> 0 | AB14: =+AB15+AB16 -> 52811.115 | AC14: =+AC15+AC16 -> 11939.083 | ... AJ14: =+AJ15+AJ16 -> 196704.9 | AK14: =+AJ14 -> 196704.9
A15: 510060 | B15: ACC | C15: ACCESORIOS | Q15: =SUM(D15:P15) -> 0 | R15: =Q15/S15 -> 0 | S15: =+S14 -> 871.41 | T15: =IFERROR((D15/$S$5),0) -> 0 | U15: =IFERROR((#REF!/$S$5),0) -> 0 | V15: =IFERROR((#REF!/$S$5),0) -> 0 | W15: =IFERROR((E15/$S$5),0) -> 0 | X15: =IFERROR((F15/$S$5),0) -> 0 | Y15: =IFERROR((G15/$S$5),0) -> 0 | Z15: =IFERROR((H15/$S$5),0) -> 0 | AA15: =IFERROR((I15/$S$5),0) -> 0 | AB15: =IFERROR((J15/$S$5),0) -> 0 | AC15: =IFERROR((K15/$S$5),0) -> 0 | AD15: =IFERROR((L15/$S$5),0) -> 0 | AE15: =IFERROR((M15/$S$5),0) -> 0 | AF15: =IFERROR((#REF!/$S$5),0) -> 0 | AG15: =IFERROR((N15/$S$5),0) -> 0 | AH15: =IFERROR((O15/$S$5),0) -> 0 | AI15: =IFERROR((P15/$S$5),0) -> 0 | AJ15: =SUM(T15:AI15) -> 0
A16: 510020 | B16: CAL | C16: CALZADO | E16: 20188230 | F16: 9144942.9 | G16: 18738756 | H16: 4629941.2 | J16: 47691077 | K16: 10781589 | M16: 21770211 | N16: 10644697 | O16: 11782568 | P16: 22262344 | Q16: =SUM(D16:P16) -> 1.7763436e+08 | R16: =Q16/S16 -> 203847.05 | S16: =+S15 -> 871.41 | T16: =IFERROR((D16/$S$5),0) -> 0 | U16: =IFERROR((#REF!/$S$5),0) -> 0 | V16: =IFERROR((#REF!/$S$5),0) -> 0 | W16: =IFERROR((E16/$S$5),0) -> 22355.606 | X16: =IFERROR((F16/$S$5),0) -> 10126.729 | Y16: =IFERROR((G16/$S$5),0) -> 20750.519 | Z16: =IFERROR((H16/$S$5),0) -> 5127.0042 | AA16: =IFERROR((I16/$S$5),0) -> 0 | AB16: =IFERROR((J16/$S$5),0) -> 52811.115 | AC16: =IFERROR((K16/$S$5),0) -> 11939.083 | AD16: =IFERROR((L16/$S$5),0) -> 0 | AE16: =IFERROR((M16/$S$5),0) -> 24107.426 | AF16: =IFERROR((#REF!/$S$5),0) -> 0 | AG16: =IFERROR((N16/$S$5),0) -> 11787.494 | AH16: =IFERROR((O16/$S$5),0) -> 13047.526 | AI16: =IFERROR((P16/$S$5),0) -> 24652.393 | AJ16: =SUM(T16:AI16) -> 196704.9
A17: =SUMIF('Balanza ok'!D:D,B17,'Balanza ok'!B:B) -> 610000 | B17: 3.1.02.101 | C17: COSTO DE VENTAS | E17: -8579160 | F17: -3710766 | G17: -7603450 | H17: -2079036 | J17: -20233730 | K17: -4493616 | M17: -9071392 | N17: -4524686 | O17: -5028056 | P17: -9210647 | Q17: =SUM(D17:P17) -> -74534539 | R17: =Q17/S17 -> -85533.261 | S17: =+S16 -> 871.41 | T17: =IFERROR((D17/$S$8),0) -> 0 | U17: =IFERROR((#REF!/$S$8),0) -> 0 | V17: =IFERROR((#REF!/$S$8),0) -> 0 | W17: =IFERROR((E17/$S$8),0) -> -9500.2049 | X17: =IFERROR((F17/$S$8),0) -> -4109.1479 | Y17: =IFERROR((G17/$S$8),0) -> -8419.7442 | Z17: =IFERROR((H17/$S$8),0) -> -2302.238 | AA17: =IFERROR((I17/$S$8),0) -> 0 | AB17: =IFERROR((J17/$S$8),0) -> -22405.991 | AC17: =IFERROR((K17/$S$8),0) -> -4976.0434 | AD17: =IFERROR((L17/$S$8),0) -> 0 | AE17: =IFERROR((M17/$S$8),0) -> -10045.282 | AF17: =IFERROR((#REF!/$S$8),0) -> 0 | AG17: =IFERROR((N17/$S$8),0) -> -5010.449 | AH17: =IFERROR((O17/$S$8),0) -> -5567.86 | AI17: =IFERROR((P17/$S$8),0) -> -10199.487 | AJ17: =SUM(T17:AI17) -> -82536.448 | AK17: =+AJ17 -> -82536.448
B18: Resultado por Centro de Beneficio | D18: =+D14+D17 -> 0 | E18: =+E14+E17 -> 11609070 | F18: =+F14+F17 -> 5434176.9 | G18: =+G14+G17 -> 11135306 | H18: =+H14+H17 -> 2550905.2 | I18: =+I14+I17 -> 0 | J18: =+J14+J17 -> 27457347 | K18: =+K14+K17 -> 6287973.1 | ... R18: =+R14+R17 -> 118313.79 | T18: =SUM(T15:T17) -> 0 | U18: =SUM(U15:U17) -> 0 | V18: =SUM(V15:V17) -> 0 | W18: =SUM(W15:W17) -> 12855.401 | X18: =SUM(X15:X17) -> 6017.5814 | Y18: =SUM(Y15:Y17) -> 12330.775 | Z18: =SUM(Z15:Z17) -> 2824.7663 | AA18: =SUM(AA15:AA17) -> 0 | ... AJ18: =SUM(AJ15:AJ17) -> 114168.45 | AK18: =SUM(AK14:AK17) -> 114168.45
D20: C89004120 | E20: C89004530 | F20: C89004540 | G20: C89004550 | H20: C89004560 | I20: C89005070 | J20: C89004580 | K20: C89004590 | M20: C89004610 | N20: C89004640 | T20: C89004120 | U20: C89004510 | V20: C89004520 | W20: C89004530 | X20: C89004540 | Y20: C89004550 | Z20: C89004560 | AA20: C89005070 | AB20: C89004580 | AC20: C89004590 | AD20: C89004570 | AE20: C89004630 | AF20: C89004620 | AG20: C89004640 | AH20: C89004660 | AI20: C89004650
B21: N° CUENTA | C21: NOMBRE CUENTA | D21: CEDIS CHILE | E21: EGAÑA | F21: VESPUCIO | G21: TREBOL | H21: ONLINE | I21: ADMINISTRACION | J21: COSTANERA CENTER | K21: FLORIDA CENTER | L21: DEPARTAMENTALES | M21: SANTIAGO CENTRO | N21: TALCA | O21: PLAZA NORTE | P21: PLAZA OESTE | Q21: TOTAL | T21: CEDIS CHILE | U21: DOMINICOS | V21: MAIPU | W21: EGAÑA | X21: VESPUCIO | Y21: TREBOL | Z21: ONLINE | AA21: ADMINISTRACION | AB21: COSTANERA CENTER | AC21: FLORIDA CENTER | AD21: DEPARTAMENTALES | AE21: SANTIAGO CENTRO | AF21: CONCEPCION CENTRO | AG21: TALCA | AH21: PLAZA NORTE | AI21: PLAZA OESTE | AJ21: TOTAL
AK22: =-AK9 -> -400954.88
A23: =SUMIF('Balanza ok'!D:D,B23,'Balanza ok'!B:B) -> 570500 | B23: 3.1.01.300 | C23: OTROS INGRESOS | D23: 0 | E23: 0 | F23: 0 | G23: 0 | H23: 10765435 | I23: 0 | J23: 0 | K23: 0 | L23: 0 | M23: 0 | N23: 0 | O23: 0 | P23: 0 | Q23: =SUM(D23:P23) -> 10765435 | R23: =Q23/S23 -> 11921.195 | S23: =+S8 -> 903.05 | T23: =IFERROR((D23/$S23),0) -> 0 | U23: =IFERROR((#REF!/$S23),0) -> 0 | V23: =IFERROR((#REF!/$S23),0) -> 0 | W23: =IFERROR((E23/$S23),0) -> 0 | X23: =IFERROR((F23/$S23),0) -> 0 | Y23: =IFERROR((G23/$S23),0) -> 0 | Z23: =IFERROR((H23/$S23),0) -> 11921.195 | AA23: =IFERROR((I23/$S23),0) -> 0 | AB23: =IFERROR((J23/$S23),0) -> 0 | AC23: =IFERROR((K23/$S23),0) -> 0 | AD23: =IFERROR((L23/$S23),0) -> 0 | AE23: =IFERROR((M23/$S23),0) -> 0 | AF23: =IFERROR((#REF!/$S23),0) -> 0 | AG23: =IFERROR((N23/$S23),0) -> 0 | AH23: =IFERROR((O23/$S23),0) -> 0 | AI23: =IFERROR((P23/$S23),0) -> 0 | AJ23: =SUM(T23:AI23) -> 11921.195 | AK23: =+AJ23 -> 11921.195 | AL23: =+R23-AJ23 -> 0 | AN23: 3.1.01.300 | AO23: =EXACT(B23,AN23) -> TRUE
A24: =SUMIF('Balanza ok'!D:D,B24,'Balanza ok'!B:B) -> 708130 | B24: 3.1.02.102 | C24: COSTOS OPERATIVOS - FLETES INTERNOS | D24: -9366599 | E24: -311388 | F24: -108593 | G24: -311388 | H24: 150000 | I24: 0 | J24: -311388 | K24: -311388 | L24: 0 | M24: -311388 | N24: -311388 | O24: -311388 | P24: -311388 | Q24: =SUM(D24:P24) -> -11816296 | R24: =Q24/S24 -> -13084.875 | S24: =+S23 -> 903.05 | T24: =IFERROR((D24/$S24),0) -> -10372.182 | U24: =IFERROR((#REF!/$S24),0) -> 0 | V24: =IFERROR((#REF!/$S24),0) -> 0 | W24: =IFERROR((E24/$S24),0) -> -344.81812 | X24: =IFERROR((F24/$S24),0) -> -120.25137 | Y24: =IFERROR((G24/$S24),0) -> -344.81812 | Z24: =IFERROR((H24/$S24),0) -> 166.10376 | AA24: =IFERROR((I24/$S24),0) -> 0 | AB24: =IFERROR((J24/$S24),0) -> -344.81812 | AC24: =IFERROR((K24/$S24),0) -> -344.81812 | AD24: =IFERROR((L24/$S24),0) -> 0 | AE24: =IFERROR((M24/$S24),0) -> -344.81812 | AF24: =IFERROR((#REF!/$S24),0) -> 0 | AG24: =IFERROR((N24/$S24),0) -> -344.81812 | AH24: =IFERROR((O24/$S24),0) -> -344.81812 | AI24: =IFERROR((P24/$S24),0) -> -344.81812 | AJ24: =SUM(T24:AI24) -> -13084.875 | AK24: =+AJ24 -> -13084.875 | AL24: =+R24-AJ24 -> 0 | AN24: 3.1.02.102 | AO24: =EXACT(B24,AN24) -> TRUE
A25: =SUMIF('Balanza ok'!D:D,B25,'Balanza ok'!B:B) -> 709226 | B25: 3.1.02.104 | C25: COMISIÓN - CANAL DIGITAL | D25: 0 | E25: 0 | F25: 0 | G25: 0 | H25: -4702554 | I25: 0 | J25: 0 | K25: 0 | L25: -7242837 | M25: 0 | N25: 0 | O25: 0 | P25: 0 | Q25: =SUM(D25:P25) -> -11945391 | R25: =Q25/S25 -> -13227.829 | S25: =+S24 -> 903.05 | T25: =IFERROR((D25/$S25),0) -> 0 | U25: =IFERROR((#REF!/$S25),0) -> 0 | V25: =IFERROR((#REF!/$S25),0) -> 0 | W25: =IFERROR((E25/$S25),0) -> 0 | X25: =IFERROR((F25/$S25),0) -> 0 | Y25: =IFERROR((G25/$S25),0) -> 0 | Z25: =IFERROR((H25/$S25),0) -> -5207.4127 | AA25: =IFERROR((I25/$S25),0) -> 0 | AB25: =IFERROR((J25/$S25),0) -> 0 | AC25: =IFERROR((K25/$S25),0) -> 0 | AD25: =IFERROR((L25/$S25),0) -> -8020.4164 | AE25: =IFERROR((M25/$S25),0) -> 0 | AF25: =IFERROR((#REF!/$S25),0) -> 0 | AG25: =IFERROR((N25/$S25),0) -> 0 | AH25: =IFERROR((O25/$S25),0) -> 0 | AI25: =IFERROR((P25/$S25),0) -> 0 | AJ25: =SUM(T25:AI25) -> -13227.829 | AK25: =+AJ25 -> -13227.829 | AL25: =+R25-AJ25 -> 0 | AN25: 3.1.02.104 | AO25: =EXACT(B25,AN25) -> TRUE
A26: =SUMIF('Balanza ok'!D:D,B26,'Balanza ok'!B:B) -> 708130 | B26: 3.1.02.105 | C26: FLETES - CANAL DIGITAL | D26: 0 | E26: 0 | F26: 0 | G26: 0 | H26: -14363756 | I26: 0 | J26: 0 | K26: 0 | L26: -2866174 | M26: 0 | N26: 0 | O26: 0 | P26: 0 | Q26: =SUM(D26:P26) -> -17229930 | R26: =Q26/S26 -> -19079.708 | S26: =+S25 -> 903.05 | T26: =IFERROR((D26/$S26),0) -> 0 | U26: =IFERROR((#REF!/$S26),0) -> 0 | V26: =IFERROR((#REF!/$S26),0) -> 0 | W26: =IFERROR((E26/$S26),0) -> 0 | X26: =IFERROR((F26/$S26),0) -> 0 | Y26: =IFERROR((G26/$S26),0) -> 0 | Z26: =IFERROR((H26/$S26),0) -> -15905.826 | AA26: =IFERROR((I26/$S26),0) -> 0 | AB26: =IFERROR((J26/$S26),0) -> 0 | AC26: =IFERROR((K26/$S26),0) -> 0 | AD26: =IFERROR((L26/$S26),0) -> -3173.8818 | AE26: =IFERROR((M26/$S26),0) -> 0 | AF26: =IFERROR((#REF!/$S26),0) -> 0 | AG26: =IFERROR((N26/$S26),0) -> 0 | AH26: =IFERROR((O26/$S26),0) -> 0 | AI26: =IFERROR((P26/$S26),0) -> 0 | AJ26: =SUM(T26:AI26) -> -19079.708 | AK26: =+AJ26 -> -19079.708 | AL26: =+R26-AJ26 -> 0 | AN26: 3.1.02.105 | AO26: =EXACT(B26,AN26) -> TRUE
A27: =SUMIF('Balanza ok'!D:D,B27,'Balanza ok'!B:B) -> 709226 | B27: 3.1.02.108 | C27: SERVICIOS - CANAL DIGITAL | D27: 0 | E27: 0 | F27: 0 | G27: 0 | H27: -222925 | I27: 0 | J27: 0 | K27: 0 | L27: -8258503 | M27: 0 | N27: 0 | O27: 0 | P27: 0 | Q27: =SUM(D27:P27) -> -8481428 | R27: =Q27/S27 -> -9391.9805 | S27: =+S26 -> 903.05 | T27: =IFERROR((D27/$S27),0) -> 0 | U27: =IFERROR((#REF!/$S27),0) -> 0 | V27: =IFERROR((#REF!/$S27),0) -> 0 | W27: =IFERROR((E27/$S27),0) -> 0 | X27: =IFERROR((F27/$S27),0) -> 0 | Y27: =IFERROR((G27/$S27),0) -> 0 | Z27: =IFERROR((H27/$S27),0) -> -246.85787 | AA27: =IFERROR((I27/$S27),0) -> 0 | AB27: =IFERROR((J27/$S27),0) -> 0 | AC27: =IFERROR((K27/$S27),0) -> 0 | AD27: =IFERROR((L27/$S27),0) -> -9145.1226 | AE27: =IFERROR((M27/$S27),0) -> 0 | AF27: =IFERROR((#REF!/$S27),0) -> 0 | AG27: =IFERROR((N27/$S27),0) -> 0 | AH27: =IFERROR((O27/$S27),0) -> 0 | AI27: =IFERROR((P27/$S27),0) -> 0 | AJ27: =SUM(T27:AI27) -> -9391.9805 | AK27: =+AJ27 -> -9391.9805 | AL27: =+R27-AJ27 -> 0 | AN27: 3.1.02.108 | AO27: =EXACT(B27,AN27) -> TRUE
A28: =SUMIF('Balanza ok'!D:D,B28,'Balanza ok'!B:B) -> 720716 | B28: 3.1.02.109 | C28: DESCUENTOS GIFTCARD | D28: 0 | E28: 0 | F28: 0 | G28: 0 | H28: 0 | I28: 0 | J28: -60000 | K28: 0 | L28: 0 | M28: -44990 | N28: 0 | O28: 0 | P28: 0 | Q28: =SUM(D28:P28) -> -104990 | R28: =Q28/S28 -> -116.26156 | S28: =+S27 -> 903.05 | AJ28: =SUM(T28:AI28) -> 0 | AK28: =+AJ28 -> 0 | AN28: 3.1.02.109 | AO28: =EXACT(B28,AN28) -> TRUE
A29: =SUMIF('Balanza ok'!D:D,B29,'Balanza ok'!B:B) -> 720716 | B29: 3.1.02.110 | C29: DESCUENTOS CLUB FLEXI | D29: 0 | E29: -10120 | F29: -10776 | G29: -5696 | H29: 0 | I29: 0 | J29: -18330 | K29: -100966 | L29: 0 | M29: -32386 | N29: 0 | O29: 0 | P29: 0 | Q29: =SUM(D29:P29) -> -178274 | R29: =Q29/S29 -> -197.41321 | S29: =+S28 -> 903.05 | AJ29: =SUM(T29:AI29) -> 0 | AK29: =+AJ29 -> 0 | AN29: 3.1.02.110 | AO29: =EXACT(B29,AN29) -> TRUE
A30: =SUMIF('Balanza ok'!D:D,B30,'Balanza ok'!B:B) -> 701011 | B30: 3.1.05.101 | C30: REMUNERACIONES | D30: 0 | E30: -19605284 | F30: -4340553 | G30: -19777384 | H30: -13430862 | I30: -1005381 | J30: -23788136 | K30: -15596068 | L30: -5733292 | M30: -21549622 | N30: -15454865 | O30: -15892636 | P30: -16884316 | Q30: =SUM(D30:P30) -> -173058399 | R30: =Q30/S30 -> -191637.67 | S30: =+S29 -> 903.05 | T30: =IFERROR((D30/$S30),0) -> 0 | U30: =IFERROR((#REF!/$S30),0) -> 0 | V30: =IFERROR((#REF!/$S30),0) -> 0 | W30: =IFERROR((E30/$S30),0) -> -21710.076 | X30: =IFERROR((F30/$S30),0) -> -4806.5478 | Y30: =IFERROR((G30/$S30),0) -> -21900.652 | Z30: =IFERROR((H30/$S30),0) -> -14872.778 | AA30: =IFERROR((I30/$S30),0) -> -1113.3171 | AB30: =IFERROR((J30/$S30),0) -> -26341.992 | AC30: =IFERROR((K30/$S30),0) -> -17270.437 | AD30: =IFERROR((L30/$S30),0) -> -6348.809 | AE30: =IFERROR((M30/$S30),0) -> -23863.155 | AF30: =IFERROR((#REF!/$S30),0) -> 0 | AG30: =IFERROR((N30/$S30),0) -> -17114.075 | AH30: =IFERROR((O30/$S30),0) -> -17598.844 | AI30: =IFERROR((P30/$S30),0) -> -18696.989 | AJ30: =SUM(T30:AI30) -> -191637.67 | AK30: =+AJ30 -> -191637.67 | AL30: =+R30-AJ30 -> 0 | AN30: 3.1.05.101 | AO30: =EXACT(B30,AN30) -> TRUE
A31: =SUMIF('Balanza ok'!D:D,B31,'Balanza ok'!B:B) -> 701025 | B31: 3.1.05.102 | C31: BONOS | D31: 0 | E31: -718846 | F31: -8666 | G31: -387944 | H31: -945271 | I31: -20000 | J31: -635071 | K31: -404590 | L31: 0 | M31: -1518574 | N31: -367293 | O31: 323240 | P31: -953000 | Q31: =SUM(D31:P31) -> -5636015 | R31: =Q31/S31 -> -6241.0885 | S31: =+S30 -> 903.05 | T31: =IFERROR((D31/$S31),0) -> 0 | U31: =IFERROR((#REF!/$S31),0) -> 0 | V31: =IFERROR((#REF!/$S31),0) -> 0 | W31: =IFERROR((E31/$S31),0) -> -796.02015 | X31: =IFERROR((F31/$S31),0) -> -9.5963679 | Y31: =IFERROR((G31/$S31),0) -> -429.59305 | Z31: =IFERROR((H31/$S31),0) -> -1046.7538 | AA31: =IFERROR((I31/$S31),0) -> -22.147168 | AB31: =IFERROR((J31/$S31),0) -> -703.2512 | AC31: =IFERROR((K31/$S31),0) -> -448.02613 | AD31: =IFERROR((L31/$S31),0) -> 0 | AE31: =IFERROR((M31/$S31),0) -> -1681.6057 | AF31: =IFERROR((#REF!/$S31),0) -> 0 | AG31: =IFERROR((N31/$S31),0) -> -406.72499 | AH31: =IFERROR((O31/$S31),0) -> 357.94253 | AI31: =IFERROR((P31/$S31),0) -> -1055.3126 | AJ31: =SUM(T31:AI31) -> -6241.0885 | AK31: =+AJ31 -> -6241.0885 | AL31: =+R31-AJ31 -> 0 | AN31: 3.1.05.102 | AO31: =EXACT(B31,AN31) -> TRUE
A32: =SUMIF('Balanza ok'!D:D,B32,'Balanza ok'!B:B) -> 702059 | B32: 3.1.05.103 | C32: SEGURO DE CESANTIA | D32: 0 | E32: -692642 | F32: -176477 | G32: -718791 | H32: -379112 | I32: -81064 | J32: -866143 | K32: -554933 | L32: -140387 | M32: -804251 | N32: -555974 | O32: -564822 | P32: -613548 | Q32: =SUM(D32:P32) -> -6148144 | R32: =Q32/S32 -> -6808.1989 | S32: =+S31 -> 903.05 | T32: =IFERROR((D32/$S32),0) -> 0 | U32: =IFERROR((#REF!/$S32),0) -> 0 | V32: =IFERROR((#REF!/$S32),0) -> 0 | W32: =IFERROR((E32/$S32),0) -> -767.00293 | X32: =IFERROR((F32/$S32),0) -> -195.42329 | Y32: =IFERROR((G32/$S32),0) -> -795.95925 | Z32: =IFERROR((H32/$S32),0) -> -419.81286 | AA32: =IFERROR((I32/$S32),0) -> -89.766901 | AB32: =IFERROR((J32/$S32),0) -> -959.13072 | AC32: =IFERROR((K32/$S32),0) -> -614.50972 | AD32: =IFERROR((L32/$S32),0) -> -155.45872 | AE32: =IFERROR((M32/$S32),0) -> -890.5941 | AF32: =IFERROR((#REF!/$S32),0) -> 0 | AG32: =IFERROR((N32/$S32),0) -> -615.66248 | AH32: =IFERROR((O32/$S32),0) -> -625.46038 | AI32: =IFERROR((P32/$S32),0) -> -679.41753 | AJ32: =SUM(T32:AI32) -> -6808.1989 | AK32: =+AJ32 -> -6808.1989 | AL32: =+R32-AJ32 -> 0 | AN32: 3.1.05.103 | AO32: =EXACT(B32,AN32) -> TRUE
A33: =SUMIF('Balanza ok'!D:D,B33,'Balanza ok'!B:B) -> 701025 | B33: 3.1.05.104 | C33: GRATIFICACION | D33: 0 | E33: -4698748 | F33: -1339662 | G33: -4820799 | H33: -1839436 | I33: -305874 | J33: -5574494 | K33: -3913639 | L33: -591154 | M33: -5185749 | N33: -3973103 | O33: -3973505 | P33: -4093878 | Q33: =SUM(D33:P33) -> -40310041 | R33: =Q33/S33 -> -44637.662 | S33: =+S32 -> 903.05 | T33: =IFERROR((D33/$S33),0) -> 0 | U33: =IFERROR((#REF!/$S33),0) -> 0 | V33: =IFERROR((#REF!/$S33),0) -> 0 | W33: =IFERROR((E33/$S33),0) -> -5203.1981 | X33: =IFERROR((F33/$S33),0) -> -1483.486 | Y33: =IFERROR((G33/$S33),0) -> -5338.3523 | Z33: =IFERROR((H33/$S33),0) -> -2036.9149 | AA33: =IFERROR((I33/$S33),0) -> -338.71214 | AB33: =IFERROR((J33/$S33),0) -> -6172.9627 | AC33: =IFERROR((K33/$S33),0) -> -4333.801 | AD33: =IFERROR((L33/$S33),0) -> -654.61935 | AE33: =IFERROR((M33/$S33),0) -> -5742.4827 | AF33: =IFERROR((#REF!/$S33),0) -> 0 | AG33: =IFERROR((N33/$S33),0) -> -4399.649 | AH33: =IFERROR((O33/$S33),0) -> -4400.0941 | AI33: =IFERROR((P33/$S33),0) -> -4533.3902 | AJ33: =SUM(T33:AI33) -> -44637.662 | AK33: =+AJ33 -> -44637.662 | AL33: =+R33-AJ33 -> 0 | AN33: 3.1.05.104 | AO33: =EXACT(B33,AN33) -> TRUE
A34: =SUMIF('Balanza ok'!D:D,B34,'Balanza ok'!B:B) -> 701026 | B34: 3.1.05.107 | C34: FINIQUITOS | D34: 0 | E34: -701842 | F34: 0 | G34: -90809 | H34: 0 | I34: -1279325 | J34: 0 | K34: -59888 | L34: 0 | M34: 0 | N34: -86412 | O34: -105208 | P34: -502172 | Q34: =SUM(D34:P34) -> -2825656 | R34: =Q34/S34 -> -3129.0139 | S34: =+S33 -> 903.05 | T34: =IFERROR((D34/$S34),0) -> 0 | U34: =IFERROR((#REF!/$S34),0) -> 0 | V34: =IFERROR((#REF!/$S34),0) -> 0 | W34: =IFERROR((E34/$S34),0) -> -777.19063 | X34: =IFERROR((F34/$S34),0) -> 0 | Y34: =IFERROR((G34/$S34),0) -> -100.55811 | Z34: =IFERROR((H34/$S34),0) -> 0 | AA34: =IFERROR((I34/$S34),0) -> -1416.6713 | AB34: =IFERROR((J34/$S34),0) -> 0 | AC34: =IFERROR((K34/$S34),0) -> -66.31748 | AD34: =IFERROR((L34/$S34),0) -> 0 | AE34: =IFERROR((M34/$S34),0) -> 0 | AF34: =IFERROR((#REF!/$S34),0) -> 0 | AG34: =IFERROR((N34/$S34),0) -> -95.689054 | AH34: =IFERROR((O34/$S34),0) -> -116.50296 | AI34: =IFERROR((P34/$S34),0) -> -556.08438 | AJ34: =SUM(T34:AI34) -> -3129.0139 | AK34: =+AJ34 -> -3129.0139 | AL34: =+R34-AJ34 -> 0 | AN34: 3.1.05.107 | AO34: =EXACT(B34,AN34) -> TRUE
A35: =SUMIF('Balanza ok'!D:D,B35,'Balanza ok'!B:B) -> 702051 | B35: 3.1.05.110 | C35: MUTUAL DE SEGURIDAD | D35: 0 | E35: -260348 | F35: -65861 | G35: -257184 | H35: -141509 | I35: -15661 | J35: -323752 | K35: -200082 | L35: -48283 | M35: -300022 | N35: -204243 | O35: -202216 | P35: -220885 | Q35: =SUM(D35:P35) -> -2240046 | R35: =Q35/S35 -> -2480.5337 | S35: =+S34 -> 903.05 | T35: =IFERROR((D35/$S35),0) -> 0 | U35: =IFERROR((#REF!/$S35),0) -> 0 | V35: =IFERROR((#REF!/$S35),0) -> 0 | W35: =IFERROR((E35/$S35),0) -> -288.29854 | X35: =IFERROR((F35/$S35),0) -> -72.931731 | Y35: =IFERROR((G35/$S35),0) -> -284.79486 | Z35: =IFERROR((H35/$S35),0) -> -156.70118 | AA35: =IFERROR((I35/$S35),0) -> -17.34234 | AB35: =IFERROR((J35/$S35),0) -> -358.5095 | AC35: =IFERROR((K35/$S35),0) -> -221.56248 | AD35: =IFERROR((L35/$S35),0) -> -53.466585 | AE35: =IFERROR((M35/$S35),0) -> -332.23188 | AF35: =IFERROR((#REF!/$S35),0) -> 0 | AG35: =IFERROR((N35/$S35),0) -> -226.1702 | AH35: =IFERROR((O35/$S35),0) -> -223.92559 | AI35: =IFERROR((P35/$S35),0) -> -244.59886 | AJ35: =SUM(T35:AI35) -> -2480.5337 | AK35: =+AJ35 -> -2480.5337 | AL35: =+R35-AJ35 -> 0 | AN35: 3.1.05.110 | AO35: =EXACT(B35,AN35) -> TRUE
A36: =SUMIF('Balanza ok'!D:D,B36,'Balanza ok'!B:B) -> 702052 | B36: 3.1.05.111 | C36: SEGURO INVALIDEZ (AFP) | D36: 0 | E36: -436142 | F36: -114723 | G36: -442491 | H36: -237394 | I36: -52016 | J36: -543253 | K36: -344879 | L36: -81001 | M36: -501846 | N36: -346669 | O36: -339584 | P36: -375381 | Q36: =SUM(D36:P36) -> -3815379 | R36: =Q36/S36 -> -4224.992 | S36: =+S35 -> 903.05 | T36: =IFERROR((D36/$S36),0) -> 0 | U36: =IFERROR((#REF!/$S36),0) -> 0 | V36: =IFERROR((#REF!/$S36),0) -> 0 | W36: =IFERROR((E36/$S36),0) -> -482.96551 | X36: =IFERROR((F36/$S36),0) -> -127.03948 | Y36: =IFERROR((G36/$S36),0) -> -489.99612 | Z36: =IFERROR((H36/$S36),0) -> -262.88024 | AA36: =IFERROR((I36/$S36),0) -> -57.600354 | AB36: =IFERROR((J36/$S36),0) -> -601.57577 | AC36: =IFERROR((K36/$S36),0) -> -381.90466 | AD36: =IFERROR((L36/$S36),0) -> -89.697137 | AE36: =IFERROR((M36/$S36),0) -> -555.72338 | AF36: =IFERROR((#REF!/$S36),0) -> 0 | AG36: =IFERROR((N36/$S36),0) -> -383.88683 | AH36: =IFERROR((O36/$S36),0) -> -376.04119 | AI36: =IFERROR((P36/$S36),0) -> -415.6813 | AJ36: =SUM(T36:AI36) -> -4224.992 | AK36: =+AJ36 -> -4224.992 | AL36: =+R36-AJ36 -> 0 | AN36: 3.1.05.111 | AO36: =EXACT(B36,AN36) -> TRUE
A37: =SUMIF('Balanza ok'!D:D,B37,'Balanza ok'!B:B) -> 702052 | B37: 3.1.05.112 | C37: CAPITALIZACION INDIVIDUAL AFP | D37: 0 | E37: -27997 | F37: -7083 | G37: -27627 | H37: -15218 | I37: -1628 | J37: -34812 | K37: -21494 | L37: -5192 | M37: -32261 | N37: -21952 | O37: -21744 | P37: -23739 | Q37: =SUM(D37:P37) -> -240747 | R37: =Q37/S37 -> -266.59321 | S37: =+S36 -> 903.05 | T37: =IFERROR((D37/$S37),0) -> 0 | U37: =IFERROR((#REF!/$S37),0) -> 0 | V37: =IFERROR((#REF!/$S37),0) -> 0 | W37: =IFERROR((E37/$S37),0) -> -31.002713 | X37: =IFERROR((F37/$S37),0) -> -7.8434195 | Y37: =IFERROR((G37/$S37),0) -> -30.59299 | Z37: =IFERROR((H37/$S37),0) -> -16.85178 | AA37: =IFERROR((I37/$S37),0) -> -1.8027795 | AB37: =IFERROR((J37/$S37),0) -> -38.549361 | AC37: =IFERROR((K37/$S37),0) -> -23.801561 | AD37: =IFERROR((L37/$S37),0) -> -5.7494048 | AE37: =IFERROR((M37/$S37),0) -> -35.724489 | AF37: =IFERROR((#REF!/$S37),0) -> 0 | AG37: =IFERROR((N37/$S37),0) -> -24.308732 | AH37: =IFERROR((O37/$S37),0) -> -24.078401 | AI37: =IFERROR((P37/$S37),0) -> -26.287581 | AJ37: =SUM(T37:AI37) -> -266.59321 | AK37: =+AJ37 -> -266.59321 | AL37: =+R37-AJ37 -> 0 | AN37: 3.1.05.112 | AO37: =EXACT(B37,AN37) -> TRUE
A38: =SUMIF('Balanza ok'!D:D,B38,'Balanza ok'!B:B) -> 702052 | B38: 3.1.05.113 | C38: EXPECTATIVA DE VIDA | D38: 0 | E38: -251947 | F38: -63734 | G38: -255509 | H38: -136944 | I38: -30400 | J38: -313308 | K38: -199693 | L38: -46727 | M38: -290346 | N38: -199937 | O38: -195701 | P38: -216739 | Q38: =SUM(D38:P38) -> -2200985 | R38: =Q38/S38 -> -2437.2792 | S38: =+S37 -> 903.05 | T38: =IFERROR((D38/$S38),0) -> 0 | U38: =IFERROR((#REF!/$S38),0) -> 0 | V38: =IFERROR((#REF!/$S38),0) -> 0 | W38: =IFERROR((E38/$S38),0) -> -278.99563 | X38: =IFERROR((F38/$S38),0) -> -70.57638 | Y38: =IFERROR((G38/$S38),0) -> -282.94004 | Z38: =IFERROR((H38/$S38),0) -> -151.64609 | AA38: =IFERROR((I38/$S38),0) -> -33.663695 | AB38: =IFERROR((J38/$S38),0) -> -346.94424 | AC38: =IFERROR((K38/$S38),0) -> -221.13172 | AD38: =IFERROR((L38/$S38),0) -> -51.743536 | AE38: =IFERROR((M38/$S38),0) -> -321.51708 | AF38: =IFERROR((#REF!/$S38),0) -> 0 | AG38: =IFERROR((N38/$S38),0) -> -221.40192 | AH38: =IFERROR((O38/$S38),0) -> -216.71115 | AI38: =IFERROR((P38/$S38),0) -> -240.00775 | AJ38: =SUM(T38:AI38) -> -2437.2792 | AK38: =+AJ38 -> -2437.2792 | AL38: =+R38-AJ38 -> 0 | AN38: 3.1.05.113 | AO38: =EXACT(B38,AN38) -> TRUE
A39: =SUMIF('Balanza ok'!D:D,B39,'Balanza ok'!B:B) -> 701004 | B39: 3.1.05.114 | C39: HORAS EXTRAS | D39: 0 | E39: 0 | F39: 0 | G39: 0 | H39: 0 | I39: 0 | J39: 0 | K39: 0 | L39: 0 | M39: 0 | N39: 0 | O39: 0 | P39: 0 | Q39: =SUM(D39:P39) -> 0 | R39: =Q39/S39 -> 0 | S39: =+S36 -> 903.05 | T39: =IFERROR((D39/$S39),0) -> 0 | U39: =IFERROR((#REF!/$S39),0) -> 0 | V39: =IFERROR((#REF!/$S39),0) -> 0 | W39: =IFERROR((E39/$S39),0) -> 0 | X39: =IFERROR((F39/$S39),0) -> 0 | Y39: =IFERROR((G39/$S39),0) -> 0 | Z39: =IFERROR((H39/$S39),0) -> 0 | AA39: =IFERROR((I39/$S39),0) -> 0 | AB39: =IFERROR((J39/$S39),0) -> 0 | AC39: =IFERROR((K39/$S39),0) -> 0 | AD39: =IFERROR((L39/$S39),0) -> 0 | AE39: =IFERROR((M39/$S39),0) -> 0 | AF39: =IFERROR((#REF!/$S39),0) -> 0 | AG39: =IFERROR((N39/$S39),0) -> 0 | AH39: =IFERROR((O39/$S39),0) -> 0 | AI39: =IFERROR((P39/$S39),0) -> 0 | AJ39: =SUM(T39:AI39) -> 0 | AK39: =+AJ39 -> 0 | AL39: =+R39-AJ39 -> 0 | AN39: 3.1.05.114 | AO39: =EXACT(B39,AN39) -> TRUE
A40: =SUMIF('Balanza ok'!D:D,B40,'Balanza ok'!B:B) -> 701028 | B40: 3.1.05.117 | C40: DOMINGOS Y FESTIVOS | D40: 0 | E40: -756319 | F40: -470770 | G40: -1034152 | H40: 0 | I40: -7718 | J40: -625126 | K40: -493923 | L40: 0 | M40: 0 | N40: -833493 | O40: -725449 | P40: -455337 | Q40: =SUM(D40:P40) -> -5402287 | R40: =Q40/S40 -> -5982.2679 | S40: =+S39 -> 903.05 | T40: =IFERROR((D40/$S40),0) -> 0 | U40: =IFERROR((#REF!/$S40),0) -> 0 | V40: =IFERROR((#REF!/$S40),0) -> 0 | W40: =IFERROR((E40/$S40),0) -> -837.5162 | X40: =IFERROR((F40/$S40),0) -> -521.31111 | Y40: =IFERROR((G40/$S40),0) -> -1145.1769 | Z40: =IFERROR((H40/$S40),0) -> 0 | AA40: =IFERROR((I40/$S40),0) -> -8.5465921 | AB40: =IFERROR((J40/$S40),0) -> -692.23852 | AC40: =IFERROR((K40/$S40),0) -> -546.94978 | AD40: =IFERROR((L40/$S40),0) -> 0 | AE40: =IFERROR((M40/$S40),0) -> 0 | AF40: =IFERROR((#REF!/$S40),0) -> 0 | AG40: =IFERROR((N40/$S40),0) -> -922.97547 | AH40: =IFERROR((O40/$S40),0) -> -803.33204 | AI40: =IFERROR((P40/$S40),0) -> -504.22125 | AJ40: =SUM(T40:AI40) -> -5982.2679 | AK40: =+AJ40 -> -5982.2679 | AL40: =+R40-AJ40 -> 0 | AN40: 3.1.05.117 | AO40: =EXACT(B40,AN40) -> TRUE
A41: =SUMIF('Balanza ok'!D:D,B41,'Balanza ok'!B:B) -> 701009 | B41: 3.1.05.121 | C41: SEMANA CORRIDA | D41: 0 | E41: -678344 | F41: -237589 | G41: -549134 | H41: 0 | I41: -80923 | J41: -1189945 | K41: -405019 | L41: 0 | M41: -1170652 | N41: -447565 | O41: -337145 | P41: -495606 | Q41: =SUM(D41:P41) -> -5591922 | R41: =Q41/S41 -> -6192.2618 | S41: =+S40 -> 903.05 | T41: =IFERROR((D41/$S41),0) -> 0 | U41: =IFERROR((#REF!/$S41),0) -> 0 | V41: =IFERROR((#REF!/$S41),0) -> 0 | W41: =IFERROR((E41/$S41),0) -> -751.16992 | X41: =IFERROR((F41/$S41),0) -> -263.09617 | Y41: =IFERROR((G41/$S41),0) -> -608.08815 | Z41: =IFERROR((H41/$S41),0) -> 0 | AA41: =IFERROR((I41/$S41),0) -> -89.610764 | AB41: =IFERROR((J41/$S41),0) -> -1317.6956 | AC41: =IFERROR((K41/$S41),0) -> -448.50119 | AD41: =IFERROR((L41/$S41),0) -> 0 | AE41: =IFERROR((M41/$S41),0) -> -1296.3313 | AF41: =IFERROR((#REF!/$S41),0) -> 0 | AG41: =IFERROR((N41/$S41),0) -> -495.61486 | AH41: =IFERROR((O41/$S41),0) -> -373.34035 | AI41: =IFERROR((P41/$S41),0) -> -548.81347 | AJ41: =SUM(T41:AI41) -> -6192.2618 | AK41: =+AJ41 -> -6192.2618 | AL41: =+R41-AJ41 -> 0 | AN41: 3.1.05.121 | AO41: =EXACT(B41,AN41) -> TRUE
A42: =SUMIF('Balanza ok'!D:D,B42,'Balanza ok'!B:B) -> 701013 | B42: 3.1.05.122 | C42: COMISION POR VENTA | D42: 0 | E42: -3028261 | F42: -989208 | G42: -2231239 | H42: 0 | I42: -360252 | J42: -5199117 | K42: -1779090 | L42: 0 | M42: -4443222 | N42: -1696561 | O42: -1452179 | P42: -2110592 | Q42: =SUM(D42:P42) -> -23289721 | R42: =Q42/S42 -> -25790.068 | S42: =+S41 -> 903.05 | T42: =IFERROR((D42/$S42),0) -> 0 | U42: =IFERROR((#REF!/$S42),0) -> 0 | V42: =IFERROR((#REF!/$S42),0) -> 0 | W42: =IFERROR((E42/$S42),0) -> -3353.3702 | X42: =IFERROR((F42/$S42),0) -> -1095.4078 | Y42: =IFERROR((G42/$S42),0) -> -2470.7812 | Z42: =IFERROR((H42/$S42),0) -> 0 | AA42: =IFERROR((I42/$S42),0) -> -398.92808 | AB42: =IFERROR((J42/$S42),0) -> -5757.2859 | AC42: =IFERROR((K42/$S42),0) -> -1970.0902 | AD42: =IFERROR((L42/$S42),0) -> 0 | AE42: =IFERROR((M42/$S42),0) -> -4920.2392 | AF42: =IFERROR((#REF!/$S42),0) -> 0 | AG42: =IFERROR((N42/$S42),0) -> -1878.7011 | AH42: =IFERROR((O42/$S42),0) -> -1608.0826 | AI42: =IFERROR((P42/$S42),0) -> -2337.1818 | AJ42: =SUM(T42:AI42) -> -25790.068 | AK42: =+AJ42 -> -25790.068 | AL42: =+R42-AJ42 -> 0 | AN42: 3.1.05.122 | AO42: =EXACT(B42,AN42) -> TRUE
A43: =SUMIF('Balanza ok'!D:D,B43,'Balanza ok'!B:B) -> 704083 | B43: 3.1.06.108 | C43: ASIGNACION COLACION | D43: 0 | E43: -1184946 | F43: -229140 | G43: -987223 | H43: -428691 | I43: -62000 | J43: -1290879 | K43: -843943 | L43: -278975 | M43: -1206733 | N43: -825957 | O43: -758701 | P43: -888978 | Q43: =SUM(D43:P43) -> -8986166 | R43: =Q43/S43 -> -9950.9064 | S43: =+S42 -> 903.05 | T43: =IFERROR((D43/$S43),0) -> 0 | U43: =IFERROR((#REF!/$S43),0) -> 0 | V43: =IFERROR((#REF!/$S43),0) -> 0 | W43: =IFERROR((E43/$S43),0) -> -1312.1599 | X43: =IFERROR((F43/$S43),0) -> -253.7401 | Y43: =IFERROR((G43/$S43),0) -> -1093.2097 | Z43: =IFERROR((H43/$S43),0) -> -474.71458 | AA43: =IFERROR((I43/$S43),0) -> -68.656221 | AB43: =IFERROR((J43/$S43),0) -> -1429.4657 | AC43: =IFERROR((K43/$S43),0) -> -934.54737 | AD43: =IFERROR((L43/$S43),0) -> -308.92531 | AE43: =IFERROR((M43/$S43),0) -> -1336.2859 | AF43: =IFERROR((#REF!/$S43),0) -> 0 | AG43: =IFERROR((N43/$S43),0) -> -914.63042 | AH43: =IFERROR((O43/$S43),0) -> -840.15392 | AI43: =IFERROR((P43/$S43),0) -> -984.41725 | AJ43: =SUM(T43:AI43) -> -9950.9064 | AK43: =+AJ43 -> -9950.9064 | AL43: =+R43-AJ43 -> 0 | AN43: 3.1.06.108 | AO43: =EXACT(B43,AN43) -> TRUE
A44: =SUMIF('Balanza ok'!D:D,B44,'Balanza ok'!B:B) -> 704086 | B44: 3.1.06.109 | C44: ASIGNACION MOVILIZACION | D44: 0 | E44: -1184946 | F44: -231000 | G44: -985363 | H44: -428691 | I44: -62000 | J44: -1290879 | K44: -843943 | L44: -278975 | M44: -1206733 | N44: -825957 | O44: -758701 | P44: -888978 | Q44: =SUM(D44:P44) -> -8986166 | R44: =Q44/S44 -> -9950.9064 | S44: =+S43 -> 903.05 | T44: =IFERROR((D44/$S44),0) -> 0 | U44: =IFERROR((#REF!/$S44),0) -> 0 | V44: =IFERROR((#REF!/$S44),0) -> 0 | W44: =IFERROR((E44/$S44),0) -> -1312.1599 | X44: =IFERROR((F44/$S44),0) -> -255.79979 | Y44: =IFERROR((G44/$S44),0) -> -1091.15 | Z44: =IFERROR((H44/$S44),0) -> -474.71458 | AA44: =IFERROR((I44/$S44),0) -> -68.656221 | AB44: =IFERROR((J44/$S44),0) -> -1429.4657 | AC44: =IFERROR((K44/$S44),0) -> -934.54737 | AD44: =IFERROR((L44/$S44),0) -> -308.92531 | AE44: =IFERROR((M44/$S44),0) -> -1336.2859 | AF44: =IFERROR((#REF!/$S44),0) -> 0 | AG44: =IFERROR((N44/$S44),0) -> -914.63042 | AH44: =IFERROR((O44/$S44),0) -> -840.15392 | AI44: =IFERROR((P44/$S44),0) -> -984.41725 | AJ44: =SUM(T44:AI44) -> -9950.9064 | AK44: =+AJ44 -> -9950.9064 | AL44: =+R44-AJ44 -> 0 | AN44: 3.1.06.109 | AO44: =EXACT(B44,AN44) -> TRUE
A45: =SUMIF('Balanza ok'!D:D,B45,'Balanza ok'!B:B) -> 712362 | B45: 3.1.06.116 | C45: UNIFORMES | D45: -50143 | E45: -476275 | F45: -229667 | G45: -339542 | H45: 0 | I45: -29980 | J45: -559442 | K45: -492897 | L45: 0 | M45: -466462 | N45: -538872 | O45: -491024 | P45: -406541 | Q45: =SUM(D45:P45) -> -4080845 | R45: =Q45/S45 -> -4518.958 | S45: =+S44 -> 903.05 | T45: =IFERROR((D45/$S45),0) -> -55.526272 | U45: =IFERROR((#REF!/$S45),0) -> 0 | V45: =IFERROR((#REF!/$S45),0) -> 0 | W45: =IFERROR((E45/$S45),0) -> -527.40712 | X45: =IFERROR((F45/$S45),0) -> -254.32368 | Y45: =IFERROR((G45/$S45),0) -> -375.99468 | Z45: =IFERROR((H45/$S45),0) -> 0 | AA45: =IFERROR((I45/$S45),0) -> -33.198605 | AB45: =IFERROR((J45/$S45),0) -> -619.5028 | AC45: =IFERROR((K45/$S45),0) -> -545.81363 | AD45: =IFERROR((L45/$S45),0) -> 0 | AE45: =IFERROR((M45/$S45),0) -> -516.54061 | AF45: =IFERROR((#REF!/$S45),0) -> 0 | AG45: =IFERROR((N45/$S45),0) -> -596.72443 | AH45: =IFERROR((O45/$S45),0) -> -543.73955 | AI45: =IFERROR((P45/$S45),0) -> -450.18659 | AJ45: =SUM(T45:AI45) -> -4518.958 | AK45: =+AJ45 -> -4518.958 | AL45: =+R45-AJ45 -> 0 | AN45: 3.1.06.116 | AO45: =EXACT(B45,AN45) -> TRUE
A46: =SUMIF('Balanza ok'!D:D,B46,'Balanza ok'!B:B) -> 706111 | B46: 3.1.06.201 | C46: HONORARIOS PROFESIONALES | D46: 0 | E46: -904489 | F46: -291302 | G46: -931681 | H46: 0 | I46: -2442000 | J46: -904490 | K46: -904490 | L46: 0 | M46: -904487 | N46: -904487 | O46: -904487 | P46: -904487 | Q46: =SUM(D46:P46) -> -9996400 | R46: =Q46/S46 -> -11069.597 | S46: =+S45 -> 903.05 | T46: =IFERROR((D46/$S46),0) -> 0 | U46: =IFERROR((#REF!/$S46),0) -> 0 | V46: =IFERROR((#REF!/$S46),0) -> 0 | W46: =IFERROR((E46/$S46),0) -> -1001.5935 | X46: =IFERROR((F46/$S46),0) -> -322.57572 | Y46: =IFERROR((G46/$S46),0) -> -1031.7048 | Z46: =IFERROR((H46/$S46),0) -> 0 | AA46: =IFERROR((I46/$S46),0) -> -2704.1692 | AB46: =IFERROR((J46/$S46),0) -> -1001.5946 | AC46: =IFERROR((K46/$S46),0) -> -1001.5946 | AD46: =IFERROR((L46/$S46),0) -> 0 | AE46: =IFERROR((M46/$S46),0) -> -1001.5913 | AF46: =IFERROR((#REF!/$S46),0) -> 0 | AG46: =IFERROR((N46/$S46),0) -> -1001.5913 | AH46: =IFERROR((O46/$S46),0) -> -1001.5913 | AI46: =IFERROR((P46/$S46),0) -> -1001.5913 | AJ46: =SUM(T46:AI46) -> -11069.597 | AK46: =+AJ46 -> -11069.597 | AL46: =+R46-AJ46 -> 0 | AN46: 3.1.06.201 | AO46: =EXACT(B46,AN46) -> TRUE
A47: =SUMIF('Balanza ok'!D:D,B47,'Balanza ok'!B:B) -> 706112 | B47: 3.1.06.206 | C47: ASESORIA CONTABLE | D47: 0 | E47: 0 | F47: 0 | G47: 0 | H47: 0 | I47: -14800624 | J47: 0 | K47: 0 | L47: 0 | M47: 0 | N47: 0 | O47: 0 | P47: 0 | Q47: =SUM(D47:P47) -> -14800624 | R47: =Q47/S47 -> -16389.595 | S47: =+S46 -> 903.05 | T47: =IFERROR((D47/$S47),0) -> 0 | U47: =IFERROR((#REF!/$S47),0) -> 0 | V47: =IFERROR((#REF!/$S47),0) -> 0 | W47: =IFERROR((E47/$S47),0) -> 0 | X47: =IFERROR((F47/$S47),0) -> 0 | Y47: =IFERROR((G47/$S47),0) -> 0 | Z47: =IFERROR((H47/$S47),0) -> 0 | AA47: =IFERROR((I47/$S47),0) -> -16389.595 | AB47: =IFERROR((J47/$S47),0) -> 0 | AC47: =IFERROR((K47/$S47),0) -> 0 | AD47: =IFERROR((L47/$S47),0) -> 0 | AE47: =IFERROR((M47/$S47),0) -> 0 | AF47: =IFERROR((#REF!/$S47),0) -> 0 | AG47: =IFERROR((N47/$S47),0) -> 0 | AH47: =IFERROR((O47/$S47),0) -> 0 | AI47: =IFERROR((P47/$S47),0) -> 0 | AJ47: =SUM(T47:AI47) -> -16389.595 | AK47: =+AJ47 -> -16389.595 | AL47: =+R47-AJ47 -> 0 | AN47: 3.1.06.206 | AO47: =EXACT(B47,AN47) -> TRUE
A48: =SUMIF('Balanza ok'!D:D,B48,'Balanza ok'!B:B) -> 706112 | B48: 3.1.06.209 | C48: HONORARIOS POR ASESORIAS INFORMATICAS | D48: 0 | E48: 0 | F48: 0 | G48: 0 | H48: -769896 | I48: -500932 | J48: 0 | K48: 0 | L48: 0 | M48: 0 | N48: 0 | O48: 0 | P48: 0 | Q48: =SUM(D48:P48) -> -1270828 | R48: =Q48/S48 -> -1407.2621 | S48: =+S47 -> 903.05 | T48: =IFERROR((D48/$S48),0) -> 0 | U48: =IFERROR((#REF!/$S48),0) -> 0 | V48: =IFERROR((#REF!/$S48),0) -> 0 | W48: =IFERROR((E48/$S48),0) -> 0 | X48: =IFERROR((F48/$S48),0) -> 0 | Y48: =IFERROR((G48/$S48),0) -> 0 | Z48: =IFERROR((H48/$S48),0) -> -852.5508 | AA48: =IFERROR((I48/$S48),0) -> -554.71126 | AB48: =IFERROR((J48/$S48),0) -> 0 | AC48: =IFERROR((K48/$S48),0) -> 0 | AD48: =IFERROR((L48/$S48),0) -> 0 | AE48: =IFERROR((M48/$S48),0) -> 0 | AF48: =IFERROR((#REF!/$S48),0) -> 0 | AG48: =IFERROR((N48/$S48),0) -> 0 | AH48: =IFERROR((O48/$S48),0) -> 0 | AI48: =IFERROR((P48/$S48),0) -> 0 | AJ48: =SUM(T48:AI48) -> -1407.2621 | AK48: =+AJ48 -> -1407.2621 | AL48: =+R48-AJ48 -> 0 | AN48: 3.1.06.209 | AO48: =EXACT(B48,AN48) -> TRUE
A49: =SUMIF('Balanza ok'!D:D,B49,'Balanza ok'!B:B) -> 706111 | B49: 3.1.06.210 | C49: HONORARIOS ADMINISTRACIÓN DE PERSONAL | D49: 0 | E49: 0 | F49: 0 | G49: 0 | H49: 0 | I49: -1886536 | J49: 0 | K49: 0 | L49: 0 | M49: 0 | N49: 0 | O49: 0 | P49: 0 | Q49: =SUM(D49:P49) -> -1886536 | R49: =Q49/S49 -> -2089.0715 | S49: =+S48 -> 903.05 | T49: =IFERROR((D49/$S49),0) -> 0 | U49: =IFERROR((#REF!/$S49),0) -> 0 | V49: =IFERROR((#REF!/$S49),0) -> 0 | W49: =IFERROR((E49/$S49),0) -> 0 | X49: =IFERROR((F49/$S49),0) -> 0 | Y49: =IFERROR((G49/$S49),0) -> 0 | Z49: =IFERROR((H49/$S49),0) -> 0 | AA49: =IFERROR((I49/$S49),0) -> -2089.0715 | AB49: =IFERROR((J49/$S49),0) -> 0 | AC49: =IFERROR((K49/$S49),0) -> 0 | AD49: =IFERROR((L49/$S49),0) -> 0 | AE49: =IFERROR((M49/$S49),0) -> 0 | AF49: =IFERROR((#REF!/$S49),0) -> 0 | AG49: =IFERROR((N49/$S49),0) -> 0 | AH49: =IFERROR((O49/$S49),0) -> 0 | AI49: =IFERROR((P49/$S49),0) -> 0 | AJ49: =SUM(T49:AI49) -> -2089.0715 | AK49: =+AJ49 -> -2089.0715 | AL49: =+R49-AJ49 -> 0 | AN49: 3.1.06.210 | AO49: =EXACT(B49,AN49) -> TRUE
A50: =SUMIF('Balanza ok'!D:D,B50,'Balanza ok'!B:B) -> 707121 | B50: 3.1.06.301 | C50: ARRIENDOS | D50: 0 | E50: -32298763 | F50: -4020148 | G50: -32689973 | H50: 0 | I50: -3630987 | J50: -64050539 | K50: -28740442 | L50: 0 | M50: -28634045 | N50: -15141505 | O50: -21251744 | P50: -33363145 | Q50: =SUM(D50:P50) -> -263821291 | R50: =Q50/S50 -> -292144.72 | S50: =+S48 -> 903.05 | T50: =IFERROR((D50/$S50),0) -> 0 | U50: =IFERROR((#REF!/$S50),0) -> 0 | V50: =IFERROR((#REF!/$S50),0) -> 0 | W50: =IFERROR((E50/$S50),0) -> -35766.306 | X50: =IFERROR((F50/$S50),0) -> -4451.7446 | Y50: =IFERROR((G50/$S50),0) -> -36199.516 | Z50: =IFERROR((H50/$S50),0) -> 0 | AA50: =IFERROR((I50/$S50),0) -> -4020.8039 | AB50: =IFERROR((J50/$S50),0) -> -70926.902 | AC50: =IFERROR((K50/$S50),0) -> -31825.97 | AD50: =IFERROR((L50/$S50),0) -> 0 | AE50: =IFERROR((M50/$S50),0) -> -31708.15 | AF50: =IFERROR((#REF!/$S50),0) -> 0 | AG50: =IFERROR((N50/$S50),0) -> -16767.073 | AH50: =IFERROR((O50/$S50),0) -> -23533.297 | AI50: =IFERROR((P50/$S50),0) -> -36944.959 | AJ50: =SUM(T50:AI50) -> -292144.72 | AK50: =+AJ50 -> -292144.72 | AL50: =+R50-AJ50 -> 0 | AN50: 3.1.06.301 | AO50: =EXACT(B50,AN50) -> TRUE
A51: =SUMIF('Balanza ok'!D:D,B51,'Balanza ok'!B:B) -> 707121 | B51: 3.1.06.302 | C51: ARRIENDO DE BODEGAS | D51: -12437499 | E51: 0 | F51: 0 | G51: 0 | H51: 0 | I51: 0 | J51: 0 | K51: 0 | L51: 0 | M51: 0 | N51: 0 | O51: 0 | P51: 0 | Q51: =SUM(D51:P51) -> -12437499 | R51: =Q51/S51 -> -13772.769 | S51: =+S50 -> 903.05 | T51: =IFERROR((D51/$S51),0) -> -13772.769 | U51: =IFERROR((#REF!/$S51),0) -> 0 | V51: =IFERROR((#REF!/$S51),0) -> 0 | W51: =IFERROR((E51/$S51),0) -> 0 | X51: =IFERROR((F51/$S51),0) -> 0 | Y51: =IFERROR((G51/$S51),0) -> 0 | Z51: =IFERROR((H51/$S51),0) -> 0 | AA51: =IFERROR((I51/$S51),0) -> 0 | AB51: =IFERROR((J51/$S51),0) -> 0 | AC51: =IFERROR((K51/$S51),0) -> 0 | AD51: =IFERROR((L51/$S51),0) -> 0 | AE51: =IFERROR((M51/$S51),0) -> 0 | AF51: =IFERROR((#REF!/$S51),0) -> 0 | AG51: =IFERROR((N51/$S51),0) -> 0 | AH51: =IFERROR((O51/$S51),0) -> 0 | AI51: =IFERROR((P51/$S51),0) -> 0 | AJ51: =SUM(T51:AI51) -> -13772.769 | AK51: =+AJ51 -> -13772.769 | AL51: =+R51-AJ51 -> 0 | AN51: 3.1.06.302 | AO51: =EXACT(B51,AN51) -> TRUE
A52: =SUMIF('Balanza ok'!D:D,B52,'Balanza ok'!B:B) -> 730765 | B52: 3.1.06.305 | C52: GASTOS DIVERSOS | D52: -949276 | E52: -168660 | F52: -216747 | G52: -283782 | H52: 0 | I52: -159919 | J52: -193071 | K52: -117511 | L52: 0 | M52: -151891 | N52: 73011 | O52: -117880 | P52: -87844 | Q52: =SUM(D52:P52) -> -2373570 | R52: =Q52/S52 -> -2628.3927 | S52: =+S51 -> 903.05 | T52: =IFERROR((D52/$S52),0) -> -1051.1887 | U52: =IFERROR((#REF!/$S52),0) -> 0 | V52: =IFERROR((#REF!/$S52),0) -> 0 | W52: =IFERROR((E52/$S52),0) -> -186.76707 | X52: =IFERROR((F52/$S52),0) -> -240.01661 | Y52: =IFERROR((G52/$S52),0) -> -314.24838 | Z52: =IFERROR((H52/$S52),0) -> 0 | AA52: =IFERROR((I52/$S52),0) -> -177.08765 | AB52: =IFERROR((J52/$S52),0) -> -213.79879 | AC52: =IFERROR((K52/$S52),0) -> -130.12679 | AD52: =IFERROR((L52/$S52),0) -> 0 | AE52: =IFERROR((M52/$S52),0) -> -168.19777 | AF52: =IFERROR((#REF!/$S52),0) -> 0 | AG52: =IFERROR((N52/$S52),0) -> 80.849344 | AH52: =IFERROR((O52/$S52),0) -> -130.53541 | AI52: =IFERROR((P52/$S52),0) -> -97.274791 | AJ52: =SUM(T52:AI52) -> -2628.3927 | AK52: =+AJ52 -> -2628.3927 | AL52: =+R52-AJ52 -> 0 | AN52: 3.1.06.305 | AO52: =EXACT(B52,AN52) -> TRUE
A53: =SUMIF('Balanza ok'!D:D,B53,'Balanza ok'!B:B) -> 712361 | B53: 3.1.06.306 | C53: SEGURIDAD INDUSTRIAL | D53: 0 | E53: -60634 | F53: -18334 | G53: -18334 | H53: 0 | I53: 0 | J53: -18333 | K53: -45033 | L53: 0 | M53: -18333 | N53: -18333 | O53: -18333 | P53: -18333 | Q53: =SUM(D53:P53) -> -234000 | R53: =Q53/S53 -> -259.12186 | S53: =+S52 -> 903.05 | T53: =IFERROR((D53/$S53),0) -> 0 | U53: =IFERROR((#REF!/$S53),0) -> 0 | V53: =IFERROR((#REF!/$S53),0) -> 0 | W53: =IFERROR((E53/$S53),0) -> -67.143569 | X53: =IFERROR((F53/$S53),0) -> -20.302309 | Y53: =IFERROR((G53/$S53),0) -> -20.302309 | Z53: =IFERROR((H53/$S53),0) -> 0 | AA53: =IFERROR((I53/$S53),0) -> 0 | AB53: =IFERROR((J53/$S53),0) -> -20.301201 | AC53: =IFERROR((K53/$S53),0) -> -49.867671 | AD53: =IFERROR((L53/$S53),0) -> 0 | AE53: =IFERROR((M53/$S53),0) -> -20.301201 | AF53: =IFERROR((#REF!/$S53),0) -> 0 | AG53: =IFERROR((N53/$S53),0) -> -20.301201 | AH53: =IFERROR((O53/$S53),0) -> -20.301201 | AI53: =IFERROR((P53/$S53),0) -> -20.301201 | AJ53: =SUM(T53:AI53) -> -259.12186 | AK53: =+AJ53 -> -259.12186 | AL53: =+R53-AJ53 -> 0 | AN53: 3.1.06.306 | AO53: =EXACT(B53,AN53) -> TRUE
A54: =SUMIF('Balanza ok'!D:D,B54,'Balanza ok'!B:B) -> 730789 | B54: 3.1.06.307 | C54: GASTOS FUERA DE PLANIFICACION | D54: -900000 | E54: 0 | F54: 0 | G54: 126030 | H54: 0 | I54: 139930 | J54: 341900 | K54: 0 | L54: 0 | M54: 0 | N54: 183170 | O54: 262920 | P54: 341910 | Q54: =SUM(D54:P54) -> 495860 | R54: =Q54/S54 -> 549.09473 | S54: =+S53 -> 903.05 | T54: =IFERROR((D54/$S54),0) -> -996.62256 | U54: =IFERROR((#REF!/$S54),0) -> 0 | V54: =IFERROR((#REF!/$S54),0) -> 0 | W54: =IFERROR((E54/$S54),0) -> 0 | X54: =IFERROR((F54/$S54),0) -> 0 | Y54: =IFERROR((G54/$S54),0) -> 139.56038 | Z54: =IFERROR((H54/$S54),0) -> 0 | AA54: =IFERROR((I54/$S54),0) -> 154.95266 | AB54: =IFERROR((J54/$S54),0) -> 378.60584 | AC54: =IFERROR((K54/$S54),0) -> 0 | AD54: =IFERROR((L54/$S54),0) -> 0 | AE54: =IFERROR((M54/$S54),0) -> 0 | AF54: =IFERROR((#REF!/$S54),0) -> 0 | AG54: =IFERROR((N54/$S54),0) -> 202.83484 | AH54: =IFERROR((O54/$S54),0) -> 291.14667 | AI54: =IFERROR((P54/$S54),0) -> 378.61691 | AJ54: =SUM(T54:AI54) -> 549.09473 | AK54: =+AJ54 -> 549.09473 | AL54: =+R54-AJ54 -> 0 | AN54: 3.1.06.307 | AO54: =EXACT(B54,AN54) -> TRUE
A55: =SUMIF('Balanza ok'!D:D,B55,'Balanza ok'!B:B) -> 711353 | B55: 3.1.06.401 | C55: SERVICIOS DE TELECOMUNICACION | D55: -249651 | E55: -249658 | F55: -57816 | G55: -249658 | H55: -249651 | I55: 294562 | J55: -249657 | K55: -249657 | L55: -249651 | M55: -249656 | N55: -249655 | O55: -249655 | P55: -249652 | Q55: =SUM(D55:P55) -> -2509455 | R55: =Q55/S55 -> -2778.8661 | S55: =+S53 -> 903.05 | T55: =IFERROR((D55/$S55),0) -> -276.45313 | U55: =IFERROR((#REF!/$S55),0) -> 0 | V55: =IFERROR((#REF!/$S55),0) -> 0 | W55: =IFERROR((E55/$S55),0) -> -276.46088 | X55: =IFERROR((F55/$S55),0) -> -64.023033 | Y55: =IFERROR((G55/$S55),0) -> -276.46088 | Z55: =IFERROR((H55/$S55),0) -> -276.45313 | AA55: =IFERROR((I55/$S55),0) -> 326.1857 | AB55: =IFERROR((J55/$S55),0) -> -276.45978 | AC55: =IFERROR((K55/$S55),0) -> -276.45978 | AD55: =IFERROR((L55/$S55),0) -> -276.45313 | AE55: =IFERROR((M55/$S55),0) -> -276.45867 | AF55: =IFERROR((#REF!/$S55),0) -> 0 | AG55: =IFERROR((N55/$S55),0) -> -276.45756 | AH55: =IFERROR((O55/$S55),0) -> -276.45756 | AI55: =IFERROR((P55/$S55),0) -> -276.45424 | AJ55: =SUM(T55:AI55) -> -2778.8661 | AK55: =+AJ55 -> -2778.8661 | AL55: =+R55-AJ55 -> 0 | AN55: 3.1.06.401 | AO55: =EXACT(B55,AN55) -> TRUE
A56: =SUMIF('Balanza ok'!D:D,B56,'Balanza ok'!B:B) -> 711355 | B56: 3.1.06.406 | C56: GASTOS DE TELEFONIA MOVIL | D56: 0 | E56: -57302 | F56: -13265 | G56: -57302 | H56: 0 | I56: -54092 | J56: -57303 | K56: -57303 | L56: 0 | M56: -57303 | N56: -57303 | O56: -57303 | P56: -57301 | Q56: =SUM(D56:P56) -> -525777 | R56: =Q56/S56 -> -582.22358 | S56: =+S55 -> 903.05 | T56: =IFERROR((D56/$S56),0) -> 0 | U56: =IFERROR((#REF!/$S56),0) -> 0 | V56: =IFERROR((#REF!/$S56),0) -> 0 | W56: =IFERROR((E56/$S56),0) -> -63.453851 | X56: =IFERROR((F56/$S56),0) -> -14.689109 | Y56: =IFERROR((G56/$S56),0) -> -63.453851 | Z56: =IFERROR((H56/$S56),0) -> 0 | AA56: =IFERROR((I56/$S56),0) -> -59.89923 | AB56: =IFERROR((J56/$S56),0) -> -63.454958 | AC56: =IFERROR((K56/$S56),0) -> -63.454958 | AD56: =IFERROR((L56/$S56),0) -> 0 | AE56: =IFERROR((M56/$S56),0) -> -63.454958 | AF56: =IFERROR((#REF!/$S56),0) -> 0 | AG56: =IFERROR((N56/$S56),0) -> -63.454958 | AH56: =IFERROR((O56/$S56),0) -> -63.454958 | AI56: =IFERROR((P56/$S56),0) -> -63.452743 | AJ56: =SUM(T56:AI56) -> -582.22358 | AK56: =+AJ56 -> -582.22358 | AL56: =+R56-AJ56 -> 0 | AN56: 3.1.06.406 | AO56: =EXACT(B56,AN56) -> TRUE
A57: =SUMIF('Balanza ok'!D:D,B57,'Balanza ok'!B:B) -> 730779 | B57: 3.1.06.501 | C57: PATENTE COMERCIAL | D57: 0 | E57: -38256 | F57: -11619 | G57: -179492 | H57: 0 | I57: -334990 | J57: -220876 | K57: -46476 | L57: 0 | M57: -2144956 | N57: -17032 | O57: -151448 | P57: -211920 | Q57: =SUM(D57:P57) -> -3357065 | R57: =Q57/S57 -> -3717.4741 | S57: =+S56 -> 903.05 | T57: =IFERROR((D57/$S57),0) -> 0 | U57: =IFERROR((#REF!/$S57),0) -> 0 | V57: =IFERROR((#REF!/$S57),0) -> 0 | W57: =IFERROR((E57/$S57),0) -> -42.363103 | X57: =IFERROR((F57/$S57),0) -> -12.866397 | Y57: =IFERROR((G57/$S57),0) -> -198.76197 | Z57: =IFERROR((H57/$S57),0) -> 0 | AA57: =IFERROR((I57/$S57),0) -> -370.95399 | AB57: =IFERROR((J57/$S57),0) -> -244.58889 | AC57: =IFERROR((K57/$S57),0) -> -51.465589 | AD57: =IFERROR((L57/$S57),0) -> 0 | AE57: =IFERROR((M57/$S57),0) -> -2375.235 | AF57: =IFERROR((#REF!/$S57),0) -> 0 | AG57: =IFERROR((N57/$S57),0) -> -18.860528 | AH57: =IFERROR((O57/$S57),0) -> -167.70721 | AI57: =IFERROR((P57/$S57),0) -> -234.67139 | AJ57: =SUM(T57:AI57) -> -3717.4741 | AK57: =+AJ57 -> -3717.4741 | AL57: =+R57-AJ57 -> 0 | AN57: 3.1.06.501 | AO57: =EXACT(B57,AN57) -> TRUE
A58: =SUMIF('Balanza ok'!D:D,B58,'Balanza ok'!B:B) -> 730779 | B58: 3.1.06.504 | C58: IVA IRRECUPERABLE | D58: 0 | E58: 0 | F58: 0 | G58: 0 | H58: 0 | I58: -1065119 | J58: 0 | K58: 0 | L58: 0 | M58: 0 | N58: 0 | O58: 0 | P58: 0 | Q58: =SUM(D58:P58) -> -1065119 | R58: =Q58/S58 -> -1179.4685 | S58: =+S57 -> 903.05 | T58: =IFERROR((D58/$S58),0) -> 0 | U58: =IFERROR((#REF!/$S58),0) -> 0 | V58: =IFERROR((#REF!/$S58),0) -> 0 | W58: =IFERROR((E58/$S58),0) -> 0 | X58: =IFERROR((F58/$S58),0) -> 0 | Y58: =IFERROR((G58/$S58),0) -> 0 | Z58: =IFERROR((H58/$S58),0) -> 0 | AA58: =IFERROR((I58/$S58),0) -> -1179.4685 | AB58: =IFERROR((J58/$S58),0) -> 0 | AC58: =IFERROR((K58/$S58),0) -> 0 | AD58: =IFERROR((L58/$S58),0) -> 0 | AE58: =IFERROR((M58/$S58),0) -> 0 | AF58: =IFERROR((#REF!/$S58),0) -> 0 | AG58: =IFERROR((N58/$S58),0) -> 0 | AH58: =IFERROR((O58/$S58),0) -> 0 | AI58: =IFERROR((P58/$S58),0) -> 0 | AJ58: =SUM(T58:AI58) -> -1179.4685 | AK58: =+AJ58 -> -1179.4685 | AL58: =+R58-AJ58 -> 0 | AN58: 3.1.06.504 | AO58: =EXACT(B58,AN58) -> TRUE
A59: =SUMIF('Balanza ok'!D:D,B59,'Balanza ok'!B:B) -> 717602 | B59: 3.1.06.505 | C59: MULTAS E INTERESES | D59: 0 | E59: -506 | F59: 0 | G59: 0 | H59: 0 | I59: -420710 | J59: -232 | K59: 0 | L59: 0 | M59: 0 | N59: 0 | O59: 0 | P59: 0 | Q59: =SUM(D59:P59) -> -421448 | R59: =Q59/S59 -> -466.69398 | S59: =+S57 -> 903.05 | T59: =IFERROR((D59/$S59),0) -> 0 | U59: =IFERROR((#REF!/$S59),0) -> 0 | V59: =IFERROR((#REF!/$S59),0) -> 0 | W59: =IFERROR((E59/$S59),0) -> -0.56032335 | X59: =IFERROR((F59/$S59),0) -> 0 | Y59: =IFERROR((G59/$S59),0) -> 0 | Z59: =IFERROR((H59/$S59),0) -> 0 | AA59: =IFERROR((I59/$S59),0) -> -465.87675 | AB59: =IFERROR((J59/$S59),0) -> -0.25690715 | AC59: =IFERROR((K59/$S59),0) -> 0 | AD59: =IFERROR((L59/$S59),0) -> 0 | AE59: =IFERROR((M59/$S59),0) -> 0 | AF59: =IFERROR((#REF!/$S59),0) -> 0 | AG59: =IFERROR((N59/$S59),0) -> 0 | AH59: =IFERROR((O59/$S59),0) -> 0 | AI59: =IFERROR((P59/$S59),0) -> 0 | AJ59: =SUM(T59:AI59) -> -466.69398 | AK59: =+AJ59 -> -466.69398 | AL59: =+R59-AJ59 -> 0 | AN59: 3.1.06.505 | AO59: =EXACT(B59,AN59) -> TRUE
A60: =SUMIF('Balanza ok'!D:D,B60,'Balanza ok'!B:B) -> 730787 | B60: 3.1.06.506 | C60: SEGUROS | D60: -994960 | E60: -169586 | F60: -34236 | G60: -166796 | H60: 0 | I60: -190690 | J60: -163176 | K60: -147094 | L60: 0 | M60: -157804 | N60: -149850 | O60: -168054 | P60: -168054 | Q60: =SUM(D60:P60) -> -2510300 | R60: =Q60/S60 -> -2779.8018 | S60: =+S59 -> 903.05 | T60: =IFERROR((D60/$S60),0) -> -1101.7773 | U60: =IFERROR((#REF!/$S60),0) -> 0 | V60: =IFERROR((#REF!/$S60),0) -> 0 | W60: =IFERROR((E60/$S60),0) -> -187.79248 | X60: =IFERROR((F60/$S60),0) -> -37.911522 | Y60: =IFERROR((G60/$S60),0) -> -184.70295 | Z60: =IFERROR((H60/$S60),0) -> 0 | AA60: =IFERROR((I60/$S60),0) -> -211.16217 | AB60: =IFERROR((J60/$S60),0) -> -180.69431 | AC60: =IFERROR((K60/$S60),0) -> -162.88578 | AD60: =IFERROR((L60/$S60),0) -> 0 | AE60: =IFERROR((M60/$S60),0) -> -174.74558 | AF60: =IFERROR((#REF!/$S60),0) -> 0 | AG60: =IFERROR((N60/$S60),0) -> -165.93766 | AH60: =IFERROR((O60/$S60),0) -> -186.09601 | AI60: =IFERROR((P60/$S60),0) -> -186.09601 | AJ60: =SUM(T60:AI60) -> -2779.8018 | AK60: =+AJ60 -> -2779.8018 | AL60: =+R60-AJ60 -> 0 | AN60: 3.1.06.506 | AO60: =EXACT(B60,AN60) -> TRUE
A61: =SUMIF('Balanza ok'!D:D,B61,'Balanza ok'!B:B) -> 730788 | B61: 3.1.06.507 | C61: SERVICIO DE VIGILANCIA | D61: 0 | E61: 0 | F61: 0 | G61: 0 | H61: 0 | I61: 0 | J61: 0 | K61: 0 | L61: 0 | M61: -182591 | N61: 0 | O61: 0 | P61: 0 | Q61: =SUM(D61:P61) -> -182591 | R61: =Q61/S61 -> -202.19368 | S61: =+S60 -> 903.05 | T61: =IFERROR((D61/$S61),0) -> 0 | U61: =IFERROR((#REF!/$S61),0) -> 0 | V61: =IFERROR((#REF!/$S61),0) -> 0 | W61: =IFERROR((E61/$S61),0) -> 0 | X61: =IFERROR((F61/$S61),0) -> 0 | Y61: =IFERROR((G61/$S61),0) -> 0 | Z61: =IFERROR((H61/$S61),0) -> 0 | AA61: =IFERROR((I61/$S61),0) -> 0 | AB61: =IFERROR((J61/$S61),0) -> 0 | AC61: =IFERROR((K61/$S61),0) -> 0 | AD61: =IFERROR((L61/$S61),0) -> 0 | AE61: =IFERROR((M61/$S61),0) -> -202.19368 | AF61: =IFERROR((#REF!/$S61),0) -> 0 | AG61: =IFERROR((N61/$S61),0) -> 0 | AH61: =IFERROR((O61/$S61),0) -> 0 | AI61: =IFERROR((P61/$S61),0) -> 0 | AJ61: =SUM(T61:AI61) -> -202.19368 | AK61: =+AJ61 -> -202.19368 | AL61: =+R61-AJ61 -> 0 | AN61: 3.1.06.507 | AO61: =EXACT(B61,AN61) -> TRUE
A62: =SUMIF('Balanza ok'!D:D,B62,'Balanza ok'!B:B) -> 710303 | B62: 3.1.06.601 | C62: GASTO MANTENCION SUCURSALES | D62: -319960 | E62: -172777 | F62: -19384 | G62: -187879 | H62: 0 | I62: 0 | J62: -302571 | K62: -96079 | L62: 0 | M62: -1679738 | N62: -212580 | O62: -113779 | P62: -255373 | Q62: =SUM(D62:P62) -> -3360120 | R62: =Q62/S62 -> -3720.8571 | S62: =+S61 -> 903.05 | T62: =IFERROR((D62/$S62),0) -> -354.31039 | U62: =IFERROR((#REF!/$S62),0) -> 0 | V62: =IFERROR((#REF!/$S62),0) -> 0 | W62: =IFERROR((E62/$S62),0) -> -191.32606 | X62: =IFERROR((F62/$S62),0) -> -21.465035 | Y62: =IFERROR((G62/$S62),0) -> -208.04939 | Z62: =IFERROR((H62/$S62),0) -> 0 | AA62: =IFERROR((I62/$S62),0) -> 0 | AB62: =IFERROR((J62/$S62),0) -> -335.05454 | AC62: =IFERROR((K62/$S62),0) -> -106.39389 | AD62: =IFERROR((L62/$S62),0) -> 0 | AE62: =IFERROR((M62/$S62),0) -> -1860.072 | AF62: =IFERROR((#REF!/$S62),0) -> 0 | AG62: =IFERROR((N62/$S62),0) -> -235.40225 | AH62: =IFERROR((O62/$S62),0) -> -125.99413 | AI62: =IFERROR((P62/$S62),0) -> -282.78944 | AJ62: =SUM(T62:AI62) -> -3720.8571 | AK62: =+AJ62 -> -3720.8571 | AL62: =+R62-AJ62 -> 0 | AN62: 3.1.06.601 | AO62: =EXACT(B62,AN62) -> TRUE
A63: =SUMIF('Balanza ok'!D:D,B63,'Balanza ok'!B:B) -> 709222 | B63: 3.1.06.602 | C63: BOLSA IMPRESA | D63: 0 | E63: -273841 | F63: -64217 | G63: -273841 | H63: -273838 | I63: -39894 | J63: -273841 | K63: -273842 | L63: 0 | M63: -273841 | N63: -273841 | O63: -273838 | P63: -273838 | Q63: =SUM(D63:P63) -> -2568672 | R63: =Q63/S63 -> -2844.4405 | S63: =+S62 -> 903.05 | T63: =IFERROR((D63/$S63),0) -> 0 | U63: =IFERROR((#REF!/$S63),0) -> 0 | V63: =IFERROR((#REF!/$S63),0) -> 0 | W63: =IFERROR((E63/$S63),0) -> -303.24013 | X63: =IFERROR((F63/$S63),0) -> -71.111234 | Y63: =IFERROR((G63/$S63),0) -> -303.24013 | Z63: =IFERROR((H63/$S63),0) -> -303.23681 | AA63: =IFERROR((I63/$S63),0) -> -44.176956 | AB63: =IFERROR((J63/$S63),0) -> -303.24013 | AC63: =IFERROR((K63/$S63),0) -> -303.24124 | AD63: =IFERROR((L63/$S63),0) -> 0 | AE63: =IFERROR((M63/$S63),0) -> -303.24013 | AF63: =IFERROR((#REF!/$S63),0) -> 0 | AG63: =IFERROR((N63/$S63),0) -> -303.24013 | AH63: =IFERROR((O63/$S63),0) -> -303.23681 | AI63: =IFERROR((P63/$S63),0) -> -303.23681 | AJ63: =SUM(T63:AI63) -> -2844.4405 | AK63: =+AJ63 -> -2844.4405 | AL63: =+R63-AJ63 -> 0 | AN63: 3.1.06.602 | AO63: =EXACT(B63,AN63) -> TRUE
A64: =SUMIF('Balanza ok'!D:D,B64,'Balanza ok'!B:B) -> 714382 | B64: 3.1.06.603 | C64: GASTOS DE ALMACENAJE | D64: 0 | E64: 0 | F64: 0 | G64: 0 | H64: 0 | I64: 0 | J64: 0 | K64: 0 | L64: 0 | M64: 0 | N64: 0 | O64: 0 | P64: 0 | Q64: =SUM(D64:P64) -> 0 | R64: =Q64/S64 -> 0 | S64: =+S63 -> 903.05 | T64: =IFERROR((D64/$S64),0) -> 0 | U64: =IFERROR((#REF!/$S64),0) -> 0 | V64: =IFERROR((#REF!/$S64),0) -> 0 | W64: =IFERROR((E64/$S64),0) -> 0 | X64: =IFERROR((F64/$S64),0) -> 0 | Y64: =IFERROR((G64/$S64),0) -> 0 | Z64: =IFERROR((H64/$S64),0) -> 0 | AA64: =IFERROR((I64/$S64),0) -> 0 | AB64: =IFERROR((J64/$S64),0) -> 0 | AC64: =IFERROR((K64/$S64),0) -> 0 | AD64: =IFERROR((L64/$S64),0) -> 0 | AE64: =IFERROR((M64/$S64),0) -> 0 | AF64: =IFERROR((#REF!/$S64),0) -> 0 | AG64: =IFERROR((N64/$S64),0) -> 0 | AH64: =IFERROR((O64/$S64),0) -> 0 | AI64: =IFERROR((P64/$S64),0) -> 0 | AJ64: =SUM(T64:AI64) -> 0 | AK64: =+AJ64 -> 0 | AL64: =+R64-AJ64 -> 0 | AN64: 3.1.06.603 | AO64: =EXACT(B64,AN64) -> TRUE
A65: =SUMIF('Balanza ok'!D:D,B65,'Balanza ok'!B:B) -> 715392 | B65: 3.1.06.802 | C65: SUMINISTROS COMPUTACIONALES | D65: -142640 | E65: 0 | F65: 0 | G65: 0 | H65: 0 | I65: 0 | J65: 0 | K65: 0 | L65: 0 | M65: 0 | N65: 0 | O65: 0 | P65: -152990 | Q65: =SUM(D65:P65) -> -295630 | R65: =Q65/S65 -> -327.36836 | S65: =+S64 -> 903.05 | T65: =IFERROR((D65/$S65),0) -> -157.9536 | U65: =IFERROR((#REF!/$S65),0) -> 0 | V65: =IFERROR((#REF!/$S65),0) -> 0 | W65: =IFERROR((E65/$S65),0) -> 0 | X65: =IFERROR((F65/$S65),0) -> 0 | Y65: =IFERROR((G65/$S65),0) -> 0 | Z65: =IFERROR((H65/$S65),0) -> 0 | AA65: =IFERROR((I65/$S65),0) -> 0 | AB65: =IFERROR((J65/$S65),0) -> 0 | AC65: =IFERROR((K65/$S65),0) -> 0 | AD65: =IFERROR((L65/$S65),0) -> 0 | AE65: =IFERROR((M65/$S65),0) -> 0 | AF65: =IFERROR((#REF!/$S65),0) -> 0 | AG65: =IFERROR((N65/$S65),0) -> 0 | AH65: =IFERROR((O65/$S65),0) -> 0 | AI65: =IFERROR((P65/$S65),0) -> -169.41476 | AJ65: =SUM(T65:AI65) -> -327.36836 | AK65: =+AJ65 -> -327.36836 | AL65: =+R65-AJ65 -> 0 | AN65: 3.1.06.802 | AO65: =EXACT(B65,AN65) -> TRUE
A66: =SUMIF('Balanza ok'!D:D,B66,'Balanza ok'!B:B) -> 715391 | B66: 3.1.06.803 | C66: UTILES DE OFICINA Y PAPELERIA | D66: 0 | E66: -167288 | F66: -43928 | G66: -167288 | H66: 0 | I66: -3890 | J66: -167285 | K66: -167285 | L66: 0 | M66: -167284 | N66: -167276 | O66: -167275 | P66: -167270 | Q66: =SUM(D66:P66) -> -1386069 | R66: =Q66/S66 -> -1534.8751 | S66: =+S65 -> 903.05 | T66: =IFERROR((D66/$S66),0) -> 0 | U66: =IFERROR((#REF!/$S66),0) -> 0 | V66: =IFERROR((#REF!/$S66),0) -> 0 | W66: =IFERROR((E66/$S66),0) -> -185.24777 | X66: =IFERROR((F66/$S66),0) -> -48.64404 | Y66: =IFERROR((G66/$S66),0) -> -185.24777 | Z66: =IFERROR((H66/$S66),0) -> 0 | AA66: =IFERROR((I66/$S66),0) -> -4.3076242 | AB66: =IFERROR((J66/$S66),0) -> -185.24445 | AC66: =IFERROR((K66/$S66),0) -> -185.24445 | AD66: =IFERROR((L66/$S66),0) -> 0 | AE66: =IFERROR((M66/$S66),0) -> -185.24334 | AF66: =IFERROR((#REF!/$S66),0) -> 0 | AG66: =IFERROR((N66/$S66),0) -> -185.23448 | AH66: =IFERROR((O66/$S66),0) -> -185.23338 | AI66: =IFERROR((P66/$S66),0) -> -185.22784 | AJ66: =SUM(T66:AI66) -> -1534.8751 | AK66: =+AJ66 -> -1534.8751 | AL66: =+R66-AJ66 -> 0 | AN66: 3.1.06.803 | AO66: =EXACT(B66,AN66) -> TRUE
A67: 730791 | B67: 3.1.06.805 | C67: GASTOS LEGALES Y NOTARIALES DIRECTOS | D67: 0 | E67: 0 | F67: 0 | G67: 0 | H67: 0 | I67: 0 | J67: 0 | K67: 0 | L67: 0 | M67: 0 | N67: 0 | O67: 0 | P67: 0 | Q67: =SUM(D67:P67) -> 0 | R67: =Q67/S67 -> 0 | S67: =+S66 -> 903.05 | T67: =IFERROR((D67/$S67),0) -> 0 | U67: =IFERROR((#REF!/$S67),0) -> 0 | V67: =IFERROR((#REF!/$S67),0) -> 0 | W67: =IFERROR((E67/$S67),0) -> 0 | X67: =IFERROR((F67/$S67),0) -> 0 | Y67: =IFERROR((G67/$S67),0) -> 0 | Z67: =IFERROR((H67/$S67),0) -> 0 | AA67: =IFERROR((I67/$S67),0) -> 0 | AB67: =IFERROR((J67/$S67),0) -> 0 | AC67: =IFERROR((K67/$S67),0) -> 0 | AD67: =IFERROR((L67/$S67),0) -> 0 | AE67: =IFERROR((M67/$S67),0) -> 0 | AF67: =IFERROR((#REF!/$S67),0) -> 0 | AG67: =IFERROR((N67/$S67),0) -> 0 | AH67: =IFERROR((O67/$S67),0) -> 0 | AI67: =IFERROR((P67/$S67),0) -> 0 | AJ67: =SUM(T67:AI67) -> 0 | AK67: =+AJ67 -> 0 | AL67: =+R67-AJ67 -> 0 | AN67: 3.1.06.805 | AO67: =EXACT(B67,AN67) -> TRUE
A68: =SUMIF('Balanza ok'!D:D,B68,'Balanza ok'!B:B) -> 810040 | B68: 3.1.06.806 | C68: COMISIONES Y GASTOS BANCARIOS | D68: 0 | E68: 0 | F68: 0 | G68: 0 | H68: 0 | I68: -1458890 | J68: 0 | K68: 0 | L68: 0 | M68: 0 | N68: 0 | O68: 0 | P68: 0 | Q68: =SUM(D68:P68) -> -1458890 | R68: =Q68/S68 -> -1615.5141 | S68: =+S67 -> 903.05 | T68: =IFERROR((D68/$S68),0) -> 0 | U68: =IFERROR((#REF!/$S68),0) -> 0 | V68: =IFERROR((#REF!/$S68),0) -> 0 | W68: =IFERROR((E68/$S68),0) -> 0 | X68: =IFERROR((F68/$S68),0) -> 0 | Y68: =IFERROR((G68/$S68),0) -> 0 | Z68: =IFERROR((H68/$S68),0) -> 0 | AA68: =IFERROR((I68/$S68),0) -> -1615.5141 | AB68: =IFERROR((J68/$S68),0) -> 0 | AC68: =IFERROR((K68/$S68),0) -> 0 | AD68: =IFERROR((L68/$S68),0) -> 0 | AE68: =IFERROR((M68/$S68),0) -> 0 | AF68: =IFERROR((#REF!/$S68),0) -> 0 | AG68: =IFERROR((N68/$S68),0) -> 0 | AH68: =IFERROR((O68/$S68),0) -> 0 | AI68: =IFERROR((P68/$S68),0) -> 0 | AJ68: =SUM(T68:AI68) -> -1615.5141 | AK68: =+AJ68 -> -1615.5141 | AL68: =+R68-AJ68 -> 0 | AN68: 3.1.06.806 | AO68: =EXACT(B68,AN68) -> TRUE
A69: =SUMIF('Balanza ok'!D:D,B69,'Balanza ok'!B:B) -> 717604 | B69: 3.1.06.812 | C69: COMISIONES TRANSBANK | D69: 0 | E69: -1480761 | F69: -96105 | G69: -1480762 | H69: -1480762 | I69: 866 | J69: -1480761 | K69: -1480762 | L69: 0 | M69: -1480760 | N69: -1480761 | O69: 0 | P69: 0 | Q69: =SUM(D69:P69) -> -10460568 | R69: =Q69/S69 -> -11583.598 | S69: =+S68 -> 903.05 | T69: =IFERROR((D69/$S69),0) -> 0 | U69: =IFERROR((#REF!/$S69),0) -> 0 | V69: =IFERROR((#REF!/$S69),0) -> 0 | W69: =IFERROR((E69/$S69),0) -> -1639.7331 | X69: =IFERROR((F69/$S69),0) -> -106.42268 | Y69: =IFERROR((G69/$S69),0) -> -1639.7342 | Z69: =IFERROR((H69/$S69),0) -> -1639.7342 | AA69: =IFERROR((I69/$S69),0) -> 0.95897237 | AB69: =IFERROR((J69/$S69),0) -> -1639.7331 | AC69: =IFERROR((K69/$S69),0) -> -1639.7342 | AD69: =IFERROR((L69/$S69),0) -> 0 | AE69: =IFERROR((M69/$S69),0) -> -1639.732 | AF69: =IFERROR((#REF!/$S69),0) -> 0 | AG69: =IFERROR((N69/$S69),0) -> -1639.7331 | AH69: =IFERROR((O69/$S69),0) -> 0 | AI69: =IFERROR((P69/$S69),0) -> 0 | AJ69: =SUM(T69:AI69) -> -11583.598 | AK69: =+AJ69 -> -11583.598 | AL69: =+R69-AJ69 -> 0 | AN69: 3.1.06.812 | AO69: =EXACT(B69,AN69) -> TRUE
A70: =SUMIF('Balanza ok'!D:D,B70,'Balanza ok'!B:B) -> 717604 | B70: 3.1.06.813 | C70: COMISIONES GETNET | D70: 0 | E70: 0 | F70: -196439 | G70: 0 | H70: 0 | I70: 0 | J70: 0 | K70: 0 | L70: 0 | M70: 0 | N70: 0 | O70: -1047425 | P70: -1200031 | Q70: =SUM(D70:P70) -> -2443895 | R70: =Q70/S70 -> -2706.2676 | S70: =+S69 -> 903.05 | T70: =IFERROR((D70/$S70),0) -> 0 | U70: =IFERROR((#REF!/$S70),0) -> 0 | V70: =IFERROR((#REF!/$S70),0) -> 0 | W70: =IFERROR((E70/$S70),0) -> 0 | X70: =IFERROR((F70/$S70),0) -> -217.52838 | Y70: =IFERROR((G70/$S70),0) -> 0 | Z70: =IFERROR((H70/$S70),0) -> 0 | AA70: =IFERROR((I70/$S70),0) -> 0 | AB70: =IFERROR((J70/$S70),0) -> 0 | AC70: =IFERROR((K70/$S70),0) -> 0 | AD70: =IFERROR((L70/$S70),0) -> 0 | AE70: =IFERROR((M70/$S70),0) -> 0 | AF70: =IFERROR((#REF!/$S70),0) -> 0 | AG70: =IFERROR((N70/$S70),0) -> 0 | AH70: =IFERROR((O70/$S70),0) -> -1159.8749 | AI70: =IFERROR((P70/$S70),0) -> -1328.8644 | AJ70: =SUM(T70:AI70) -> -2706.2676 | AK70: =+AJ70 -> -2706.2676 | AL70: =+R70-AJ70 -> 0 | AN70: 3.1.06.813 | AO70: =EXACT(B70,AN70) -> TRUE
A71: =SUMIF('Balanza ok'!D:D,B71,'Balanza ok'!B:B) -> 730780 | B71: 3.1.06.817 | C71: GASTOS DE REPRESENTACION | D71: 0 | E71: 0 | F71: 0 | G71: 0 | H71: 0 | I71: -1133557 | J71: 0 | K71: 0 | L71: 0 | M71: 0 | N71: 0 | O71: 0 | P71: 0 | Q71: =SUM(D71:P71) -> -1133557 | R71: =Q71/S71 -> -1255.2539 | S71: =+S70 -> 903.05 | T71: =IFERROR((D71/$S71),0) -> 0 | U71: =IFERROR((#REF!/$S71),0) -> 0 | V71: =IFERROR((#REF!/$S71),0) -> 0 | W71: =IFERROR((E71/$S71),0) -> 0 | X71: =IFERROR((F71/$S71),0) -> 0 | Y71: =IFERROR((G71/$S71),0) -> 0 | Z71: =IFERROR((H71/$S71),0) -> 0 | AA71: =IFERROR((I71/$S71),0) -> -1255.2539 | AB71: =IFERROR((J71/$S71),0) -> 0 | AC71: =IFERROR((K71/$S71),0) -> 0 | AD71: =IFERROR((L71/$S71),0) -> 0 | AE71: =IFERROR((M71/$S71),0) -> 0 | AF71: =IFERROR((#REF!/$S71),0) -> 0 | AG71: =IFERROR((N71/$S71),0) -> 0 | AH71: =IFERROR((O71/$S71),0) -> 0 | AI71: =IFERROR((P71/$S71),0) -> 0 | AJ71: =SUM(T71:AI71) -> -1255.2539 | AK71: =+AJ71 -> -1255.2539 | AL71: =+R71-AJ71 -> 0 | AN71: 3.1.06.817 | AO71: =EXACT(B71,AN71) -> TRUE
A72: =SUMIF('Balanza ok'!D:D,B72,'Balanza ok'!B:B) -> 721752 | B72: 3.1.06.818 | C72: LICENCIAS SOTWARE RENTAS | D72: -497134 | E72: -497134 | F72: -121354 | G72: -497134 | H72: -4331016 | I72: -1315075 | J72: -497133 | K72: -497133 | L72: -497134 | M72: -497134 | N72: -497134 | O72: -497134 | P72: -497134 | Q72: =SUM(D72:P72) -> -10738783 | R72: =Q72/S72 -> -11891.682 | S72: =+S71 -> 903.05 | T72: =IFERROR((D72/$S72),0) -> -550.50551 | U72: =IFERROR((#REF!/$S72),0) -> 0 | V72: =IFERROR((#REF!/$S72),0) -> 0 | W72: =IFERROR((E72/$S72),0) -> -550.50551 | X72: =IFERROR((F72/$S72),0) -> -134.38237 | Y72: =IFERROR((G72/$S72),0) -> -550.50551 | Z72: =IFERROR((H72/$S72),0) -> -4795.9869 | AA72: =IFERROR((I72/$S72),0) -> -1456.2593 | AB72: =IFERROR((J72/$S72),0) -> -550.5044 | AC72: =IFERROR((K72/$S72),0) -> -550.5044 | AD72: =IFERROR((L72/$S72),0) -> -550.50551 | AE72: =IFERROR((M72/$S72),0) -> -550.50551 | AF72: =IFERROR((#REF!/$S72),0) -> 0 | AG72: =IFERROR((N72/$S72),0) -> -550.50551 | AH72: =IFERROR((O72/$S72),0) -> -550.50551 | AI72: =IFERROR((P72/$S72),0) -> -550.50551 | AJ72: =SUM(T72:AI72) -> -11891.682 | AK72: =+AJ72 -> -11891.682 | AL72: =+R72-AJ72 -> 0 | AN72: 3.1.06.818 | AO72: =EXACT(B72,AN72) -> TRUE
A73: =SUMIF('Balanza ok'!D:D,B73,'Balanza ok'!B:B) -> 730786 | B73: 3.1.06.831 | C73: MEMBRESÍAS Y ASOCIACIONES | D73: 0 | E73: 0 | F73: 0 | G73: 0 | H73: 0 | I73: -537122 | J73: 0 | K73: 0 | L73: 0 | M73: 0 | N73: 0 | O73: 0 | P73: 0 | Q73: =SUM(D73:P73) -> -537122 | R73: =Q73/S73 -> -594.78656 | S73: =+S72 -> 903.05 | T73: =IFERROR((D73/$S73),0) -> 0 | U73: =IFERROR((#REF!/$S73),0) -> 0 | V73: =IFERROR((#REF!/$S73),0) -> 0 | W73: =IFERROR((E73/$S73),0) -> 0 | X73: =IFERROR((F73/$S73),0) -> 0 | Y73: =IFERROR((G73/$S73),0) -> 0 | Z73: =IFERROR((H73/$S73),0) -> 0 | AA73: =IFERROR((I73/$S73),0) -> -594.78656 | AB73: =IFERROR((J73/$S73),0) -> 0 | AC73: =IFERROR((K73/$S73),0) -> 0 | AD73: =IFERROR((L73/$S73),0) -> 0 | AE73: =IFERROR((M73/$S73),0) -> 0 | AF73: =IFERROR((#REF!/$S73),0) -> 0 | AG73: =IFERROR((N73/$S73),0) -> 0 | AH73: =IFERROR((O73/$S73),0) -> 0 | AI73: =IFERROR((P73/$S73),0) -> 0 | AJ73: =SUM(T73:AI73) -> -594.78656 | AK73: =+AJ73 -> -594.78656 | AL73: =+R73-AJ73 -> 0 | AN73: 3.1.06.831 | AO73: =EXACT(B73,AN73) -> TRUE
A74: =SUMIF('Balanza ok'!D:D,B74,'Balanza ok'!B:B) -> 709225 | B74: 3.1.06.837 | C74: MONITOREO COMERCIAL | D74: 0 | E74: -262949 | F74: -60206 | G74: -262948 | H74: 0 | I74: 0 | J74: -262947 | K74: -262946 | L74: 0 | M74: -262946 | N74: -262945 | O74: -262945 | P74: -262945 | Q74: =SUM(D74:P74) -> -2163777 | R74: =Q74/S74 -> -2396.0766 | S74: =+S73 -> 903.05 | T74: =IFERROR((D74/$S74),0) -> 0 | U74: =IFERROR((#REF!/$S74),0) -> 0 | V74: =IFERROR((#REF!/$S74),0) -> 0 | W74: =IFERROR((E74/$S74),0) -> -291.17878 | X74: =IFERROR((F74/$S74),0) -> -66.66962 | Y74: =IFERROR((G74/$S74),0) -> -291.17768 | Z74: =IFERROR((H74/$S74),0) -> 0 | AA74: =IFERROR((I74/$S74),0) -> 0 | AB74: =IFERROR((J74/$S74),0) -> -291.17657 | AC74: =IFERROR((K74/$S74),0) -> -291.17546 | AD74: =IFERROR((L74/$S74),0) -> 0 | AE74: =IFERROR((M74/$S74),0) -> -291.17546 | AF74: =IFERROR((#REF!/$S74),0) -> 0 | AG74: =IFERROR((N74/$S74),0) -> -291.17435 | AH74: =IFERROR((O74/$S74),0) -> -291.17435 | AI74: =IFERROR((P74/$S74),0) -> -291.17435 | AJ74: =SUM(T74:AI74) -> -2396.0766 | AK74: =+AJ74 -> -2396.0766 | AL74: =+R74-AJ74 -> 0 | AN74: 3.1.06.837 | AO74: =EXACT(B74,AN74) -> TRUE
A75: =SUMIF('Balanza ok'!D:D,B75,'Balanza ok'!B:B) -> 709205 | B75: 3.1.07.822 | C75: GASTOS DE PUBLICIDAD Y MARKETING | D75: 0 | E75: 0 | F75: 0 | G75: 0 | H75: -11432859 | I75: 431685 | J75: 0 | K75: 0 | L75: 0 | M75: 0 | N75: 0 | O75: 0 | P75: 0 | Q75: =SUM(D75:P75) -> -11001174 | R75: =Q75/S75 -> -12182.242 | S75: =+S74 -> 903.05 | T75: =IFERROR((D75/$S75),0) -> 0 | U75: =IFERROR((#REF!/$S75),0) -> 0 | V75: =IFERROR((#REF!/$S75),0) -> 0 | W75: =IFERROR((E75/$S75),0) -> 0 | X75: =IFERROR((F75/$S75),0) -> 0 | Y75: =IFERROR((G75/$S75),0) -> 0 | Z75: =IFERROR((H75/$S75),0) -> -12660.272 | AA75: =IFERROR((I75/$S75),0) -> 478.03001 | AB75: =IFERROR((J75/$S75),0) -> 0 | AC75: =IFERROR((K75/$S75),0) -> 0 | AD75: =IFERROR((L75/$S75),0) -> 0 | AE75: =IFERROR((M75/$S75),0) -> 0 | AF75: =IFERROR((#REF!/$S75),0) -> 0 | AG75: =IFERROR((N75/$S75),0) -> 0 | AH75: =IFERROR((O75/$S75),0) -> 0 | AI75: =IFERROR((P75/$S75),0) -> 0 | AJ75: =SUM(T75:AI75) -> -12182.242 | AK75: =+AJ75 -> -12182.242 | AL75: =+R75-AJ75 -> 0 | AN75: 3.1.07.822 | AO75: =EXACT(B75,AN75) -> TRUE
A76: =SUMIF('Balanza ok'!D:D,B76,'Balanza ok'!B:B) -> 709224 | B76: 3.1.07.833 | C76: SUMINISTROS VISUAL | D76: 0 | E76: -680949 | F76: 82370 | G76: -680950 | H76: 0 | I76: -1222329 | J76: -680950 | K76: -680951 | L76: 0 | M76: -680950 | N76: -680949 | O76: -680948 | P76: -680948 | Q76: =SUM(D76:P76) -> -6587554 | R76: =Q76/S76 -> -7294.7832 | S76: =+S75 -> 903.05 | T76: =IFERROR((D76/$S76),0) -> 0 | U76: =IFERROR((#REF!/$S76),0) -> 0 | V76: =IFERROR((#REF!/$S76),0) -> 0 | W76: =IFERROR((E76/$S76),0) -> -754.05459 | X76: =IFERROR((F76/$S76),0) -> 91.213111 | Y76: =IFERROR((G76/$S76),0) -> -754.0557 | Z76: =IFERROR((H76/$S76),0) -> 0 | AA76: =IFERROR((I76/$S76),0) -> -1353.5563 | AB76: =IFERROR((J76/$S76),0) -> -754.0557 | AC76: =IFERROR((K76/$S76),0) -> -754.05681 | AD76: =IFERROR((L76/$S76),0) -> 0 | AE76: =IFERROR((M76/$S76),0) -> -754.0557 | AF76: =IFERROR((#REF!/$S76),0) -> 0 | AG76: =IFERROR((N76/$S76),0) -> -754.05459 | AH76: =IFERROR((O76/$S76),0) -> -754.05349 | AI76: =IFERROR((P76/$S76),0) -> -754.05349 | AJ76: =SUM(T76:AI76) -> -7294.7832 | AK76: =+AJ76 -> -7294.7832 | AL76: =+R76-AJ76 -> 0 | AN76: 3.1.07.833 | AO76: =EXACT(B76,AN76) -> TRUE
A77: 740818 | B77: 3.1.08.701 | C77: DEPRECIACION DEL EJERCICIO | D77: -8669001.6 | E77: -26046.172 | F77: -848768.52 | G77: -72223.97 | H77: 0 | I77: -2782219.9 | J77: -4212648.5 | K77: -1209758.2 | L77: 0 | M77: -4166376.6 | N77: -3861879.9 | O77: -3444902.7 | P77: -2559960.9 | Q77: =SUM(D77:P77) -> -31853787 | R77: =Q77/S77 -> -35273.558 | S77: =+S76 -> 903.05 | T77: =IFERROR((D77/$S77),0) -> -9599.6917 | U77: =IFERROR((#REF!/$S77),0) -> 0 | V77: =IFERROR((#REF!/$S77),0) -> 0 | W77: =IFERROR((E77/$S77),0) -> -28.842448 | X77: =IFERROR((F77/$S77),0) -> -939.89094 | Y77: =IFERROR((G77/$S77),0) -> -79.97782 | Z77: =IFERROR((H77/$S77),0) -> 0 | AA77: =IFERROR((I77/$S77),0) -> -3080.9146 | AB77: =IFERROR((J77/$S77),0) -> -4664.9117 | AC77: =IFERROR((K77/$S77),0) -> -1339.6359 | AD77: =IFERROR((L77/$S77),0) -> 0 | AE77: =IFERROR((M77/$S77),0) -> -4613.6721 | AF77: =IFERROR((#REF!/$S77),0) -> 0 | AG77: =IFERROR((N77/$S77),0) -> -4276.4852 | AH77: =IFERROR((O77/$S77),0) -> -3814.7419 | AI77: =IFERROR((P77/$S77),0) -> -2834.7942 | AJ77: =SUM(T77:AI77) -> -35273.558 | AK77: =+AJ77 -> -35273.558 | AL77: =+R77-AJ77 -> 0 | AN77: 3.1.08.701 | AO77: =EXACT(B77,AN77) -> TRUE
A78: 740814 | D78: -1655450.5 | E78: -4973.8309 | F78: -162082.59 | G78: -13792.039 | H78: 0 | I78: -531298.46 | J78: -804456.06 | K78: -231017.93 | L78: 0 | M78: -795619.89 | N78: -737472.57 | O78: -657845.74 | P78: -488855.42 | Q78: =SUM(D78:P78) -> -6082865 | R78: =Q78/S78 -> -6735.9116 | S78: =+S77 -> 903.05 | T78: =IFERROR((D78/$S78),0) -> -1833.177 | U78: =IFERROR((#REF!/$S78),0) -> 0 | V78: =IFERROR((#REF!/$S78),0) -> 0 | W78: =IFERROR((E78/$S78),0) -> -5.5078134 | X78: =IFERROR((F78/$S78),0) -> -179.48352 | Y78: =IFERROR((G78/$S78),0) -> -15.27273 | Z78: =IFERROR((H78/$S78),0) -> 0 | AA78: =IFERROR((I78/$S78),0) -> -588.33781 | AB78: =IFERROR((J78/$S78),0) -> -890.82117 | AC78: =IFERROR((K78/$S78),0) -> -255.81964 | AD78: =IFERROR((L78/$S78),0) -> 0 | AE78: =IFERROR((M78/$S78),0) -> -881.03637 | AF78: =IFERROR((#REF!/$S78),0) -> 0 | AG78: =IFERROR((N78/$S78),0) -> -816.64644 | AH78: =IFERROR((O78/$S78),0) -> -728.471 | AI78: =IFERROR((P78/$S78),0) -> -541.33816 | AJ78: =SUM(T78:AI78) -> -6735.9116 | AK78: =+AJ78 -> -6735.9116 | AL78: =+R78-AJ78 -> 0 | AO78: =EXACT(B78,AN78) -> TRUE
A79: =SUMIF('Balanza ok'!D:D,B79,'Balanza ok'!B:B) -> 810015 | B79: 3.2.08.105 | C79: INTERESES POR PRESTAMO | D79: 0 | E79: 0 | F79: 0 | G79: 0 | H79: 0 | I79: 0 | J79: -33811 | K79: 0 | L79: 0 | M79: 0 | N79: 0 | O79: -16417 | P79: -27053 | Q79: =SUM(D79:P79) -> -77281 | R79: =Q79/S79 -> -85.577764 | S79: =+S77 -> 903.05 | T79: =IFERROR((D79/$S79),0) -> 0 | U79: =IFERROR((#REF!/$S79),0) -> 0 | V79: =IFERROR((#REF!/$S79),0) -> 0 | W79: =IFERROR((E79/$S79),0) -> 0 | X79: =IFERROR((F79/$S79),0) -> 0 | Y79: =IFERROR((G79/$S79),0) -> 0 | Z79: =IFERROR((H79/$S79),0) -> 0 | AA79: =IFERROR((I79/$S79),0) -> 0 | AB79: =IFERROR((J79/$S79),0) -> -37.440895 | AC79: =IFERROR((K79/$S79),0) -> 0 | AD79: =IFERROR((L79/$S79),0) -> 0 | AE79: =IFERROR((M79/$S79),0) -> 0 | AF79: =IFERROR((#REF!/$S79),0) -> 0 | AG79: =IFERROR((N79/$S79),0) -> 0 | AH79: =IFERROR((O79/$S79),0) -> -18.179503 | AI79: =IFERROR((P79/$S79),0) -> -29.957367 | AJ79: =SUM(T79:AI79) -> -85.577764 | AK79: =+AJ79 -> -85.577764 | AL79: =+R79-AJ79 -> 0 | AN79: 3.2.08.105 | AO79: =EXACT(B79,AN79) -> TRUE
A80: =SUMIF('Balanza ok'!D:D,B80,'Balanza ok'!B:B) -> 820010 | B80: 3.2.08.114 | C80: INTERESES DEVENGADOS FONDOS MU | H80: 0 | I80: 3695613 | L80: 0 | Q80: =SUM(D80:P80) -> 3695613 | R80: =Q80/S80 -> 4092.3681 | S80: =+S78 -> 903.05 | T80: =IFERROR((D80/$S80),0) -> 0 | U80: =IFERROR((#REF!/$S80),0) -> 0 | V80: =IFERROR((#REF!/$S80),0) -> 0 | W80: =IFERROR((E80/$S80),0) -> 0 | X80: =IFERROR((F80/$S80),0) -> 0 | Y80: =IFERROR((G80/$S80),0) -> 0 | Z80: =IFERROR((H80/$S80),0) -> 0 | AA80: =IFERROR((I80/$S80),0) -> 4092.3681 | AB80: =IFERROR((J80/$S80),0) -> 0 | AC80: =IFERROR((K80/$S80),0) -> 0 | AD80: =IFERROR((L80/$S80),0) -> 0 | AE80: =IFERROR((M80/$S80),0) -> 0 | AF80: =IFERROR((#REF!/$S80),0) -> 0 | AG80: =IFERROR((N80/$S80),0) -> 0 | AH80: =IFERROR((O80/$S80),0) -> 0 | AI80: =IFERROR((P80/$S80),0) -> 0 | AJ80: =SUM(T80:AI80) -> 4092.3681 | AK80: =+AJ80 -> 4092.3681 | AL80: =+R80-AJ80 -> 0 | AN80: 3.2.08.114 | AO80: =EXACT(B80,AN80) -> TRUE
A81: =SUMIF('Balanza ok'!D:D,B81,'Balanza ok'!B:B) -> 820010 | B81: 3.2.08.116 | C81: INTERES GANADO POR DEPOSITO A PLAZO PESOS | D81: 0 | E81: 0 | F81: 0 | G81: 0 | H81: 0 | I81: 35492 | J81: 0 | K81: 0 | L81: 0 | M81: 0 | N81: 0 | O81: 0 | P81: 0 | Q81: =SUM(D81:P81) -> 35492 | R81: =Q81/S81 -> 39.302364 | S81: =+S80 -> 903.05 | T81: =IFERROR((D81/$S81),0) -> 0 | U81: =IFERROR((#REF!/$S81),0) -> 0 | V81: =IFERROR((#REF!/$S81),0) -> 0 | W81: =IFERROR((E81/$S81),0) -> 0 | X81: =IFERROR((F81/$S81),0) -> 0 | Y81: =IFERROR((G81/$S81),0) -> 0 | Z81: =IFERROR((H81/$S81),0) -> 0 | AA81: =IFERROR((I81/$S81),0) -> 39.302364 | AB81: =IFERROR((J81/$S81),0) -> 0 | AC81: =IFERROR((K81/$S81),0) -> 0 | AD81: =IFERROR((L81/$S81),0) -> 0 | AE81: =IFERROR((M81/$S81),0) -> 0 | AF81: =IFERROR((#REF!/$S81),0) -> 0 | AG81: =IFERROR((N81/$S81),0) -> 0 | AH81: =IFERROR((O81/$S81),0) -> 0 | AI81: =IFERROR((P81/$S81),0) -> 0 | AJ81: =SUM(T81:AI81) -> 39.302364 | AK81: =+AJ81 -> 39.302364 | AL81: =+R81-AJ81 -> 0 | AN81: 3.2.08.116 | AO81: =EXACT(B81,AN81) -> TRUE
A82: =SUMIF('Balanza ok'!D:D,B82,'Balanza ok'!B:B) -> 820010 | B82: 3.2.08.117 | C82: INTERES GANADO FONDOS MUTUOS | H82: 0 | I82: 775274 | L82: 0 | Q82: =SUM(D82:P82) -> 775274 | R82: =Q82/S82 -> 858.50617 | S82: =+S81 -> 903.05 | AJ82: =SUM(T82:AI82) -> 0 | AK82: =+AJ82 -> 0 | AN82: 3.2.08.117 | AO82: =EXACT(B82,AN82) -> TRUE
A83: =SUMIF('Balanza ok'!D:D,B83,'Balanza ok'!B:B) -> 820060 | B83: 3.2.11.158 | C83: DIFERENCIA DE CAMBIO | H83: 0 | I83: -10834978 | L83: 0 | Q83: =SUM(D83:P83) -> -10834978 | R83: =Q83/S83 -> -11998.204 | S83: =+S82 -> 903.05 | T83: =IFERROR((D83/$S83),0) -> 0 | U83: =IFERROR((#REF!/$S83),0) -> 0 | V83: =IFERROR((#REF!/$S83),0) -> 0 | W83: =IFERROR((E83/$S83),0) -> 0 | X83: =IFERROR((F83/$S83),0) -> 0 | Y83: =IFERROR((G83/$S83),0) -> 0 | Z83: =IFERROR((H83/$S83),0) -> 0 | AA83: =IFERROR((I83/$S83),0) -> -11998.204 | AB83: =IFERROR((J83/$S83),0) -> 0 | AC83: =IFERROR((K83/$S83),0) -> 0 | AD83: =IFERROR((L83/$S83),0) -> 0 | AE83: =IFERROR((M83/$S83),0) -> 0 | AF83: =IFERROR((#REF!/$S83),0) -> 0 | AG83: =IFERROR((N83/$S83),0) -> 0 | AH83: =IFERROR((O83/$S83),0) -> 0 | AI83: =IFERROR((P83/$S83),0) -> 0 | AJ83: =SUM(T83:AI83) -> -11998.204 | AK83: =+AJ83 -> -11998.204 | AL83: =+R83-AJ83 -> 0 | AN83: 3.2.11.158 | AO83: =EXACT(B83,AN83) -> TRUE
A84: =SUMIF('Balanza ok'!D:D,B84,'Balanza ok'!B:B) -> 810080 | B84: 3.2.13.101 | C84: CORRECCION MONETARIA ACTIVOS | D84: 0 | E84: 0 | F84: 0 | G84: 0 | H84: 0 | I84: 4515392 | J84: 0 | K84: 0 | L84: 0 | M84: 0 | N84: 0 | O84: 0 | P84: 0 | Q84: =SUM(D84:P84) -> 4515392 | R84: =Q84/S84 -> 5000.1572 | S84: =+S83 -> 903.05 | T84: =IFERROR((D84/$S84),0) -> 0 | U84: =IFERROR((#REF!/$S84),0) -> 0 | V84: =IFERROR((#REF!/$S84),0) -> 0 | W84: =IFERROR((E84/$S84),0) -> 0 | X84: =IFERROR((F84/$S84),0) -> 0 | Y84: =IFERROR((G84/$S84),0) -> 0 | Z84: =IFERROR((H84/$S84),0) -> 0 | AA84: =IFERROR((I84/$S84),0) -> 5000.1572 | AB84: =IFERROR((J84/$S84),0) -> 0 | AC84: =IFERROR((K84/$S84),0) -> 0 | AD84: =IFERROR((L84/$S84),0) -> 0 | AE84: =IFERROR((M84/$S84),0) -> 0 | AF84: =IFERROR((#REF!/$S84),0) -> 0 | AG84: =IFERROR((N84/$S84),0) -> 0 | AH84: =IFERROR((O84/$S84),0) -> 0 | AI84: =IFERROR((P84/$S84),0) -> 0 | AJ84: =SUM(T84:AI84) -> 5000.1572 | AK84: =+AJ84 -> 5000.1572 | AL84: =+R84-AJ84 -> 0 | AN84: 3.2.13.101 | AO84: =EXACT(B84,AN84) -> TRUE
A85: =SUMIF('Balanza ok'!D:D,B85,'Balanza ok'!B:B) -> 810099 | B85: 3.2.13.109 | C85: AJUSTE REDONDEO AUTO | D85: 0 | E85: 2 | F85: 0 | G85: 0 | H85: 0 | I85: -1346 | J85: 0 | K85: 0 | L85: 0 | M85: -5 | N85: 0 | O85: 0 | P85: 0 | Q85: =SUM(D85:P85) -> -1349 | R85: =Q85/S85 -> -1.4938265 | S85: =+S84 -> 903.05 | T85: =IFERROR((D85/$S85),0) -> 0 | U85: =IFERROR((#REF!/$S85),0) -> 0 | V85: =IFERROR((#REF!/$S85),0) -> 0 | W85: =IFERROR((E85/$S85),0) -> 0.0022147168 | X85: =IFERROR((F85/$S85),0) -> 0 | Y85: =IFERROR((G85/$S85),0) -> 0 | Z85: =IFERROR((H85/$S85),0) -> 0 | AA85: =IFERROR((I85/$S85),0) -> -1.4905044 | AB85: =IFERROR((J85/$S85),0) -> 0 | AC85: =IFERROR((K85/$S85),0) -> 0 | AD85: =IFERROR((L85/$S85),0) -> 0 | AE85: =IFERROR((M85/$S85),0) -> -0.005536792 | AF85: =IFERROR((#REF!/$S85),0) -> 0 | AG85: =IFERROR((N85/$S85),0) -> 0 | AH85: =IFERROR((O85/$S85),0) -> 0 | AI85: =IFERROR((P85/$S85),0) -> 0 | AJ85: =SUM(T85:AI85) -> -1.4938265 | AK85: =+AJ85 -> -1.4938265 | AL85: =+R85-AJ85 -> 0 | AN85: 3.2.13.109 | AO85: =EXACT(B85,AN85) -> TRUE
B86: Resultado por Centro de Costo | D86: =SUM(D23:D85) -> -36232314 | E86: =SUM(E23:E85) -> -72538966 | F86: =SUM(F23:F85) -> -14817083 | G86: =SUM(G23:G85) -> -71310081 | H86: =SUM(H23:H85) -> -44894950 | I86: =SUM(I23:I85) -> -38852606 | J86: =SUM(J23:J85) -> -1.1685626e+08 | K86: =SUM(K23:K85) -> -61774215 | ... P86: =SUM(P23:P85) -> -70726302 | Q86: =SUM(D86:P86) -> -742664336 | R86: =Q86/S86 -> -822395.59 | S86: =+S85 -> 903.05 | T86: =SUM(T24:T85) -> -40122.157 | U86: =SUM(U24:U85) -> 0 | V86: =SUM(V24:V85) -> 0 | W86: =SUM(W24:W85) -> -80315.427 | X86: =SUM(X24:X85) -> -16395.888 | Y86: =SUM(Y24:Y85) -> -78959.509 | Z86: =SUM(Z24:Z85) -> -61635.995 | AA86: =SUM(AA24:AA85) -> -43882.266 | ... AJ86: =SUM(AJ24:AJ85) -> -834861.61 | AK86: =AJ86-R86 -> -12466.026 | AL86: =SUM(AL24:AL85) -> 0
D87: =D88/$S$86 -> -40122.157 | E87: =E88/$S$86 -> -15677.974 | F87: =F88/$S$86 -> 2962.7063 | G87: =G88/$S$86 -> -28537.934 | H87: =H88/$S$86 -> 3206.6178 | I87: =I88/$S$86 -> -43023.76 | J87: =J88/$S$86 -> -26464.227 | K87: =K88/$S$86 -> -30151.548 | ... P87: =P88/$S$86 -> -28916.47 | Q87: =SUM(D87:P87) -> -307272.26
B88: Resultado por Centro de Costo | D88: =+D9+D86 -> -36232314 | E88: =+E9+E86+E18 -> -14157995 | F88: =+F9+F86+F18 -> 2675472 | G88: =+G9+G86+G18 -> -25771182 | H88: =+H9+H86+H18 -> 2895736.2 | I88: =+I9+I86+I18 -> -38852606 | J88: =+J9+J86+J18 -> -23898520 | K88: =+K9+K86+K18 -> -27228355 | L88: =+L9+L86+L18 -> -26318285 | ... Q88: =+Q9+Q86+Q18 -> -2.7748222e+08 | R88: =+R9+R86 -> -421440.71 | T88: =+T9+T86 -> -40122.157 | U88: =+U9+U86 -> 0 | V88: =+V9+V86 -> 0 | W88: =+W9+W86 -> -28522.169 | X88: =+X9+X86 -> -3042.9421 | Y88: =+Y9+Y86 -> -40862.402 | Z88: =+Z9+Z86 -> -11539.343 | AA88: =+AA9+AA86 -> -43882.266 | ... AJ88: =+AJ9+AJ86 -> -433906.74
N89: BALANCE 8 COLUMNAS | Q89: =+Balance!C59 -> -277482731 | R89: =Q89/S89 -> -307272.83 | S89: =+S86 -> 903.05 | AJ89: =AJ88-R88 -> -12466.026
N90: DIF | Q90: =Q89-Q88 -> -513.0084
D91: CEDIS CHILE | E91: EGAÑA | F91: VESPUCIO | G91: TREBOL | H91: ONLINE | I91: ADMINISTRACION | J91: COSTANERA CENTER | K91: FLORIDA CENTER | M91: ESTADO | N91: TALCA | O91: NORTE | P91: OESTE
C93: Proporcion depreciación | D93: -10324451 | E93: -31020 | F93: -1010851 | G93: -86016 | H93: 0 | I93: -3313518 | J93: -5017104 | K93: -1440776 | L93: 0 | M93: -4961996 | N93: -4599352 | O93: -4102748 | P93: -3048816 | Q93: =SUM(D93:P93) -> -37936648 | AJ93: =+AJ86+AL86 -> -834861.61 | AK93: 1184353.5 | AL93: =AK93-AJ93 -> 2019215.1
B94: 740818 | C94: =+H105 -> 0.83965739 | D94: =+$C$94*D93 -> -8669001.6 | E94: =+$C$94*E93 -> -26046.172 | F94: =+$C$94*F93 -> -848768.52 | G94: =+$C$94*G93 -> -72223.97 | H94: =+$C$94*H93 -> 0 | I94: =+$C$94*I93 -> -2782219.9 | J94: =+$C$94*J93 -> -4212648.5 | K94: =+$C$94*K93 -> -1209758.2 | ... P94: =+$C$94*P93 -> -2559960.9 | Q94: =SUM(D94:P94) -> -31853787 | AJ94: =827838.49 -> 827838.49 | AK94: =827838.49 -> 827838.49
B95: 740814 | C95: =+H107 -> 0.16034271 | D95: =+$C$95*D93 -> -1655450.5 | E95: =+$C$95*E93 -> -4973.8309 | F95: =+$C$95*F93 -> -162082.59 | G95: =+$C$95*G93 -> -13792.039 | H95: =+$C$95*H93 -> 0 | I95: =+$C$95*I93 -> -531298.46 | J95: =+$C$95*J93 -> -804456.06 | K95: =+$C$95*K93 -> -231017.93 | ... P95: =+$C$95*P93 -> -488855.42 | Q95: =SUM(D95:P95) -> -6082865 | AJ95: =AJ93-AJ94 -> -1662700.1 | AK95: =AK93-AK94 -> 356515.01 | AL95: =AJ95-AK95 -> -2019215.1
B98: *** Saldos negativos se suben con 50 y se suben en positivo
B99: *** Cuentas 81 y 82 revisar manualmente porque puede ser deudora o acreedora
B100: *** Gastos financieros en negativo (81) se convierten en productos financieros (82) y se suben en positivo
B101: ***Cuentas 8 miles no llevan CECO
E103: 3.1.08.701 | F103: DEPRECIACION DEL EJERCICIO | G103: 37936648
E105: 740818 | F105: Total Muebles y Otros | G105: 31853787 | H105: =G105/G103 -> 0.83965739
E107: 740814 | F107: Total Equipos Computacionales | G107: 6082865 | H107: =G107/G103 -> 0.16034271
B108: EVENTOS CAPACITACION TIENDAS | C108: 7 | D108: 709223
B109: FINANCIAMIENTO FLEXI EQUIPAMIENTO Y PROM TIENDAS | C109: 7 | D109: 709228
...

Sheet errores advicom

Sheet Resultados (2)
E1: HDOMINICOS | F1: HMAIPU | G1: HEGAÑA | H1: HVESPUCIO | I1: TREBOL | J1: HONLINE | L1: HCOSTANERA | M1: HFLORIDA | N1: HDEPARTAME | P1: Valor transaccional | Q1: Tipo de cambio transaccional | S1: HDOMINICOS | T1: HMAIPU | U1: HEGAÑA | V1: HVESPUCIO | W1: TREBOL | X1: HONLINE | Z1: HCOSTANERA | AA1: HFLORIDA | AB1: HDEPARTAME
A2: Cuenta México | B2: N° CUENTA | C2: NOMBRE CUENTA | D2: CEDIS CHILE | E2: DOMINICOS | F2: MAIPU | G2: EGAÑA | H2: VESPUCIO | I2: TREBOL | J2: ONLINE | K2: ADMINISTRACION | L2: COSTANERA CENTER | M2: FLORIDA CENTER | N2: DEPARTAMENTALES | O2: TOTAL | R2: CEDIS CHILE | S2: DOMINICOS | T2: MAIPU | U2: EGAÑA | V2: VESPUCIO | W2: TREBOL | X2: ONLINE | Y2: ADMINISTRACION | Z2: COSTANERA CENTER | AA2: FLORIDA CENTER | AB2: DEPARTAMENTALES | AC2: TOTAL
C4: VENTAS CON BOLETA | D4: 0 | E4: =SUM(E5:E6) -> 90012219 | F4: =SUM(F5:F6) -> 78182140 | G4: =SUM(G5:G6) -> 170857429 | H4: =SUM(H5:H6) -> 163083860 | I4: =SUM(I5:I6) -> 164044512 | J4: =SUM(J5:J6) -> 303243729 | K4: 0 | L4: =SUM(L5:L6) -> 243702388 | M4: =SUM(M5:M6) -> 97315248 | N4: =SUM(N5:N6) -> 312262688 | O4: =SUM(O5:O6) -> 1622704213 | P4: 1965913 | Q4: =+O4/P4 -> 825.42015 | R4: =IFERROR((D4/#REF!),0) -> 0 | S4: =+S5+S6 -> 109050.18 | T4: =+T5+T6 -> 94717.992 | U4: =+U5+U6 -> 206994.5 | V4: =+V5+V6 -> 197576.78 | W4: =+W5+W6 -> 198740.62 | X4: =+X5+X6 -> 367381.06 | Y4: =+Y5+Y6 -> 0 | Z4: =+Z5+Z6 -> 295246.47 | ... AC4: =+AC5+AC6 -> 1965913 | AD4: =+AC4 -> 1965913
A5: =SUMIF(#REF!,B5,#REF!) -> #REF! | B5: ACC | C5: ACCESORIOS | D5: 0 | E5: 3149322 | F5: 2191640 | G5: 4147928 | H5: 5225041 | I5: 3489379 | J5: 246260 | K5: 0 | L5: 8296175 | M5: 2681586 | N5: 0 | O5: =SUM(E5:N5) -> 29427331 | R5: =IFERROR((D5/$Q$4),0) -> 0 | S5: =IFERROR((E5/$Q$4),0) -> 3815.4169 | T5: =IFERROR((F5/$Q$4),0) -> 2655.1811 | U5: =IFERROR((G5/$Q$4),0) -> 5025.2323 | V5: =IFERROR((H5/$Q$4),0) -> 6330.1592 | W5: =IFERROR((I5/$Q$4),0) -> 4227.3974 | X5: =IFERROR((J5/$Q$4),0) -> 298.34503 | Y5: =IFERROR((K5/$Q$4),0) -> 0 | ... AB5: =IFERROR((N5/$Q$4),0) -> 0 | AC5: =SUM(R5:AB5) -> 35651.336
A6: =SUMIF(#REF!,B6,#REF!) -> #REF! | B6: CAL | C6: CALZADO | D6: 0 | E6: 86862897 | F6: 75990500 | G6: 166709501 | H6: 157858819 | I6: 160555133 | J6: 302997469 | K6: 0 | L6: 235406213 | M6: 94633662 | N6: 312262688 | O6: =SUM(E6:N6) -> 1593276882 | R6: =IFERROR((D6/$Q$4),0) -> 0 | S6: =IFERROR((E6/$Q$4),0) -> 105234.77 | T6: =IFERROR((F6/$Q$4),0) -> 92062.811 | U6: =IFERROR((G6/$Q$4),0) -> 201969.26 | V6: =IFERROR((H6/$Q$4),0) -> 191246.63 | W6: =IFERROR((I6/$Q$4),0) -> 194513.22 | X6: =IFERROR((J6/$Q$4),0) -> 367082.71 | Y6: =IFERROR((K6/$Q$4),0) -> 0 | ... AB6: =IFERROR((N6/$Q$4),0) -> 378307.56 | AC6: =SUM(R6:AB6) -> 1930261.7
A7: =SUMIF(#REF!,B7,#REF!) -> #REF! | B7: 3102101 | C7: COSTO DE VENTAS | D7: 0 | E7: -41466377 | F7: -35801636 | G7: -77820870 | H7: -73786688 | I7: -72355485 | J7: -142815023 | K7: 0 | L7: -109503037 | M7: -43988496 | N7: -241355672 | O7: =SUM(D7:N7) -> -838893284 | P7: -1007913 | Q7: =+O7/P7 -> 832.30724 | R7: =IFERROR((D7/$Q$7),0) -> 0 | S7: =IFERROR((E7/$Q$7),0) -> -49820.998 | T7: =IFERROR((F7/$Q$7),0) -> -43014.928 | U7: =IFERROR((G7/$Q$7),0) -> -93500.172 | V7: =IFERROR((H7/$Q$7),0) -> -88653.186 | W7: =IFERROR((I7/$Q$7),0) -> -86933.625 | X7: =IFERROR((J7/$Q$7),0) -> -171589.31 | Y7: =IFERROR((K7/$Q$7),0) -> 0 | ... AB7: =IFERROR((N7/$Q$7),0) -> -289983.87 | AC7: =SUM(R7:AB7) -> -1007913 | AD7: =+AC7 -> -1007913
B8: Resultado por Centro de Beneficio | D8: =SUM(D4:D7) -> 0 | E8: =+E4+E7 -> 48545842 | F8: =+F4+F7 -> 42380504 | G8: =+G4+G7 -> 93036559 | H8: =+H4+H7 -> 89297172 | I8: =+I4+I7 -> 91689027 | J8: =+J4+J7 -> 160428706 | L8: =+L4+L7 -> 134199351 | M8: =+M4+M7 -> 53326752 | N8: =+N4+N7 -> 70907016 | O8: =+O4+O7 -> 783810929 | P8: =+P4+P7 -> 958000 | R8: =SUM(R5:R7) -> 0 | S8: =SUM(S5:S7) -> 59229.185 | T8: =SUM(T5:T7) -> 51703.064 | U8: =SUM(U5:U7) -> 113494.32 | V8: =SUM(V5:V7) -> 108923.6 | W8: =SUM(W5:W7) -> 111806.99 | X8: =SUM(X5:X7) -> 195791.75 | Z8: =SUM(Z5:Z7) -> 163680.83 | AA8: =SUM(AA5:AA7) -> 65046.562 | AB8: =SUM(AB5:AB7) -> 88323.696 | AC8: =SUM(AC5:AC7) -> 958000 | AD8: =SUM(AD4:AD7) -> 958000
D10: C89004120 | E10: C89004510 | F10: C89004520 | G10: C89004530 | H10: C89004540 | I10: C89004550 | J10: C89004560 | K10: C89005070 | R10: C89004120 | S10: C89004510 | T10: C89004520 | U10: C89004530 | V10: C89004540 | W10: C89004550 | X10: C89004560 | Y10: C89005070 | Z10: C89004580 | AA10: C89004590 | AB10: C89004570
B11: N° CUENTA | C11: NOMBRE CUENTA | D11: CEDIS CHILE | E11: DOMINICOS | F11: MAIPU | G11: EGAÑA | H11: VESPUCIO | I11: TREBOL | J11: ONLINE | K11: ADMINISTRACION | L11: COSTANERA CENTER | M11: FLORIDA CENTER | N11: DEPARTAMENTALES | O11: TOTAL | R11: CEDIS CHILE | S11: DOMINICOS | T11: MAIPU | U11: EGAÑA | V11: VESPUCIO | W11: TREBOL | X11: ONLINE | Y11: ADMINISTRACION | Z11: COSTANERA CENTER | AA11: FLORIDA CENTER | AB11: DEPARTAMENTALES | AC11: TOTAL
AD12: =-AD8 -> -958000
A13: =SUMIF('Balanza ok'!D:D,B13,'Balanza ok'!B:B) -> 0 | B13: 3102102 | C13: COSTOS OPERATIVOS - FLETES INTERNOS | D13: 14750000 | I13: 7240993 | K13: 0 | O13: =SUM(D13:N13) -> 21990993 | P13: 26805.1 | Q13: =+O13/P13 -> 820.40332 | R13: =IFERROR((D13/$Q13),0) -> 17978.962 | S13: =IFERROR((E13/$Q13),0) -> 0 | T13: =IFERROR((F13/$Q13),0) -> 0 | U13: =IFERROR((G13/$Q13),0) -> 0 | V13: =IFERROR((H13/$Q13),0) -> 0 | W13: =IFERROR((I13/$Q13),0) -> 8826.1381 | X13: =IFERROR((J13/$Q13),0) -> 0 | Y13: =IFERROR((K13/$Q13),0) -> 0 | ... AB13: =IFERROR((N13/$Q13),0) -> 0 | AC13: =SUM(R13:AB13) -> 26805.1 | AD13: =+AC13 -> 26805.1 | AE13: =+P13-AC13 -> 0
A14: =SUMIF('Balanza ok'!D:D,B14,'Balanza ok'!B:B) -> 0 | B14: 3102104 | C14: COMISIÓN - CANAL DIGITAL | J14: 50435353 | K14: 0 | O14: =SUM(D14:N14) -> 50435353 | P14: 61172.26 | Q14: =+O14/P14 -> 824.48079 | R14: =IFERROR((D14/$Q14),0) -> 0 | S14: =IFERROR((E14/$Q14),0) -> 0 | T14: =IFERROR((F14/$Q14),0) -> 0 | U14: =IFERROR((G14/$Q14),0) -> 0 | V14: =IFERROR((H14/$Q14),0) -> 0 | W14: =IFERROR((I14/$Q14),0) -> 0 | X14: =IFERROR((J14/$Q14),0) -> 61172.26 | Y14: =IFERROR((K14/$Q14),0) -> 0 | ... AB14: =IFERROR((N14/$Q14),0) -> 0 | AC14: =SUM(R14:AB14) -> 61172.26 | AD14: =+AC14 -> 61172.26 | AE14: =+P14-AC14 -> 0
A15: =SUMIF('Balanza ok'!D:D,B15,'Balanza ok'!B:B) -> 0 | B15: 3102105 | C15: FLETES - CANAL DIGITAL | J15: 5256100 | K15: 0 | O15: =SUM(D15:N15) -> 5256100 | P15: 6200.61 | Q15: =+O15/P15 -> 847.67466 | R15: =IFERROR((D15/$Q15),0) -> 0 | S15: =IFERROR((E15/$Q15),0) -> 0 | T15: =IFERROR((F15/$Q15),0) -> 0 | U15: =IFERROR((G15/$Q15),0) -> 0 | V15: =IFERROR((H15/$Q15),0) -> 0 | W15: =IFERROR((I15/$Q15),0) -> 0 | X15: =IFERROR((J15/$Q15),0) -> 6200.61 | Y15: =IFERROR((K15/$Q15),0) -> 0 | ... AB15: =IFERROR((N15/$Q15),0) -> 0 | AC15: =SUM(R15:AB15) -> 6200.61 | AD15: =+AC15 -> 6200.61 | AE15: =+P15-AC15 -> 0
A16: =SUMIF('Balanza ok'!D:D,B16,'Balanza ok'!B:B) -> 0 | B16: 3102108 | C16: SERVICIOS - CANAL DIGITAL | J16: 13510894 | K16: 0 | O16: =SUM(D16:N16) -> 13510894 | P16: 16661.58 | Q16: =+O16/P16 -> 810.90113 | R16: =IFERROR((D16/$Q16),0) -> 0 | S16: =IFERROR((E16/$Q16),0) -> 0 | T16: =IFERROR((F16/$Q16),0) -> 0 | U16: =IFERROR((G16/$Q16),0) -> 0 | V16: =IFERROR((H16/$Q16),0) -> 0 | W16: =IFERROR((I16/$Q16),0) -> 0 | X16: =IFERROR((J16/$Q16),0) -> 16661.58 | Y16: =IFERROR((K16/$Q16),0) -> 0 | ... AB16: =IFERROR((N16/$Q16),0) -> 0 | AC16: =SUM(R16:AB16) -> 16661.58 | AD16: =+AC16 -> 16661.58 | AE16: =+P16-AC16 -> 0
A17: =SUMIF('Balanza ok'!D:D,B17,'Balanza ok'!B:B) -> 0 | B17: 3105101 | C17: REMUNERACIONES | D17: 45226534 | E17: 6559687 | F17: 5605358 | G17: 7085434 | H17: 8476247 | I17: 6443083 | J17: 8432865 | K17: 53095272 | L17: 10439407 | M17: 4552986 | O17: =SUM(D17:N17) -> 155916873 | P17: 188377.53 | Q17: =+O17/P17 -> 827.68297 | R17: =IFERROR((D17/$Q17),0) -> 54642.34 | S17: =IFERROR((E17/$Q17),0) -> 7925.3618 | T17: =IFERROR((F17/$Q17),0) -> 6772.3491 | U17: =IFERROR((G17/$Q17),0) -> 8560.5652 | V17: =IFERROR((H17/$Q17),0) -> 10240.934 | W17: =IFERROR((I17/$Q17),0) -> 7784.4818 | X17: =IFERROR((J17/$Q17),0) -> 10188.521 | Y17: =IFERROR((K17/$Q17),0) -> 64149.287 | ... AB17: =IFERROR((N17/$Q17),0) -> 0 | AC17: =SUM(R17:AB17) -> 188377.53 | AD17: =+AC17 -> 188377.53 | AE17: =+P17-AC17 -> 0
A18: =SUMIF('Balanza ok'!D:D,B18,'Balanza ok'!B:B) -> 0 | B18: 3105102 | C18: BONOS | K18: -1289336 | O18: =SUM(D18:N18) -> -1289336 | P18: -1597.29 | Q18: =+O18/P18 -> 807.2022 | R18: =IFERROR((D18/$Q18),0) -> 0 | S18: =IFERROR((E18/$Q18),0) -> 0 | T18: =IFERROR((F18/$Q18),0) -> 0 | U18: =IFERROR((G18/$Q18),0) -> 0 | V18: =IFERROR((H18/$Q18),0) -> 0 | W18: =IFERROR((I18/$Q18),0) -> 0 | X18: =IFERROR((J18/$Q18),0) -> 0 | Y18: =IFERROR((K18/$Q18),0) -> -1597.29 | ... AB18: =IFERROR((N18/$Q18),0) -> 0 | AC18: =SUM(R18:AB18) -> -1597.29 | AD18: =+AC18 -> -1597.29 | AE18: =+P18-AC18 -> 0
A19: =SUMIF('Balanza ok'!D:D,B19,'Balanza ok'!B:B) -> 0 | B19: 3105103 | C19: SEGURO DE CESANTIA | D19: 1210877 | E19: 286419 | F19: 230096 | G19: 320327 | H19: 412420 | I19: 304081 | J19: 236208 | K19: 850108 | L19: 516934 | M19: 225940 | O19: =SUM(D19:N19) -> 4593410 | P19: 5539.72 | Q19: =+O19/P19 -> 829.17729 | R19: =IFERROR((D19/$Q19),0) -> 1460.3355 | S19: =IFERROR((E19/$Q19),0) -> 345.42553 | T19: =IFERROR((F19/$Q19),0) -> 277.49916 | U19: =IFERROR((G19/$Q19),0) -> 386.31907 | V19: =IFERROR((H19/$Q19),0) -> 497.38458 | W19: =IFERROR((I19/$Q19),0) -> 366.72616 | X19: =IFERROR((J19/$Q19),0) -> 284.87032 | Y19: =IFERROR((K19/$Q19),0) -> 1025.2427 | ... AB19: =IFERROR((N19/$Q19),0) -> 0 | AC19: =SUM(R19:AB19) -> 5539.72 | AD19: =+AC19 -> 5539.72 | AE19: =+P19-AC19 -> 0
A20: =SUMIF('Balanza ok'!D:D,B20,'Balanza ok'!B:B) -> 0 | B20: 3105104 | C20: GRATIFICACION | D20: 4110402 | E20: 2095660 | F20: 1748182 | G20: 2207307 | H20: 2566056 | I20: 2242453 | J20: 1409170 | K20: 3045835 | L20: 3498772 | M20: 1621177 | O20: =SUM(D20:N20) -> 24545014 | P20: 29618.7 | Q20: =+O20/P20 -> 828.69991 | R20: =IFERROR((D20/$Q20),0) -> 4960.0609 | S20: =IFERROR((E20/$Q20),0) -> 2528.8527 | T20: =IFERROR((F20/$Q20),0) -> 2109.5477 | U20: =IFERROR((G20/$Q20),0) -> 2663.5782 | V20: =IFERROR((H20/$Q20),0) -> 3096.484 | W20: =IFERROR((I20/$Q20),0) -> 2705.9892 | X20: =IFERROR((J20/$Q20),0) -> 1700.4587 | Y20: =IFERROR((K20/$Q20),0) -> 3675.4378 | ... AB20: =IFERROR((N20/$Q20),0) -> 0 | AC20: =SUM(R20:AB20) -> 29618.7 | AD20: =+AC20 -> 29618.7 | AE20: =+P20-AC20 -> 0
A21: =SUMIF('Balanza ok'!D:D,B21,'Balanza ok'!B:B) -> 0 | B21: 3105107 | C21: FINIQUITOS | K21: 1456695 | O21: =SUM(D21:N21) -> 1456695 | P21: 1776.12 | Q21: =+O21/P21 -> 820.15573 | R21: =IFERROR((D21/$Q21),0) -> 0 | S21: =IFERROR((E21/$Q21),0) -> 0 | T21: =IFERROR((F21/$Q21),0) -> 0 | U21: =IFERROR((G21/$Q21),0) -> 0 | V21: =IFERROR((H21/$Q21),0) -> 0 | W21: =IFERROR((I21/$Q21),0) -> 0 | X21: =IFERROR((J21/$Q21),0) -> 0 | Y21: =IFERROR((K21/$Q21),0) -> 1776.12 | ... AB21: =IFERROR((N21/$Q21),0) -> 0 | AC21: =SUM(R21:AB21) -> 1776.12 | AD21: =+AC21 -> 1776.12 | AE21: =+P21-AC21 -> 0
A22: =SUMIF('Balanza ok'!D:D,B22,'Balanza ok'!B:B) -> 0 | B22: 3105108 | C22: ASIGNACION COLACION | D22: 1845001 | E22: 651733 | F22: 417000 | G22: 570500 | H22: 787000 | I22: 820667 | J22: 500000 | K22: 1208000 | L22: 1131100 | M22: 468500 | O22: =SUM(D22:N22) -> 8399501 | P22: 10140.41 | Q22: =+O22/P22 -> 828.31966 | R22: =IFERROR((D22/$Q22),0) -> 2227.4022 | S22: =IFERROR((E22/$Q22),0) -> 786.81339 | T22: =IFERROR((F22/$Q22),0) -> 503.42883 | U22: =IFERROR((G22/$Q22),0) -> 688.74376 | V22: =IFERROR((H22/$Q22),0) -> 950.11628 | W22: =IFERROR((I22/$Q22),0) -> 990.76122 | X22: =IFERROR((J22/$Q22),0) -> 603.63169 | Y22: =IFERROR((K22/$Q22),0) -> 1458.3742 | ... AB22: =IFERROR((N22/$Q22),0) -> 0 | AC22: =SUM(R22:AB22) -> 10140.41 | AD22: =+AC22 -> 10140.41 | AE22: =+P22-AC22 -> 0
A23: =SUMIF('Balanza ok'!D:D,B23,'Balanza ok'!B:B) -> 0 | B23: 3105109 | C23: ASIGNACION MOVILIZACION | D23: 1845001 | E23: 651733 | F23: 417000 | G23: 570500 | H23: 787000 | I23: 820667 | J23: 500000 | K23: 1208000 | L23: 1131100 | M23: 468500 | O23: =SUM(D23:N23) -> 8399501 | P23: 10140.41 | Q23: =+O23/P23 -> 828.31966 | R23: =IFERROR((D23/$Q23),0) -> 2227.4022 | S23: =IFERROR((E23/$Q23),0) -> 786.81339 | T23: =IFERROR((F23/$Q23),0) -> 503.42883 | U23: =IFERROR((G23/$Q23),0) -> 688.74376 | V23: =IFERROR((H23/$Q23),0) -> 950.11628 | W23: =IFERROR((I23/$Q23),0) -> 990.76122 | X23: =IFERROR((J23/$Q23),0) -> 603.63169 | Y23: =IFERROR((K23/$Q23),0) -> 1458.3742 | ... AB23: =IFERROR((N23/$Q23),0) -> 0 | AC23: =SUM(R23:AB23) -> 10140.41 | AD23: =+AC23 -> 10140.41 | AE23: =+P23-AC23 -> 0
A24: =SUMIF('Balanza ok'!D:D,B24,'Balanza ok'!B:B) -> 0 | B24: 3105110 | C24: MUTUAL DE SEGURIDAD | D24: 409920 | E24: 102105 | F24: 82528 | G24: 117060 | H24: 137500 | I24: 115675 | J24: 91531 | K24: 253847 | L24: 196492 | M24: 78642 | O24: =SUM(D24:N24) -> 1585300 | P24: 1910.26 | Q24: =+O24/P24 -> 829.88703 | R24: =IFERROR((D24/$Q24),0) -> 493.94675 | S24: =IFERROR((E24/$Q24),0) -> 123.03482 | T24: =IFERROR((F24/$Q24),0) -> 99.44486 | U24: =IFERROR((G24/$Q24),0) -> 141.05534 | V24: =IFERROR((H24/$Q24),0) -> 165.6852 | W24: =IFERROR((I24/$Q24),0) -> 139.38644 | X24: =IFERROR((J24/$Q24),0) -> 110.29332 | Y24: =IFERROR((K24/$Q24),0) -> 305.88139 | ... AB24: =IFERROR((N24/$Q24),0) -> 0 | AC24: =SUM(R24:AB24) -> 1910.26 | AD24: =+AC24 -> 1910.26 | AE24: =+P24-AC24 -> 0
A25: =SUMIF('Balanza ok'!D:D,B25,'Balanza ok'!B:B) -> 0 | B25: 3105111 | C25: SEGURO INVALIDEZ (AFP) | D25: 824422 | E25: 203645 | F25: 164671 | G25: 233250 | H25: 300434 | I25: 231573 | J25: 182486 | K25: 506379 | L25: 391934 | M25: 156733 | O25: =SUM(D25:N25) -> 3195527 | P25: 3849.15 | Q25: =+O25/P25 -> 830.1903 | R25: =IFERROR((D25/$Q25),0) -> 993.05183 | S25: =IFERROR((E25/$Q25),0) -> 245.29918 | T25: =IFERROR((F25/$Q25),0) -> 198.35332 | U25: =IFERROR((G25/$Q25),0) -> 280.95968 | V25: =IFERROR((H25/$Q25),0) -> 361.8857 | W25: =IFERROR((I25/$Q25),0) -> 278.93966 | X25: =IFERROR((J25/$Q25),0) -> 219.81225 | Y25: =IFERROR((K25/$Q25),0) -> 609.95533 | ... AB25: =IFERROR((N25/$Q25),0) -> 0 | AC25: =SUM(R25:AB25) -> 3849.15 | AD25: =+AC25 -> 3849.15 | AE25: =+P25-AC25 -> 0
A26: =SUMIF('Balanza ok'!D:D,B26,'Balanza ok'!B:B) -> 0 | B26: 3105112 | C26: GASTOS DE CAPACITACION | K26: 214500 | O26: =SUM(D26:N26) -> 214500 | P26: 246.66 | Q26: =+O26/P26 -> 869.6181 | R26: =IFERROR((D26/$Q26),0) -> 0 | S26: =IFERROR((E26/$Q26),0) -> 0 | T26: =IFERROR((F26/$Q26),0) -> 0 | U26: =IFERROR((G26/$Q26),0) -> 0 | V26: =IFERROR((H26/$Q26),0) -> 0 | W26: =IFERROR((I26/$Q26),0) -> 0 | X26: =IFERROR((J26/$Q26),0) -> 0 | Y26: =IFERROR((K26/$Q26),0) -> 246.66 | ... AB26: =IFERROR((N26/$Q26),0) -> 0 | AC26: =SUM(R26:AB26) -> 246.66 | AD26: =+AC26 -> 246.66 | AE26: =+P26-AC26 -> 0
A27: =SUMIF('Balanza ok'!D:D,B27,'Balanza ok'!B:B) -> 0 | B27: 3105116 | C27: UNIFORMES | E27: 511077 | F27: 500160 | G27: 584984 | H27: 543832 | I27: 469076 | K27: 0 | L27: 584161 | M27: 501816 | O27: =SUM(D27:N27) -> 3695106 | P27: 4401.53 | Q27: =+O27/P27 -> 839.5049 | R27: =IFERROR((D27/$Q27),0) -> 0 | S27: =IFERROR((E27/$Q27),0) -> 608.78382 | T27: =IFERROR((F27/$Q27),0) -> 595.77973 | U27: =IFERROR((G27/$Q27),0) -> 696.82023 | V27: =IFERROR((H27/$Q27),0) -> 647.80086 | W27: =IFERROR((I27/$Q27),0) -> 558.75314 | X27: =IFERROR((J27/$Q27),0) -> 0 | Y27: =IFERROR((K27/$Q27),0) -> 0 | ... AB27: =IFERROR((N27/$Q27),0) -> 0 | AC27: =SUM(R27:AB27) -> 4401.53 | AD27: =+AC27 -> 4401.53 | AE27: =+P27-AC27 -> 0
A28: =SUMIF('Balanza ok'!D:D,B28,'Balanza ok'!B:B) -> 0 | B28: 3105118 | C28: ATENCIONES AL PERSONAL | K28: 0 | O28: =SUM(D28:N28) -> 0 | P28: 0 | Q28: 0 | R28: =IFERROR((D28/$Q28),0) -> 0 | S28: =IFERROR((E28/$Q28),0) -> 0 | T28: =IFERROR((F28/$Q28),0) -> 0 | U28: =IFERROR((G28/$Q28),0) -> 0 | V28: =IFERROR((H28/$Q28),0) -> 0 | W28: =IFERROR((I28/$Q28),0) -> 0 | X28: =IFERROR((J28/$Q28),0) -> 0 | Y28: =IFERROR((K28/$Q28),0) -> 0 | ... AB28: =IFERROR((N28/$Q28),0) -> 0 | AC28: =SUM(R28:AB28) -> 0 | AD28: =+AC28 -> 0 | AE28: =+P28-AC28 -> 0
A29: =SUMIF('Balanza ok'!D:D,B29,'Balanza ok'!B:B) -> 0 | B29: 3105119 | C29: VACACIONES | E29: 187276 | G29: 13260 | H29: 172696 | I29: 262119 | K29: 5189 | L29: 564092 | O29: =SUM(D29:N29) -> 1204632 | P29: 1495.67 | Q29: =+O29/P29 -> 805.41296 | R29: =IFERROR((D29/$Q29),0) -> 0 | S29: =IFERROR((E29/$Q29),0) -> 232.52171 | T29: =IFERROR((F29/$Q29),0) -> 0 | U29: =IFERROR((G29/$Q29),0) -> 16.463604 | V29: =IFERROR((H29/$Q29),0) -> 214.4192 | W29: =IFERROR((I29/$Q29),0) -> 325.44671 | X29: =IFERROR((J29/$Q29),0) -> 0 | Y29: =IFERROR((K29/$Q29),0) -> 6.4426577 | ... AB29: =IFERROR((N29/$Q29),0) -> 0 | AC29: =SUM(R29:AB29) -> 1495.67 | AD29: =+AC29 -> 1495.67 | AE29: =+P29-AC29 -> 0
A30: =SUMIF('Balanza ok'!D:D,B30,'Balanza ok'!B:B) -> 0 | B30: 3105121 | C30: SEMANA CORRIDA | E30: 400887 | F30: 279954 | G30: 605263 | H30: 691743 | I30: 649220 | K30: 0 | L30: 1258935 | M30: 420069 | O30: =SUM(D30:N30) -> 4306071 | P30: 5155.56 | Q30: =+O30/P30 -> 835.22857 | R30: =IFERROR((D30/$Q30),0) -> 0 | S30: =IFERROR((E30/$Q30),0) -> 479.97281 | T30: =IFERROR((F30/$Q30),0) -> 335.1825 | U30: =IFERROR((G30/$Q30),0) -> 724.6675 | V30: =IFERROR((H30/$Q30),0) -> 828.20802 | W30: =IFERROR((I30/$Q30),0) -> 777.29621 | X30: =IFERROR((J30/$Q30),0) -> 0 | Y30: =IFERROR((K30/$Q30),0) -> 0 | ... AB30: =IFERROR((N30/$Q30),0) -> 0 | AC30: =SUM(R30:AB30) -> 5155.56 | AD30: =+AC30 -> 5155.56 | AE30: =+P30-AC30 -> 0
A31: =SUMIF('Balanza ok'!D:D,B31,'Balanza ok'!B:B) -> 0 | B31: 3105122 | C31: COMISION POR VENTA | E31: 1735539 | F31: 1240049 | G31: 2675854 | H31: 2955810 | I31: 2839497 | K31: 0 | L31: 5366997 | M31: 1862028 | O31: =SUM(D31:N31) -> 18675774 | P31: 22508.3 | Q31: =+O31/P31 -> 829.72832 | R31: =IFERROR((D31/$Q31),0) -> 0 | S31: =IFERROR((E31/$Q31),0) -> 2091.6955 | T31: =IFERROR((F31/$Q31),0) -> 1494.5241 | U31: =IFERROR((G31/$Q31),0) -> 3224.9761 | V31: =IFERROR((H31/$Q31),0) -> 3562.3829 | W31: =IFERROR((I31/$Q31),0) -> 3422.2009 | X31: =IFERROR((J31/$Q31),0) -> 0 | Y31: =IFERROR((K31/$Q31),0) -> 0 | ... AB31: =IFERROR((N31/$Q31),0) -> 0 | AC31: =SUM(R31:AB31) -> 22508.3 | AD31: =+AC31 -> 22508.3 | AE31: =+P31-AC31 -> 0
A32: =SUMIF('Balanza ok'!D:D,B32,'Balanza ok'!B:B) -> 0 | B32: 3105123 | C32: PROMOTORES | K32: 0 | N32: 1291619 | O32: =SUM(D32:N32) -> 1291619 | P32: 1594.36 | Q32: =+O32/P32 -> 810.11754 | R32: =IFERROR((D32/$Q32),0) -> 0 | S32: =IFERROR((E32/$Q32),0) -> 0 | T32: =IFERROR((F32/$Q32),0) -> 0 | U32: =IFERROR((G32/$Q32),0) -> 0 | V32: =IFERROR((H32/$Q32),0) -> 0 | W32: =IFERROR((I32/$Q32),0) -> 0 | X32: =IFERROR((J32/$Q32),0) -> 0 | Y32: =IFERROR((K32/$Q32),0) -> 0 | ... AB32: =IFERROR((N32/$Q32),0) -> 1594.36 | AC32: =SUM(R32:AB32) -> 1594.36 | AD32: =+AC32 -> 1594.36 | AE32: =+P32-AC32 -> 0
A33: =SUMIF('Balanza ok'!D:D,B33,'Balanza ok'!B:B) -> 0 | B33: 3105124 | C33: REMUNERACIONES EXTERNAS | E33: 4851630 | F33: 10993789 | G33: 8001453 | H33: 6584515 | I33: 6857751 | K33: 3516911 | L33: 2741442 | M33: 4460916 | O33: =SUM(D33:N33) -> 48008407 | P33: 57254.49 | Q33: =+O33/P33 -> 838.50903 | R33: =IFERROR((D33/$Q33),0) -> 0 | S33: =IFERROR((E33/$Q33),0) -> 5786.02 | T33: =IFERROR((F33/$Q33),0) -> 13111.116 | U33: =IFERROR((G33/$Q33),0) -> 9542.4768 | V33: =IFERROR((H33/$Q33),0) -> 7852.6465 | W33: =IFERROR((I33/$Q33),0) -> 8178.5058 | X33: =IFERROR((J33/$Q33),0) -> 0 | Y33: =IFERROR((K33/$Q33),0) -> 4194.2434 | ... AB33: =IFERROR((N33/$Q33),0) -> 0 | AC33: =SUM(R33:AB33) -> 57254.49 | AD33: =+AC33 -> 57254.49 | AE33: =+P33-AC33 -> 0
A34: =SUMIF('Balanza ok'!D:D,B34,'Balanza ok'!B:B) -> 0 | B34: 3105125 | C34: RE GRATIFICACION | E34: 238528 | F34: 626507 | G34: 423194 | H34: 298819 | I34: 369942 | K34: 160203 | L34: 131827 | M34: 260340 | O34: =SUM(D34:N34) -> 2509360 | P34: 2727.65 | Q34: =+O34/P34 -> 919.9714 | R34: =IFERROR((D34/$Q34),0) -> 0 | S34: =IFERROR((E34/$Q34),0) -> 259.27762 | T34: =IFERROR((F34/$Q34),0) -> 681.00704 | U34: =IFERROR((G34/$Q34),0) -> 460.00778 | V34: =IFERROR((H34/$Q34),0) -> 324.81336 | W34: =IFERROR((I34/$Q34),0) -> 402.12337 | X34: =IFERROR((J34/$Q34),0) -> 0 | Y34: =IFERROR((K34/$Q34),0) -> 174.13911 | ... AB34: =IFERROR((N34/$Q34),0) -> 0 | AC34: =SUM(R34:AB34) -> 2727.65 | AD34: =+AC34 -> 2727.65 | AE34: =+P34-AC34 -> 0
A35: =SUMIF('Balanza ok'!D:D,B35,'Balanza ok'!B:B) -> 0 | B35: 3105126 | C35: RE HORAS EXTRAS | E35: 53200 | K35: 0 | O35: =SUM(D35:N35) -> 53200 | P35: 57.83 | Q35: =+O35/P35 -> 919.93775 | R35: =IFERROR((D35/$Q35),0) -> 0 | S35: =IFERROR((E35/$Q35),0) -> 57.83 | T35: =IFERROR((F35/$Q35),0) -> 0 | U35: =IFERROR((G35/$Q35),0) -> 0 | V35: =IFERROR((H35/$Q35),0) -> 0 | W35: =IFERROR((I35/$Q35),0) -> 0 | X35: =IFERROR((J35/$Q35),0) -> 0 | Y35: =IFERROR((K35/$Q35),0) -> 0 | ... AB35: =IFERROR((N35/$Q35),0) -> 0 | AC35: =SUM(R35:AB35) -> 57.83 | AD35: =+AC35 -> 57.83 | AE35: =+P35-AC35 -> 0
A36: =SUMIF('Balanza ok'!D:D,B36,'Balanza ok'!B:B) -> 0 | B36: 3105127 | C36: RE COMISION POR VENTA | E36: 111328 | F36: 306654 | G36: 427697 | H36: 220693 | I36: 276508 | K36: 0 | L36: 165746 | M36: 151308 | O36: =SUM(D36:N36) -> 1659934 | P36: 1804.32 | Q36: =+O36/P36 -> 919.97761 | R36: =IFERROR((D36/$Q36),0) -> 0 | S36: =IFERROR((E36/$Q36),0) -> 121.01164 | T36: =IFERROR((F36/$Q36),0) -> 333.32768 | U36: =IFERROR((G36/$Q36),0) -> 464.89936 | V36: =IFERROR((H36/$Q36),0) -> 239.88953 | W36: =IFERROR((I36/$Q36),0) -> 300.55949 | X36: =IFERROR((J36/$Q36),0) -> 0 | Y36: =IFERROR((K36/$Q36),0) -> 0 | ... AB36: =IFERROR((N36/$Q36),0) -> 0 | AC36: =SUM(R36:AB36) -> 1804.32 | AD36: =+AC36 -> 1804.32 | AE36: =+P36-AC36 -> 0
A37: =SUMIF('Balanza ok'!D:D,B37,'Balanza ok'!B:B) -> 0 | B37: 3105128 | C37: RE BONOS | F37: 37500 | G37: 184473 | H37: 48603 | I37: 75000 | K37: 0 | L37: 15255 | O37: =SUM(D37:N37) -> 360831 | P37: 392.21 | Q37: =+O37/P37 -> 919.99439 | R37: =IFERROR((D37/$Q37),0) -> 0 | S37: =IFERROR((E37/$Q37),0) -> 0 | T37: =IFERROR((F37/$Q37),0) -> 40.761118 | U37: =IFERROR((G37/$Q37),0) -> 200.51535 | V37: =IFERROR((H37/$Q37),0) -> 52.82967 | W37: =IFERROR((I37/$Q37),0) -> 81.522236 | X37: =IFERROR((J37/$Q37),0) -> 0 | Y37: =IFERROR((K37/$Q37),0) -> 0 | ... AB37: =IFERROR((N37/$Q37),0) -> 0 | AC37: =SUM(R37:AB37) -> 392.21 | AD37: =+AC37 -> 392.21 | AE37: =+P37-AC37 -> 0
A38: =SUMIF('Balanza ok'!D:D,B38,'Balanza ok'!B:B) -> 0 | B38: 3105129 | C38: RE SEMANA CORRIDA | E38: 35290 | F38: 91998 | G38: 114610 | H38: 66208 | I38: 82953 | K38: 0 | L38: 26217 | M38: 45392 | O38: =SUM(D38:N38) -> 462668 | P38: 502.92 | Q38: =+O38/P38 -> 919.96341 | R38: =IFERROR((D38/$Q38),0) -> 0 | S38: =IFERROR((E38/$Q38),0) -> 38.360221 | T38: =IFERROR((F38/$Q38),0) -> 100.0018 | U38: =IFERROR((G38/$Q38),0) -> 124.58104 | V38: =IFERROR((H38/$Q38),0) -> 71.968079 | W38: =IFERROR((I38/$Q38),0) -> 90.16989 | X38: =IFERROR((J38/$Q38),0) -> 0 | Y38: =IFERROR((K38/$Q38),0) -> 0 | ... AB38: =IFERROR((N38/$Q38),0) -> 0 | AC38: =SUM(R38:AB38) -> 502.92 | AD38: =+AC38 -> 502.92 | AE38: =+P38-AC38 -> 0
A39: =SUMIF('Balanza ok'!D:D,B39,'Balanza ok'!B:B) -> 0 | B39: 3105130 | C39: RE ASIGNACION COLACION | E39: 51000 | F39: 96700 | G39: 73500 | H39: 51000 | I39: 124000 | K39: 54667 | L39: 17100 | M39: 30000 | O39: =SUM(D39:N39) -> 497967 | P39: 541.29 | Q39: =+O39/P39 -> 919.96342 | R39: =IFERROR((D39/$Q39),0) -> 0 | S39: =IFERROR((E39/$Q39),0) -> 55.436987 | T39: =IFERROR((F39/$Q39),0) -> 105.11287 | U39: =IFERROR((G39/$Q39),0) -> 79.894481 | V39: =IFERROR((H39/$Q39),0) -> 55.436987 | W39: =IFERROR((I39/$Q39),0) -> 134.78797 | X39: =IFERROR((J39/$Q39),0) -> 0 | Y39: =IFERROR((K39/$Q39),0) -> 59.423015 | ... AB39: =IFERROR((N39/$Q39),0) -> 0 | AC39: =SUM(R39:AB39) -> 541.29 | AD39: =+AC39 -> 541.29 | AE39: =+P39-AC39 -> 0
A40: =SUMIF('Balanza ok'!D:D,B40,'Balanza ok'!B:B) -> 0 | B40: 3105131 | C40: RE ASIGNACION MOVILIZACION | E40: 51000 | F40: 96700 | G40: 73500 | H40: 51000 | I40: 124000 | K40: 54667 | L40: 17100 | M40: 30000 | O40: =SUM(D40:N40) -> 497967 | P40: 541.29 | Q40: =+O40/P40 -> 919.96342 | R40: =IFERROR((D40/$Q40),0) -> 0 | S40: =IFERROR((E40/$Q40),0) -> 55.436987 | T40: =IFERROR((F40/$Q40),0) -> 105.11287 | U40: =IFERROR((G40/$Q40),0) -> 79.894481 | V40: =IFERROR((H40/$Q40),0) -> 55.436987 | W40: =IFERROR((I40/$Q40),0) -> 134.78797 | X40: =IFERROR((J40/$Q40),0) -> 0 | Y40: =IFERROR((K40/$Q40),0) -> 59.423015 | ... AB40: =IFERROR((N40/$Q40),0) -> 0 | AC40: =SUM(R40:AB40) -> 541.29 | AD40: =+AC40 -> 541.29 | AE40: =+P40-AC40 -> 0
A41: =SUMIF('Balanza ok'!D:D,B41,'Balanza ok'!B:B) -> 0 | B41: 3105132 | C41: RE SEGURO DE CESANTIA | E41: 36980 | F41: 84561 | G41: 72054 | H41: 40318 | I41: 45281 | K41: 19225 | L41: 19774 | M41: 39052 | O41: =SUM(D41:N41) -> 357245 | P41: 388.33 | Q41: =+O41/P41 -> 919.9521 | R41: =IFERROR((D41/$Q41),0) -> 0 | S41: =IFERROR((E41/$Q41),0) -> 40.197745 | T41: =IFERROR((F41/$Q41),0) -> 91.918916 | U41: =IFERROR((G41/$Q41),0) -> 78.323643 | V41: =IFERROR((H41/$Q41),0) -> 43.826195 | W41: =IFERROR((I41/$Q41),0) -> 49.221041 | X41: =IFERROR((J41/$Q41),0) -> 0 | Y41: =IFERROR((K41/$Q41),0) -> 20.897827 | ... AB41: =IFERROR((N41/$Q41),0) -> 0 | AC41: =SUM(R41:AB41) -> 388.33 | AD41: =+AC41 -> 388.33 | AE41: =+P41-AC41 -> 0
A42: =SUMIF('Balanza ok'!D:D,B42,'Balanza ok'!B:B) -> 0 | B42: 3105133 | C42: RE MUTUAL DE SEGURIDAD | E42: 11735 | F42: 29132 | G42: 21247 | H42: 13895 | I42: 17546 | K42: 7449 | L42: 6130 | M42: 12105 | O42: =SUM(D42:N42) -> 119239 | P42: 129.62 | Q42: =+O42/P42 -> 919.91205 | R42: =IFERROR((D42/$Q42),0) -> 0 | S42: =IFERROR((E42/$Q42),0) -> 12.756654 | T42: =IFERROR((F42/$Q42),0) -> 31.668245 | U42: =IFERROR((G42/$Q42),0) -> 23.096773 | V42: =IFERROR((H42/$Q42),0) -> 15.104705 | W42: =IFERROR((I42/$Q42),0) -> 19.073563 | X42: =IFERROR((J42/$Q42),0) -> 0 | Y42: =IFERROR((K42/$Q42),0) -> 8.0975132 | ... AB42: =IFERROR((N42/$Q42),0) -> 0 | AC42: =SUM(R42:AB42) -> 129.62 | AD42: =+AC42 -> 129.62 | AE42: =+P42-AC42 -> 0
A43: =SUMIF('Balanza ok'!D:D,B43,'Balanza ok'!B:B) -> 0 | B43: 3105134 | C43: RE SEGURO INVALIDEZ (AFP) | E43: 23472 | F43: 58266 | G43: 52686 | H43: 27790 | I43: 35093 | K43: 14899 | L43: 12260 | M43: 24212 | O43: =SUM(D43:N43) -> 248678 | P43: 270.32 | Q43: =+O43/P43 -> 919.93933 | R43: =IFERROR((D43/$Q43),0) -> 0 | S43: =IFERROR((E43/$Q43),0) -> 25.514726 | T43: =IFERROR((F43/$Q43),0) -> 63.336785 | U43: =IFERROR((G43/$Q43),0) -> 57.271168 | V43: =IFERROR((H43/$Q43),0) -> 30.208514 | W43: =IFERROR((I43/$Q43),0) -> 38.147081 | X43: =IFERROR((J43/$Q43),0) -> 0 | Y43: =IFERROR((K43/$Q43),0) -> 16.195633 | ... AB43: =IFERROR((N43/$Q43),0) -> 0 | AC43: =SUM(R43:AB43) -> 270.32 | AD43: =+AC43 -> 270.32 | AE43: =+P43-AC43 -> 0
A44: =SUMIF('Balanza ok'!D:D,B44,'Balanza ok'!B:B) -> 0 | B44: 3105201 | C44: HONORARIOS PROFESIONALES | D44: 5208284 | E44: 35556 | F44: 35556 | G44: 35556 | H44: 35556 | I44: 35556 | J44: 35556 | K44: 1038710 | L44: 35556 | M44: 35552 | O44: =SUM(D44:N44) -> 6531438 | P44: 7895.93 | Q44: =+O44/P44 -> 827.19046 | R44: =IFERROR((D44/$Q44),0) -> 6296.354 | S44: =IFERROR((E44/$Q44),0) -> 42.984055 | T44: =IFERROR((F44/$Q44),0) -> 42.984055 | U44: =IFERROR((G44/$Q44),0) -> 42.984055 | V44: =IFERROR((H44/$Q44),0) -> 42.984055 | W44: =IFERROR((I44/$Q44),0) -> 42.984055 | X44: =IFERROR((J44/$Q44),0) -> 42.984055 | Y44: =IFERROR((K44/$Q44),0) -> 1255.7084 | ... AB44: =IFERROR((N44/$Q44),0) -> 0 | AC44: =SUM(R44:AB44) -> 7895.93 | AD44: =+AC44 -> 7895.93 | AE44: =+P44-AC44 -> 0
A45: =SUMIF('Balanza ok'!D:D,B45,'Balanza ok'!B:B) -> 0 | B45: 3105202 | C45: HONORARIOS PROFESIONALES LEGALES | K45: 947056 | O45: =SUM(D45:N45) -> 947056 | P45: 1158.84 | Q45: =+O45/P45 -> 817.24483 | R45: =IFERROR((D45/$Q45),0) -> 0 | S45: =IFERROR((E45/$Q45),0) -> 0 | T45: =IFERROR((F45/$Q45),0) -> 0 | U45: =IFERROR((G45/$Q45),0) -> 0 | V45: =IFERROR((H45/$Q45),0) -> 0 | W45: =IFERROR((I45/$Q45),0) -> 0 | X45: =IFERROR((J45/$Q45),0) -> 0 | Y45: =IFERROR((K45/$Q45),0) -> 1158.84 | ... AB45: =IFERROR((N45/$Q45),0) -> 0 | AC45: =SUM(R45:AB45) -> 1158.84 | AD45: =+AC45 -> 1158.84 | AE45: =+P45-AC45 -> 0
A46: =SUMIF('Balanza ok'!D:D,B46,'Balanza ok'!B:B) -> 0 | B46: 3105206 | C46: ASESORIA CONTABLE | K46: 8998137 | O46: =SUM(D46:N46) -> 8998137 | P46: 10699.71 | Q46: =+O46/P46 -> 840.97018 | R46: =IFERROR((D46/$Q46),0) -> 0 | S46: =IFERROR((E46/$Q46),0) -> 0 | T46: =IFERROR((F46/$Q46),0) -> 0 | U46: =IFERROR((G46/$Q46),0) -> 0 | V46: =IFERROR((H46/$Q46),0) -> 0 | W46: =IFERROR((I46/$Q46),0) -> 0 | X46: =IFERROR((J46/$Q46),0) -> 0 | Y46: =IFERROR((K46/$Q46),0) -> 10699.71 | ... AB46: =IFERROR((N46/$Q46),0) -> 0 | AC46: =SUM(R46:AB46) -> 10699.71 | AD46: =+AC46 -> 10699.71 | AE46: =+P46-AC46 -> 0
A47: =SUMIF('Balanza ok'!D:D,B47,'Balanza ok'!B:B) -> 0 | B47: 3105209 | C47: HONORARIOS POR ASESORIAS INFORMATICAS | D47: 14377 | E47: 14377 | F47: 14377 | G47: 14377 | H47: 14377 | I47: 14377 | J47: 442932 | K47: 2938921 | L47: 14377 | M47: 14375 | O47: =SUM(D47:N47) -> 3496867 | P47: 4401.48 | Q47: =+O47/P47 -> 794.47527 | R47: =IFERROR((D47/$Q47),0) -> 18.096221 | S47: =IFERROR((E47/$Q47),0) -> 18.096221 | T47: =IFERROR((F47/$Q47),0) -> 18.096221 | U47: =IFERROR((G47/$Q47),0) -> 18.096221 | V47: =IFERROR((H47/$Q47),0) -> 18.096221 | W47: =IFERROR((I47/$Q47),0) -> 18.096221 | X47: =IFERROR((J47/$Q47),0) -> 557.51515 | Y47: =IFERROR((K47/$Q47),0) -> 3699.1976 | ... AB47: =IFERROR((N47/$Q47),0) -> 0 | AC47: =SUM(R47:AB47) -> 4401.48 | AD47: =+AC47 -> 4401.48 | AE47: =+P47-AC47 -> 0
A48: =SUMIF('Balanza ok'!D:D,B48,'Balanza ok'!B:B) -> 0 | B48: 3105210 | C48: HONORARIOS ADMINISTRACIÓN DE PERSONAL | E48: 996778 | F48: 996778 | G48: 996778 | H48: 996778 | I48: 996777 | K48: 1494976 | L48: 996777 | M48: 996780 | O48: =SUM(D48:N48) -> 8472422 | P48: 9934.72 | Q48: =+O48/P48 -> 852.80934 | R48: =IFERROR((D48/$Q48),0) -> 0 | S48: =IFERROR((E48/$Q48),0) -> 1168.8169 | T48: =IFERROR((F48/$Q48),0) -> 1168.8169 | U48: =IFERROR((G48/$Q48),0) -> 1168.8169 | V48: =IFERROR((H48/$Q48),0) -> 1168.8169 | W48: =IFERROR((I48/$Q48),0) -> 1168.8158 | X48: =IFERROR((J48/$Q48),0) -> 0 | Y48: =IFERROR((K48/$Q48),0) -> 1753.0014 | ... AB48: =IFERROR((N48/$Q48),0) -> 0 | AC48: =SUM(R48:AB48) -> 9934.72 | AD48: =+AC48 -> 9934.72 | AE48: =+P48-AC48 -> 0
A49: =SUMIF('Balanza ok'!D:D,B49,'Balanza ok'!B:B) -> 0 | B49: 3105301 | C49: ARRIENDOS | E49: 19978031 | F49: 21281249 | G49: 38353727 | H49: 29385401 | I49: 33732311 | K49: 0 | L49: 57317047 | M49: 27733178 | O49: =SUM(D49:N49) -> 227780944 | P49: 275767.1 | Q49: =+O49/P49 -> 825.99028 | R49: =IFERROR((D49/$Q49),0) -> 0 | S49: =IFERROR((E49/$Q49),0) -> 24186.763 | T49: =IFERROR((F49/$Q49),0) -> 25764.527 | U49: =IFERROR((G49/$Q49),0) -> 46433.63 | V49: =IFERROR((H49/$Q49),0) -> 35575.965 | W49: =IFERROR((I49/$Q49),0) -> 40838.63 | X49: =IFERROR((J49/$Q49),0) -> 0 | Y49: =IFERROR((K49/$Q49),0) -> 0 | ... AB49: =IFERROR((N49/$Q49),0) -> 0 | AC49: =SUM(R49:AB49) -> 275767.1 | AD49: =+AC49 -> 275767.1 | AE49: =+P49-AC49 -> 0
A50: =SUMIF('Balanza ok'!D:D,B50,'Balanza ok'!B:B) -> 0 | B50: 3105302 | C50: ARRIENDO DE BODEGAS | D50: 11217210 | K50: 0 | O50: =SUM(D50:N50) -> 11217210 | P50: 13702.25 | Q50: =+O50/P50 -> 818.64 | R50: =IFERROR((D50/$Q50),0) -> 13702.25 | S50: =IFERROR((E50/$Q50),0) -> 0 | T50: =IFERROR((F50/$Q50),0) -> 0 | U50: =IFERROR((G50/$Q50),0) -> 0 | V50: =IFERROR((H50/$Q50),0) -> 0 | W50: =IFERROR((I50/$Q50),0) -> 0 | X50: =IFERROR((J50/$Q50),0) -> 0 | Y50: =IFERROR((K50/$Q50),0) -> 0 | ... AB50: =IFERROR((N50/$Q50),0) -> 0 | AC50: =SUM(R50:AB50) -> 13702.25 | AD50: =+AC50 -> 13702.25 | AE50: =+P50-AC50 -> 0
A51: =SUMIF('Balanza ok'!D:D,B51,'Balanza ok'!B:B) -> 0 | B51: 3105303 | C51: OTROS ARRIENDOS | D51: 920189 | K51: 142951 | O51: =SUM(D51:N51) -> 1063140 | P51: 1349.53 | Q51: =+O51/P51 -> 787.78538 | R51: =IFERROR((D51/$Q51),0) -> 1168.0707 | S51: =IFERROR((E51/$Q51),0) -> 0 | T51: =IFERROR((F51/$Q51),0) -> 0 | U51: =IFERROR((G51/$Q51),0) -> 0 | V51: =IFERROR((H51/$Q51),0) -> 0 | W51: =IFERROR((I51/$Q51),0) -> 0 | X51: =IFERROR((J51/$Q51),0) -> 0 | Y51: =IFERROR((K51/$Q51),0) -> 181.45932 | ... AB51: =IFERROR((N51/$Q51),0) -> 0 | AC51: =SUM(R51:AB51) -> 1349.53 | AD51: =+AC51 -> 1349.53 | AE51: =+P51-AC51 -> 0
A52: =SUMIF('Balanza ok'!D:D,B52,'Balanza ok'!B:B) -> 0 | B52: 3105401 | C52: SERVICIOS DE TELECOMUNICACION | D52: 1037151 | E52: 1037152 | F52: 1037152 | G52: 1037152 | H52: 1037152 | I52: 1037152 | J52: 1037152 | K52: 928906 | L52: 1037151 | M52: 1037153 | O52: =SUM(D52:N52) -> 10263273 | P52: 12580.99 | Q52: =+O52/P52 -> 815.77626 | R52: =IFERROR((D52/$Q52),0) -> 1271.367 | S52: =IFERROR((E52/$Q52),0) -> 1271.3682 | T52: =IFERROR((F52/$Q52),0) -> 1271.3682 | U52: =IFERROR((G52/$Q52),0) -> 1271.3682 | V52: =IFERROR((H52/$Q52),0) -> 1271.3682 | W52: =IFERROR((I52/$Q52),0) -> 1271.3682 | X52: =IFERROR((J52/$Q52),0) -> 1271.3682 | Y52: =IFERROR((K52/$Q52),0) -> 1138.6774 | ... AB52: =IFERROR((N52/$Q52),0) -> 0 | AC52: =SUM(R52:AB52) -> 12580.99 | AD52: =+AC52 -> 12580.99 | AE52: =+P52-AC52 -> 0
A53: =SUMIF('Balanza ok'!D:D,B53,'Balanza ok'!B:B) -> 0 | B53: 3105403 | C53: GASTOS FACTURACION ELECTRONICA | D53: 116047 | E53: 505985 | F53: 505985 | G53: 505985 | H53: 505985 | I53: 505984 | J53: 116047 | K53: 518713 | L53: 505984 | M53: 505972 | O53: =SUM(D53:N53) -> 4292687 | P53: 5231.85 | Q53: =+O53/P53 -> 820.49122 | R53: =IFERROR((D53/$Q53),0) -> 141.436 | S53: =IFERROR((E53/$Q53),0) -> 616.68545 | T53: =IFERROR((F53/$Q53),0) -> 616.68545 | U53: =IFERROR((G53/$Q53),0) -> 616.68545 | V53: =IFERROR((H53/$Q53),0) -> 616.68545 | W53: =IFERROR((I53/$Q53),0) -> 616.68423 | X53: =IFERROR((J53/$Q53),0) -> 141.436 | Y53: =IFERROR((K53/$Q53),0) -> 632.19811 | ... AB53: =IFERROR((N53/$Q53),0) -> 0 | AC53: =SUM(R53:AB53) -> 5231.85 | AD53: =+AC53 -> 5231.85 | AE53: =+P53-AC53 -> 0
A54: =SUMIF('Balanza ok'!D:D,B54,'Balanza ok'!B:B) -> 0 | B54: 3105501 | C54: PATENTE COMERCIAL | G54: 66588 | H54: 53286 | K54: 62179 | M54: 53286 | O54: =SUM(D54:N54) -> 235339 | P54: 288.03 | Q54: =+O54/P54 -> 817.06419 | R54: =IFERROR((D54/$Q54),0) -> 0 | S54: =IFERROR((E54/$Q54),0) -> 0 | T54: =IFERROR((F54/$Q54),0) -> 0 | U54: =IFERROR((G54/$Q54),0) -> 81.496656 | V54: =IFERROR((H54/$Q54),0) -> 65.216418 | W54: =IFERROR((I54/$Q54),0) -> 0 | X54: =IFERROR((J54/$Q54),0) -> 0 | Y54: =IFERROR((K54/$Q54),0) -> 76.100508 | ... AB54: =IFERROR((N54/$Q54),0) -> 0 | AC54: =SUM(R54:AB54) -> 288.03 | AD54: =+AC54 -> 288.03 | AE54: =+P54-AC54 -> 0
A55: =SUMIF('Balanza ok'!D:D,B55,'Balanza ok'!B:B) -> 0 | B55: 3105504 | C55: IVA IRRECUPERABLE | K55: 213139 | O55: =SUM(D55:N55) -> 213139 | P55: 270.77 | Q55: =+O55/P55 -> 787.15884 | R55: =IFERROR((D55/$Q55),0) -> 0 | S55: =IFERROR((E55/$Q55),0) -> 0 | T55: =IFERROR((F55/$Q55),0) -> 0 | U55: =IFERROR((G55/$Q55),0) -> 0 | V55: =IFERROR((H55/$Q55),0) -> 0 | W55: =IFERROR((I55/$Q55),0) -> 0 | X55: =IFERROR((J55/$Q55),0) -> 0 | Y55: =IFERROR((K55/$Q55),0) -> 270.77 | ... AB55: =IFERROR((N55/$Q55),0) -> 0 | AC55: =SUM(R55:AB55) -> 270.77 | AD55: =+AC55 -> 270.77 | AE55: =+P55-AC55 -> 0
A56: =SUMIF('Balanza ok'!D:D,B56,'Balanza ok'!B:B) -> 0 | B56: 3105506 | C56: SEGUROS | E56: 436753 | F56: 436753 | G56: 436753 | H56: 436754 | I56: 436754 | K56: 138088 | L56: 436754 | M56: 436753 | O56: =SUM(D56:N56) -> 3195362 | P56: 3925.97 | Q56: =+O56/P56 -> 813.90383 | R56: =IFERROR((D56/$Q56),0) -> 0 | S56: =IFERROR((E56/$Q56),0) -> 536.615 | T56: =IFERROR((F56/$Q56),0) -> 536.615 | U56: =IFERROR((G56/$Q56),0) -> 536.615 | V56: =IFERROR((H56/$Q56),0) -> 536.61623 | W56: =IFERROR((I56/$Q56),0) -> 536.61623 | X56: =IFERROR((J56/$Q56),0) -> 0 | Y56: =IFERROR((K56/$Q56),0) -> 169.66132 | ... AB56: =IFERROR((N56/$Q56),0) -> 0 | AC56: =SUM(R56:AB56) -> 3925.97 | AD56: =+AC56 -> 3925.97 | AE56: =+P56-AC56 -> 0
A57: =SUMIF('Balanza ok'!D:D,B57,'Balanza ok'!B:B) -> 0 | B57: 3105601 | C57: GASTO MANTENCION SUCURSALES | D57: -118015 | E57: 140258 | F57: 178608 | G57: 149108 | H57: 1477387 | I57: 60613 | J57: 57613 | K57: 292174 | L57: 146083 | M57: 146078 | O57: =SUM(D57:N57) -> 2529907 | P57: 3014.92 | Q57: =+O57/P57 -> 839.12906 | R57: =IFERROR((D57/$Q57),0) -> -140.63987 | S57: =IFERROR((E57/$Q57),0) -> 167.14711 | T57: =IFERROR((F57/$Q57),0) -> 212.84926 | U57: =IFERROR((G57/$Q57),0) -> 177.69376 | V57: =IFERROR((H57/$Q57),0) -> 1760.6195 | W57: =IFERROR((I57/$Q57),0) -> 72.233227 | X57: =IFERROR((J57/$Q57),0) -> 68.658091 | Y57: =IFERROR((K57/$Q57),0) -> 348.1872 | ... AB57: =IFERROR((N57/$Q57),0) -> 0 | AC57: =SUM(R57:AB57) -> 3014.92 | AD57: =+AC57 -> 3014.92 | AE57: =+P57-AC57 -> 0
A58: 740814 | B58: 3105701 | C58: DEPRECIACION DEL EJERCICIO | D58: 311087.44 | E58: 34308.9 | F58: 32114.178 | G58: 34502.706 | H58: 38216.448 | I58: 60766.038 | K58: 1499119.1 | L58: 6391193.7 | O58: =SUM(D58:N58) -> 8401308.5 | P58: =11542.15*0.873 -> 10076.297 | Q58: =+O58/P58 -> 833.76945 | R58: =IFERROR((D58/$Q58),0) -> 373.10967 | S58: =IFERROR((E58/$Q58),0) -> 41.149145 | T58: =IFERROR((F58/$Q58),0) -> 38.516856 | U58: =IFERROR((G58/$Q58),0) -> 41.381591 | V58: =IFERROR((H58/$Q58),0) -> 45.83575 | W58: =IFERROR((I58/$Q58),0) -> 72.881104 | X58: =IFERROR((J58/$Q58),0) -> 0 | Y58: =IFERROR((K58/$Q58),0) -> 1798.002 | ... AB58: =IFERROR((N58/$Q58),0) -> 0 | AC58: =SUM(R58:AB58) -> 10076.297 | AD58: =+AC58 -> 10076.297 | AE58: =+P58-AC58 -> 0
A59: 740818 | D59: 45255.561 | E59: 4991.1 | F59: 4671.822 | G59: 5019.294 | H59: 5559.552 | I59: 8839.962 | K59: 218084.91 | L59: 929761.29 | O59: =SUM(D59:N59) -> 1222183.5 | P59: =11542.15*0.127 -> 1465.853 | Q59: =+O59/P59 -> 833.76945 | R59: =IFERROR((D59/$Q58),0) -> 54.278268 | S59: =IFERROR((E59/$Q58),0) -> 5.9861872 | T59: =IFERROR((F59/$Q58),0) -> 5.603254 | U59: =IFERROR((G59/$Q58),0) -> 6.0200023 | V59: =IFERROR((H59/$Q58),0) -> 6.6679728 | W59: =IFERROR((I59/$Q58),0) -> 10.602406 | X59: =IFERROR((J59/$Q58),0) -> 0 | Y59: =IFERROR((K59/$Q58),0) -> 261.565 | ... AB59: =IFERROR((N59/$Q58),0) -> 0 | AC59: =SUM(R59:AB59) -> 1465.8531 | AD59: =+AC59 -> 1465.8531 | AE59: =+P59-AC59 -> 0
A60: =SUMIF('Balanza ok'!D:D,B60,'Balanza ok'!B:B) -> 0 | B60: 3105801 | C60: SUMINISTROS Y MATERIALES DE TIENDAS | D60: 2891474 | E60: 2307466 | F60: 1152397 | G60: 1251697 | H60: 1886027 | I60: 1420770 | J60: 46146 | K60: 3121789 | L60: 1419274 | M60: 1854167 | N60: 0 | O60: =SUM(D60:N60) -> 17351207 | P60: 22152.74 | Q60: =+O60/P60 -> 783.25331 | R60: =IFERROR((D60/$Q60),0) -> 3691.6205 | S60: =IFERROR((E60/$Q60),0) -> 2946.0022 | T60: =IFERROR((F60/$Q60),0) -> 1471.2954 | U60: =IFERROR((G60/$Q60),0) -> 1598.0743 | V60: =IFERROR((H60/$Q60),0) -> 2407.94 | W60: =IFERROR((I60/$Q60),0) -> 1813.9342 | X60: =IFERROR((J60/$Q60),0) -> 58.915806 | Y60: =IFERROR((K60/$Q60),0) -> 3985.6697 | ... AB60: =IFERROR((N60/$Q60),0) -> 0 | AC60: =SUM(R60:AB60) -> 22152.74 | AD60: =+AC60 -> 22152.74 | AE60: =+P60-AC60 -> 0
A61: =SUMIF('Balanza ok'!D:D,B61,'Balanza ok'!B:B) -> 0 | B61: 3105802 | C61: SUMINISTROS COMPUTACIONALES | D61: 980424 | K61: 219900 | N61: 0 | O61: =SUM(D61:N61) -> 1200324 | P61: 1497.27 | Q61: =+O61/P61 -> 801.67505 | R61: =IFERROR((D61/$Q61),0) -> 1222.9693 | S61: =IFERROR((E61/$Q61),0) -> 0 | T61: =IFERROR((F61/$Q61),0) -> 0 | U61: =IFERROR((G61/$Q61),0) -> 0 | V61: =IFERROR((H61/$Q61),0) -> 0 | W61: =IFERROR((I61/$Q61),0) -> 0 | X61: =IFERROR((J61/$Q61),0) -> 0 | Y61: =IFERROR((K61/$Q61),0) -> 274.30067 | ... AB61: =IFERROR((N61/$Q61),0) -> 0 | AC61: =SUM(R61:AB61) -> 1497.27 | AD61: =+AC61 -> 1497.27 | AE61: =+P61-AC61 -> 0
A62: =SUMIF('Balanza ok'!D:D,B62,'Balanza ok'!B:B) -> 0 | B62: 3105803 | C62: UTILES DE OFICINA Y PAPELERIA | D62: 716285 | E62: 24499 | F62: 24499 | G62: 24499 | H62: 24499 | I62: 24499 | J62: 24499 | K62: 0 | L62: 72499 | M62: 24501 | N62: 0 | O62: =SUM(D62:N62) -> 960279 | P62: 1156.72 | Q62: =+O62/P62 -> 830.17411 | R62: =IFERROR((D62/$Q62),0) -> 862.81298 | S62: =IFERROR((E62/$Q62),0) -> 29.510677 | T62: =IFERROR((F62/$Q62),0) -> 29.510677 | U62: =IFERROR((G62/$Q62),0) -> 29.510677 | V62: =IFERROR((H62/$Q62),0) -> 29.510677 | W62: =IFERROR((I62/$Q62),0) -> 29.510677 | X62: =IFERROR((J62/$Q62),0) -> 29.510677 | Y62: =IFERROR((K62/$Q62),0) -> 0 | ... AB62: =IFERROR((N62/$Q62),0) -> 0 | AC62: =SUM(R62:AB62) -> 1156.72 | AD62: =+AC62 -> 1156.72 | AE62: =+P62-AC62 -> 0
A63: =SUMIF('Balanza ok'!D:D,B63,'Balanza ok'!B:B) -> 0 | B63: 3105805 | C63: GASTOS LEGALES Y NOTARIALES DIRECTOS | K63: 390690 | L63: 306748 | N63: 0 | O63: =SUM(D63:N63) -> 697438 | P63: 864.96 | Q63: =+O63/P63 -> 806.32399 | R63: =IFERROR((D63/$Q63),0) -> 0 | S63: =IFERROR((E63/$Q63),0) -> 0 | T63: =IFERROR((F63/$Q63),0) -> 0 | U63: =IFERROR((G63/$Q63),0) -> 0 | V63: =IFERROR((H63/$Q63),0) -> 0 | W63: =IFERROR((I63/$Q63),0) -> 0 | X63: =IFERROR((J63/$Q63),0) -> 0 | Y63: =IFERROR((K63/$Q63),0) -> 484.53228 | ... AB63: =IFERROR((N63/$Q63),0) -> 0 | AC63: =SUM(R63:AB63) -> 864.96 | AD63: =+AC63 -> 864.96 | AE63: =+P63-AC63 -> 0
A64: =SUMIF('Balanza ok'!D:D,B64,'Balanza ok'!B:B) -> 0 | B64: 3105806 | C64: COMISIONES Y GASTOS BANCARIOS | K64: 3384386.2 | N64: 0 | O64: =SUM(D64:N64) -> 3384386.2 | P64: 12232.17 | Q64: =+O64/P64 -> 276.67913 | R64: =IFERROR((D64/$Q64),0) -> 0 | S64: =IFERROR((E64/$Q64),0) -> 0 | T64: =IFERROR((F64/$Q64),0) -> 0 | U64: =IFERROR((G64/$Q64),0) -> 0 | V64: =IFERROR((H64/$Q64),0) -> 0 | W64: =IFERROR((I64/$Q64),0) -> 0 | X64: =IFERROR((J64/$Q64),0) -> 0 | Y64: =IFERROR((K64/$Q64),0) -> 12232.17 | ... AB64: =IFERROR((N64/$Q64),0) -> 0 | AC64: =SUM(R64:AB64) -> 12232.17 | AD64: =+AC64 -> 12232.17 | AE64: =+P64-AC64 -> 0
A65: =SUMIF('Balanza ok'!D:D,B65,'Balanza ok'!B:B) -> 0 | B65: 3105812 | C65: COMISIONES TRANSBANK | E65: 1870698 | F65: 1412435 | G65: 3177533 | H65: 2665885 | I65: 2752602 | J65: 1604612 | K65: 0 | L65: 3859583 | M65: 1375714 | N65: 0 | O65: =SUM(D65:N65) -> 18719062 | P65: 22719.71 | Q65: =+O65/P65 -> 823.91289 | R65: =IFERROR((D65/$Q65),0) -> 0 | S65: =IFERROR((E65/$Q65),0) -> 2270.5046 | T65: =IFERROR((F65/$Q65),0) -> 1714.3014 | U65: =IFERROR((G65/$Q65),0) -> 3856.6371 | V65: =IFERROR((H65/$Q65),0) -> 3235.6394 | W65: =IFERROR((I65/$Q65),0) -> 3340.8896 | X65: =IFERROR((J65/$Q65),0) -> 1947.5505 | Y65: =IFERROR((K65/$Q65),0) -> 0 | ... AB65: =IFERROR((N65/$Q65),0) -> 0 | AC65: =SUM(R65:AB65) -> 22719.71 | AD65: =+AC65 -> 22719.71 | AE65: =+P65-AC65 -> 0
A66: =SUMIF('Balanza ok'!D:D,B66,'Balanza ok'!B:B) -> 0 | B66: 3105815 | C66: GASTOS DE PASAJES Y TRASLADO NACIONAL | K66: 30042 | N66: 0 | O66: =SUM(D66:N66) -> 30042 | P66: 36.44 | Q66: =+O66/P66 -> 824.42371 | R66: =IFERROR((D66/$Q66),0) -> 0 | S66: =IFERROR((E66/$Q66),0) -> 0 | T66: =IFERROR((F66/$Q66),0) -> 0 | U66: =IFERROR((G66/$Q66),0) -> 0 | V66: =IFERROR((H66/$Q66),0) -> 0 | W66: =IFERROR((I66/$Q66),0) -> 0 | X66: =IFERROR((J66/$Q66),0) -> 0 | Y66: =IFERROR((K66/$Q66),0) -> 36.44 | ... AB66: =IFERROR((N66/$Q66),0) -> 0 | AC66: =SUM(R66:AB66) -> 36.44 | AD66: =+AC66 -> 36.44 | AE66: =+P66-AC66 -> 0
A67: =SUMIF('Balanza ok'!D:D,B67,'Balanza ok'!B:B) -> 0 | B67: 3105819 | C67: GASTOS DE HOSPEDAJE NACIONAL | K67: 94000 | N67: 0 | O67: =SUM(D67:N67) -> 94000 | P67: 108.91 | Q67: =+O67/P67 -> 863.09797 | R67: =IFERROR((D67/$Q67),0) -> 0 | S67: =IFERROR((E67/$Q67),0) -> 0 | T67: =IFERROR((F67/$Q67),0) -> 0 | U67: =IFERROR((G67/$Q67),0) -> 0 | V67: =IFERROR((H67/$Q67),0) -> 0 | W67: =IFERROR((I67/$Q67),0) -> 0 | X67: =IFERROR((J67/$Q67),0) -> 0 | Y67: =IFERROR((K67/$Q67),0) -> 108.91 | ... AB67: =IFERROR((N67/$Q67),0) -> 0 | AC67: =SUM(R67:AB67) -> 108.91 | AD67: =+AC67 -> 108.91 | AE67: =+P67-AC67 -> 0
A68: =SUMIF('Balanza ok'!D:D,B68,'Balanza ok'!B:B) -> 0 | B68: 3105822 | C68: GASTOS DE PUBLICIDAD Y MARKETING | D68: 7529962 | E68: 7860328 | F68: 7860328 | G68: 7860328 | H68: 7860328 | I68: 7860328 | J68: 10655078 | K68: 21434219 | L68: 7860329 | M68: 8293373 | N68: 0 | O68: =SUM(D68:N68) -> 95074601 | P68: 116006.82 | Q68: =+O68/P68 -> 819.56044 | R68: =IFERROR((D68/$Q68),0) -> 9187.8055 | S68: =IFERROR((E68/$Q68),0) -> 9590.907 | T68: =IFERROR((F68/$Q68),0) -> 9590.907 | U68: =IFERROR((G68/$Q68),0) -> 9590.907 | V68: =IFERROR((H68/$Q68),0) -> 9590.907 | W68: =IFERROR((I68/$Q68),0) -> 9590.907 | X68: =IFERROR((J68/$Q68),0) -> 13000.967 | Y68: =IFERROR((K68/$Q68),0) -> 26153.311 | ... AB68: =IFERROR((N68/$Q68),0) -> 0 | AC68: =SUM(R68:AB68) -> 116006.82 | AD68: =+AC68 -> 116006.82 | AE68: =+P68-AC68 -> 0
A69: =SUMIF('Balanza ok'!D:D,B69,'Balanza ok'!B:B) -> 0 | B69: 3105833 | C69: SUMINISTROS PUBLICIDAD Y MARKETING | E69: 1366579 | F69: 1366579 | G69: 1366579 | H69: 1366579 | I69: 1366580 | K69: 30700 | L69: 1446180 | M69: 1366572 | O69: =SUM(D69:N69) -> 9676348 | P69: 10518.11 | Q69: =+O69/P69 -> 919.97022 | R69: =IFERROR((D69/$Q69),0) -> 0 | S69: =IFERROR((E69/$Q69),0) -> 1485.46 | T69: =IFERROR((F69/$Q69),0) -> 1485.46 | U69: =IFERROR((G69/$Q69),0) -> 1485.46 | V69: =IFERROR((H69/$Q69),0) -> 1485.46 | W69: =IFERROR((I69/$Q69),0) -> 1485.4611 | X69: =IFERROR((J69/$Q69),0) -> 0 | Y69: =IFERROR((K69/$Q69),0) -> 33.370645 | ... AB69: =IFERROR((N69/$Q69),0) -> 0 | AC69: =SUM(R69:AB69) -> 10518.11 | AD69: =+AC69 -> 10518.11 | AE69: =+P69-AC69 -> 0
S70: =+S68+S69 -> 11076.367 | T70: =+T68+T69 -> 11076.367 | U70: =+U68+U69 -> 11076.367 | V70: =+V68+V69 -> 11076.367 | W70: =+W68+W69 -> 11076.368 | X70: =+X68+X69 -> 13000.967 | Y70: =+Y68+Y69 -> 26186.681 | Z70: =+Z68+Z69 -> 11162.894 | AA70: =+AA68+AA69 -> 11604.746
S71: 12779.93 | T71: 12691.3 | U71: 13800.6 | V71: 13846.51 | W71: 13864.95 | X71: 24759.08 | Z71: 13990.19 | AA71: 13432.58 | AB71: 7359.81
S72: =+S71-S70 -> 1703.563 | T72: =+T71-T70 -> 1614.933 | U72: =+U71-U70 -> 2724.233 | V72: =+V71-V70 -> 2770.143 | W72: =+W71-W70 -> 2788.5819 | X72: =+X71-X70 -> 11758.113 | Y72: =+Y71-Y70 -> -26186.681 | Z72: =+Z71-Z70 -> 2827.2961 | ... AB72: =+AB71-AB70 -> 7359.81
A73: =SUMIF('Balanza ok'!D:D,B73,'Balanza ok'!B:B) -> 0 | B73: 3105830 | C73: AJUSTE SENCILLO LEY DE REDONDEO | E73: 343 | F73: 330 | G73: 804 | H73: 724 | I73: 774 | J73: 607 | K73: -939.64 | L73: 830 | M73: 388 | N73: 0 | O73: =SUM(D73:N73) -> 3860.36 | P73: 4.03 | Q73: =+O73/P73 -> 957.90571 | R73: =IFERROR((D73/$Q73),0) -> 0 | S73: =IFERROR((E73/$Q73),0) -> 0.35807282 | T73: =IFERROR((F73/$Q73),0) -> 0.34450155 | U73: =IFERROR((G73/$Q73),0) -> 0.83933105 | V73: =IFERROR((H73/$Q73),0) -> 0.75581552 | W73: =IFERROR((I73/$Q73),0) -> 0.80801272 | X73: =IFERROR((J73/$Q73),0) -> 0.63367406 | Y73: =IFERROR((K73/$Q73),0) -> -0.98093162 | ... AB73: =IFERROR((N73/$Q73),0) -> 0 | AC73: =SUM(R73:AB73) -> 4.03 | AD73: =+AC73 -> 4.03 | AE73: =+P73-AC73 -> 0
A74: =SUMIF('Balanza ok'!D:D,B74,'Balanza ok'!B:B) -> 0 | B74: 3105831 | C74: MEMBRESÍAS Y ASOCIACIONES | K74: 189482 | N74: 0 | O74: =SUM(D74:N74) -> 189482 | P74: 227.86 | Q74: =+O74/P74 -> 831.57202 | R74: =IFERROR((D74/$Q74),0) -> 0 | S74: =IFERROR((E74/$Q74),0) -> 0 | T74: =IFERROR((F74/$Q74),0) -> 0 | U74: =IFERROR((G74/$Q74),0) -> 0 | V74: =IFERROR((H74/$Q74),0) -> 0 | W74: =IFERROR((I74/$Q74),0) -> 0 | X74: =IFERROR((J74/$Q74),0) -> 0 | Y74: =IFERROR((K74/$Q74),0) -> 227.86 | ... AB74: =IFERROR((N74/$Q74),0) -> 0 | AC74: =SUM(R74:AB74) -> 227.86 | AD74: =+AC74 -> 227.86 | AE74: =+P74-AC74 -> 0
A75: =SUMIF('Balanza ok'!D:D,B75,'Balanza ok'!B:B) -> 0 | B75: 3108116 | C75: INTERES GANADO POR DEPOSITO A PLAZO PESOS | K75: -97458 | N75: 0 | O75: =SUM(D75:N75) -> -97458 | P75: -118.7 | Q75: =+O75/P75 -> 821.04465 | R75: =IFERROR((D75/$Q75),0) -> 0 | S75: =IFERROR((E75/$Q75),0) -> 0 | T75: =IFERROR((F75/$Q75),0) -> 0 | U75: =IFERROR((G75/$Q75),0) -> 0 | V75: =IFERROR((H75/$Q75),0) -> 0 | W75: =IFERROR((I75/$Q75),0) -> 0 | X75: =IFERROR((J75/$Q75),0) -> 0 | Y75: =IFERROR((K75/$Q75),0) -> -118.7 | ... AB75: =IFERROR((N75/$Q75),0) -> 0 | AC75: =SUM(R75:AB75) -> -118.7 | AD75: =+AC75 -> -118.7 | AE75: =+P75-AC75 -> 0
A76: =SUMIF('Balanza ok'!D:D,B76,'Balanza ok'!B:B) -> 0 | B76: 3109105 | C76: INTERESES POR PRESTAMO EN EERR | K76: 19662543 | N76: 0 | O76: =SUM(D76:N76) -> 19662543 | P76: 23914.54 | Q76: =+O76/P76 -> 822.20033 | R76: =IFERROR((D76/$Q76),0) -> 0 | S76: =IFERROR((E76/$Q76),0) -> 0 | T76: =IFERROR((F76/$Q76),0) -> 0 | U76: =IFERROR((G76/$Q76),0) -> 0 | V76: =IFERROR((H76/$Q76),0) -> 0 | W76: =IFERROR((I76/$Q76),0) -> 0 | X76: =IFERROR((J76/$Q76),0) -> 0 | Y76: =IFERROR((K76/$Q76),0) -> 23914.54 | ... AB76: =IFERROR((N76/$Q76),0) -> 0 | AC76: =SUM(R76:AB76) -> 23914.54 | AD76: =+AC76 -> 23914.54 | AE76: =+P76-AC76 -> 0
A77: =SUMIF('Balanza ok'!D:D,B77,'Balanza ok'!B:B) -> 0 | B77: 3111101 | C77: DIF_CAM__EFECTIVO Y EQUIVALENTES AL EFECTIVO | K77: -10073138 | N77: 0 | O77: =SUM(D77:N77) -> -10073138 | P77: 0 | Q77: 0 | R77: =IFERROR((D77/$Q77),0) -> 0 | S77: =IFERROR((E77/$Q77),0) -> 0 | T77: =IFERROR((F77/$Q77),0) -> 0 | U77: =IFERROR((G77/$Q77),0) -> 0 | V77: =IFERROR((H77/$Q77),0) -> 0 | W77: =IFERROR((I77/$Q77),0) -> 0 | X77: =IFERROR((J77/$Q77),0) -> 0 | Y77: =IFERROR((K77/$Q77),0) -> 0 | ... AB77: =IFERROR((N77/$Q77),0) -> 0 | AC77: =SUM(R77:AB77) -> 0 | AD77: =+AC77 -> 0 | AE77: =+P77-AC77 -> 0
A78: =SUMIF('Balanza ok'!D:D,B78,'Balanza ok'!B:B) -> 0 | B78: 3111151 | C78: DIF_CAM__OTROS PASIVOS FINANCIEROS | K78: 49379686 | N78: 0 | O78: =SUM(D78:N78) -> 49379686 | P78: 0 | Q78: 0 | R78: =IFERROR((D78/$Q78),0) -> 0 | S78: =IFERROR((E78/$Q78),0) -> 0 | T78: =IFERROR((F78/$Q78),0) -> 0 | U78: =IFERROR((G78/$Q78),0) -> 0 | V78: =IFERROR((H78/$Q78),0) -> 0 | W78: =IFERROR((I78/$Q78),0) -> 0 | X78: =IFERROR((J78/$Q78),0) -> 0 | Y78: =IFERROR((K78/$Q78),0) -> 0 | ... AB78: =IFERROR((N78/$Q78),0) -> 0 | AC78: =SUM(R78:AB78) -> 0 | AD78: =+AC78 -> 0 | AE78: =+P78-AC78 -> 0
A79: =SUMIF('Balanza ok'!D:D,B79,'Balanza ok'!B:B) -> 0 | B79: 3111152 | C79: DIF_CAM__CUENTAS POR PAGAR COMERCIALES Y OTRAS CUENTAS POR P | K79: 1.7574316e+08 | N79: 0 | O79: =SUM(D79:N79) -> 1.7574316e+08 | P79: 127420.91 | Q79: =+O79/P79 -> 1379.2333 | R79: =IFERROR((D79/$Q79),0) -> 0 | S79: =IFERROR((E79/$Q79),0) -> 0 | T79: =IFERROR((F79/$Q79),0) -> 0 | U79: =IFERROR((G79/$Q79),0) -> 0 | V79: =IFERROR((H79/$Q79),0) -> 0 | W79: =IFERROR((I79/$Q79),0) -> 0 | X79: =IFERROR((J79/$Q79),0) -> 0 | Y79: =IFERROR((K79/$Q79),0) -> 127420.91 | ... AB79: =IFERROR((N79/$Q79),0) -> 0 | AC79: =SUM(R79:AB79) -> 127420.91 | AD79: =+AC79 -> 127420.91 | AE79: =+P79-AC79 -> 0
A80: =SUMIF('Balanza ok'!D:D,B80,'Balanza ok'!B:B) -> 0 | B80: 3113101 | C80: CORRECCION MONETARIA ACTIVOS | K80: -5751487 | N80: 0 | O80: =SUM(D80:N80) -> -5751487 | P80: -6811.95 | Q80: =+O80/P80 -> 844.32314 | R80: =IFERROR((D80/$Q80),0) -> 0 | S80: =IFERROR((E80/$Q80),0) -> 0 | T80: =IFERROR((F80/$Q80),0) -> 0 | U80: =IFERROR((G80/$Q80),0) -> 0 | V80: =IFERROR((H80/$Q80),0) -> 0 | W80: =IFERROR((I80/$Q80),0) -> 0 | X80: =IFERROR((J80/$Q80),0) -> 0 | Y80: =IFERROR((K80/$Q80),0) -> -6811.95 | ... AB80: =IFERROR((N80/$Q80),0) -> 0 | AC80: =SUM(R80:AB80) -> -6811.95 | AD80: =+AC80 -> -6811.95 | AE80: =+P80-AC80 -> 0
A81: =SUMIF('Balanza ok'!D:D,B81,'Balanza ok'!B:B) -> 0 | B81: 3113109 | C81: AJUSTE REDONDEO AUTO | K81: -1256.65 | N81: 0 | O81: =SUM(D81:N81) -> -1256.65 | P81: -1.05 | Q81: =+O81/P81 -> 1196.8095 | R81: =IFERROR((D81/$Q81),0) -> 0 | S81: =IFERROR((E81/$Q81),0) -> 0 | T81: =IFERROR((F81/$Q81),0) -> 0 | U81: =IFERROR((G81/$Q81),0) -> 0 | V81: =IFERROR((H81/$Q81),0) -> 0 | W81: =IFERROR((I81/$Q81),0) -> 0 | X81: =IFERROR((J81/$Q81),0) -> 0 | Y81: =IFERROR((K81/$Q81),0) -> -1.05 | ... AB81: =IFERROR((N81/$Q81),0) -> 0 | AC81: =SUM(R81:AB81) -> -1.05 | AD81: =+AC81 -> -1.05 | AE81: =+P81-AC81 -> 0
B82: Resultado por Centro de Costo | D82: =SUM(D13:D81) -> 101091888 | E82: =SUM(E13:E81) -> 55464027 | F82: =SUM(F13:F81) -> 59446617 | G82: =SUM(G13:G81) -> 79745139 | H82: =SUM(H13:H81) -> 73024073 | I82: =SUM(I13:I81) -> 80761861 | J82: =SUM(J13:J81) -> 94574849 | K82: =SUM(K13:K81) -> 3.4156999e+08 | ... N82: =SUM(N13:N81) -> 1291619 | O82: =SUM(D82:N82) -> 1.0572625e+09 | P82: =SUM(P13:P81) -> 1154300.6 | R82: =SUM(R13:R81) -> 122833.03 | S82: =SUM(S13:S81) -> 92544.631 | T82: =SUM(T13:T81) -> 96903.383 | U82: =SUM(U13:U81) -> 123741.27 | V82: =SUM(V13:V81) -> 115809.68 | W82: =SUM(W13:W81) -> 125236.1 | X82: =SUM(X13:X81) -> 164383.37 | Y82: =SUM(Y13:Y81) -> 289029.32 | ... AC82: =SUM(AC13:AC81) -> 1154300.6
B84: Resultado por Centro de Costo | D84: =+D8-D82 -> -101091888 | E84: =+E8-E82 -> -6918185 | F84: =+F8-F82 -> -17066113 | G84: =+G8-G82 -> 13291420 | H84: =+H8-H82 -> 16273099 | I84: =+I8-I82 -> 10927166 | J84: =+J8-J82 -> 65853857 | K84: =+K8-K82 -> -3.4156999e+08 | ... P84: =+P8-P82 -> -196300.64 | R84: =+R8-R82 -> -122833.03 | S84: =+S8-S82 -> -33315.446 | T84: =+T8-T82 -> -45200.318 | U84: =+U8-U82 -> -10246.946 | V84: =+V8-V82 -> -6886.0836 | W84: =+W8-W82 -> -13429.107 | X84: =+X8-X82 -> 31408.381 | Y84: =+Y8-Y82 -> -289029.32 | ... AC84: =+AC8-AC82 -> -196300.64
C89: Proporcion depreciación | D89: 356343 | E89: 39300 | F89: 36786 | G89: 39522 | H89: 43776 | I89: 69606 | K89: 1717204 | L89: 7320955 | O89: =SUM(D89:L89) -> 9623492
B90: 740814 | C90: 0.873 | D90: =+$C$90*D89 -> 311087.44 | E90: =+$C$90*E89 -> 34308.9 | F90: =+$C$90*F89 -> 32114.178 | G90: =+$C$90*G89 -> 34502.706 | H90: =+$C$90*H89 -> 38216.448 | I90: =+$C$90*I89 -> 60766.038 | K90: =+$C$90*K89 -> 1499119.1 | L90: =+$C$90*L89 -> 6391193.7 | O90: =SUM(D90:L90) -> 8401308.5
B91: 740818 | C91: =1-C90 -> 0.127 | D91: =+$C$91*D89 -> 45255.561 | E91: =+$C$91*E89 -> 4991.1 | F91: =+$C$91*F89 -> 4671.822 | G91: =+$C$91*G89 -> 5019.294 | H91: =+$C$91*H89 -> 5559.552 | I91: =+$C$91*I89 -> 8839.962 | K91: =+$C$91*K89 -> 218084.91 | L91: =+$C$91*L89 -> 929761.29 | O91: =SUM(D91:L91) -> 1222183.5
B94: *** Saldos negativos se suben con 50 y se suben en positivo
B95: *** Cuentas 81 y 82 revisar manualmente porque puede ser deudora o acreedora
B96: *** Gastos financieros en negativo (81) se convierten en productos financieros (82) y se suben en positivo
B97: ***Cuentas 8 miles no llevan CECO
C103: CAMPAÑAS PUBLICIDAD EN TIENDAS | D103: 7 | E103: 709229
C104: EVENTOS CAPACITACION TIENDAS | D104: 7 | E104: 709223
C105: FINANCIAMIENTO FLEXI EQUIPAMIENTO Y PROM TIENDAS | D105: 7 | E105: 709228
C106: PROMOCION Y DIFUSION | D106: 88 | E106: 730781
