Workbook

Sheet ENERO
C1: RENDICION CAJA CHICA
C2: FLORIDA CENTER
G3: MES | H3: ENERO
B4: SALDO ANTERIOR | E4: =DICIEMBRE!H8 -> 44420
B5: DEPÓSITO RENDICION ANTERIOR | E5: 55580
B6: MONTO ADICIONAL | E6: 0
B7: MONTO A RENDIR | E7: =SUM(E4:E6) -> 100000
B8: RENDIDO | E8: =+G26 -> 17000 | G8: SALDO AL CIERRE | H8: =E7-E8 -> 83000
A10: N° | B10: Fecha | C10: Tipo Documento (boleta venta-boleta honorarios-factura) | D10: N° documento | E10: RUT Titular del documento | F10: Detalle | G10: Total | H10: Código Imputacion (RSM) 180
A11: 1 | B11: 46024 | C11: VALE | D11: 34 | F11: MOVILIZACION RETIRO DE MATERIAL SALE | G11: 2000
A12: 2 | B12: 46036 | C12: BOLETA | D12: 17207 | F12: LIMPIEZA VITRINA | G12: 15000
A13: 3
A14: 4
A15: 5
A16: 6
A17: 7
A18: 8
A19: 9
A20: 10
A21: 11
A22: 12
A23: 13
A24: 14
A25: 15
B26: TOTALES | G26: =SUM(G11:G25) -> 17000

Sheet FEBRERO
C1: RENDICION CAJA CHICA
C2: FLORIDA CENTER
G3: MES | H3: FEBRERO
B4: SALDO ANTERIOR | E4: =+ENERO!H8 -> 83000
B5: DEPÓSITO RENDICION ANTERIOR | E5: 59400
B6: MONTO ADICIONAL | E6: 0
B7: MONTO A RENDIR | E7: =SUM(E4:E6) -> 142400
B8: RENDIDO | E8: =+G26 -> 22080 | G8: SALDO AL CIERRE | H8: =E7-E8 -> 120320
A10: N° | B10: Fecha | C10: Tipo Documento (boleta venta-boleta honorarios-factura) | D10: N° documento | E10: RUT Titular del documento | F10: Detalle | G10: Total | H10: Código Imputacion (RSM) 180
A11: 1 | B11: 45694 | C11: BOLETA | D11: 15069 | F11: LIMPIEZA VIDRIOS | G11: 15000
A12: 2 | B12: 45702 | C12: BOLETA | D12: 39534464 | F12: DESAYUNO RECEPCION MERCDERIA | G12: 5080
A13: 3 | B13: 45712 | C13: BOLETA | D13: 11 | F13: MOVILIZACION OTRA TIENDA | G13: 2000
A14: 4
A15: 5
A16: 6
A17: 7
A18: 8
A19: 9
A20: 10
A21: 11
A22: 12
A23: 13
A24: 14
A25: 15
B26: TOTALES | G26: =SUM(G11:G25) -> 22080

Sheet MARZO
C1: RENDICION CAJA CHICA
C2: FLORIDA CENTER
G3: MES | H3: MARZO
B4: SALDO ANTERIOR | E4: =+FEBRERO!H8 -> 120320
B5: DEPÓSITO RENDICION ANTERIOR | E5: 22080
B6: MONTO ADICIONAL | E6: 0
B7: MONTO A RENDIR | E7: =SUM(E4:E6) -> 142400
B8: RENDIDO | E8: =+G26 -> 62470 | G8: SALDO AL CIERRE | H8: =E7-E8 -> 79930
A10: N° | B10: Fecha | C10: Tipo Documento (boleta venta-boleta honorarios-factura) | D10: N° documento | E10: RUT Titular del documento | F10: Detalle | G10: Total | H10: Código Imputacion (RSM) 180
A11: 1 | B11: 45723 | C11: BOLETA | D11: 80941267 | F11: DESAYUNO RECEPCION MERCDERIA | G11: 5190
A12: 2 | B12: 45724 | C12: BOLETA | D12: 3016081088 | F12: TORTA DIA DE LA MUJER | G12: 19020
A13: 3 | B13: 45726 | C13: BOLETA | D13: 15284 | F13: LIMPIEZA VIDRIOS | G13: 15000
A14: 4 | B14: 45729 | C14: BOLETA | D14: 3019744464 | F14: BIENVENIDA NUEVA INTEGRANTE | G14: 2690
A15: 5 | B15: 45729 | C15: VALE | D15: 12 | F15: MOVILIZACION | G15: 2000
A16: 6 | B16: 45736 | C16: VALE | D16: 13 | F16: MOVILIZACION | G16: 1000
A17: 7 | B17: 45742 | C17: BOLETA | D17: 4231451 | F17: CINTA METRICA PARA UNIFORMES | G17: 3490
A18: 8 | B18: 45744 | C18: BOLETA | D18: 3030388623 | F18: DESAYUNO RECEPCION MERCDERIA | G18: 4090
A19: 9 | B19: 45747 | C19: BOLETA | D19: 247135803 | F19: CORDEL PLASTICO DEVOLUCIONES | G19: 9990
A20: 10
A21: 11
A22: 12
A23: 13
A24: 14
A25: 15
B26: TOTALES | G26: =SUM(G11:G25) -> 62470

Sheet ABRIL
C1: RENDICION CAJA CHICA
C2: FLORIDA CENTER
G3: MES | H3: ABRIL
B4: SALDO ANTERIOR | E4: =+MARZO!H8 -> 79930
B5: DEPÓSITO RENDICION ANTERIOR | E5: 62470
B6: MONTO ADICIONAL | E6: 0
B7: MONTO A RENDIR | E7: =SUM(E4:E6) -> 142400
B8: RENDIDO | E8: =+G26 -> 32670 | G8: SALDO AL CIERRE | H8: =E7-E8 -> 109730
A10: N° | B10: Fecha | C10: Tipo Documento (boleta venta-boleta honorarios-factura) | D10: N° documento | E10: RUT Titular del documento | F10: Detalle | G10: Total | H10: Código Imputacion (RSM) 180
A11: 1 | B11: 45747 | C11: BOLETA | D11: 15343 | F11: LIMPIEZA VIDRIOS | G11: 20000
A12: 2 | B12: 45764 | C12: VALE | D12: 14 | F12: MOVILIZACION RETIRO DE MATERIAL VISUAL | G12: 2000
A13: 3 | B13: 45765 | C13: VALE | D13: 15 | F13: MOVILIZACION RETIRO DE MATERIAL VISUAL | G13: 2000
A14: 4 | B14: 45773 | C14: BOLETA | D14: 3057914719 | F14: DESAYUNO RECEPCION MERCADERIA | G14: 4680
A15: 5 | B15: 45775 | C15: BOLETA | D15: 14451400 | F15: ´PILAS CONTROL TV | G15: 3990
A16: 6
A17: 7
A18: 8
A19: 9
A20: 10
A21: 11
A22: 12
A23: 13
A24: 14
A25: 15
B26: TOTALES | G26: =SUM(G11:G25) -> 32670

Sheet MAYO
C1: RENDICION CAJA CHICA
C2: FLORIDA CENTER
G3: MES | H3: MAYO
B4: SALDO ANTERIOR | E4: =+ABRIL!H8 -> 109730
B5: DEPÓSITO RENDICION ANTERIOR | E5: 32670
B6: MONTO ADICIONAL | E6: 0
B7: MONTO A RENDIR | E7: =SUM(E4:E6) -> 142400
B8: RENDIDO | E8: =+G26 -> 39550 | G8: SALDO AL CIERRE | H8: =E7-E8 -> 102850
A10: N° | B10: Fecha | C10: Tipo Documento (boleta venta-boleta honorarios-factura) | D10: N° documento | E10: RUT Titular del documento | F10: Detalle | G10: Total | H10: Código Imputacion (RSM) 180
A11: 1 | B11: 45779 | C11: BOLETA | D11: 3061564786 | F11: DESAYUNO RECEPCION MERCADERIA | G11: 5320
A12: 2 | B12: 45784 | C12: BOLETA | D12: 15606 | F12: LIMPIEZA VIDRIOS | G12: 15000
A13: 3 | B13: 45790 | C13: BOLETA | D13: 39563255 | F13: DESAYUNO RECEPCION MERCADERIA | G13: 3390
A14: 4 | B14: 45790 | C14: BOLETA | D14: 246357847 | F14: BLOQUES VITRINA INVIERNO | G14: 4570
A15: 5 | B15: 45790 | C15: VALE | D15: 16 | F15: MOVILIZACION RETIRO DE MATERIAL V.M | G15: 2000
A16: 6 | B16: 45793 | C16: VALE | D16: 17 | F16: MOVILIZACION APOYO COLACIONES A VESPUCIO | G16: 2000
A17: 7 | B17: 45800 | C17: BOLETA | D17: 3083261761 | F17: DESAYUNO RECEPCION MERCADERIA | G17: 3880
A18: 8 | B18: 45807 | C18: BOLETA | D18: 43316111 | F18: DESAYUNO RECEPCION MERCADERIA | G18: 3390
A19: 9
A20: 10
A21: 11
A22: 12
A23: 13
A24: 14
A25: 15
B26: TOTALES | G26: =SUM(G11:G25) -> 39550

Sheet JUNIO
C1: RENDICION CAJA CHICA
C2: FLORIDA CENTER
G3: MES | H3: JUNIO
B4: SALDO ANTERIOR | E4: =+MAYO!H8 -> 102850
B5: DEPÓSITO RENDICION ANTERIOR | E5: 39550
B6: MONTO ADICIONAL | E6: 0
B7: MONTO A RENDIR | E7: =SUM(E4:E6) -> 142400
B8: RENDIDO | E8: =+G26 -> 40538 | G8: SALDO AL CIERRE | H8: =E7-E8 -> 101862
A10: N° | B10: Fecha | C10: Tipo Documento (boleta venta-boleta honorarios-factura) | D10: N° documento | E10: RUT Titular del documento | F10: Detalle | G10: Total | H10: Código Imputacion (RSM) 180
A11: 1 | B11: 45807 | C11: BOLETA | D11: 15708 | F11: LIMPIEZA VIDRIOS | G11: 20000
A12: 2 | B12: 45812 | C12: VALE | D12: 18 | F12: MOVILIZACION ENTRE TIENDAS | G12: 2000
A13: 3 | B13: 45815 | C13: BOLETA | D13: 16058733 | F13: CINTA ADHESIVA | G13: 2990
A14: 4 | B14: 45817 | C14: VALE | D14: 19 | F14: MOVILIZACION ENTRE TIENDAS | G14: 2000
A15: 5 | B15: 45821 | C15: VALE | D15: 20 | F15: MOVILIZACION ENTRE TIENDAS | G15: 2000
A16: 6 | B16: 45823 | C16: VALE | D16: 22 | F16: MOVILIZACION ENTRE TIENDAS | G16: 1000
A17: 7 | B17: 45831 | C17: VALE | D17: 23 | F17: MOVILIZACION ENTRE TIENDAS | G17: 2000
A18: 8 | B18: 45835 | C18: BOLETA | D18: 3108890925 | F18: DESAYUNO RECEPCION MERCADERIA | G18: 4858
A19: 9 | B19: 45835 | C19: BOLETA | D19: 3108890926 | F19: COMPRA PEGAMENTO REPARACIONES | G19: 3690
A20: 10
A21: 11
A22: 12
A23: 13
A24: 14
A25: 15
B26: TOTALES | G26: =SUM(G11:G25) -> 40538

Sheet JULIO 
C1: RENDICION CAJA CHICA
C2: FLORIDA CENTER
G3: MES | H3: JULIO
B4: SALDO ANTERIOR | E4: 59462
B5: DEPÓSITO RENDICION ANTERIOR | E5: 40538
B6: MONTO ADICIONAL | E6: 0
B7: MONTO A RENDIR | E7: =SUM(E4:E6) -> 100000
B8: RENDIDO | E8: =+G26 -> 35356 | G8: SALDO AL CIERRE | H8: =E7-E8 -> 64644
A10: N° | B10: Fecha | C10: Tipo Documento (boleta venta-boleta honorarios-factura) | D10: N° documento | E10: RUT Titular del documento | F10: Detalle | G10: Total | H10: Código Imputacion (RSM) 180
A11: 1 | B11: 45842 | C11: BOLETA | D11: 3121016001 | E11: - | F11: DESAYUNO RECEPCION MERCADERIA | G11: 5220
A12: 2 | B12: 45849 | C12: BOLETA | D12: 3125528771 | E12: - | F12: DESAYUNO RECEPCION MERCADERIA | G12: 4600
A13: 3 | B13: 45852 | C13: BOLETA | D13: 16014 | E13: - | F13: LIMPIEZA VIDRIOS | G13: 15546
A14: 4 | B14: 45852 | C14: VALE | D14: 24 | F14: MOVILIZACION ENTRE TIENDAS | G14: 2000
A15: 5 | B15: 45855 | C15: VALE | D15: 25 | F15: MOVILIZACION ENTRE TIENDAS | G15: 1000
A16: 6 | B16: 45857 | C16: BOLETA | D16: 3132966218 | F16: COMPRA DE PILAS CONTROL REMOTO TV Y AROMATIZANTE | G16: 6990
A17: 7
A18: 8
A19: 9
A20: 10
A21: 11
A22: 12
A23: 13
A24: 14
A25: 15
B26: TOTALES | G26: =SUM(G11:G25) -> 35356

Sheet AGOSTO
C1: RENDICION CAJA CHICA
C2: FLORIDA CENTER
G3: MES | H3: AGOSTO
B4: SALDO ANTERIOR | E4: =+'JULIO '!H8 -> 64644
B5: DEPÓSITO RENDICION ANTERIOR | E5: 35356
B6: MONTO ADICIONAL | E6: 0
B7: MONTO A RENDIR | E7: =SUM(E4:E6) -> 100000
B8: RENDIDO | E8: =+G26 -> 32570 | G8: SALDO AL CIERRE | H8: =E7-E8 -> 67430
A10: N° | B10: Fecha | C10: Tipo Documento (boleta venta-boleta honorarios-factura) | D10: N° documento | E10: RUT Titular del documento | F10: Detalle | G10: Total | H10: Código Imputacion (RSM) 180
A11: 1 | B11: 45866 | C11: BOLETA | E11: 257154891 | F11: DESTORNILLADOR PARA CONTROL DE CORTINA | G11: 3990
A12: 2 | B12: 45866 | C12: BOLETA | E12: 14933328 | F12: PILA A27 PARA CONTROL DE CORTNIA | G12: 1490
A13: 3 | B13: 45877 | C13: BOLETA | E13: 3152694205 | F13: DESAYUNO RECEPCION DE MERCADERIA | G13: 5090
A14: 4 | B14: 45880 | C14: VALE | E14: 27 | F14: MOVILIZACION A COSTANERA PARA RETIRO DE MATERIAL V.M | G14: 2000
A15: 5 | B15: 45881 | C15: BOLETA | E15: 16199 | F15: LIMPIEZA VIDRIOS | G15: 20000
A16: 6
A17: 7
A18: 8
A19: 9
A20: 10
A21: 11
A22: 12
A23: 13
A24: 14
A25: 15
B26: TOTALES | G26: =SUM(G11:G25) -> 32570

Sheet SEPTIEMBRE
C1: RENDICION CAJA CHICA
C2: FLORIDA CENTER
G3: MES | H3: SEPTIEMBRE
B4: SALDO ANTERIOR | E4: =+AGOSTO!H8 -> 67430
B5: DEPÓSITO RENDICION ANTERIOR | E5: 32570
B6: MONTO ADICIONAL | E6: 0
B7: MONTO A RENDIR | E7: =SUM(E4:E6) -> 100000
B8: RENDIDO | E8: =+G26 -> 57190 | G8: SALDO AL CIERRE | H8: =E7-E8 -> 42810
A10: N° | B10: Fecha | C10: Tipo Documento (boleta venta-boleta honorarios-factura) | D10: N° documento | E10: RUT Titular del documento | F10: Detalle | G10: Total | H10: Código Imputacion (RSM) 180
A11: 1 | B11: 45898 | C11: BOLETA | D11: 16246 | F11: LIMPIEZA VIDRIOS | G11: 20000
A12: 2 | B12: 45905 | C12: BOLETA | D12: 3175891188 | F12: DESAYUNO RECEPCION MERCADERIA | G12: 4570
A13: 3 | B13: 45907 | C13: BOLETA | D13: 3177614355 | F13: BIDON DE AGUA | G13: 2190
A14: 4 | B14: 45909 | C14: VALE | D14: 28 | F14: MOVILIZACION A OTRA TIENDA | G14: 2000
A15: 5 | B15: 45915 | C15: BOLETA | D15: 3181195168 | F15: GASTOS FIESTAS PATRIAS | G15: 16020
A16: 6 | B16: 45916 | C16: BOLETA | D16: 3176608308 | F16: GASTOS FIESTAS PATRIAS | G16: 6830
A17: 7 | B17: 45916 | C17: BOLETA | D17: 43332955 | F17: DESAYUNO RECEPCION MERCADERIA | G17: 4580
A18: 8 | B18: 45920 | C18: VALE | D18: 29 | F18: MOVILIZACION A OTRA TIENDA | G18: 1000
A19: 9
A20: 10
A21: 11
A22: 12
A23: 13
A24: 14
A25: 15
B26: TOTALES | G26: =SUM(G11:G25) -> 57190

Sheet OCTUBRE
C1: RENDICION CAJA CHICA
C2: FLORIDA CENTER
G3: MES | H3: OCTUBRE
B4: SALDO ANTERIOR | E4: =+SEPTIEMBRE!H8 -> 42810
B5: DEPÓSITO RENDICION ANTERIOR | E5: 57190
B6: MONTO ADICIONAL | E6: 0
B7: MONTO A RENDIR | E7: =SUM(E4:E6) -> 100000
B8: RENDIDO | E8: =+G26 -> 28500 | G8: SALDO AL CIERRE | H8: =E7-E8 -> 71500
A10: N° | B10: Fecha | C10: Tipo Documento (boleta venta-boleta honorarios-factura) | D10: N° documento | E10: RUT Titular del documento | F10: Detalle | G10: Total | H10: Código Imputacion (RSM) 180
A11: 1 | B11: 45930 | C11: BOLETA | D11: 3194568253 | F11: DESAYUNO RECEPCION MERCADERIA | G11: 4850
A12: 2 | B12: 45936 | C12: VALE | D12: 30 | F12: MOVILIZACION RETIRO DE MATERIAL DE CYBER | G12: 2000
A13: 3 | B13: 45940 | C13: BOLETA | D13: 16558 | F13: LIMPIEZA VITRINA | G13: 15000
A14: 4 | B14: 45941 | C14: BOLETA | D14: 3201790921 | F14: TOALLA DE PAPEL ABSORBENTE | G14: 4650
A15: 5 | B15: 45580 | C15: VALE | D15: 31 | F15: MOVILIZACION RETIRO DE MATERIAL TAMARIS | G15: 2000
A16: 6
A17: 7
A18: 8
A19: 9
A20: 10
A21: 11
A22: 12
A23: 13
A24: 14
A25: 15
B26: TOTALES | G26: =SUM(G11:G25) -> 28500

Sheet NOVIEMBRE
C1: RENDICION CAJA CHICA
C2: FLORIDA CENTER
G3: MES | H3: NOVIEMBRE
B4: SALDO ANTERIOR | E4: =+OCTUBRE!H8 -> 71500
B5: DEPÓSITO RENDICION ANTERIOR | E5: 28500
B6: MONTO ADICIONAL | E6: 0
B7: MONTO A RENDIR | E7: =SUM(E4:E6) -> 100000
B8: RENDIDO | E8: =+G26 -> 20000 | G8: SALDO AL CIERRE | H8: =E7-E8 -> 80000
A10: N° | B10: Fecha | C10: Tipo Documento (boleta venta-boleta honorarios-factura) | D10: N° documento | E10: RUT Titular del documento | F10: Detalle | G10: Total | H10: Código Imputacion (RSM) 180
A11: 1 | B11: 45961 | C11: BOLETA | D11: 16630 | F11: LIMPIEZA VITRINA | G11: 20000
A12: 2
A13: 3
A14: 4
A15: 5
A16: 6
A17: 7
A18: 8
A19: 9
A20: 10
A21: 11
A22: 12
A23: 13
... A25: 15
B26: TOTALES | G26: =SUM(G11:G25) -> 20000

Sheet DICIEMBRE
C1: RENDICION CAJA CHICA
C2: FLORIDA CENTER
G3: MES | H3: DICIEMBRE
B4: SALDO ANTERIOR | E4: =+NOVIEMBRE!H8 -> 80000
B5: DEPÓSITO RENDICION ANTERIOR | E5: 20000
B6: MONTO ADICIONAL | E6: 0
B7: MONTO A RENDIR | E7: =SUM(E4:E6) -> 100000
B8: RENDIDO | E8: =+G26 -> 55580 | G8: SALDO AL CIERRE | H8: =E7-E8 -> 44420
A10: N° | B10: Fecha | C10: Tipo Documento (boleta venta-boleta honorarios-factura) | D10: N° documento | E10: RUT Titular del documento | F10: Detalle | G10: Total | H10: Código Imputacion (RSM) 180
A11: 1 | B11: 45989 | C11: vale | D11: 32 | F11: movilizacion retiro de material | G11: 2000
A12: 2 | B12: 45991 | C12: boleta | D12: 16820 | F12: limpieza de vitrina | G12: 20000
A13: 3 | B13: 46007 | C13: vale | D13: 33 | F13: movilizacion retiro gift card | G13: 2000
A14: 4 | B14: 46013 | C14: boleta | D14: 16926299 | F14: cintas de regalo | G14: 5980
A15: 5 | B15: 46014 | C15: boleta | D15: 3260934153 | F15: reunion fin de año equipo | G15: 25600
A16: 6
A17: 7
A18: 8
A19: 9
A20: 10
A21: 11
A22: 12
A23: 13
A24: 14
A25: 15
B26: TOTALES | G26: =SUM(G11:G25) -> 55580
