Workbook

Sheet JULIO 
C1: RENDICION CAJA CHICA
C2: TALCA
G3: MES | H3: JULIO
B4: SALDO ANTERIOR | E4: 49830
B5: DEPÓSITO RENDICION ANTERIOR | E5: 50170
B6: MONTO ADICIONAL | E6: 0
B7: MONTO A RENDIR | E7: =SUM(E4:E6) -> 100000
B8: RENDIDO | E8: =+G26 -> 22760 | G8: SALDO AL CIERRE | H8: =E7-E8 -> 77240
A10: N° | B10: Fecha | C10: Tipo Documento (boleta venta-boleta honorarios-factura) | D10: N° documento | E10: RUT Titular del documento | F10: Detalle | G10: Total | H10: Código Imputacion (RSM) 195
A11: 1 | B11: 45503 | C11: boleta venta | D11: 1117884534 | E11: - | F11: DESAYUNO EQUIPO | G11: 17880
A12: 2 | B12: 45505 | C12: - | D12: - | E12: - | F12: AGUA | G12: 2000
A13: 3 | B13: 45505 | C13: - | D13: - | E13: - | F13: PAN DESAYUNO | G13: 2880
A14: 4
A15: 5
A16: 6
A17: 7
A18: 8
A19: 9
A20: 10
A21: 11
A22: 12
A23: 13
A24: 14
A25: 15
B26: TOTALES | G26: =SUM(G11:G25) -> 22760

Sheet AGOSTO
C1: RENDICION CAJA CHICA
C2: TALCA
G3: MES | H3: AGOSTO
B4: SALDO ANTERIOR | E4: =+'JULIO '!H8 -> 77240
B5: DEPÓSITO RENDICION ANTERIOR | E5: 26750
B6: MONTO ADICIONAL | E6: 0
B7: MONTO A RENDIR | E7: =SUM(E4:E6) -> 103990
B8: RENDIDO | E8: =+G26 -> 19080 | G8: SALDO AL CIERRE | H8: =E7-E8 -> 84910
A10: N° | B10: Fecha | C10: Tipo Documento (boleta venta-boleta honorarios-factura) | D10: N° documento | E10: RUT Titular del documento | F10: Detalle | G10: Total | H10: Código Imputacion (RSM) 195
A11: 1 | B11: 45512 | C11: boleta | D11: 17886144 | F11: dulces | G11: 4150
A12: 2 | B12: 45512 | C12: boleta | D12: 10182397 | F12: pecera | G12: 2990
A13: 3 | B13: 45518 | C13: boleta | D13: 1126736506 | F13: dulces | G13: 3990
A14: 4 | B14: 45528 | C14: boleta | D14: 2777327 | F14: agua | G14: 2000
A15: 5 | B15: 45527 | C15: boleta | D15: 1117724436 | F15: lisoform + pan | G15: 3750
A16: 6 | B16: 45532 | C16: boleta | D16: 277327 | F16: agua | G16: 2200
A17: 7
A18: 8
A19: 9
A20: 10
A21: 11
A22: 12
A23: 13
A24: 14
A25: 15
B26: TOTALES | G26: =SUM(G11:G25) -> 19080

Sheet SEPTIEMBRE
C1: RENDICION CAJA CHICA
C2: TALCA
G3: MES | H3: SEPTIEMBRE
B4: SALDO ANTERIOR | E4: =+AGOSTO!H8 -> 84910
B5: DEPÓSITO RENDICION ANTERIOR | E5: 19080
B6: MONTO ADICIONAL | E6: 0
B7: MONTO A RENDIR | E7: =SUM(E4:E6) -> 103990
B8: RENDIDO | E8: =+G26 -> 100398 | G8: SALDO AL CIERRE | H8: =E7-E8 -> 3592
A10: N° | B10: Fecha | C10: Tipo Documento (boleta venta-boleta honorarios-factura) | D10: N° documento | E10: RUT Titular del documento | F10: Detalle | G10: Total | H10: Código Imputacion (RSM) 195
A11: 1 | C11: BOLETA | F11: agua | G11: 2000
A12: 2 | C12: BOLETA | F12: agua | G12: 2000
A13: 3 | C13: BOLETA | F13: agua | G13: 2000
A14: 4 | C14: BOLETA | F14: agua | G14: 2000
A15: 5 | C15: BOLETA | F15: cordoneria | G15: 2750
A16: 6 | F16: colectivo | G16: 1600
A17: 7 | C17: BOLETA | F17: banderin | G17: 1000
A18: 8 | C18: BOLETA | F18: desayuno con Mafer | G18: 6330
A19: 9 | C19: FACTURA | F19: LIMPIEZA VITRINA | G19: 35000
A20: 10 | C20: BOLETA | F20: desayuno equipo | G20: 9378
A21: 11 | C21: BOLETA | F21: maskin | G21: 6380
A22: 12 | C22: BOLETA | F22: 2 pizza reunion Mafer | G22: 16080
A23: 13 | C23: BOLETA | F23: 2 pizza reunion Mafer | G23: 13880
A24: 14
A25: 15
B26: TOTALES | G26: =SUM(G11:G25) -> 100398

Sheet OCTUBRE
C1: RENDICION CAJA CHICA
C2: TALCA
G3: MES | H3: OCTUBRE
B4: SALDO ANTERIOR | E4: =+SEPTIEMBRE!H8 -> 3592
B5: DEPÓSITO RENDICION ANTERIOR | E5: 100398
B6: MONTO ADICIONAL | E6: 0
B7: MONTO A RENDIR | E7: =SUM(E4:E6) -> 103990
B8: RENDIDO | E8: =+G30 -> 130883 | G8: SALDO AL CIERRE | H8: =E7-E8 -> -26893
A10: N° | B10: Fecha | C10: Tipo Documento (boleta venta-boleta honorarios-factura) | D10: N° documento | E10: RUT Titular del documento | F10: Detalle | G10: Total | H10: Código Imputacion (RSM) 195
A11: 1 | B11: 45569 | C11: boleta | F11: AGUA | G11: 2000
A12: 2 | B12: 45569 | C12: boleta | F12: lavaloza+bolsas | G12: 3340
A13: 3 | B13: 45570 | C13: boleta | F13: pilas | G13: 3050
A14: 4 | B14: 45570 | C14: boleta | F14: desayuno | G14: 17256
A15: 5 | B15: 45570 | C15: 2 da boleta | F15: desayuno continuación | G15: 6255
A16: 6 | B16: 45572 | C16: boleta | F16: agua+ vaso | G16: 2240
A17: 7 | B17: 45577 | C17: boleta | F17: agua bidon | G17: 2000
A18: 8 | B18: 45580 | C18: boleta | F18: dulces | G18: 4000
A19: 9 | B19: 45582 | C19: boleta | F19: cinta embalaje | G19: 3780
A20: 10 | B20: 45583 | C20: boleta | F20: cinta embalaje | G20: 3780
A21: 11 | B21: 45585 | C21: boleta | F21: colectivo municipalidad | G21: 3200
A22: 12 | B22: 45588 | C22: boleta | F22: despacho chileexpress | G22: 13832
... A29: 19 | B29: 45595 | C29: factura | F29: limpieza vitrina | G29: 35000
B30: TOTALES | G30: =SUM(G11:G29) -> 130883

Sheet NOVIEMBRE
C1: RENDICION CAJA CHICA
C2: TALCA
G3: MES | H3: NOVIEMBRE
B4: SALDO ANTERIOR | E4: =+OCTUBRE!H8 -> -26893
B5: DEPÓSITO RENDICION ANTERIOR | E5: 130883
B6: MONTO ADICIONAL | E6: 0
B7: MONTO A RENDIR | E7: =SUM(E4:E6) -> 103990
B8: RENDIDO | E8: =+G26 -> 59700 | G8: SALDO AL CIERRE | H8: =E7-E8 -> 44290
A10: N° | B10: Fecha | C10: Tipo Documento (boleta venta-boleta honorarios-factura) | D10: N° documento | E10: RUT Titular del documento | F10: Detalle | G10: Total | H10: Código Imputacion (RSM) 195
A11: 1 | B11: 45607 | C11: boleta | F11: cintas de regalo | G11: 690
A12: 2 | B12: 45607 | C12: boleta | F12: agua bidon | G12: 6000
A13: 3 | B13: 45617 | C13: boleta | F13: limpieza vitrina | G13: 35000
A14: 4 | B14: 45621 | C14: boleta | F14: ganchos | G14: 1290
A15: 5 | B15: 45617 | C15: boleta | F15: agua de bidon | G15: 6000
A16: 6 | B16: 45617 | C16: boleta | F16: agua | G16: 1000
A17: 7 | B17: 45619 | C17: boleta | F17: insumos | G17: 4000
A18: 8 | B18: 45615 | C18: boleta | F18: panaderia | G18: 3240
A19: 9 | B19: 45610 | C19: boleta | F19: paqueteria | G19: 2480
A20: 10
A21: 11
A22: 12
A23: 13
A24: 14
A25: 15
B26: TOTALES | G26: =SUM(G11:G25) -> 59700

Sheet DICIEMBRE
C1: RENDICION CAJA CHICA
C2: TALCA
G3: MES | H3: DICIEMBRE
B4: SALDO ANTERIOR | E4: =+NOVIEMBRE!H8 -> 44290
B5: DEPÓSITO RENDICION ANTERIOR | E5: 59700
B6: MONTO ADICIONAL | E6: 0
B7: MONTO A RENDIR | E7: =SUM(E4:E6) -> 103990
B8: RENDIDO | E8: =+G26 -> 85383 | G8: SALDO AL CIERRE | H8: =E7-E8 -> 18607
A10: N° | B10: Fecha | C10: Tipo Documento (boleta venta-boleta honorarios-factura) | D10: N° documento | E10: RUT Titular del documento | F10: Detalle | G10: Total | H10: Código Imputacion (RSM) 195
A11: 1 | B11: 45633 | C11: boleta | F11: boleta lider/ desayuno | G11: 18661
A12: 2 | B12: 45631 | C12: boleta | F12: boleta almacen/ pan desayuno | G12: 2760
A13: 3 | B13: 45631 | C13: boleta | F13: agua bollenes | G13: 6000
A14: 4 | B14: 45637 | C14: boleta | F14: dulces para clientes en navidad | G14: 3440
A15: 5 | B15: 45643 | C15: boleta | F15: agua bollenes | G15: 6000
A16: 6 | B16: 45637 | C16: boleta | F16: librería/ cintas de regalo para ventas | G16: 3930
A17: 7 | B17: 45645 | C17: boleta honorario | F17: limpieza de vidrios | G17: 35000
A18: 8 | B18: 45648 | C18: boleta | F18: boleta tucan / scotch | G18: 462
A19: 9 | B19: 45648 | C19: boleta lider | F19: dulces para clientes en navidad | G19: 2990
A20: 10 | B20: 45648 | C20: boleta lider | F20: barra de helados y dulce clientes | G20: 6140
A21: 11 | B21: 45293 | C21: boleta | F21: agua bollenes
A22: 12
A23: 13
A24: 14
A25: 15
B26: TOTALES | G26: =SUM(G11:G25) -> 85383

Sheet ENERO 25
D1: RENDICION CAJA CHICA
D2: TALCA
H3: MES | I3: ENERO 25
C4: SALDO ANTERIOR
C5: DEPÓSITO RENDICION ANTERIOR
C6: MONTO ADICIONAL | F6: 0
C7: MONTO A RENDIR
C8: RENDIDO | F8: =+H26 -> 90688 | H8: SALDO AL CIERRE | I8: =F7-F8 -> -90688
B10: N° | C10: Fecha | D10: Tipo Documento (boleta venta-boleta honorarios-factura) | E10: N° documento | F10: RUT Titular del documento | G10: Detalle | H10: Total | I10: Código Imputacion (RSM) 195
B11: 1 | C11: 46028 | D11: boleta | E11: 813566322 | G11: pilas | H11: 3960
B12: 2 | C12: 46027 | D12: boleto venta | E12: 18717330131 | G12: pasaje a Santiago (reunión) | H12: 10000
B13: 3 | C13: 46029 | D13: comprobante | E13: S/N | G13: uber terminal Talca | H13: 4793
B14: 4 | C14: 46029 | D14: comprobante | E14: S/N | G14: uber hacia renunion Stgo | H14: 6314
B15: 5 | C15: 46029 | D15: boleta | E15: 597034144697 | G15: metro de Santiago | H15: 2000
B16: 6 | C16: 46033 | D16: boleto venta | E16: 00NX7WTB | G16: pasaje a Talca (devuelta) | H16: 8500
B17: 7 | C17: 46033 | D17: comprobante | E17: S/N | G17: uber desde terminal | H17: 2748
B18: 8 | C18: 46040 | D18: boleta | E18: 1957655 | G18: cinta embalaje | H18: 2680
B19: 9 | C19: 46046 | D19: boleta | E19: 129925 | G19: cafes desayuno equipo | H19: 4000
B20: 10 | C20: 46046 | D20: boleta | E20: 56716 | G20: comida desayuno equipo | H20: 5000
B21: 11 | C21: 46048 | D21: boleta | E21: 6252 | G21: agua purificada | H21: 6000
B22: 12 | C22: 46049 | D22: boleta honorario | E22: 59 | G22: Limpieza Vitrina | H22: 34693
B23: 13
B24: 14
B25: 15
C26: TOTALES | H26: =SUM(H11:H25) -> 90688
G31: RESPONSABLE FONDO FIJO
G32: Belen Gatica

Sheet FEB25
C1: RENDICION CAJA CHICA
C2: TALCA
G3: MES | H3: FEBRERO
B4: SALDO ANTERIOR | E4: =+'ENERO 25'!I8 -> -90688
B5: DEPÓSITO RENDICION ANTERIOR | E5: 84854
B6: MONTO ADICIONAL | E6: 0
B7: MONTO A RENDIR | E7: =SUM(E4:E6) -> -5834
B8: RENDIDO | E8: =+G26 -> 83594 | G8: SALDO AL CIERRE | H8: =E7-E8 -> -89428
A10: N° | B10: Fecha | C10: Tipo Documento (boleta venta-boleta honorarios-factura) | D10: N° documento | E10: RUT Titular del documento | F10: Detalle | G10: Total | H10: Código Imputacion (RSM) 195
A11: 1 | B11: 45691 | C11: BOLETA | F11: AGUA | G11: 6000
A12: 2 | B12: 45696 | C12: BOLETA | F12: agua y parte del desayuno | G12: 9150
A13: 3 | B13: 45696 | C13: BOLETA | F13: utiles de aseo | G13: 5700
A14: 4 | B14: 45696 | C14: BOLETA | F14: utiles de aseo | G14: 7200
A15: 5 | B15: 45698 | C15: boleta | F15: desayuno equipo | G15: 18327
A16: 6 | B16: 45703 | C16: boleta | F16: agua (imprevisto) | G16: 2000
A17: 7 | B17: 45709 | C17: boleta | F17: agua | G17: 6000
A18: 8 | B18: 45700 | C18: boleta colectivo | F18: colectivo por pedido de chileexpress - Belen | G18: 800
A19: 9 | B19: 45700 | C19: boleta colectivo | F19: colectivo por pedido de chileexpress - Belén | G19: 800
A20: 10 | B20: 45703 | C20: boleta colectivo | F20: colectivo sector nor oriente (chileexpress) - Delfina | G20: 1500
A21: 11 | B21: 45703 | C21: boleta colectivo | F21: colectivo sector nor oriente (chileexpress) - Delfina | G21: 1500
A22: 12 | B22: 45706 | C22: boleta uber | F22: uber entrega chileexpress - Sarita | G22: 4497
A23: 13 | B23: 45708 | C23: Boleta honorarios | F23: VITRINA | G23: 17500
A24: 14 | B24: 20/02/20225 | C24: BOLETA | F24: didi entrega chileexpress | G24: 2620
A25: 15
B26: TOTALES | G26: =SUM(G11:G25) -> 83594
F30: RESPONSABLE FONDO FIJO
F31: Belen Gatica

Sheet MAR25
C1: RENDICION CAJA CHICA
C2: TALCA
G3: MES | H3: MARZO
B4: SALDO ANTERIOR | E4: =+'FEB25'!H8 -> -89428
B5: DEPÓSITO RENDICION ANTERIOR | E5: 83594
B6: MONTO ADICIONAL | E6: 0
B7: MONTO A RENDIR | E7: =SUM(E4:E6) -> -5834
B8: RENDIDO | E8: =+G30 -> 159038 | G8: SALDO AL CIERRE | H8: =E7-E8 -> -164872
A10: N° | B10: Fecha | C10: Tipo Documento (boleta venta-boleta honorarios-factura) | D10: N° documento | E10: RUT Titular del documento | F10: Detalle | G10: Total | H10: Código Imputacion (RSM) 195
A11: 1 | B11: 44993 | C11: BOLETA | F11: DESAYUNO 08/03 | G11: 12593
A12: 2 | B12: 45724 | C12: BOLETA | F12: DESAYUNO 08/03 | G12: 2050
A13: 3 | B13: 45724 | C13: BOLETA | F13: pie de limon, dia de la mujer | G13: 8990
A14: 4 | B14: 45724 | C14: BOLETA | F14: pie de otro sabor para Sara (alergia) | G14: 4100
A15: 5 | B15: 27/02/205 | C15: BOLETA | F15: entrega en Chile express Benjamin | G15: 1798
A16: 6 | B16: 45726 | C16: BOLETA | F16: flores decorativas | G16: 2800
A17: 7 | B17: 45726 | C17: BOLETA | F17: cinta adhesiva | G17: 3780
A18: 9 | B18: 45726 | C18: BOLETA | F18: plasti flechas / Compra Esteban | G18: 16645
A19: 10 | B19: 45726 | C19: BOLETA | F19: enchufes cuadros vitrina / compra Esteban | G19: 12330
A20: 11 | B20: 45727 | C20: BOLETA | F20: agua | G20: 6000
A21: 12 | B21: 31/04/2025 | C21: BOLETA | F21: agua | G21: 6000
A22: 13 | B22: 45738 | C22: BOLETA | F22: cuaderno | G22: 3990
A23: 14 | B23: 45742 | C23: BOLETA | F23: pilas teclado | G23: 2420
A24: 15 | B24: 45742 | C24: PASAJE | F24: pasaje ida Santiago | G24: 10500
A25: 16 | B25: 45742 | C25: RECIBO | F25: uber Santiago | G25: 8416
A26: 17 | B26: 45743 | C26: RECIBO | F26: uber a bodega | G26: 10700
A27: 18 | B27: 45745 | C27: PASAJE | F27: pasaje vuelta a Talca | G27: 8500
A28: 19 | B28: 45745 | C28: RECIBO | F28: uber en Talca | G28: 2426
A29: 20 | B29: 45378 | C29: HONORARIO | F29: limpieza vitrina | G29: 35000
B30: TOTALES | G30: =SUM(G11:G29) -> 159038
F34: RESPONSABLE FONDO FIJO
F35: Belen Gatica

Sheet ABR25
C1: RENDICION CAJA CHICA
C2: TALCA
G3: MES | H3: ABRIL
B4: SALDO ANTERIOR | E4: =+'MAR25'!H8 -> -164872
B5: DEPÓSITO RENDICION ANTERIOR | E5: 159038
B6: MONTO ADICIONAL | E6: 0
B7: MONTO A RENDIR | E7: =SUM(E4:E6) -> -5834
B8: RENDIDO | E8: =+G24 -> 83668 | G8: SALDO AL CIERRE | H8: =E7-E8 -> -89502
A10: N° | B10: Fecha | C10: Tipo Documento (boleta venta-boleta honorarios-factura) | D10: N° documento | E10: RUT Titular del documento | F10: Detalle | G10: Total | H10: Código Imputacion (RSM) 195
A11: 1 | B11: 45749 | C11: boleta | D11: 1177470973 | F11: toalla nova | G11: 1000
A12: 2 | B12: 45748 | C12: boleta | D12: 5955 | F12: agua | G12: 6000
A13: 3 | B13: 45762 | C13: boleta | D13: 1800678 | F13: cinta embalaje | G13: 3780
A14: 4 | B14: 45762 | C14: boleta | D14: 53803405 | F14: envio de precios (Esteban) | G14: 6218
A15: 5 | B15: 45768 | C15: boleta | D15: 1801818 | F15: cinta embalaje | G15: 5670
A16: 6 | B16: 45768 | C16: boleta | D16: 5966 | F16: agua | G16: 6000
A17: 7 | B17: 45408 | C17: boleta | D17: 9 | F17: limpieza vitrina | G17: 35000
A18: 8 | B18: 45384 | C18: Comprobante Banco | D18: S/N | F18: billete falso | G18: 20000
A19: 9
A20: 10
A21: 11
A22: 12
A23: 13
B24: TOTALES | G24: =SUM(G11:G23) -> 83668
F28: RESPONSABLE FONDO FIJO
F29: Belen Gatica

Sheet MAY25
C1: RENDICION CAJA CHICA
C2: TALCA
G3: MES | H3: MAYO
B4: SALDO ANTERIOR | E4: =+'ABR25'!H8 -> -89502
B5: DEPÓSITO RENDICION ANTERIOR | E5: 0
B6: MONTO ADICIONAL
B7: MONTO A RENDIR | E7: =SUM(E4:E6) -> -89502
B8: RENDIDO | E8: =+G26 -> 82270 | G8: SALDO AL CIERRE | H8: =E7-E8 -> -171772
A10: N° | B10: Fecha | C10: Tipo Documento (boleta venta-boleta honorarios-factura) | D10: N° documento | E10: RUT Titular del documento | F10: Detalle | G10: Total | H10: Código Imputacion (RSM) 195
A11: 1 | B11: 45782 | C11: BOLETA | D11: 1804390 | F11: cinta embalaje | G11: 7560
A12: 2 | B12: 45784 | C12: BOLETA | D12: 1188648993 | F12: toallas de papel | G12: 2990
A13: 3 | B13: 45780 | C13: BOLETO | D13: 1455506 | F13: colectivo para envio chileexpress | G13: 800
A14: 4 | B14: 45780 | C14: BOLETO | D14: 8106987 | F14: colectivo para envio chileexpress | G14: 800
A15: 5 | B15: 45785 | C15: BOLETO | D15: 2222438 | F15: colectivo para envio chileexpress | G15: 800
A16: 6 | B16: 45785 | C16: BOLETO | D16: 858149 | F16: colectivo para envio chileexpress | G16: 800
A17: 7 | B17: 45788 | C17: BOLETA | D17: 1188356928 | F17: agua purificada | G17: 790
A18: 8 | B18: 45789 | C18: BOLETA | D18: 5978 | F18: bidones de agua purificada | G18: 6000
A19: 9 | B19: 45807 | C19: boleta | D19: 1.9336921e+15 | F19: Desayuno Cassi | G19: 26730
A20: 10 | B20: 45808 | C20: boleta | F20: Limpieza Vitrina | G20: 35000
A21: 11
A22: 12
A23: 13
A24: 14
A25: 15
B26: TOTALES | G26: =SUM(G11:G25) -> 82270
F30: RESPONSABLE FONDO FIJO
F31: Belen Gatica

Sheet JUN25
C1: RENDICION CAJA CHICA
C2: TALCA
G3: MES | H3: JUNIO
B4: SALDO ANTERIOR | E4: =+'MAY25'!H8 -> -171772
B5: DEPÓSITO RENDICION ANTERIOR | E5: 165938
B6: MONTO ADICIONAL | E6: 4
B7: MONTO A RENDIR | E7: =SUM(E4:E6) -> -5830
B8: RENDIDO | E8: =+G26 -> 51599 | G8: SALDO AL CIERRE | H8: =E7-E8 -> -57429
A10: N° | B10: Fecha | C10: Tipo Documento (boleta venta-boleta honorarios-factura) | D10: N° documento | E10: RUT Titular del documento | F10: Detalle | G10: Total | H10: Código Imputacion (RSM) 195
A11: 1 | B11: 45836 | C11: BOLETA | D11: 792523517 | F11: SODIMAC - ALAMBRE | G11: 2129
A12: 2 | B12: 45836 | C12: BOLETA | D12: 1188556337 | F12: LIDER - PILAS | G12: 5490
A13: 3 | B13: 228438 | C13: BOLETA | F13: AGUA PURIFICADA | G13: 6000
A14: 4 | B14: 45823 | C14: BOLETA | F14: VITRINA | G14: 35000
A15: 5 | B15: 45819 | C15: boleta | D15: 21523427 | F15: MINISO- BOTELLAS SPRAY | G15: 2980
A16: 6
A17: 7
A18: 8
A19: 9
A20: 10
A21: 11
A22: 12
A23: 13
A24: 14
A25: 15
B26: TOTALES | G26: =SUM(G11:G25) -> 51599
F30: RESPONSABLE FONDO FIJO
F31: Belen Gatica

Sheet JUL25 
C1: RENDICION CAJA CHICA
C2: TALCA
G3: MES | H3: JULIO
B4: SALDO ANTERIOR | E4: =+'JUN25'!H8 -> -57429
B5: DEPÓSITO RENDICION ANTERIOR | E5: 0
B6: MONTO ADICIONAL | E6: 0
B7: MONTO A RENDIR | E7: =SUM(E4:E6) -> -57429
B8: RENDIDO | E8: =+G27 -> 126228 | G8: SALDO AL CIERRE | H8: =E7-E8 -> -183657
A10: N° | B10: Fecha | C10: Tipo Documento (boleta venta-boleta honorarios-factura) | D10: N° documento | E10: RUT Titular del documento | F10: Detalle | G10: Total | H10: Código Imputacion (RSM) 195
A11: 1 | B11: 45842 | C11: boleta | D11: 25067 | F11: bidones de agua | G11: 6000
A12: 2 | B12: 45851 | C12: boleta | D12: 23.726 | F12: pilas | G12: 6000
A13: 3 | B13: 45855 | C13: boleta | D13: 21533962 | F13: cajas organizadoras | G13: 1990
A14: 4 | B14: 45855 | C14: boleto | D14: 1430200 | F14: colectivo para chilexpress | G14: 800
A15: 5 | B15: 45855 | C15: boleto | D15: 22006 | F15: colectivo para chilexpress | G15: 800
A16: 6 | B16: 45856 | C16: boleta | D16: 55321 | F16: DESAYUNO REUNION | G16: 6000
A17: 7 | B17: 45842 | C17: boleta | D17: 21 | F17: vitrina | G17: 35000
A18: 8 | B18: 45861 | C18: boleta | D18: 6043 | F18: agua | G18: 6000
A19: 9 | B19: 45862 | C19: boleto | D19: 187-16645776 | F19: Bus Talca - Paris - Londres | G19: 10000
A20: 10 | B20: 45862 | C20: boleto | D20: 1534879440 | F20: Bus Altas Cumbres | G20: 10500
A21: 11 | B21: 45862 | C21: comprobante | F21: Uber | G21: 4598
A22: 12 | B22: 45862 | C22: comprobante | F22: DIDI | G22: 2540
A23: 13 | B23: 45862 | C23: comprobante | F23: recarga metro | G23: 1000
A24: 14 | B24: 45863 | C24: boleta | D24: 22 | F24: vitrina | G24: 35000
A25: 15
A26: 16
B27: TOTALES | G27: =SUM(G11:G26) -> 126228
F31: RESPONSABLE FONDO FIJO
F32: Belen Gatica

Sheet AGO25
C1: RENDICION CAJA CHICA
C2: TALCA
G3: MES | H3: AGOSTO
B4: SALDO ANTERIOR | E4: =+'JUL25 '!H8 -> -183657
B5: DEPÓSITO RENDICION ANTERIOR | E5: 177827
B6: MONTO ADICIONAL
B7: MONTO A RENDIR | E7: =SUM(E4:E6) -> -5830
B8: RENDIDO | E8: =+G26 -> 75481 | G8: SALDO AL CIERRE | H8: =E7-E8 -> -81311
A10: N° | B10: Fecha | C10: Tipo Documento (boleta venta-boleta honorarios-factura) | D10: N° documento | E10: RUT Titular del documento | F10: Detalle | G10: Total | H10: Código Imputacion (RSM) 195
A11: 1 | B11: 45894 | C11: boleta | D11: 68448081 | F11: marco para patente | G11: 4990
A12: 2 | B12: 45894 | C12: boleta | D12: 1214038783 | F12: boleta lider - desayuno | G12: 22501
A13: 3 | B13: 45870 | C13: boleta | D13: 21537675 | F13: caja plasticas | G13: 990
A14: 4 | B14: 45894 | C14: boleta | D14: 24 | F14: vitrina | G14: 35000
A15: 5 | B15: 45876 | C15: boleta | D15: 6054 | F15: agua bidon | G15: 6000
A16: 6 | B16: 45894 | C16: boleta | F16: agua bidon | G16: 6000
A17: 7
A18: 8
A19: 9
A20: 10
A21: 11
A22: 12
A23: 13
A24: 14
A25: 15
B26: TOTALES | G26: =SUM(G11:G25) -> 75481
F30: RESPONSABLE FONDO FIJO
F31: Belen Gatica

Sheet SEPT25
C1: RENDICION CAJA CHICA
C2: TALCA
G3: MES | H3: SEPTIEMBRE
B4: SALDO ANTERIOR | E4: =+'AGO25'!H8 -> -81311
B5: DEPÓSITO RENDICION ANTERIOR | E5: 75481
B6: MONTO ADICIONAL
B7: MONTO A RENDIR | E7: =SUM(E4:E6) -> -5830
B8: RENDIDO | E8: =+G26 -> 92323 | G8: SALDO AL CIERRE | H8: =E7-E8 -> -98153
A10: N° | B10: Fecha | C10: Tipo Documento (boleta venta-boleta honorarios-factura) | D10: N° documento | E10: RUT Titular del documento | F10: Detalle | G10: Total | H10: Código Imputacion (RSM) 195
A11: 1 | B11: 45897 | C11: boleta | D11: 21545778 | F11: cable USB | G11: 2995
A12: 2 | B12: 45897 | C12: boleta | D12: 21545728 | F12: organizador de plastico | G12: 3490
A13: 3 | B13: 45903 | C13: boleta | D13: 1887241 | F13: cinta embalaje | G13: 5670
A14: 4 | B14: 45907 | C14: boleta | D14: 13156641 | F14: guirnaldas | G14: 1980
A15: 5 | B15: 45913 | C15: boletta | D15: 572420 | F15: escarapelas | G15: 5000
A16: 6 | B16: 45917 | C16: comprobante | D16: s/n | F16: uber delfina | G16: 3298
A17: 7 | B17: 45920 | C17: boleta | D17: 11494014 | F17: bebida | G17: 2890
A18: 8 | B18: 45916 | C18: boleta | D18: 6088 | F18: agua de bidon | G18: 6000
A19: 9 | B19: 45922 | C19: boleta | D19: 283 | F19: celebracion fiestas patrias | G19: 26000
A20: 10 | B20: 45924 | C20: honorarios | D20: 32 | F20: limpieza de vitrina | G20: 35000
A21: 11
A22: 12
A23: 13
A24: 14
A25: 15
B26: TOTALES | G26: =SUM(G11:G25) -> 92323
F30: RESPONSABLE FONDO FIJO
F31: Belen Gatica

Sheet OCT25
C1: RENDICION CAJA CHICA
C2: TALCA
G3: MES | H3: OCTUBRE
B4: SALDO ANTERIOR | E4: 92323
B5: DEPÓSITO RENDICION ANTERIOR
B6: MONTO ADICIONAL | E6: 4
B7: MONTO A RENDIR | E7: =SUM(E4:E6) -> 92327
B8: RENDIDO | E8: =+G26 -> 58180 | G8: SALDO AL CIERRE | H8: =E7-E8 -> 34147
A10: N° | B10: Fecha | C10: Tipo Documento (boleta venta-boleta honorarios-factura) | D10: N° documento | E10: RUT Titular del documento | F10: Detalle | G10: Total | H10: Código Imputacion (RSM) 195
A11: 1 | B11: 45940 | D11: 341276 | F11: desayuno equipo | G11: 2800
A12: 2 | B12: 45940 | D12: 112874 | F12: desayuno equipo | G12: 9000
A13: 3 | B13: 45939 | D13: 1907067 | F13: cinta embalaje | G13: 3780
A14: 4 | B14: 45950 | D14: 38 | F14: vitrina | G14: 35000
A15: 5 | B15: 45936 | D15: 8867132 | F15: colectivo entrega chileexpress | G15: 800
A16: 6 | B16: 45936 | D16: 8799398 | F16: colectivo entrega chileexpress | G16: 800
A17: 7 | B17: 45938 | D17: 6108 | F17: agua bidon | G17: 6000
A18: 8
A19: 9
A20: 10
A21: 11
A22: 12
A23: 13
A24: 14
A25: 15
B26: TOTALES | G26: =SUM(G11:G25) -> 58180
F30: RESPONSABLE FONDO FIJO
F31: Belen Gatica

Sheet NOV25
C1: RENDICION CAJA CHICA
C2: TALCA
G3: MES | H3: NOVIEMBRE
B4: SALDO ANTERIOR | E4: =+'OCT25'!H8 -> 34147
B5: DEPÓSITO RENDICION ANTERIOR
B6: MONTO ADICIONAL | E6: 4
B7: MONTO A RENDIR | E7: =SUM(E4:E6) -> 34151
B8: RENDIDO | E8: =+G27 -> 83497 | G8: SALDO AL CIERRE | H8: =E7-E8 -> -49346
A10: N° | B10: Fecha | C10: Tipo Documento (boleta venta-boleta honorarios-factura) | D10: N° documento | E10: RUT Titular del documento | F10: Detalle | G10: Total | H10: Código Imputacion (RSM) 195
A11: 1 | B11: 45960 | F11: ENTREVISTAS recursos humanos | G11: 3800
A12: 2 | B12: 45960 | F12: ENTREVISTAS recursos humanos | G12: 2600
A13: 3 | F13: Locomocion entrega starken | G13: 800
A14: 4 | F14: Locomocion entrega starken | G14: 800
A15: 5 | F15: Locomocion entrega starken | G15: 800
A16: 6 | F16: Locomocion entrega starken | G16: 800
A17: 7 | B17: 45966 | C17: 6138 | F17: agua de bidon | G17: 6000
A18: 8 | B18: 45967 | C18: 3224433758 | F18: Carpeta documentos + dulces | G18: 4121
A19: 9 | B19: 45974 | C19: 28871 | F19: scotch | G19: 3000
A20: 10 | B20: 45976 | C20: 52139 | F20: toallas humedas de limpieza | G20: 3690
A21: 11 | B21: 45978 | C21: 1233000736 | F21: Desayuno Equipo - reunión | G21: 22086
A22: 12 | B22: 45978 | F22: Vitrina | G22: 35000
A23: 13
A24: 14
A25: 15
A26: 16
B27: TOTALES | G27: =SUM(G11:G26) -> 83497
F31: RESPONSABLE FONDO FIJO
F32: Belen Gatica

Sheet DIC25
C1: RENDICION CAJA CHICA
C2: TALCA
G3: MES | H3: DICIEMBRE
B4: SALDO ANTERIOR | E4: =+'NOV25'!H8 -> -49346
B5: DEPÓSITO RENDICION ANTERIOR
B6: MONTO ADICIONAL | E6: 4
B7: MONTO A RENDIR | E7: =SUM(E4:E6) -> -49342
B8: RENDIDO | E8: =+G26 -> 94510 | G8: SALDO AL CIERRE | H8: =E7-E8 -> -143852
A10: N° | B10: Fecha | C10: Tipo Documento (boleta venta-boleta honorarios-factura) | D10: N° documento | E10: RUT Titular del documento | F10: Detalle | G10: Total | H10: Código Imputacion (RSM) 195
A11: 1 | B11: 45630 | D11: 135032 | F11: paqueteria | G11: 4200
A12: 2 | B12: 45996 | D12: 1270512487 | F12: desayuno equipo | G12: 4040
A13: 3 | B13: 45990 | D13: 774191 | F13: desayuno paltas | G13: 3400
A14: 4 | B14: 45987 | D14: 304155 | F14: reunion | G14: 6000
A15: 5 | B15: 45993 | D15: 9874 | F15: cinta | G15: 2500
A16: 6 | B16: 46008 | D16: 1947152 | F16: cinta de regalo | G16: 1380
A17: 7 | B17: 45995 | D17: 6181 | F17: agua de bidon | G17: 6000
A18: 8 | B18: 46010 | D18: 1947581 | F18: scotch | G18: 1350
A19: 9 | B19: 46003 | D19: 11840 | F19: toalla papel | G19: 2200
A20: 10 | B20: 46004 | D20: 777606 | F20: toallas de limpieza humedas | G20: 3300
A21: 11 | B21: 45642 | D21: 14066917 | F21: caja organizadora | G21: 2490
A22: 12 | B22: 45646 | D22: 1246786929 | F22: agua + dulces | G22: 3770
... A25: 15 | B25: 46021 | D25: 6212 | F25: AGUA | G25: 6000
B26: TOTALES | G26: =SUM(G11:G25) -> 94510
F30: RESPONSABLE FONDO FIJO
F31: Belen Gatica
