Workbook

Sheet DICIEMBRE 
C1: RENDICION CAJA CHICA
C2: OESTE
G3: MES | H3: DICIEMBRTE
B4: SALDO ANTERIOR
B5: DEPÓSITO RENDICION ANTERIOR | E5: 100000
B6: MONTO ADICIONAL | E6: 0
B7: MONTO A RENDIR | E7: =SUM(E4:E6) -> 100000
B8: RENDIDO | E8: =SUM(G28) -> 101900 | G8: SALDO AL CIERRE | H8: =E7-E8 -> -1900
A10: N° | B10: Fecha | C10: Tipo Documento (boleta venta-boleta honorarios-factura) | D10: N° documento | E10: RUT Titular del documento | F10: Detalle | G10: Total | H10: Código Imputacion (RSM) 210
A11: 1 | B11: 45640 | C11: BOLETA | D11: 53301541 | E11: 80.478.200-1 | F11: CORCHETERA | G11: 6990
A12: 2 | B12: 45640 | C12: BOLETA | D12: 729951278 | E12: 78.627.210-6 | F12: REUNION TIENDA | G12: 10250
A13: 3 | B13: 45645 | C13: BOLETA | D13: 53302227 | E13: 80.478.200-1 | F13: CALCULA/PERFORADO | G13: 23680
A14: 4 | B14: 45645 | C14: BOLETA | D14: 764356469 | E14: 96.792.430-K | F14: BASURERO | G14: 10990
A15: 5 | B15: 45646 | C15: BOLETA | D15: 764869867 | E15: 96.792.430-k | F15: CLOSET TIENDA | G15: 49990
A16: 6
A17: 7
A18: 8
A19: 9
A20: 10
A21: 11
A22: 12
A23: 13
A24: 14
A25: 15
A26: 16
A27: 17
B28: TOTALES | G28: =SUM(G11:G27) -> 101900

Sheet ENERO 25
C1: RENDICION CAJA CHICA
C2: OESTE
G3: MES | H3: ENERO
B4: SALDO ANTERIOR | E4: =+'DICIEMBRE '!H8 -> -1900
B5: DEPÓSITO RENDICION ANTERIOR | E5: 101900
B6: MONTO ADICIONAL | E6: 0
B7: MONTO A RENDIR | E7: =SUM(E4:E6) -> 100000
B8: RENDIDO | E8: =SUM(G28) -> 40000 | G8: SALDO AL CIERRE | H8: =E7-E8 -> 60000
A10: N° | B10: Fecha | C10: Tipo Documento (boleta venta-boleta honorarios-factura) | D10: N° documento | E10: RUT Titular del documento | F10: Detalle | G10: Total | H10: Código Imputacion (RSM) 210
A11: 1 | B11: 46019 | C11: BOLETA | D11: 1119 | E11: 5.666.822-5 | F11: fashada y salon limpieza | G11: 40000
A12: 2
A13: 3
A14: 4
A15: 5
A16: 6
A17: 7
A18: 8
A19: 9
A20: 10
A21: 11
A22: 12
A23: 13
... A27: 17
B28: TOTALES | G28: =SUM(G11:G27) -> 40000
F30: RESPONSABLE FONDO FIJO
F31: Jhonatan Canales

Sheet FEBRERO 25
C1: RENDICION CAJA CHICA
C2: OESTE
G3: MES | H3: FEBRERO
B4: SALDO ANTERIOR | E4: =+'ENERO 25'!H8 -> 60000
B5: DEPÓSITO RENDICION ANTERIOR | E5: 40000
B6: MONTO ADICIONAL | E6: 0
B7: MONTO A RENDIR | E7: =SUM(E4:E6) -> 100000
B8: RENDIDO | E8: =SUM(G18) -> 83620 | G8: SALDO AL CIERRE | H8: =E7-E8 -> 16380
A10: N° | B10: Fecha | C10: Tipo Documento (boleta venta-boleta honorarios-factura) | D10: N° documento | E10: RUT Titular del documento | F10: Detalle | G10: Total | H10: Código Imputacion (RSM) 210
A11: 1 | B11: 45687 | C11: boleta | D11: 2509445 | E11: 76.800.177-4 | F11: cumpleaños cata y camila | G11: 21060
A12: 2 | B12: 45690 | C12: boleta | D12: 749514850 | E12: 78.627.210-6 | F12: reunion tienda | G12: 8390
A13: 3 | B13: 45715 | C13: boleta | D13: 777610403 | E13: 96.792.430-k | F13: pitilla amarrar cajas | G13: 4790
A14: 4 | B14: 45714 | C14: boleta | D14: 778988929 | E14: 96.792.430-k | F14: manilla puerta/atornillador | G14: 9380
A15: 5 | B15: 45349 | C15: boleta | D15: 1162 | E15: 5.666.822-5 | F15: limpieza vidrios | G15: 40000
A16: 6
A17: 7
B18: TOTALES | G18: =SUM(G11:G17) -> 83620
G21: RESPONSABLE FONDO FIJO
G22: Jhonatan Canales

Sheet MARZO 25
C1: RENDICION CAJA CHICA
C2: OESTE
G3: MES | H3: MARZO
B4: SALDO ANTERIOR | E4: =+'FEBRERO 25'!H8 -> 16380
B5: DEPÓSITO RENDICION ANTERIOR | E5: 83620
B6: MONTO ADICIONAL | E6: 0
B7: MONTO A RENDIR | E7: =SUM(E4:E6) -> 100000
B8: RENDIDO | E8: =SUM(G28) -> 62050 | G8: SALDO AL CIERRE | H8: =E7-E8 -> 37950
A10: N° | B10: Fecha | C10: Tipo Documento (boleta venta-boleta honorarios-factura) | D10: N° documento | E10: RUT Titular del documento | F10: Detalle | G10: Total | H10: Código Imputacion (RSM) 210
A11: 1 | B11: 45724 | C11: BOLETA | D11: 61096 | E11: 76471568-3 | F11: DIA DE LA MUJER | G11: 5890
A12: 2 | B12: 45724 | C12: BOLETA | D12: 81482203 | E12: 96811130-2 | F12: DIA DE LA MUJER | G12: 16160
A13: 3 | B13: 45684 | C13: BOLETA | D13: 1140 | E13: 5666822-5 | F13: LIMPIEZA CRISTALES | G13: 40000
A14: 4
A15: 5
A16: 6
A17: 7
A18: 8
A19: 9
A20: 10
A21: 11
A22: 12
A23: 13
A24: 14
A25: 15
... A27: 17
B28: TOTALES | G28: =SUM(G11:G27) -> 62050
F32: RESPONSABLE FONDO FIJO

Sheet ABRIL 25
C1: RENDICION CAJA CHICA
C2: OESTE
G3: MES | H3: ABRIL
B4: SALDO ANTERIOR | E4: =+'MARZO 25'!H8 -> 37950
B5: DEPÓSITO RENDICION ANTERIOR | E5: 57930
B6: MONTO ADICIONAL | E6: 0
B7: MONTO A RENDIR | E7: =SUM(E4:E6) -> 95880
B8: RENDIDO | E8: =SUM(G28) -> 0 | G8: SALDO AL CIERRE | H8: =E7-E8 -> 95880
A10: N° | B10: Fecha | C10: Tipo Documento (boleta venta-boleta honorarios-factura) | D10: N° documento | E10: RUT Titular del documento | F10: Detalle | G10: Total | H10: Código Imputacion (RSM) 210
A11: 1
A12: 2
A13: 3
A14: 4
A15: 5
A16: 6
A17: 7
A18: 8
A19: 9
A20: 10
A21: 11
A22: 12
... A27: 17
B28: TOTALES | G28: =SUM(G11:G27) -> 0
F32: RESPONSABLE FONDO FIJO

Sheet MAYO 25
C1: RENDICION CAJA CHICA
C2: OESTE
G3: MES | H3: MAYO
B4: SALDO ANTERIOR | E4: =+'ABRIL 25'!H8 -> 95880
B5: DEPÓSITO RENDICION ANTERIOR
B6: MONTO ADICIONAL | E6: 0
B7: MONTO A RENDIR | E7: =SUM(E4:E6) -> 95880
B8: RENDIDO | E8: =SUM(G28) -> 40000 | G8: SALDO AL CIERRE | H8: =E7-E8 -> 55880
A10: N° | B10: Fecha | C10: Tipo Documento (boleta venta-boleta honorarios-factura) | D10: N° documento | E10: RUT Titular del documento | F10: Detalle | G10: Total | H10: Código Imputacion (RSM) 210
A11: 1 | B11: 45779 | C11: boleta | D11: 1215 | E11: 5.666.822-5 | F11: limpieza vidrios | G11: 40000
A12: 2
A13: 3
A14: 4
A15: 5
A16: 6
A17: 7
A18: 8
A19: 9
A20: 10
A21: 11
A22: 12
A23: 13
... A27: 17
B28: TOTALES | G28: =SUM(G11:G27) -> 40000
F32: RESPONSABLE FONDO FIJO
F33: jonathan Canales

Sheet JUNIO 25
C1: RENDICION CAJA CHICA
C2: OESTE
G3: MES | H3: JUNIO
B4: SALDO ANTERIOR | E4: =+'MAYO 25'!H8 -> 55880
B5: DEPÓSITO RENDICION ANTERIOR | E5: 40000
B6: MONTO ADICIONAL | E6: 0
B7: MONTO A RENDIR | E7: =SUM(E4:E6) -> 95880
B8: RENDIDO | E8: =SUM(G28) -> 46990 | G8: SALDO AL CIERRE | H8: =E7-E8 -> 48890
A10: N° | B10: Fecha | C10: Tipo Documento (boleta venta-boleta honorarios-factura) | D10: N° documento | E10: RUT Titular del documento | F10: Detalle | G10: Total | H10: Código Imputacion (RSM) 210
A11: 1 | B11: 45813 | C11: boleta | D11: 1243 | E11: 5.666.822-5 | F11: limpieza cristales | G11: 40000
A12: 2 | B12: 45810 | C12: boleta | D12: 14736423 | E12: 83.030.600-5 | F12: pilas. Mause y teclado | G12: 6990
A13: 3
A14: 4
A15: 5
A16: 6
A17: 7
A18: 8
A19: 9
A20: 10
A21: 11
A22: 12
A23: 13
A24: 14
... A27: 17
B28: TOTALES | G28: =SUM(G11:G27) -> 46990
F32: RESPONSABLE FONDO FIJO
F33: Jhonatan Canales

Sheet JULIO25
C1: RENDICION CAJA CHICA
C2: OESTE
G3: MES | H3: JUNIO
B4: SALDO ANTERIOR | E4: =+'MAYO 25'!H8 -> 55880
B5: DEPÓSITO RENDICION ANTERIOR | E5: 44120
B6: MONTO ADICIONAL
B7: MONTO A RENDIR | E7: =SUM(E4:E6) -> 100000
B8: RENDIDO | E8: =SUM(G28) -> 56695 | G8: SALDO AL CIERRE | H8: =E7-E8 -> 43305
A10: N° | B10: Fecha | C10: Tipo Documento (boleta venta-boleta honorarios-factura) | D10: N° documento | E10: RUT Titular del documento | F10: Detalle | G10: Total | H10: Código Imputacion (RSM) 210
A11: 1 | B11: 45843 | C11: BOLETA | D11: 1262 | E11: 5.666.822-5 | F11: LIMPIEZA DE VIDRIOS | G11: 40000
A12: 2 | B12: 45822 | C12: BOLETA | D12: 776908073 | E12: 78.627.210-6 | F12: REUNION TIENDA | G12: 14505
A13: 3 | B13: 45860 | C13: BOLETA | D13: 794833121 | E13: 96.792.430-K | F13: ANCLAGE TV VIRINA | G13: 2190
A14: 4
A15: 5
A16: 6
A17: 7
A18: 8
A19: 9
A20: 10
A21: 11
A22: 12
A23: 13
A24: 14
A25: 15
... A27: 17
B28: TOTALES | G28: =SUM(G11:G27) -> 56695
F32: RESPONSABLE FONDO FIJO
F33: Jhonatan Canales

Sheet AGOSTO 25
C1: RENDICION CAJA CHICA
C2: OESTE
G3: MES | H3: AGOSTO
B4: SALDO ANTERIOR | E4: =+'MAYO 25'!H8 -> 55880
B5: DEPÓSITO RENDICION ANTERIOR | E5: 44120
B6: MONTO ADICIONAL
B7: MONTO A RENDIR | E7: =SUM(E4:E6) -> 100000
B8: RENDIDO | E8: =SUM(G28) -> 50990 | G8: SALDO AL CIERRE | H8: =E7-E8 -> 49010
A10: N° | B10: Fecha | C10: Tipo Documento (boleta venta-boleta honorarios-factura) | D10: N° documento | E10: RUT Titular del documento | F10: Detalle | G10: Total | H10: Código Imputacion (RSM) 210
A11: 1 | B11: 45874 | C11: boleta | D11: 1294 | E11: 5.666.822-5 | F11: limpieza cristales | G11: 40000
A12: 2 | B12: 45863 | C12: boleta | D12: 14738093 | E12: 83.030.600-5 | F12: pendrive monitor vitrina | G12: 5990
A13: 3 | B13: 45888 | C13: boleta | D13: 31010 | E13: 10.558.647-7 | F13: gotita | G13: 5000
A14: 4
A15: 5
A16: 6
A17: 7
A18: 8
A19: 9
A20: 10
A21: 11
A22: 12
A23: 13
A24: 14
A25: 15
... A27: 17
B28: TOTALES | G28: =SUM(G11:G27) -> 50990
F32: RESPONSABLE FONDO FIJO
F33: Jhonatan Canales

Sheet SEPTIEMBRE 25
C1: RENDICION CAJA CHICA
C2: OESTE
G3: MES | H3: AGOSTO
B4: SALDO ANTERIOR | E4: =+'MAYO 25'!H8 -> 55880
B5: DEPÓSITO RENDICION ANTERIOR | E5: 44120
B6: MONTO ADICIONAL
B7: MONTO A RENDIR | E7: =SUM(E4:E6) -> 100000
B8: RENDIDO | E8: =SUM(G28) -> 72110 | G8: SALDO AL CIERRE | H8: =E7-E8 -> 27890
A10: N° | B10: Fecha | C10: Tipo Documento (boleta venta-boleta honorarios-factura) | D10: N° documento | E10: RUT Titular del documento | F10: Detalle | G10: Total | H10: Código Imputacion (RSM) 210
A11: 1 | B11: 45912 | C11: BOLETA | D11: 15086125 | E11: 83.030.600-5 | F11: PENDRIVE ATRIL TIENDA | G11: 4990
A12: 2 | B12: 45915 | C12: BOLETA | D12: 2103 | E12: 78.145.063-4 | F12: FIESTAS PATRIAS | G12: 27120
A13: 3 | B13: 45905 | C13: BOLETA | D13: 1315 | E13: 5.666.822-5 | F13: LIMPIEZA VIDRIOS TIENDA | G13: 40000
A14: 4
A15: 5
A16: 6
A17: 7
A18: 8
A19: 9
A20: 10
A21: 11
A22: 12
A23: 13
A24: 14
A25: 15
... A27: 17
B28: TOTALES | G28: =SUM(G11:G27) -> 72110
F32: RESPONSABLE FONDO FIJO
F33: Jhonatan Canales

Sheet OCTUBRE 25
C1: RENDICION CAJA CHICA
C2: OESTE
G3: MES | H3: octubre
B4: SALDO ANTERIOR | E4: 27890
B5: DEPÓSITO RENDICION ANTERIOR | E5: 72110
B6: MONTO ADICIONAL
B7: MONTO A RENDIR | E7: =SUM(E4:E6) -> 100000
B8: RENDIDO | E8: =SUM(G28) -> 51000 | G8: SALDO AL CIERRE | H8: =E7-E8 -> 49000
A10: N° | B10: Fecha | C10: Tipo Documento (boleta venta-boleta honorarios-factura) | D10: N° documento | E10: RUT Titular del documento | F10: Detalle | G10: Total | H10: Código Imputacion (RSM) 210
A11: 1 | B11: 45935 | C11: BOLETA | D11: 1324 | E11: 5.666.822-5 | F11: LIMPIEZA CRISTALES | G11: 40000
A12: 2 | B12: 45948 | C12: BOLETA | D12: 109889 | E12: 9.968.127-6 | F12: REUNION TIENDA | G12: 11000
A13: 3
A14: 4
A15: 5
A16: 6
A17: 7
A18: 8
A19: 9
A20: 10
A21: 11
A22: 12
A23: 13
A24: 14
... A27: 17
B28: TOTALES | G28: =SUM(G11:G27) -> 51000
F32: RESPONSABLE FONDO FIJO
F33: Jhonatan Canales

Sheet NOVIEMBRE 25
C1: RENDICION CAJA CHICA
C2: OESTE
G3: MES | H3: noviembre
B4: SALDO ANTERIOR | E4: 49000
B5: DEPÓSITO RENDICION ANTERIOR | E5: 51000
B6: MONTO ADICIONAL
B7: MONTO A RENDIR | E7: =SUM(E4:E6) -> 100000
B8: RENDIDO | E8: =SUM(G28) -> 40000 | G8: SALDO AL CIERRE | H8: =E7-E8 -> 60000
A10: N° | B10: Fecha | C10: Tipo Documento (boleta venta-boleta honorarios-factura) | D10: N° documento | E10: RUT Titular del documento | F10: Detalle | G10: Total | H10: Código Imputacion (RSM) 210
A11: 1 | B11: 45966 | C11: BOLETA | D11: 1348 | E11: 5.666.822-5 | F11: LIMPIEZA CRISTALES | G11: 40000
A12: 2
A13: 3
A14: 4
A15: 5
A16: 6
A17: 7
A18: 8
A19: 9
A20: 10
A21: 11
A22: 12
A23: 13
... A27: 17
B28: TOTALES | G28: =SUM(G11:G27) -> 40000
F32: RESPONSABLE FONDO FIJO
F33: Jhonatan Canales

Sheet DICIEMBRE 25
C1: RENDICION CAJA CHICA
C2: OESTE
G3: MES | H3: DICIEMBRE
B4: SALDO ANTERIOR | E4: 49000
B5: DEPÓSITO RENDICION ANTERIOR | E5: 51000
B6: MONTO ADICIONAL
B7: MONTO A RENDIR | E7: =SUM(E4:E6) -> 100000
B8: RENDIDO | E8: =SUM(G28) -> 135671 | G8: SALDO AL CIERRE | H8: =E7-E8 -> -35671
A10: N° | B10: Fecha | C10: Tipo Documento (boleta venta-boleta honorarios-factura) | D10: N° documento | E10: RUT Titular del documento | F10: Detalle | G10: Total | H10: Código Imputacion (RSM) 210
A11: 1 | B11: 45996 | C11: BOLETA | D11: 1389 | E11: 5.666.822-5 | F11: LIMPIEZA CRISTALES | G11: 40000
A12: 2 | B12: 46004 | C12: NOTA DE CREDITO | D12: 24619 | E12: 10.780.964-3 | F12: DEVOLUCION CALZADO | G12: 74950
A13: 3 | B13: 46000 | C13: BOLETA | D13: 4692 | E13: CATALINA | F13: RECEP. MERCADE.NOCTUR | G13: 5987
A14: 4 | B14: 46000 | C14: BOLETA | D14: 393 | E14: ISABEL | F14: RECEP. MERCADE.NOCTUR | G14: 8491
A15: 5 | B15: 46012 | C15: BOLETA | D15: 312 | E15: ANTONIA | F15: RECEP. MERCADE.NOCTUR | G15: 6243
A16: 6
A17: 7
A18: 8
A19: 9
A20: 10
A21: 11
A22: 12
A23: 13
A24: 14
A25: 15
A26: 16
A27: 17
B28: TOTALES | G28: =SUM(G11:G27) -> 135671
F32: RESPONSABLE FONDO FIJO
F33: Jhonatan Canales

Sheet ENERO 26
C1: RENDICION CAJA CHICA
C2: OESTE
G3: MES | H3: ENERO
B4: SALDO ANTERIOR | E4: =+'DICIEMBRE 25'!H8 -> -35671
B5: DEPÓSITO RENDICION ANTERIOR | E5: 135671
B6: MONTO ADICIONAL
B7: MONTO A RENDIR | E7: =SUM(E4:E6) -> 100000
B8: RENDIDO | E8: =SUM(G28) -> 40000 | G8: SALDO AL CIERRE | H8: =E7-E8 -> 60000
A10: N° | B10: Fecha | C10: Tipo Documento (boleta venta-boleta honorarios-factura) | D10: N° documento | E10: RUT Titular del documento | F10: Detalle | G10: Total | H10: Código Imputacion (RSM) 210
A11: 1 | B11: 46045 | C11: BOLETA | D11: 1443 | E11: 5.666.822-5 | F11: LIMPIEZA FACHADA Y CRISTALES | G11: 40000
A12: 2
A13: 3
A14: 4
A15: 5
A16: 6
A17: 7
A18: 8
A19: 9
A20: 10
A21: 11
A22: 12
A23: 13
... A27: 17
B28: TOTALES | G28: =SUM(G11:G27) -> 40000
F32: RESPONSABLE FONDO FIJO
F33: Jhonatan Canales

Sheet FEBRERO 2026
C1: RENDICION CAJA CHICA
C2: OESTE
G3: MES | H3: FEBRERO
B4: SALDO ANTERIOR | E4: =+'ENERO 26'!H8 -> 60000
B5: DEPÓSITO RENDICION ANTERIOR
B6: MONTO ADICIONAL
B7: MONTO A RENDIR | E7: =SUM(E4:E6) -> 60000
B8: RENDIDO | E8: =SUM(G28) -> 0 | G8: SALDO AL CIERRE | H8: =E7-E8 -> 60000
A10: N° | B10: Fecha | C10: Tipo Documento (boleta venta-boleta honorarios-factura) | D10: N° documento | E10: RUT Titular del documento | F10: Detalle | G10: Total | H10: Código Imputacion (RSM) 210
A11: 1
A12: 2
A13: 3
A14: 4
A15: 5
A16: 6
A17: 7
A18: 8
A19: 9
A20: 10
A21: 11
A22: 12
... A27: 17
B28: TOTALES | G28: =SUM(G11:G27) -> 0
F32: RESPONSABLE FONDO FIJO
F33: Jhonatan Canales

Sheet MARZO 2026
C1: RENDICION CAJA CHICA
C2: OESTE
G3: MES | H3: MARZO
B4: SALDO ANTERIOR | E4: =+'FEBRERO 2026'!H8 -> 60000
B5: DEPÓSITO RENDICION ANTERIOR
B6: MONTO ADICIONAL
B7: MONTO A RENDIR | E7: =SUM(E4:E6) -> 60000
B8: RENDIDO | E8: =SUM(G28) -> 0 | G8: SALDO AL CIERRE | H8: =E7-E8 -> 60000
A10: N° | B10: Fecha | C10: Tipo Documento (boleta venta-boleta honorarios-factura) | D10: N° documento | E10: RUT Titular del documento | F10: Detalle | G10: Total | H10: Código Imputacion (RSM) 210
A11: 1
A12: 2
A13: 3
A14: 4
A15: 5
A16: 6
A17: 7
A18: 8
A19: 9
A20: 10
A21: 11
A22: 12
... A27: 17
B28: TOTALES | G28: =SUM(G11:G27) -> 0
F32: RESPONSABLE FONDO FIJO
F33: Jhonatan Canales

Sheet ABRIL 2026
C1: RENDICION CAJA CHICA
C2: OESTE
G3: MES | H3: ABRIL
B4: SALDO ANTERIOR | E4: =+'MARZO 2026'!H8 -> 60000
B5: DEPÓSITO RENDICION ANTERIOR
B6: MONTO ADICIONAL
B7: MONTO A RENDIR | E7: =SUM(E4:E6) -> 60000
B8: RENDIDO | E8: =SUM(G28) -> 0 | G8: SALDO AL CIERRE | H8: =E7-E8 -> 60000
A10: N° | B10: Fecha | C10: Tipo Documento (boleta venta-boleta honorarios-factura) | D10: N° documento | E10: RUT Titular del documento | F10: Detalle | G10: Total | H10: Código Imputacion (RSM) 210
A11: 1
A12: 2
A13: 3
A14: 4
A15: 5
A16: 6
A17: 7
A18: 8
A19: 9
A20: 10
A21: 11
A22: 12
... A27: 17
B28: TOTALES | G28: =SUM(G11:G27) -> 0
F32: RESPONSABLE FONDO FIJO
F33: Jhonatan Canales

Sheet MAYO 2026
C1: RENDICION CAJA CHICA
C2: OESTE
G3: MES | H3: MAYO
B4: SALDO ANTERIOR | E4: =+'ABRIL 2026'!H8 -> 60000
B5: DEPÓSITO RENDICION ANTERIOR
B6: MONTO ADICIONAL
B7: MONTO A RENDIR | E7: =SUM(E4:E6) -> 60000
B8: RENDIDO | E8: =SUM(G28) -> 0 | G8: SALDO AL CIERRE | H8: =E7-E8 -> 60000
A10: N° | B10: Fecha | C10: Tipo Documento (boleta venta-boleta honorarios-factura) | D10: N° documento | E10: RUT Titular del documento | F10: Detalle | G10: Total | H10: Código Imputacion (RSM) 210
A11: 1
A12: 2
A13: 3
A14: 4
A15: 5
A16: 6
A17: 7
A18: 8
A19: 9
A20: 10
A21: 11
A22: 12
... A27: 17
B28: TOTALES | G28: =SUM(G11:G27) -> 0
F32: RESPONSABLE FONDO FIJO
F33: Jhonatan Canales

Sheet JUNIO 2026 
C1: RENDICION CAJA CHICA
C2: OESTE
G3: MES | H3: JUNIO
B4: SALDO ANTERIOR | E4: =+'MAYO 2026'!H8 -> 60000
B5: DEPÓSITO RENDICION ANTERIOR
B6: MONTO ADICIONAL
B7: MONTO A RENDIR | E7: =SUM(E4:E6) -> 60000
B8: RENDIDO | E8: =SUM(G28) -> 0 | G8: SALDO AL CIERRE | H8: =E7-E8 -> 60000
A10: N° | B10: Fecha | C10: Tipo Documento (boleta venta-boleta honorarios-factura) | D10: N° documento | E10: RUT Titular del documento | F10: Detalle | G10: Total | H10: Código Imputacion (RSM) 210
A11: 1
A12: 2
A13: 3
A14: 4
A15: 5
A16: 6
A17: 7
A18: 8
A19: 9
A20: 10
A21: 11
A22: 12
... A27: 17
B28: TOTALES | G28: =SUM(G11:G27) -> 0
F32: RESPONSABLE FONDO FIJO
F33: Jhonatan Canales
