Workbook

Sheet DETALLE
C1: CUENTA | D1: DESCRIPCION | E1: Totales
C2: 3.1.01.101 | D2: VENTAS CON BOLETA | E2: 0
C3: 3.1.01.102 | D3: VENTAS CON FACTURA | E3: 0 | H3: Proveedor | I3: monto | J3: cto cto | K3: Proveedor | L3: monto | M3: cto cto | N3: Proveedor | O3: monto | P3: cto cto | Q3: Proveedor | R3: monto | S3: cto cto | T3: Proveedor | U3: monto | V3: cto cto | W3: Proveedor | X3: monto | Y3: cto cto | Z3: Proveedor | AA3: monto | AB3: cto cto | AC3: Proveedor | AD3: monto | AE3: cto cto | AF3: Proveedor | AG3: monto | AH3: cto cto | AI3: Proveedor | AJ3: monto | AK3: cto cto | AL3: Proveedor | AM3: monto | AN3: cto cto | AO3: Proveedor | AP3: monto | AQ3: cto cto | AR3: Proveedor | AS3: monto | AT3: cto cto | AU3: Proveedor | AV3: monto | AW3: cto cto | AX3: Proveedor | AY3: monto | AZ3: cto cto | BA3: Proveedor | BB3: monto | BC3: cto cto | BD3: Proveedor | BE3: monto | BF3: cto cto | BG3: Proveedor | BH3: monto | BI3: cto cto | BJ3: Proveedor | BK3: monto | BL3: cto cto | BM3: Proveedor | BN3: monto | BO3: cto cto | BP3: Proveedor | BQ3: monto | BR3: cto cto | BS3: Proveedor | BT3: monto | BU3: cto cto | BV3: Proveedor | BW3: monto | BX3: cto cto | BY3: Proveedor | BZ3: monto | CA3: cto cto | CB3: Proveedor | CC3: monto | CD3: cto cto | CE3: Proveedor | CF3: monto | CG3: cto cto | CH3: Proveedor | CI3: monto | CJ3: cto cto | CK3: Proveedor | CL3: monto | CM3: cto cto | CN3: Proveedor | CO3: monto | CP3: cto cto | CQ3: Proveedor | CR3: monto | CS3: cto cto | CT3: Proveedor | CU3: monto | CV3: cto cto | CW3: Proveedor | CX3: monto | CY3: cto cto
A4: =EXACT(B4,C4) -> TRUE | B4: =+EERR!A2 -> 3.1.01.103 | C4: 3.1.01.103 | D4: VENTAS CON BOLETA (RPA) | E4: 246614292
A5: =EXACT(B5,C5) -> TRUE | B5: =+EERR!A3 -> 3.1.01.300 | C5: 3.1.01.300 | D5: OTROS INGRESOS | E5: 3751074
A6: =EXACT(B6,C6) -> TRUE | B6: =+EERR!A4 -> 3.1.02.101 | C6: 3.1.02.101 | D6: COSTO DE VENTAS | E6: -134839072
A7: =EXACT(B7,C7) -> TRUE | B7: =+EERR!A5 -> 3.1.02.102 | C7: 3.1.02.102 | D7: COSTOS OPERATIVOS - FLETES INTERNOS | E7: -1840455 | F7: =+I7+L7+O7+R7+U7+X7+AA7+AD7+AG7+AJ7+AM7+AP7+AS7+AV7+AY7+BB7+BE7+BH7+BK7+BN7+BQ7+BT7+BW7+BZ7+CC7+CF7+CI7+CL7+CO7+CR7+CU7 -> 1840455 | G7: =+E7+F7 -> 0 | H7: AP LOGISTICS SPA | I7: 179300 | J7: 300 | K7: VS CARGO SPA | L7: 967680 | M7: 1 | N7: VS CARGO SPA | O7: 725760 | P7: DIVIDIR 10 | Q7: VS CARGO SPA | R7: 300000 | S7: DIVIDIR 10 | T7: VS CARGO SPA | U7: -967680 | V7: 1 | W7: VS CARGO SPA | X7: -1500000 | Y7: DIVIDIR 10 | Z7: AP LOGISTICS SPA | AA7: 2135395 | AB7: 300
A8: =EXACT(B8,C8) -> TRUE | B8: =+EERR!A6 -> 3.1.02.104 | C8: 3.1.02.104 | D8: COMISIÓN - CANAL DIGITAL | E8: -2699824 | F8: =+I8+L8+O8+R8+U8+X8+AA8+AD8+AG8+AJ8+AM8+AP8+AS8+AV8+AY8+BB8+BE8+BH8+BK8+BN8+BQ8+BT8+BW8+BZ8+CC8+CF8+CI8+CL8+CO8+CR8+CU8 -> 2699824 | G8: =+E8+F8 -> 0 | H8: Comercial Eccsa S.A. | I8: 22708 | J8: 404 | K8: Comercial Eccsa S.A. | L8: 135671 | M8: 404 | N8: Comercial Eccsa S.A. | O8: 64694 | P8: 404 | Q8: MercadoLibre Chile Ltda. | R8: 1801 | S8: 402 | T8: MercadoLibre Chile Ltda. | U8: -288630 | V8: 402 | W8: MercadoLibre Chile Ltda. | X8: -17715 | Y8: 402 | Z8: PROVISION CENCOSUD RETAIL | AA8: 539421 | AB8: 400 | AC8: Falabella.com SpA | AD8: 2241874 | AE8: 405
A9: =EXACT(B9,C9) -> TRUE | B9: =+EERR!A7 -> 3.1.02.105 | C9: 3.1.02.105 | D9: FLETES - CANAL DIGITAL | E9: -800047 | F9: =+I9+L9+O9+R9+U9+X9+AA9+AD9+AG9+AJ9+AM9+AP9+AS9+AV9+AY9+BB9+BE9+BH9+BK9+BN9+BQ9+BT9+BW9+BZ9+CC9+CF9+CI9+CL9+CO9+CR9+CU9 -> 800047 | G9: =+E9+F9 -> 0 | H9: Comercial Eccsa S.A. | I9: 21909 | J9: 404 | K9: Comercial Eccsa S.A. | L9: 14252 | M9: 404 | N9: Comercial Eccsa S.A. | O9: 14606 | P9: 404 | Q9: DESPACHALO SPA | R9: 345000 | S9: 100 | T9: ENVIAME LATAM SPA | U9: 4684604 | V9: 100 | W9: Comercial Eccsa S.A. | X9: 25143 | Y9: 404 | Z9: Comercial Eccsa S.A. | AA9: 30160 | AB9: 404 | AC9: Falabella.com SpA | AD9: =4426624-2241874 -> 2184750 | AE9: 405 | AF9: Comercial Eccsa S.A. | AG9: 32954 | AH9: 404 | AI9: Comercial Eccsa S.A. | AJ9: 36723 | AK9: 404 | AL9: Falabella.com SpA | AM9: 4117 | AN9: 405 | AO9: Falabella.com SpA | AP9: -1564567 | AQ9: 405 | AR9: ENVIAME | AS9: -4684604 | AT9: 100 | AU9: DESPACHALO | AV9: -345000 | AW9: 100
A10: =EXACT(B10,C10) -> TRUE | B10: =+EERR!A8 -> 3.1.02.108 | C10: 3.1.02.108 | D10: SERVICIOS - CANAL DIGITAL | E10: -1976022 | F10: =+I10+L10+O10+R10+U10+X10+AA10+AD10+AG10+AJ10+AM10+AP10+AS10+AV10+AY10+BB10+BE10+BH10+BK10+BN10+BQ10+BT10+BW10+BZ10+CC10+CF10+CI10+CL10+CO10+CR10+CU10 -> 1976022 | G10: =+E10+F10 -> 0 | H10: FINTOC SPA | I10: 15497 | J10: 400 | K10: Comercial Eccsa S.A. | L10: 6301 | M10: 404 | N10: Comercial Eccsa S.A. | O10: 86318 | P10: 404 | Q10: Comercial Eccsa S.A. | R10: 21129 | S10: 404 | T10: MercadoLibre Chile Ltda. | U10: 1855095 | V10: 402 | W10: MercadoLibre Chile Ltda. | X10: -8318 | Y10: 402
A11: =EXACT(B11,C11) -> TRUE | B11: =+EERR!A9 -> 3.1.02.109 | C11: 3.1.02.109 | D11: DESCUENTOS GIFTCARD | E11: -44990
A12: =EXACT(B12,C12) -> TRUE | B12: =+EERR!A10 -> 3.1.02.110 | C12: 3.1.02.110 | D12: DESCUENTOS CLUB FLEXI | E12: -46507
A13: =EXACT(B13,C13) -> TRUE | B13: =+EERR!A11 -> 3.1.05.101 | C13: 3.1.05.101 | D13: REMUNERACIONES | E13: -45117151
A14: =EXACT(B14,C14) -> TRUE | B14: =+EERR!A12 -> 3.1.05.102 | C14: 3.1.05.102 | D14: BONOS | E14: -1730490
A15: =EXACT(B15,C15) -> TRUE | B15: =+EERR!A13 -> 3.1.05.103 | C15: 3.1.05.103 | D15: SEGURO DE CESANTIA | E15: -1655083
A16: =EXACT(B16,C16) -> TRUE | B16: =+EERR!A14 -> 3.1.05.104 | C16: 3.1.05.104 | D16: GRATIFICACION | E16: -10584152
A17: =EXACT(B17,C17) -> TRUE | B17: =+EERR!A15 -> 3.1.05.107 | C17: 3.1.05.107 | D17: FINIQUITOS | E17: -4000
A18: =EXACT(B18,C18) -> TRUE | B18: =+EERR!A16 -> 3.1.05.110 | C18: 3.1.05.110 | D18: MUTUAL DE SEGURIDAD | E18: -600154
A19: =EXACT(B19,C19) -> TRUE | B19: =+EERR!A17 -> 3.1.05.111 | C19: 3.1.05.111 | D19: SEGURO INVALIDEZ (AFP) | E19: -1012481
A20: =EXACT(B20,C20) -> TRUE | B20: =+EERR!A18 -> 3.1.05.112 | C20: 3.1.05.112 | D20: CAPITALIZACION INDIVIDUAL AFP | E20: -64495
A21: =EXACT(B21,C21) -> TRUE | B21: =+EERR!A19 -> 3.1.05.113 | C21: 3.1.05.113 | D21: EXPECTATIVA DE VIDA | E21: -591718
A22: =EXACT(B22,C22) -> TRUE | B22: =+EERR!A20 -> 3.1.05.114 | C22: 3.1.05.114 | D22: HORAS EXTRAS | E22: 0
... A27: =EXACT(B27,C27) -> TRUE | B27: =+EERR!A25 -> 3.1.06.109 | C27: 3.1.06.109 | D27: ASIGNACION MOVILIZACION | E27: -2326500
A28: =EXACT(B28,C28) -> TRUE | B28: =+EERR!A26 -> 3.1.06.116 | C28: 3.1.06.116 | D28: UNIFORMES | E28: 1138389 | F28: =+I28+L28+O28+R28+U28+X28+AA28+AD28+AG28+AJ28+AM28+AP28+AS28+AV28+AY28+BB28+BE28+BH28+BK28+BN28+BQ28+BT28+BW28+BZ28+CC28+CF28+CI28+CL28+CO28+CR28+CU28 -> -1138389 | G28: =+E28+F28 -> 0 | H28: COMERCIAL ECCSA S.A. | I28: 18471 | J28: 200 | K28: MARIA ISABEL SANTANA MOLINA | L28: 239000 | M28: DIVIDIR 10 | N28: REVERSO PROV DIC | O28: =-341900-183170-126030-262920-341910-139930 -> -1395860 | P28: 170-195-150-200-210-185
A29: =EXACT(B29,C29) -> TRUE | B29: =+EERR!A27 -> 3.1.06.201 | C29: 3.1.06.201 | D29: HONORARIOS PROFESIONALES | E29: -505000 | F29: =+I29+L29+O29+R29+U29+X29+AA29+AD29+AG29+AJ29+AM29+AP29+AS29+AV29+AY29+BB29+BE29+BH29+BK29+BN29+BQ29+BT29+BW29+BZ29+CC29+CF29+CI29+CL29+CO29+CR29+CU29 -> 505000 | G29: =+E29+F29 -> 0 | H29: DOC.HON.NRO.122008 | I29: 5000 | J29: 2 | K29: PROVISION ME CONECTO SPA | L29: 500000 | M29: DIVIDIR 10
A30: =EXACT(B30,C30) -> TRUE | B30: =+EERR!A28 -> 3.1.06.206 | C30: 3.1.06.206 | D30: ASESORIA CONTABLE | E30: -3101478 | F30: =+I30+L30+O30+R30+U30+X30+AA30+AD30+AG30+AJ30+AM30+AP30+AS30+AV30+AY30+BB30+BE30+BH30+BK30+BN30+BQ30+BT30+BW30+BZ30+CC30+CF30+CI30+CL30+CO30+CR30+CU30 -> 3101478 | G30: =+E30+F30 -> 0 | H30: RSM CHILE ACCOUNTING TAX AND CONSULTING SERVICES LIMITADA | I30: 3893716 | J30: 2 | K30: RSM CHILE ACCOUNTING TAX AND CONSULTING SERVICES LIMITADA | L30: -3893716 | M30: 2 | N30: RSM CHILE ACCOUNTING TAX AND CONSULTING SERVICES LIMITADA | O30: 3101478 | P30: 2
A31: =EXACT(B31,C31) -> TRUE | B31: =+EERR!A29 -> 3.1.06.209 | C31: 3.1.06.209 | D31: HONORARIOS POR ASESORIAS INFORMATICAS | E31: 0 | F31: =+I31+L31+O31+R31+U31+X31+AA31+AD31+AG31+AJ31+AM31+AP31+AS31+AV31+AY31+BB31+BE31+BH31+BK31+BN31+BQ31+BT31+BW31+BZ31+CC31+CF31+CI31+CL31+CO31+CR31+CU31 -> 0 | G31: =+E31+F31 -> 0 | H31: Migratoria Servicios InformÃ¡ticos Limitada | I31: 179571 | J31: 2 | K31: Migratoria Servicios InformÃ¡ticos Limitada | L31: -179571 | M31: 2
A32: =EXACT(B32,C32) -> TRUE | B32: =+EERR!A30 -> 3.1.06.301 | C32: 3.1.06.301 | D32: ARRIENDOS | E32: -72497896 | F32: =+I32+L32+O32+R32+U32+X32+AA32+AD32+AG32+AJ32+AM32+AP32+AS32+AV32+AY32+BB32+BE32+BH32+BK32+BN32+BQ32+BT32+BW32+BZ32+CC32+CF32+CI32+CL32+CO32+CR32+CU32+CX32 -> 72497896 | G32: =+E32+F32 -> 0 | H32: Banco de Chile | I32: 6953063 | J32: 190 | K32: Cencosud_Shopping_S.A. | L32: 7481208 | M32: 180 | N32: ADM_C.C._CENCOSUD_SPA. | O32: 712269 | P32: 180 | Q32: ADM_C.C._CENCOSUD_SPA. | R32: 1736156 | S32: 180 | T32: Comercializadora_Costanera_Center_SPA | U32: 18229632 | V32: 170 | W32: PLAZA MAULE S.A. | X32: 243455 | Y32: 195 | Z32: ADM_C.C._CENCOSUD_SPA. | AA32: 1752865 | AB32: 170 | AC32: ADM_C.C._CENCOSUD_SPA. | AD32: 2497977 | AE32: 170 | AF32: PLAZA MAULE S.A. | AG32: 877400 | AH32: 195 | AI32: Plaza del TrÃ©bol SpA | AJ32: 8141381 | AK32: 150 | AL32: Plaza Oeste SpA | AM32: 7160165 | AN32: 200 | AO32: Plaza Oeste SpA | AP32: 8318499 | AQ32: 210 | AR32: Plaza Oeste SpA | AS32: 8054712 | AT32: 130 | AU32: PLAZA MAULE S.A. | AV32: 1989148 | AW32: 195 | AX32: PLAZA MAULE S.A. | AY32: 1541590 | AZ32: 195 | BA32: Plaza Oeste SpA | BB32: 11912 | BC32: 200 | BD32: Plaza Oeste SpA | BE32: 11912 | BF32: 210 | BG32: Plaza Oeste SpA | BH32: 11912 | BI32: 130 | BJ32: Plaza del TrÃ©bol SpA | BK32: 11912 | BL32: 150 | BM32: AMORTIZACIÓN VMN COSTANER | BN32: 766657 | BO32: 170 | BP32: AMORTIZACIÓN VMN FLORIDA | BQ32: 590879 | BR32: 180 | BS32: AMORTIZACIÓN VMN CONCEPCI | BT32: 134481 | BU32: 185 | BV32: GGCC ESTADO | BW32: 396877 | BX32: 190 | BY32: CENCOSUD | BZ32: =-1752865-2497977 -> -4250842 | CA32: 170 | CB32: PLAZA MAULE | CC32: -877324 | CD32: 195
A33: =EXACT(B33,C33) -> TRUE | B33: =+EERR!A31 -> 3.1.06.302 | C33: 3.1.06.302 | D33: ARRIENDO DE BODEGAS | E33: -3126087 | F33: =+I33+L33+O33+R33+U33+X33+AA33+AD33+AG33+AJ33+AM33+AP33+AS33+AV33+AY33+BB33+BE33+BH33+BK33+BN33+BQ33+BT33+BW33+BZ33+CC33+CF33+CI33+CL33+CO33+CR33+CU33 -> 3126087 | G33: =+E33+F33 -> 0 | H33: BODEGAS SAN FRANCISCO LIMITADA | I33: 3126087 | J33: 300
A34: =EXACT(B34,C34) -> TRUE | B34: =+EERR!A32 -> 3.1.06.305 | C34: 3.1.06.305 | D34: GASTOS DIVERSOS | E34: -631049 | F34: =+I34+L34+O34+R34+U34+X34+AA34+AD34+AG34+AJ34+AM34+AP34+AS34+AV34+AY34+BB34+BE34+BH34+BK34+BN34+BQ34+BT34+BW34+BZ34+CC34+CF34+CI34+CL34+CO34+CR34+CU34 -> 631049 | G34: =+E34+F34 -> 0 | H34: Manantial S.A | I34: 17716 | J34: 300 | K34: INVERSIONES IMPERIO SPA | L34: 18862 | M34: 300 | N34: SMARTCTL SPA | O34: 11247 | P34: 300 | Q34: FONDO F ESTADO ENE26 | R34: 13150 | S34: 190 | T34: FONDO F TALCA ENE26 | U34: 55995 | V34: 195 | W34: FONDO F TREBOL ENE26 | X34: 82318 | Y34: 150 | Z34: FONDO F FLORIDA ENE26 | AA34: 2000 | AB34: 180 | AC34: FONDO F EGAÑA ENE26 | AD34: 40308 | AE34: 130 | AF34: FONDO F COSTANERA ENE26 | AG34: 68130 | AH34: 170 | AI34: FONDO F OESTE ENE26 | AJ34: 7000 | AK34: 200 | AL34: FXR CEDIS ENE26 | AM34: 119468 | AN34: 300 | AO34: FONDO F ARANA ENE26 | AP34: 31490 | AQ34: 185 | AR34: FXR ANDREA ENE26 | AS34: 5938 | AT34: 2 | AU34: PROVISION RENTOKIL INITIA | AV34: 104803 | AW34: 300 | AX34: PROVISION LATAMFIT CHILE | AY34: 315744 | AZ34: DIVIDIR 10 | BA34: RECLASIF. LATAM FIT AL CI | BB34: -263120 | BC34: DIVIDIR 10
A35: =EXACT(B35,C35) -> TRUE | B35: =+EERR!A33 -> 3.1.06.306 | C35: 3.1.06.306 | D35: SEGURIDAD INDUSTRIAL | E35: 0 | F35: =+I35+L35+O35+R35+U35+X35+AA35+AD35+AG35+AJ35+AM35+AP35+AS35+AV35+AY35+BB35+BE35+BH35+BK35+BN35+BQ35+BT35+BW35+BZ35+CC35+CF35+CI35+CL35+CO35+CR35+CU35 -> 0 | G35: =+E35+F35 -> 0
A36: =EXACT(B36,C36) -> TRUE | B36: =+EERR!A34 -> 3.1.06.401 | C36: 3.1.06.401 | D36: SERVICIOS DE TELECOMUNICACION | E36: -177715 | F36: =+I36+L36+O36+R36+U36+X36+AA36+AD36+AG36+AJ36+AM36+AP36+AS36+AV36+AY36+BB36+BE36+BH36+BK36+BN36+BQ36+BT36+BW36+BZ36+CC36+CF36+CI36+CL36+CO36+CR36+CU36 -> 177715 | G36: =+E36+F36 -> 0 | H36: Telefonica Chile S.A | I36: 648423 | J36: TELEFONICA | K36: GTD MANQUEHUE S.A. | L36: 93361 | M36: 185 | N36: Entel PCS Telecomunicaciones S.A. | O36: 84354 | P36: DIVIDIR 14 | Q36: Telefonica Chile S.A | R36: -648423 | S36: TELEFONICA
A37: =EXACT(B37,C37) -> TRUE | B37: =+EERR!A35 -> 3.1.06.406 | C37: 3.1.06.406 | D37: GASTOS DE TELEFONIA MOVIL | E37: -131229 | F37: =+I37+L37+O37+R37+U37+X37+AA37+AD37+AG37+AJ37+AM37+AP37+AS37+AV37+AY37+BB37+BE37+BH37+BK37+BN37+BQ37+BT37+BW37+BZ37+CC37+CF37+CI37+CL37+CO37+CR37+CU37 -> 131229 | G37: =+E37+F37 -> 0 | H37: WOM S.A. | I37: 131229 | J37: DIVIDIR 11
A38: =EXACT(B38,C38) -> TRUE | B38: =+EERR!A36 -> 3.1.06.501 | C38: 3.1.06.501 | D38: PATENTE COMERCIAL | E38: -839257 | F38: =+I38+L38+O38+R38+U38+X38+AA38+AD38+AG38+AJ38+AM38+AP38+AS38+AV38+AY38+BB38+BE38+BH38+BK38+BN38+BQ38+BT38+BW38+BZ38+CC38+CF38+CI38+CL38+CO38+CR38+CU38 -> 839257 | G38: =+E38+F38 -> 0 | H38: AMORTIZACIÓN PATENTE CUOT | I38: 68062 | J38: 2 | K38: AMORTIZACIÓN PATENTE CUOT | L38: 9564 | M38: 130 | N38: AMORTIZACIÓN PATENTE CUOT | O38: 11619 | P38: 140 | Q38: AMORTIZACIÓN PATENTE CUOT | R38: 44873 | S38: 150 | T38: AMORTIZACIÓN PATENTE CUOT | U38: 55219 | V38: 170 | W38: AMORTIZACIÓN PATENTE CUOT | X38: 11619 | Y38: 180 | Z38: AMORTIZACIÓN PATENTE CUOT | AA38: 6962 | AB38: 185 | AC38: AMORTIZACIÓN PATENTE CUOT | AD38: 536239 | AE38: 190 | AF38: AMORTIZACIÓN PATENTE CUOT | AG38: 4258 | AH38: 195 | AI38: AMORTIZACIÓN PATENTE CUOT | AJ38: 37862 | AK38: 200 | AL38: AMORTIZACIÓN PATENTE CUOT | AM38: 52980 | AN38: 210
A39: =EXACT(B39,C39) -> TRUE | B39: =+EERR!A37 -> 3.1.06.504 | C39: 3.1.06.504 | D39: IVA IRRECUPERABLE | E39: -1065119 | F39: =+I39+L39+O39+R39+U39+X39+AA39+AD39+AG39+AJ39+AM39+AP39+AS39+AV39+AY39+BB39+BE39+BH39+BK39+BN39+BQ39+BT39+BW39+BZ39+CC39+CF39+CI39+CL39+CO39+CR39+CU39 -> 1065119 | G39: =+E39+F39 -> 0 | H39: IVA NO ECUPERABLES NOTAS | I39: 1065119 | J39: 2
A40: =EXACT(B40,C40) -> TRUE | B40: =+EERR!A38 -> 3.1.06.505 | C40: 3.1.06.505 | D40: MULTAS E INTERESES | E40: -420710 | F40: =+I40+L40+O40+R40+U40+X40+AA40+AD40+AG40+AJ40+AM40+AP40+AS40+AV40+AY40+BB40+BE40+BH40+BK40+BN40+BQ40+BT40+BW40+BZ40+CC40+CF40+CI40+CL40+CO40+CR40+CU40 -> 420710 | G40: =+E40+F40 -> 0 | H40: MULTAS PUB ATRASADA | I40: 420710 | J40: 2
A41: =EXACT(B41,C41) -> TRUE | B41: =+EERR!A39 -> 3.1.06.506 | C41: 3.1.06.506 | D41: SEGUROS | E41: -663414 | F41: =+I41+L41+O41+R41+U41+X41+AA41+AD41+AG41+AJ41+AM41+AP41+AS41+AV41+AY41+BB41+BE41+BH41+BK41+BN41+BQ41+BT41+BW41+BZ41+CC41+CF41+CI41+CL41+CO41+CR41+CU41 -> 663414 | G41: =+E41+F41 -> 0 | H41: AMORTIZACIÓN SEGURO CUOTA | I41: 663414 | J41: TODAS LAS TIENDAS
A42: =EXACT(B42,C42) -> TRUE | B42: =+EERR!A40 -> 3.1.06.507 | C42: 3.1.06.507 | D42: SERVICIO DE VIGILANCIA | E42: 1 | F42: =+I42+L42+O42+R42+U42+X42+AA42+AD42+AG42+AJ42+AM42+AP42+AS42+AV42+AY42+BB42+BE42+BH42+BK42+BN42+BQ42+BT42+BW42+BZ42+CC42+CF42+CI42+CL42+CO42+CR42+CU42 -> -1 | G42: =+E42+F42 -> 0 | H42: VERISURE CHILE SPA | I42: 61186 | J42: 190 | K42: VERISURE CHILE SPA | L42: -61187 | M42: 190
A43: =EXACT(B43,C43) -> TRUE | B43: =+EERR!A41 -> 3.1.06.601 | C43: 3.1.06.601 | D43: GASTO MANTENCION SUCURSALES | E43: -1105609 | F43: =+I43+L43+O43+R43+U43+X43+AA43+AD43+AG43+AJ43+AM43+AP43+AS43+AV43+AY43+BB43+BE43+BH43+BK43+BN43+BQ43+BT43+BW43+BZ43+CC43+CF43+CI43+CL43+CO43+CR43+CU43 -> 1105609 | G43: =+E43+F43 -> 0 | H43: PAMELA FRANCISCA BARRA QUINTANA | I43: 80000 | J43: 150 | K43: SERVICIOS DE MANTENCIÃ“N LABBÃ‰ SPA | L43: 5072199 | M43: 185 | N43: SERVICIOS DE MANTENCIÃ“N LABBÃ‰ SPA | O43: 1716000 | P43: 185 | Q43: RVR CLIMATIZACION LIMITADA | R43: 319960 | S43: 300 | T43: JUAN ANTONIO MELO SAAVEDRA | U43: 47198 | V43: 210 | W43: JUAN ANTONIO MELO SAAVEDRA | X43: 47198 | Y43: 130 | Z43: ANGELO LUIS MEDINA TORRES | AA43: 21239 | AB43: 130 | AC43: ANGELO LUIS MEDINA TORRES | AD43: 17699 | AE43: 180 | AF43: JORGE ORLANDO VENEGAS GOMEZ | AG43: 374446 | AH43: 190 | AI43: JUAN ANTONIO MELO SAAVEDRA | AJ43: 47198 | AK43: 170 | AL43: JUAN JESUS ARRIAGADA GONZALEZ | AM43: 17699 | AN43: 150 | AO43: ANA PAULA MARTINS DA SILVA | AP43: 40936 | AQ43: 195 | AR43: FERNANDO ANTONIO OLGUEA CARREN | AS43: 23599 | AT43: 200 | AU43: ANGELO LUIS MEDINA TORRES | AV43: 21239 | AW43: 130 | AX43: JUAN ANTONIO MELO SAAVEDRA | AY43: 47198 | AZ43: 210 | BA43: SERVICIOS DE MANTENCIÃ“N LABBÃ‰ SPA | BB43: =-1716000-5072199 -> -6788199 | BC43: 185
A44: =EXACT(B44,C44) -> TRUE | B44: =+EERR!A42 -> 3.1.06.602 | C44: 3.1.06.602 | D44: BOLSA IMPRESA | E44: -642168 | F44: =+I44+L44+O44+R44+U44+X44+AA44+AD44+AG44+AJ44+AM44+AP44+AS44+AV44+AY44+BB44+BE44+BH44+BK44+BN44+BQ44+BT44+BW44+BZ44+CC44+CF44+CI44+CL44+CO44+CR44+CU44 -> 642168 | G44: =+E44+F44 -> 0 | H44: AMORTIZACIÓN BOLSA IMPRES | I44: 642168 | J44: DIVIDIR 12
A45: =EXACT(B45,C45) -> TRUE | B45: =+EERR!A43 -> 3.1.06.603 | C45: 3.1.06.603 | D45: GASTOS DE ALMACENAJE | E45: 0 | F45: =+I45+L45+O45+R45+U45+X45+AA45+AD45+AG45+AJ45+AM45+AP45+AS45+AV45+AY45+BB45+BE45+BH45+BK45+BN45+BQ45+BT45+BW45+BZ45+CC45+CF45+CI45+CL45+CO45+CR45+CU45 -> 0 | G45: =+E45+F45 -> 0
A46: =EXACT(B46,C46) -> TRUE | B46: =+EERR!A44 -> 3.1.06.802 | C46: 3.1.06.802 | D46: SUMINISTROS COMPUTACIONALES | E46: 0 | F46: =+I46+L46+O46+R46+U46+X46+AA46+AD46+AG46+AJ46+AM46+AP46+AS46+AV46+AY46+BB46+BE46+BH46+BK46+BN46+BQ46+BT46+BW46+BZ46+CC46+CF46+CI46+CL46+CO46+CR46+CU46 -> 0 | G46: =+E46+F46 -> 0
A47: =EXACT(B47,C47) -> TRUE | B47: =+EERR!A45 -> 3.1.06.803 | C47: 3.1.06.803 | D47: UTILES DE OFICINA Y PAPELERIA | E47: -371590 | F47: =+I47+L47+O47+R47+U47+X47+AA47+AD47+AG47+AJ47+AM47+AP47+AS47+AV47+AY47+BB47+BE47+BH47+BK47+BN47+BQ47+BT47+BW47+BZ47+CC47+CF47+CI47+CL47+CO47+CR47+CU47 -> 371590 | G47: =+E47+F47 -> 0 | H47: PROVEEDORES INTEGRALES PRISA S A | I47: 41703 | J47: DIVIDIR 10 | K47: PROVEEDORES INTEGRALES PRISA S A | L47: 107127 | M47: DIVIDIR 10 | N47: PROVEEDORES INTEGRALES PRISA S A | O47: 35613 | P47: DIVIDIR 10 | Q47: PROVEEDORES INTEGRALES PRISA S A | R47: 23287 | S47: DIVIDIR 10 | T47: PROVEEDORES INTEGRALES PRISA S A | U47: 21205 | V47: DIVIDIR 10 | W47: PROVEEDORES INTEGRALES PRISA S A | X47: 23314 | Y47: DIVIDIR 10 | Z47: PROVEEDORES INTEGRALES PRISA S A | AA47: 36433 | AB47: DIVIDIR 10 | AC47: PROVEEDORES INTEGRALES PRISA S A | AD47: 82908 | AE47: DIVIDIR 10
A48: =EXACT(B48,C48) -> TRUE | B48: =+EERR!A46 -> 3.1.06.805 | C48: 3.1.06.805 | D48: GASTOS LEGALES Y NOTARIALES DIRECTOS | E48: 0 | F48: =+I48+L48+O48+R48+U48+X48+AA48+AD48+AG48+AJ48+AM48+AP48+AS48+AV48+AY48+BB48+BE48+BH48+BK48+BN48+BQ48+BT48+BW48+BZ48+CC48+CF48+CI48+CL48+CO48+CR48+CU48 -> 0 | G48: =+E48+F48 -> 0
A49: =EXACT(B49,C49) -> TRUE | B49: =+EERR!A47 -> 3.1.06.806 | C49: 3.1.06.806 | D49: COMISIONES Y GASTOS BANCARIOS | E49: -502259 | F49: =+I49+L49+O49+R49+U49+X49+AA49+AD49+AG49+AJ49+AM49+AP49+AS49+AV49+AY49+BB49+BE49+BH49+BK49+BN49+BQ49+BT49+BW49+BZ49+CC49+CF49+CI49+CL49+CO49+CR49+CU49 -> 502259 | G49: =+E49+F49 -> 0 | H49: Santander - Chile | I49: 31750 | J49: 2 | K49: Santander - Chile | L49: 118191 | M49: 2 | N49: Santander - Chile | O49: 318140 | P49: 2 | Q49: Santander - Chile | R49: 25035 | S49: 2 | T49: TDC ENERO | U49: 9143 | V49: 2
A50: =EXACT(B50,C50) -> TRUE | B50: =+EERR!A48 -> 3.1.06.812 | C50: 3.1.06.812 | D50: COMISIONES TRANSBANK | E50: -2853756 | F50: =+I50+L50+O50+R50+U50+X50+AA50+AD50+AG50+AJ50+AM50+AP50+AS50+AV50+AY50+BB50+BE50+BH50+BK50+BN50+BQ50+BT50+BW50+BZ50+CC50+CF50+CI50+CL50+CO50+CR50+CU50 -> 2853756 | G50: =+E50+F50 -> 0 | H50: Transbank S.A | I50: 2070225 | J50: TRANSBANK | K50: TRANSBANK S.A. | L50: -5531 | M50: TRANSBANK | N50: TRANSBANK S.A. | O50: -66129 | P50: TRANSBANK | Q50: PROVISION TRANSBANK S.A | R50: 855191 | S50: TRANSBANK
A51: =EXACT(B51,C51) -> TRUE | B51: =+EERR!A49 -> 3.1.06.813 | C51: 3.1.06.813 | D51: COMISIONES GETNET | E51: -597458 | F51: =+I51+L51+O51+R51+U51+X51+AA51+AD51+AG51+AJ51+AM51+AP51+AS51+AV51+AY51+BB51+BE51+BH51+BK51+BN51+BQ51+BT51+BW51+BZ51+CC51+CF51+CI51+CL51+CO51+CR51+CU51 -> 597458 | G51: =+E51+F51 -> 0 | H51: SOCIEDAD OPERADORA DE TARJETAS DE PAGO SANTANDER GETNET CHILE S.A. | I51: 235050 | J51: 200 | K51: SOCIEDAD OPERADORA DE TARJETAS DE PAGO SANTANDER GETNET CHILE S.A. | L51: 362408 | M51: 210
A52: =EXACT(B52,C52) -> TRUE | B52: =+EERR!A50 -> 3.1.06.817 | C52: 3.1.06.817 | D52: GASTOS DE REPRESENTACION | E52: -868786 | F52: =+I52+L52+O52+R52+U52+X52+AA52+AD52+AG52+AJ52+AM52+AP52+AS52+AV52+AY52+BB52+BE52+BH52+BK52+BN52+BQ52+BT52+BW52+BZ52+CC52+CF52+CI52+CL52+CO52+CR52+CU52 -> 868786 | G52: =+E52+F52 -> 0 | H52: FXR RAUL ENE26 | I52: 868786 | J52: 100
A53: =EXACT(B53,C53) -> TRUE | B53: =+EERR!A51 -> 3.1.06.818 | C53: 3.1.06.818 | D53: LICENCIAS SOTWARE RENTAS | E53: -2919321 | F53: =+I53+L53+O53+R53+U53+X53+AA53+AD53+AG53+AJ53+AM53+AP53+AS53+AV53+AY53+BB53+BE53+BH53+BK53+BN53+BQ53+BT53+BW53+BZ53+CC53+CF53+CI53+CL53+CO53+CR53+CU53 -> 2919321 | G53: =+E53+F53 -> 0 | H53: CARGA ARCHIVO EXTERNO | I53: 170096 | J53: 2 | K53: N/C NRO. 186 | L53: -357504 | M53: TODAS LAS TIENDAS | N53: FAC. NRO.20550 | O53: 198680 | P53: 100 | Q53: FAC. NRO.3631 | R53: 1881600 | S53: TODAS LAS TIENDAS | T53: PROVISION GASTOS ENERO EN | U53: 158794 | V53: 2 | W53: PROVISION VTEX CHILE SPA | X53: 1097655 | Y53: 100 | Z53: MULTIVENDE | AA53: -230000 | AB53: 100
A54: =EXACT(B54,C54) -> TRUE | B54: =+EERR!A52 -> 3.1.06.831 | C54: 3.1.06.831 | D54: MEMBRESÍAS Y ASOCIACIONES | E54: -268190 | F54: =+I54+L54+O54+R54+U54+X54+AA54+AD54+AG54+AJ54+AM54+AP54+AS54+AV54+AY54+BB54+BE54+BH54+BK54+BN54+BQ54+BT54+BW54+BZ54+CC54+CF54+CI54+CL54+CO54+CR54+CU54 -> 268190 | G54: =+E54+F54 -> 0 | H54: ASOCIACION GREMIAL DEL RETAIL COMERCIAL A.G. | I54: 268190 | J54: 2
A55: =EXACT(B55,C55) -> TRUE | B55: =+EERR!A53 -> 3.1.06.837 | C55: 3.1.06.837 | D55: MONITOREO COMERCIAL | E55: -588258 | F55: =+I55+L55+O55+R55+U55+X55+AA55+AD55+AG55+AJ55+AM55+AP55+AS55+AV55+AY55+BB55+BE55+BH55+BK55+BN55+BQ55+BT55+BW55+BZ55+CC55+CF55+CI55+CL55+CO55+CR55+CU55 -> 588258 | G55: =+E55+F55 -> 0 | H55: Jach Technology SpA | I55: 854564 | J55: 1 | K55: Jach Technology SpA | L55: -854564 | M55: 1 | N55: PROVISION JACH TECHNOLOGY | O55: 1240111 | P55: TODAS LAS TIENDAS | Q55: REVERSO JACH TECHNOLOGY | R55: -651853 | S55: TODAS LAS TIENDAS
A56: =EXACT(B56,C56) -> TRUE | B56: =+EERR!A54 -> 3.1.07.822 | C56: 3.1.07.822 | D56: GASTOS DE PUBLICIDAD Y MARKETING | E56: -2086868 | F56: =+I56+L56+O56+R56+U56+X56+AA56+AD56+AG56+AJ56+AM56+AP56+AS56+AV56+AY56+BB56+BE56+BH56+BK56+BN56+BQ56+BT56+BW56+BZ56+CC56+CF56+CI56+CL56+CO56+CR56+CU56 -> 2086868 | G56: =+E56+F56 -> 0 | H56: HELLO CONTENT SPA | I56: 245000 | J56: 3 | K56: SOFIA ALEJANDRA JORQUERA ESPIN | L56: 88496 | M56: 3 | N56: JANICE DESIREE CACERES BARRIA | O56: 40000 | P56: 3 | Q56: PAGO GETTY IMAGES PRO TDC | R56: -27489 | S56: 3 | T56: PROVISION GASTOS ENERO EN | U56: 1159217 | V56: 3 | W56: TDC ENERO | X56: 581644 | Y56: 3
A57: =EXACT(B57,C57) -> TRUE | B57: =+EERR!A55 -> 3.1.07.833 | C57: 3.1.07.833 | D57: SUMINISTROS VISUAL | E57: -1831072 | F57: =+I57+L57+O57+R57+U57+X57+AA57+AD57+AG57+AJ57+AM57+AP57+AS57+AV57+AY57+BB57+BE57+BH57+BK57+BN57+BQ57+BT57+BW57+BZ57+CC57+CF57+CI57+CL57+CO57+CR57+CU57 -> 1831072 | G57: =+E57+F57 -> 0 | H57: Getty Images Chile SPA | I57: 23100 | J57: DIVIDIR 10 | K57: LA VITRINERIA DISENO LIMITADA | L57: 1415500 | M57: DIVIDIR 10 | N57: ARTE IMPRESO LIMITADA | O57: 26000 | P57: DIVIDIR 10 | Q57: LA VITRINERIA DISENO LIMITADA | R57: 63900 | S57: DIVIDIR 10 | T57: LA VITRINERIA DISENO LIMITADA | U57: 63900 | V57: 1 | W57: LA VITRINERIA DISENO LIMITADA | X57: -63900 | Y57: 1 | Z57: FXR VISUAL (1)ENE26 | AA57: 199703 | AB57: 2 | AC57: FXR VISUAL ENE26 | AD57: 41000 | AE57: 2 | AF57: PROVISION GASTOS ENERO EN | AG57: 61869 | AH57: TODAS LAS TIENDAS
A58: =EXACT(B58,C58) -> TRUE | B58: =+EERR!A56 -> 3.1.08.701 | C58: 3.1.08.701 | D58: DEPRECIACION DEL EJERCICIO | E58: -8846337
A59: =EXACT(B59,C59) -> TRUE | B59: =+EERR!A57 -> 3.2.08.105 | C59: 3.2.08.105 | D59: INTERESES POR PRESTAMO | E59: -19305
A60: =EXACT(B60,C60) -> TRUE | B60: =+EERR!A58 -> 3.2.08.114 | C60: 3.2.08.114 | D60: INTERESES DEVENGADOS FONDOS MU | E60: 0
A61: =EXACT(B61,C61) -> TRUE | B61: =+EERR!A59 -> 3.2.08.116 | C61: 3.2.08.116 | D61: INTERES GANADO POR DEPOSITO A PLAZO PESOS | E61: 5791
A62: =EXACT(B62,C62) -> TRUE | B62: =+EERR!A60 -> 3.2.08.117 | C62: 3.2.08.117 | D62: INTERES GANADO FONDOS MUTUOS | E62: 0
A63: =EXACT(B63,C63) -> TRUE | B63: =+EERR!A61 -> 3.2.11.158 | C63: 3.2.11.158 | D63: DIFERENCIA DE CAMBIO | E63: 24026172
A64: =EXACT(B64,C64) -> TRUE | B64: =+EERR!A62 -> 3.2.13.101 | C64: 3.2.13.101 | D64: CORRECCION MONETARIA ACTIVOS | E64: -623797
A65: =EXACT(B65,C65) -> TRUE | B65: =+EERR!A63 -> 3.2.13.109 | C65: 3.2.13.109 | D65: AJUSTE REDONDEO AUTO | E65: -34

Sheet EERR
A1: Item | B1: Item | C1: Cuenta | D1: Descripción | E1: Totales
A2: 3.1.01.103 | B2: 4 | C2: 3.1.01.103 | D2: VENTAS CON BOLETA (RPA) | E2: 250365366 | G2: 3.1.01.103 | H2: VENTAS CON BOLETA (RPA) | I2: =C2=G2 -> TRUE
A3: 3.1.01.300 | G3: 3.1.01.300 | H3: OTROS INGRESOS | I3: =C9=G3 -> FALSE
A4: 3.1.02.101 | B4: 9 | C4: 3.1.02.101 | D4: COSTO DE VENTAS | E4: -134839072 | G4: 3.1.02.101 | H4: COSTO DE VENTAS | I4: =C4=G4 -> TRUE
A5: 3.1.02.102 | B5: 111 | C5: 3.1.02.102 | D5: COSTOS OPERATIVOS - FLETES INTERNOS | E5: -1205060 | G5: 3.1.02.102 | H5: COSTOS OPERATIVOS - FLETES INTERNOS | I5: =C5=G5 -> TRUE
A6: 3.1.02.104 | B6: 11 | C6: 3.1.02.104 | D6: COMISIÓN - CANAL DIGITAL | E6: -457950 | G6: 3.1.02.104 | H6: COMISIÓN - CANAL DIGITAL | I6: =C6=G6 -> TRUE
A7: 3.1.02.105 | B7: 112 | C7: 3.1.02.105 | D7: FLETES - CANAL DIGITAL | E7: -8071525 | G7: 3.1.02.105 | H7: FLETES - CANAL DIGITAL | I7: =C7=G7 -> TRUE
A8: 3.1.02.108 | B8: 12 | C8: 3.1.02.108 | D8: SERVICIOS - CANAL DIGITAL | E8: -1976022 | G8: 3.1.02.108 | H8: SERVICIOS - CANAL DIGITAL | I8: =C8=G8 -> TRUE
A9: 3.1.02.109 | B9: 6 | C9: 3.1.01.105 | D9: DESCUENTOS GIFTCARD | E9: -44990 | G9: 3.1.02.109 | H9: DESCUENTOS GIFTCARD | I9: =C9=G9 -> FALSE
A10: 3.1.02.110 | B10: 14 | C10: 3.1.02.110 | D10: DESCUENTOS CLUB FLEXI | E10: -46507 | G10: 3.1.02.110 | H10: DESCUENTOS CLUB FLEXI | I10: =C10=G10 -> TRUE
A11: 3.1.05.101 | B11: 17 | C11: 3.1.05.101 | D11: REMUNERACIONES | E11: -45117151 | G11: 3.1.05.101 | H11: REMUNERACIONES | I11: =C11=G11 -> TRUE
A12: 3.1.05.102 | B12: 18 | C12: 3.1.05.102 | D12: BONOS | E12: -3506290 | G12: 3.1.05.102 | H12: BONOS | I12: =C12=G12 -> TRUE
A13: 3.1.05.103 | B13: 19 | C13: 3.1.05.103 | D13: SEGURO DE CESANTIA | E13: -1655083 | G13: 3.1.05.103 | H13: SEGURO DE CESANTIA | I13: =C13=G13 -> TRUE
A14: 3.1.05.104 | B14: 20 | C14: 3.1.05.104 | D14: GRATIFICACION | E14: -10584152 | G14: 3.1.05.104 | H14: GRATIFICACION | I14: =C14=G14 -> TRUE
A15: 3.1.05.107 | G15: 3.1.05.107 | H15: FINIQUITOS | I15: =C15=G15 -> FALSE
A16: 3.1.05.110 | B16: 23 | C16: 3.1.05.110 | D16: MUTUAL DE SEGURIDAD | E16: -600154 | G16: 3.1.05.110 | H16: MUTUAL DE SEGURIDAD | I16: =C16=G16 -> TRUE
A17: 3.1.05.111 | B17: 24 | C17: 3.1.05.111 | D17: SEGURO INVALIDEZ (AFP) | E17: -1012481 | G17: 3.1.05.111 | H17: SEGURO INVALIDEZ (AFP) | I17: =C17=G17 -> TRUE
A18: 3.1.05.112 | B18: 25 | C18: 3.1.05.112 | D18: CAPITALIZACION INDIVIDUAL AFP | E18: -64495 | G18: 3.1.05.112 | H18: CAPITALIZACION INDIVIDUAL AFP | I18: =C18=G18 -> TRUE
A19: 3.1.05.113 | B19: 26 | C19: 3.1.05.113 | D19: EXPECTATIVA DE VIDA | E19: -591718 | G19: 3.1.05.113 | H19: EXPECTATIVA DE VIDA | I19: =C19=G19 -> TRUE
A20: 3.1.05.114 | G20: 3.1.05.114 | H20: HORAS EXTRAS | I20: =C20=G20 -> FALSE
A21: 3.1.05.117 | B21: 30 | C21: 3.1.05.117 | D21: DOMINGOS Y FESTIVOS | E21: -756324 | G21: 3.1.05.117 | H21: DOMINGOS Y FESTIVOS | I21: =C21=G21 -> TRUE
A22: 3.1.05.121 | B22: 32 | C22: 3.1.05.121 | D22: SEMANA CORRIDA | E22: -1447552 | G22: 3.1.05.121 | H22: SEMANA CORRIDA | I22: =C22=G22 -> TRUE
A23: 3.1.05.122 | B23: 33 | C23: 3.1.05.122 | D23: COMISION POR VENTA | E23: -6445321 | G23: 3.1.05.122 | H23: COMISION POR VENTA | I23: =C23=G23 -> TRUE
A24: 3.1.06.108 | B24: 49 | C24: 3.1.06.108 | D24: ASIGNACION COLACION | E24: -2326500 | G24: 3.1.06.108 | H24: ASIGNACION COLACION | I24: =C24=G24 -> TRUE
A25: 3.1.06.109 | B25: 50 | C25: 3.1.06.109 | D25: ASIGNACION MOVILIZACION | E25: -2326500 | G25: 3.1.06.109 | H25: ASIGNACION MOVILIZACION | I25: =C25=G25 -> TRUE
A26: 3.1.06.116 | B26: 52 | C26: 3.1.06.116 | D26: UNIFORMES | E26: -257471 | G26: 3.1.06.116 | H26: UNIFORMES | I26: =C26=G26 -> TRUE
A27: 3.1.06.201 | B27: 57 | C27: 3.1.06.201 | D27: HONORARIOS PROFESIONALES | E27: -505000 | G27: 3.1.06.201 | H27: HONORARIOS PROFESIONALES | I27: =C27=G27 -> TRUE
A28: 3.1.06.206 | B28: 59 | C28: 3.1.06.206 | D28: ASESORIA CONTABLE | E28: -3101478 | G28: 3.1.06.206 | H28: ASESORIA CONTABLE | I28: =C28=G28 -> TRUE
A29: 3.1.06.209 | B29: 60 | C29: 3.1.06.209 | D29: HONORARIOS POR ASESORIAS INFORMATICAS | E29: -179571 | G29: 3.1.06.209 | H29: HONORARIOS POR ASESORIAS INFORMATICAS | I29: =C29=G29 -> TRUE
A30: 3.1.06.301 | B30: 62 | C30: 3.1.06.301 | D30: ARRIENDOS | E30: -77626062 | G30: 3.1.06.301 | H30: ARRIENDOS | I30: =C30=G30 -> TRUE
A31: 3.1.06.302 | B31: 63 | C31: 3.1.06.302 | D31: ARRIENDO DE BODEGAS | E31: -3126087 | G31: 3.1.06.302 | H31: ARRIENDO DE BODEGAS | I31: =C31=G31 -> TRUE
A32: 3.1.06.305 | B32: 66 | C32: 3.1.06.305 | D32: GASTOS DIVERSOS | E32: -631049 | G32: 3.1.06.305 | H32: GASTOS DIVERSOS | I32: =C32=G32 -> TRUE
A33: 3.1.06.306 | G33: 3.1.06.306 | H33: SEGURIDAD INDUSTRIAL | I33: =C33=G33 -> FALSE
A34: 3.1.06.401 | B34: 68 | C34: 3.1.06.401 | D34: SERVICIOS DE TELECOMUNICACION | E34: -826138 | G34: 3.1.06.401 | H34: SERVICIOS DE TELECOMUNICACION | I34: =C34=G34 -> TRUE
A35: 3.1.06.406 | B35: 70 | C35: 3.1.06.406 | D35: GASTOS DE TELEFONIA MOVIL | E35: -131229 | G35: 3.1.06.406 | H35: GASTOS DE TELEFONIA MOVIL | I35: =C35=G35 -> TRUE
A36: 3.1.06.501 | B36: 71 | C36: 3.1.06.501 | D36: PATENTE COMERCIAL | E36: -839257 | G36: 3.1.06.501 | H36: PATENTE COMERCIAL | I36: =C36=G36 -> TRUE
A37: 3.1.06.504 | B37: 72 | C37: 3.1.06.504 | D37: IVA IRRECUPERABLE | E37: -1075489 | G37: 3.1.06.504 | H37: IVA IRRECUPERABLE | I37: =C37=G37 -> TRUE
A38: 3.1.06.505 | B38: 73 | C38: 3.1.06.505 | D38: MULTAS E INTERESES | E38: -420710 | G38: 3.1.06.505 | H38: MULTAS E INTERESES | I38: =C38=G38 -> TRUE
A39: 3.1.06.506 | B39: 74 | C39: 3.1.06.506 | D39: SEGUROS | E39: -663414 | G39: 3.1.06.506 | H39: SEGUROS | I39: =C39=G39 -> TRUE
A40: 3.1.06.507 | B40: 75 | C40: 3.1.06.507 | D40: SERVICIO DE VIGILANCIA | E40: -61186 | G40: 3.1.06.507 | H40: SERVICIO DE VIGILANCIA | I40: =C40=G40 -> TRUE
A41: 3.1.06.601 | B41: 76 | C41: 3.1.06.601 | D41: GASTO MANTENCION SUCURSALES | E41: -7893808 | G41: 3.1.06.601 | H41: GASTO MANTENCION SUCURSALES | I41: =C41=G41 -> TRUE
A42: 3.1.06.602 | B42: 77 | C42: 3.1.06.602 | D42: BOLSA IMPRESA | E42: -642168 | G42: 3.1.06.602 | H42: BOLSA IMPRESA | I42: =C42=G42 -> TRUE
A43: 3.1.06.603 | G43: 3.1.06.603 | H43: GASTOS DE ALMACENAJE | I43: =C43=G43 -> FALSE
A44: 3.1.06.802 | G44: 3.1.06.802 | H44: SUMINISTROS COMPUTACIONALES | I44: =C44=G44 -> FALSE
A45: 3.1.06.803 | B45: 81 | C45: 3.1.06.803 | D45: UTILES DE OFICINA Y PAPELERIA | E45: -371590 | G45: 3.1.06.803 | H45: UTILES DE OFICINA Y PAPELERIA | I45: =C45=G45 -> TRUE
A46: 3.1.06.805 | G46: 3.1.06.805 | H46: GASTOS LEGALES Y NOTARIALES DIRECTOS | I46: =C46=G46 -> FALSE
A47: 3.1.06.806 | B47: 83 | C47: 3.1.06.806 | D47: COMISIONES Y GASTOS BANCARIOS | E47: -502259 | G47: 3.1.06.806 | H47: COMISIONES Y GASTOS BANCARIOS | I47: =C47=G47 -> TRUE
A48: 3.1.06.812 | B48: 86 | C48: 3.1.06.812 | D48: COMISIONES TRANSBANK | E48: -2853756 | G48: 3.1.06.812 | H48: COMISIONES TRANSBANK | I48: =C48=G48 -> TRUE
A49: 3.1.06.813 | B49: 87 | C49: 3.1.06.813 | D49: COMISIONES GETNET | E49: -597458 | G49: 3.1.06.813 | H49: COMISIONES GETNET | I49: =C49=G49 -> TRUE
A50: 3.1.06.817 | B50: 90 | C50: 3.1.06.817 | D50: GASTOS DE REPRESENTACION | E50: -868786 | G50: 3.1.06.817 | H50: GASTOS DE REPRESENTACION | I50: =C50=G50 -> TRUE
A51: 3.1.06.818 | B51: 91 | C51: 3.1.06.818 | D51: LICENCIAS SOTWARE RENTAS | E51: -3149321 | G51: 3.1.06.818 | H51: LICENCIAS SOTWARE RENTAS | I51: =C51=G51 -> TRUE
A52: 3.1.06.831 | B52: 95 | C52: 3.1.06.831 | D52: MEMBRESÍAS Y ASOCIACIONES | E52: -268190 | G52: 3.1.06.831 | H52: MEMBRESÍAS Y ASOCIACIONES | I52: =C52=G52 -> TRUE
A53: 3.1.06.837 | B53: 99 | C53: 3.1.06.837 | D53: MONITOREO COMERCIAL | E53: -588258 | G53: 3.1.06.837 | H53: MONITOREO COMERCIAL | I53: =C53=G53 -> TRUE
A54: 3.1.07.822 | B54: 117 | C54: 3.1.07.822 | D54: GASTOS DE PUBLICIDAD Y MARKETING | E54: -2086868 | G54: 3.1.07.822 | H54: GASTOS DE PUBLICIDAD Y MARKETING | I54: =C54=G54 -> TRUE
A55: 3.1.07.833 | B55: 118 | C55: 3.1.07.833 | D55: SUMINISTROS VISUAL | E55: -1831072 | G55: 3.1.07.833 | H55: SUMINISTROS VISUAL | I55: =C55=G55 -> TRUE
A56: 3.1.08.701 | B56: 114 | C56: 3.1.08.701 | D56: DEPRECIACION DEL EJERCICIO | E56: -8846337 | G56: 3.1.08.701 | H56: DEPRECIACION DEL EJERCICIO | I56: =C56=G56 -> TRUE
A57: 3.2.08.105 | B57: 101 | C57: 3.2.08.105 | D57: INTERESES POR PRESTAMO | E57: -19305 | G57: 3.2.08.105 | H57: INTERESES POR PRESTAMO | I57: =C57=G57 -> TRUE
A58: 3.2.08.114 | G58: 3.2.08.114 | H58: INTERESES DEVENGADOS FONDOS MU | I58: =C58=G58 -> FALSE
A59: 3.2.08.116 | B59: 103 | C59: 3.2.08.116 | D59: INTERES GANADO POR DEPOSITO A PLAZO PESOS | E59: 5791 | G59: 3.2.08.116 | H59: INTERES GANADO POR DEPOSITO A PLAZO PESOS | I59: =C59=G59 -> TRUE
A60: 3.2.08.117 | G60: 3.2.08.117 | H60: INTERES GANADO FONDOS MUTUOS | I60: =C60=G60 -> FALSE
A61: 3.2.11.158 | B61: 109 | C61: 3.2.11.158 | D61: DIFERENCIA DE CAMBIO | E61: 47424578 | G61: 3.2.11.158 | H61: DIFERENCIA DE CAMBIO | I61: =C61=G61 -> TRUE
A62: 3.2.13.101 | B62: 121 | C62: 3.2.13.101 | D62: CORRECCION MONETARIA ACTIVOS | E62: -623797 | G62: 3.2.13.101 | H62: CORRECCION MONETARIA ACTIVOS | I62: =C62=G62 -> TRUE
A63: 3.2.13.109 | B63: 115 | C63: 3.2.13.109 | D63: AJUSTE REDONDEO AUTO | E63: -1 | G63: 3.2.13.109 | H63: AJUSTE REDONDEO AUTO | I63: =C63=G63 -> TRUE
A29836: #N/A
B29849: #N/A | C29849: #N/A | D29849: #N/A | E29849: #N/A
A30002: #N/A
B30015: #N/A | C30015: #N/A | D30015: #N/A | E30015: #N/A
