Workbook

Sheet Hoja1
C1: CUENTA | D1: DESCRIPCION | E1: CEDIS CHILE | F1: FLEXI PLAZA EGAÑA | G1: FLEXI PLAZA VESPUCIO | H1: FLEXI EL TREBOL | I1: ON LINE | J1: ADMINISTRACION | K1: FLEXI COSTANERA CENTER | L1: FLEXI FLORIDA CENTER | M1: FLEXI BARROS ARANA | N1: DEPARTAMENTAL | O1: FLEXI ESTADO | P1: FLEXI TALCA | Q1: FLEXI PLAZA NORTE | R1: PLAZA OESTE | S1: TRANSITO | T1: MARKETING | U1: FLEXI ECOMMERCE | V1: MARKETPLACE | W1: RIPLEY MARKETPLACE | X1: DAFITI | Y1: MERCADO LIBRE | Z1: CENCOSUD | AA1: FALABELLA | AB1: MULTICENTRO | AC1: RIPLEY | AD1: Totales
C2: 3.1.01.103 | D2: VENTAS CON BOLETA (RPA) | E2: -8184789 | F2: 32964864 | G2: 0 | H2: 23111537 | I2: =+T2+U2+V2+W2 -> 35498033 | J2: 0 | K2: 47457079 | L2: 21001665 | M2: 0 | N2: =+X2+Y2+Z2+AB2+AC2 -> 176430 | O2: 35890391 | P2: 16930023 | Q2: 16796815 | R2: 24972244 | S2: =SUM(E2:R2) -> 246614292 | T2: 0 | U2: 35498033 | V2: 0 | W2: 0 | X2: 0 | Y2: 176430 | Z2: 0 | AA2: 0 | AB2: 0 | AC2: 0 | AD2: 246614292 | AE2: =S2-AD2 -> 0
C3: 3.1.02.101 | D3: COSTO DE VENTAS | E3: 5408771 | F3: -17793331 | G3: 0 | H3: -11944357 | I3: =+T3+U3+V3+W3 -> -22854624 | J3: 0 | K3: -25211214 | L3: -11190542 | M3: 0 | N3: =+X3+Y3+Z3+AB3+AC3 -> 0 | O3: -19343670 | P3: -9135162 | Q3: -9119820 | R3: -13655123 | S3: =SUM(E3:R3) -> -134839072 | T3: 0 | U3: -22854624 | V3: 0 | W3: 0 | X3: 0 | Y3: 0 | Z3: 0 | AA3: 0 | AB3: 0 | AC3: 0 | AD3: -134839072 | AE3: =S3-AD3 -> 0
A4: =EXACT(C4,B4) -> TRUE | B4: =+Hoja2!A1 -> 3.1.01.300 | C4: 3.1.01.300 | D4: OTROS INGRESOS | E4: 0 | F4: 0 | G4: 0 | H4: 0 | I4: =+T4+U4+V4+W4 -> 3751074 | J4: 0 | K4: 0 | L4: 0 | M4: 0 | N4: =+X4+Y4+Z4+AB4+AC4 -> 0 | O4: 0 | P4: 0 | Q4: 0 | R4: 0 | S4: =SUM(E4:R4) -> 3751074 | T4: 3751074 | U4: 0 | V4: 0 | W4: 0 | X4: 0 | Y4: 0 | Z4: 0 | AA4: 0 | AB4: 0 | AC4: 0 | AD4: 3751074 | AE4: =S4-AD4 -> 0
A5: =EXACT(C5,B5) -> TRUE | B5: =+Hoja2!A2 -> 3.1.02.102 | C5: 3.1.02.102 | D5: COSTOS OPERATIVOS - FLETES INTERNOS | E5: -2164695 | F5: 21780 | G5: 0 | H5: 21780 | I5: =+T5+U5+V5+W5 -> 150000 | J5: 0 | K5: 21780 | L5: 21780 | M5: 0 | N5: =+X5+Y5+Z5+AB5+AC5 -> 0 | O5: 21780 | P5: 21780 | Q5: 21780 | R5: 21780 | S5: =SUM(E5:R5) -> -1840455 | T5: 0 | U5: 150000 | V5: 0 | W5: 0 | X5: 0 | Y5: 0 | Z5: 0 | AA5: 0 | AB5: 0 | AC5: 0 | AD5: -1840455 | AE5: =S5-AD5 -> 0
A6: =EXACT(C6,B6) -> TRUE | B6: =+Hoja2!A3 -> 3.1.02.104 | C6: 3.1.02.104 | D6: COMISIÓN - CANAL DIGITAL | E6: 0 | F6: 0 | G6: 0 | H6: 0 | I6: =+T6+U6+V6+W6 -> -3004368 | J6: 0 | K6: 0 | L6: 0 | M6: 0 | N6: =+X6+Y6+Z6+AB6+AC6 -> 304544 | O6: 0 | P6: 0 | Q6: 0 | R6: 0 | S6: =SUM(E6:R6) -> -2699824 | T6: 0 | U6: -2241874 | V6: -539421 | W6: -223073 | X6: 0 | Y6: 304544 | Z6: 0 | AA6: 0 | AB6: 0 | AC6: 0 | AD6: -2699824 | AE6: =S6-AD6 -> 0
A7: =EXACT(C7,B7) -> TRUE | B7: =+Hoja2!A4 -> 3.1.02.105 | C7: 3.1.02.105 | D7: FLETES - CANAL DIGITAL | E7: 0 | F7: 0 | G7: 0 | H7: 0 | I7: =+T7+U7+V7+W7 -> 2066127 | J7: 0 | K7: 0 | L7: 0 | M7: 0 | N7: =+X7+Y7+Z7+AB7+AC7+AA7 -> -2866174 | O7: 0 | P7: 0 | Q7: 0 | R7: 0 | S7: =SUM(E7:R7) -> -800047 | T7: 0 | U7: 2241874 | V7: 0 | W7: -175747 | X7: 0 | Y7: 0 | Z7: 0 | AA7: -2866174 | AB7: 0 | AC7: 0 | AD7: -800047 | AE7: =S7-AD7 -> 0
A8: =EXACT(C8,B8) -> TRUE | B8: =+Hoja2!A5 -> 3.1.02.108 | C8: 3.1.02.108 | D8: SERVICIOS - CANAL DIGITAL | E8: 0 | F8: 0 | G8: 0 | H8: 0 | I8: =+T8+U8+V8+W8 -> -129245 | J8: 0 | K8: 0 | L8: 0 | M8: 0 | N8: =+X8+Y8+Z8+AB8+AC8 -> -1846777 | O8: 0 | P8: 0 | Q8: 0 | R8: 0 | S8: =SUM(E8:R8) -> -1976022 | T8: 0 | U8: 0 | V8: -15497 | W8: -113748 | X8: 0 | Y8: -1846777 | Z8: 0 | AA8: 0 | AB8: 0 | AC8: 0 | AD8: -1976022 | AE8: =S8-AD8 -> 0
A9: =EXACT(C9,B9) -> TRUE | B9: =+Hoja2!A6 -> 3.1.02.109 | C9: 3.1.02.109 | D9: DESCUENTOS GIFTCARD | E9: 0 | F9: 0 | G9: 0 | H9: 0 | I9: =+T9+U9+V9+W9 -> 0 | J9: 0 | K9: 0 | L9: 0 | M9: 0 | N9: =+X9+Y9+Z9+AB9+AC9 -> 0 | O9: -44990 | P9: 0 | Q9: 0 | R9: 0 | S9: =SUM(E9:R9) -> -44990 | T9: 0 | U9: 0 | V9: 0 | W9: 0 | X9: 0 | Y9: 0 | Z9: 0 | AA9: 0 | AB9: 0 | AC9: 0 | AD9: -44990 | AE9: =S9-AD9 -> 0
A10: =EXACT(C10,B10) -> TRUE | B10: =+Hoja2!A7 -> 3.1.02.110 | C10: 3.1.02.110 | D10: DESCUENTOS CLUB FLEXI | E10: 0 | F10: 0 | G10: 0 | H10: 0 | I10: =+T10+U10+V10+W10 -> 0 | J10: 0 | K10: -14372 | L10: -27334 | M10: 0 | N10: =+X10+Y10+Z10+AB10+AC10 -> 0 | O10: -4801 | P10: 0 | Q10: 0 | R10: 0 | S10: =SUM(E10:R10) -> -46507 | T10: 0 | U10: 0 | V10: 0 | W10: 0 | X10: 0 | Y10: 0 | Z10: 0 | AA10: 0 | AB10: 0 | AC10: 0 | AD10: -46507 | AE10: =S10-AD10 -> 0
A11: =EXACT(C11,B11) -> TRUE | B11: =+Hoja2!A8 -> 3.1.05.101 | C11: 3.1.05.101 | D11: REMUNERACIONES | E11: 0 | F11: -5471370 | G11: 47363 | H11: -5105142 | I11: =+T11+U11+V11+W11 -> -3360231 | J11: 0 | K11: -6163578 | L11: -4432782 | M11: -637144 | N11: =+X11+Y11+Z11+AB11+AC11 -> -1429576 | O11: -5819291 | P11: -3991543 | Q11: -4129167 | R11: -4624690 | S11: =SUM(E11:R11) -> -45117151 | T11: 0 | U11: -3360231 | V11: 0 | W11: 0 | X11: 0 | Y11: 0 | Z11: 0 | AA11: 0 | AB11: -1429576 | AC11: 0 | AD11: -45117151 | AE11: =S11-AD11 -> 0
A12: =EXACT(C12,B12) -> TRUE | B12: =+Hoja2!A9 -> 3.1.05.102 | C12: 3.1.05.102 | D12: BONOS | E12: 0 | F12: -273846 | G12: 0 | H12: -183785 | I12: =+T12+U12+V12+W12 -> -127312 | J12: 0 | K12: -295071 | L12: -167527 | M12: 0 | N12: =+X12+Y12+Z12+AB12+AC12 -> 0 | O12: -668574 | P12: -17293 | Q12: 805918 | R12: -803000 | S12: =SUM(E12:R12) -> -1730490 | T12: 0 | U12: -127312 | V12: 0 | W12: 0 | X12: 0 | Y12: 0 | Z12: 0 | AA12: 0 | AB12: 0 | AC12: 0 | AD12: -1730490 | AE12: =S12-AD12 -> 0
A13: =EXACT(C13,B13) -> TRUE | B13: =+Hoja2!A10 -> 3.1.05.103 | C13: 3.1.05.103 | D13: SEGURO DE CESANTIA | E13: 0 | F13: -190943 | G13: -17338 | H13: -203449 | I13: =+T13+U13+V13+W13 -> -92175 | J13: 0 | K13: -226386 | L13: -163670 | M13: -26805 | N13: =+X13+Y13+Z13+AB13+AC13 -> -34952 | O13: -219642 | P13: -149355 | Q13: -149071 | R13: -181297 | S13: =SUM(E13:R13) -> -1655083 | T13: 0 | U13: -92175 | V13: 0 | W13: 0 | X13: 0 | Y13: 0 | Z13: 0 | AA13: 0 | AB13: -34952 | AC13: 0 | AD13: -1655083 | AE13: =S13-AD13 -> 0
A14: =EXACT(C14,B14) -> TRUE | B14: =+Hoja2!A11 -> 3.1.05.104 | C14: 3.1.05.104 | D14: GRATIFICACION | E14: 0 | F14: -1260847 | G14: -11561 | H14: -1345486 | I14: =+T14+U14+V14+W14 -> -460102 | J14: 0 | K14: -1419780 | L14: -1136975 | M14: -203747 | N14: =+X14+Y14+Z14+AB14+AC14 -> -147415 | O14: -1338001 | P14: -1000642 | Q14: -1039174 | R14: -1220422 | S14: =SUM(E14:R14) -> -10584152 | T14: 0 | U14: -460102 | V14: 0 | W14: 0 | X14: 0 | Y14: 0 | Z14: 0 | AA14: 0 | AB14: -147415 | AC14: 0 | AD14: -10584152 | AE14: =S14-AD14 -> 0
A15: =EXACT(C15,B15) -> TRUE | B15: =+Hoja2!A12 -> 3.1.05.107 | C15: 3.1.05.107 | D15: FINIQUITOS | E15: 0 | F15: 0 | G15: 0 | H15: 0 | I15: =+T15+U15+V15+W15 -> 0 | J15: -4000 | K15: 0 | L15: 0 | M15: 0 | N15: =+X15+Y15+Z15+AB15+AC15 -> 0 | O15: 0 | P15: 0 | Q15: 0 | R15: 0 | S15: =SUM(E15:R15) -> -4000 | T15: 0 | U15: 0 | V15: 0 | W15: 0 | X15: 0 | Y15: 0 | Z15: 0 | AA15: 0 | AB15: 0 | AC15: 0 | AD15: -4000 | AE15: =S15-AD15 -> 0
A16: =EXACT(C16,B16) -> TRUE | B16: =+Hoja2!A13 -> 3.1.05.110 | C16: 3.1.05.110 | D16: MUTUAL DE SEGURIDAD | E16: 0 | F16: -71936 | G16: -737 | H16: -73997 | I16: =+T16+U16+V16+W16 -> -34371 | J16: 0 | K16: -84795 | L16: -58447 | M16: -10387 | N16: =+X16+Y16+Z16+AB16+AC16 -> -12025 | O16: -82866 | P16: -51899 | Q16: -52421 | R16: -66273 | S16: =SUM(E16:R16) -> -600154 | T16: 0 | U16: -34371 | V16: 0 | W16: 0 | X16: 0 | Y16: 0 | Z16: 0 | AA16: 0 | AB16: -12025 | AC16: 0 | AD16: -600154 | AE16: =S16-AD16 -> 0
A17: =EXACT(C17,B17) -> TRUE | B17: =+Hoja2!A14 -> 3.1.05.111 | C17: 3.1.05.111 | D17: SEGURO INVALIDEZ (AFP) | E17: 0 | F17: -119119 | G17: -11125 | H17: -124090 | I17: =+T17+U17+V17+W17 -> -56916 | J17: 0 | K17: -140414 | L17: -100092 | M17: -17200 | N17: =+X17+Y17+Z17+AB17+AC17 -> -19912 | O17: -137221 | P17: -89846 | Q17: -86806 | R17: -109740 | S17: =SUM(E17:R17) -> -1012481 | T17: 0 | U17: -56916 | V17: 0 | W17: 0 | X17: 0 | Y17: 0 | Z17: 0 | AA17: 0 | AB17: -19912 | AC17: 0 | AD17: -1012481 | AE17: =S17-AD17 -> 0
A18: =EXACT(C18,B18) -> TRUE | B18: =+Hoja2!A15 -> 3.1.05.112 | C18: 3.1.05.112 | D18: CAPITALIZACION INDIVIDUAL AFP | E18: 0 | F18: -7736 | G18: -58 | H18: -7952 | I18: =+T18+U18+V18+W18 -> -3696 | J18: 0 | K18: -9119 | L18: -6279 | M18: -1117 | N18: =+X18+Y18+Z18+AB18+AC18 -> -1293 | O18: -8910 | P18: -5572 | Q18: -5637 | R18: -7126 | S18: =SUM(E18:R18) -> -64495 | T18: 0 | U18: -3696 | V18: 0 | W18: 0 | X18: 0 | Y18: 0 | Z18: 0 | AA18: 0 | AB18: -1293 | AC18: 0 | AD18: -64495 | AE18: =S18-AD18 -> 0
A19: =EXACT(C19,B19) -> TRUE | B19: =+Hoja2!A16 -> 3.1.05.113 | C19: 3.1.05.113 | D19: EXPECTATIVA DE VIDA | E19: 0 | F19: -69616 | G19: -6502 | H19: -72523 | I19: =+T19+U19+V19+W19 -> -33262 | J19: 0 | K19: -82059 | L19: -58497 | M19: -10052 | N19: =+X19+Y19+Z19+AB19+AC19 -> -11637 | O19: -80194 | P19: -52509 | Q19: -50733 | R19: -64134 | S19: =SUM(E19:R19) -> -591718 | T19: 0 | U19: -33262 | V19: 0 | W19: 0 | X19: 0 | Y19: 0 | Z19: 0 | AA19: 0 | AB19: -11637 | AC19: 0 | AD19: -591718 | AE19: =S19-AD19 -> 0
... A57: =EXACT(C57,B57) -> TRUE | B57: =+Hoja2!A54 -> 3.2.08.105 | C57: 3.2.08.105 | D57: INTERESES POR PRESTAMO | E57: 0 | F57: 0 | G57: 0 | H57: 0 | I57: =+T57+U57+V57+W57 -> 0 | J57: 0 | K57: -8446 | L57: 0 | M57: 0 | N57: =+X57+Y57+Z57+AB57+AC57 -> 0 | O57: 0 | P57: 0 | Q57: -4101 | R57: -6758 | S57: =SUM(E57:R57) -> -19305 | T57: 0 | U57: 0 | V57: 0 | W57: 0 | X57: 0 | Y57: 0 | Z57: 0 | AA57: 0 | AB57: 0 | AC57: 0 | AD57: -19305 | AE57: =S57-AD57 -> 0
A58: =EXACT(C58,B58) -> TRUE | B58: =+Hoja2!A55 -> 3.2.08.114 | C58: 3.2.08.114 | D58: INTERESES DEVENGADOS FONDOS MU | E58: 0 | F58: 0 | G58: 0 | H58: 0 | I58: =+T58+U58+V58+W58 -> 0 | J58: 0 | K58: 0 | L58: 0 | M58: 0 | N58: =+X58+Y58+Z58+AB58+AC58 -> 0 | O58: 0 | P58: 0 | S58: =SUM(E58:R58) -> 0 | T58: 0 | U58: 0 | V58: 0 | W58: 0 | X58: 0 | Y58: 0 | Z58: 0 | AA58: 0 | AB58: 0 | AC58: 0 | AD58: 0 | AE58: =S58-AD58 -> 0
A59: =EXACT(C59,B59) -> TRUE | B59: =+Hoja2!A56 -> 3.2.08.116 | C59: 3.2.08.116 | D59: INTERES GANADO POR DEPOSITO A PLAZO PESOS | E59: 0 | F59: 0 | G59: 0 | H59: 0 | I59: =+T59+U59+V59+W59 -> 0 | J59: 5791 | K59: 0 | L59: 0 | M59: 0 | N59: =+X59+Y59+Z59+AB59+AC59 -> 0 | O59: 0 | P59: 0 | Q59: 0 | R59: 0 | S59: =SUM(E59:R59) -> 5791 | T59: 0 | U59: 0 | V59: 0 | W59: 0 | X59: 0 | Y59: 0 | Z59: 0 | AA59: 0 | AB59: 0 | AC59: 0 | AD59: 5791 | AE59: =S59-AD59 -> 0
A60: =EXACT(C60,B60) -> TRUE | B60: =+Hoja2!A57 -> 3.2.08.117 | C60: 3.2.08.117 | D60: INTERES GANADO FONDOS MUTUOS | E60: 0 | F60: 0 | G60: 0 | H60: 0 | I60: =+T60+U60+V60+W60 -> 0 | J60: 0 | K60: 0 | L60: 0 | M60: 0 | N60: =+X60+Y60+Z60+AB60+AC60 -> 0 | O60: 0 | P60: 0 | S60: =SUM(E60:R60) -> 0 | T60: 0 | U60: 0 | V60: 0 | W60: 0 | X60: 0 | Y60: 0 | Z60: 0 | AA60: 0 | AB60: 0 | AC60: 0 | AD60: 0 | AE60: =S60-AD60 -> 0
A61: =EXACT(C61,B61) -> TRUE | B61: =+Hoja2!A58 -> 3.2.11.158 | C61: 3.2.11.158 | D61: DIFERENCIA DE CAMBIO | I61: =+T61+U61+V61+W61 -> 0 | J61: 24026172 | N61: =+X61+Y61+Z61+AB61+AC61 -> 0 | S61: =SUM(E61:R61) -> 24026172 | AD61: 24026172 | AE61: =S61-AD61 -> 0
A62: =EXACT(C62,B62) -> TRUE | B62: =+Hoja2!A59 -> 3.2.13.101 | C62: 3.2.13.101 | D62: CORRECCION MONETARIA ACTIVOS | E62: 0 | F62: 0 | G62: 0 | H62: 0 | I62: =+T62+U62+V62+W62 -> 0 | J62: -623797 | K62: 0 | L62: 0 | M62: 0 | N62: =+X62+Y62+Z62+AB62+AC62 -> 0 | O62: 0 | P62: 0 | Q62: 0 | R62: 0 | S62: =SUM(E62:R62) -> -623797 | T62: 0 | U62: 0 | V62: 0 | W62: 0 | X62: 0 | Y62: 0 | Z62: 0 | AA62: 0 | AB62: 0 | AC62: 0 | AD62: -623797 | AE62: =S62-AD62 -> 0
A63: =EXACT(C63,B63) -> TRUE | B63: =+Hoja2!A60 -> 3.2.13.109 | C63: 3.2.13.109 | D63: AJUSTE REDONDEO AUTO | E63: 0 | F63: 0 | G63: 0 | H63: 0 | I63: =+T63+U63+V63+W63 -> 0 | J63: -34 | K63: 0 | L63: 0 | M63: 0 | N63: =+X63+Y63+Z63+AB63+AC63 -> 0 | O63: 0 | P63: 0 | Q63: 0 | R63: 0 | S63: =SUM(E63:R63) -> -34 | T63: 0 | U63: 0 | V63: 0 | W63: 0 | X63: 0 | Y63: 0 | Z63: 0 | AA63: 0 | AB63: 0 | AC63: 0 | AD63: -34 | AE63: =S63-AD63 -> 0
D64: Total Ing. de Explotación | E64: -8184789 | F64: 32964864 | G64: 0 | H64: 23111537 | J64: 0 | K64: 47457079 | L64: 21001665 | M64: 0 | N64: =+X64+Y64+Z64+AB64+AC64 -> 176430 | O64: 35890391 | P64: 16930023 | Q64: 16796815 | R64: 24972244 | S64: 0 | T64: 3751074 | U64: 35498033 | V64: 0 | W64: 0 | X64: 0 | Y64: 176430 | Z64: 0 | AA64: 0 | AB64: 0 | AC64: 0 | AD64: 250365366
D67: Total Costo de Explotación | E67: 5408771 | F67: -17793331 | G67: 0 | H67: -11944357 | J67: 0 | K67: -25225586 | L67: -11217876 | M67: 0 | O67: -19393461 | P67: -9135162 | Q67: -9119820 | R67: -13655123 | S67: 0 | T67: 0 | U67: -25096498 | V67: -554918 | W67: -336821 | X67: 0 | Y67: -1542233 | Z67: 0 | AA67: 0 | AB67: 0 | AC67: 0 | AD67: -139606415
D69: PORCENTAJE MARGEN/VENTA | E69: 0.3392 | F69: 0.4602 | G69: 0 | H69: 0.4832 | J69: 0 | K69: 0.4685 | L69: 0.4659 | M69: 0 | O69: 0.4596 | P69: 0.4604 | Q69: 0.4571 | R69: 0.4532 | S69: 0 | T69: 1 | U69: 0.293 | V69: 0 | W69: 0 | X69: 0 | Y69: 7.7413 | Z69: 0 | AA69: 0 | AB69: 0 | AC69: 0 | AD69: 0.4424
D70: MARGEN DE EXPLOTACION | E70: -2776018 | F70: 15171533 | G70: 0 | H70: 11167180 | J70: 0 | K70: 22231493 | L70: 9783789 | M70: 0 | O70: 16496930 | P70: 7794861 | Q70: 7676995 | R70: 11317121 | S70: 0 | T70: 3751074 | U70: 10401535 | V70: -554918 | W70: -336821 | X70: 0 | Y70: -1365803 | Z70: 0 | AA70: 0 | AB70: 0 | AC70: 0 | AD70: 110758951
D72: Total Gasto Administ. y Venta | E72: -4132600 | F72: -18373033 | G72: -100547 | H72: -17773928 | J72: -6199626 | K72: -30652774 | L72: -18891635 | M72: -1437340 | O72: -19723514 | P72: -11155318 | Q72: -13492838 | R72: -17366628 | S72: 0 | T72: 0 | U72: -6116097 | V72: 0 | W72: 0 | X72: 0 | Y72: 0 | Z72: 0 | AA72: 0 | AB72: -1984002 | AC72: 0 | AD72: -167399880
D74: RESULTADO OPERACIONAL | E74: -6908618 | F74: -3201500 | G74: -100547 | H74: -6606748 | J74: -6199626 | K74: -8421281 | L74: -9107846 | M74: -1437340 | O74: -3226584 | P74: -3360457 | Q74: -5815843 | R74: -6049507 | S74: 0 | T74: 3751074 | U74: 4285438 | V74: -554918 | W74: -336821 | X74: 0 | Y74: -1365803 | Z74: 0 | AA74: 0 | AB74: -1984002 | AC74: 0 | AD74: -56640929
D76: Total Ing. no Operacionales | E76: 0 | F76: 0 | G76: 0 | H76: 0 | J76: 24031963 | K76: -8446 | L76: 0 | M76: 0 | O76: 0 | P76: 0 | Q76: -4101 | R76: -6758 | S76: 0 | T76: 0 | U76: 0 | V76: 0 | W76: 0 | X76: 0 | Y76: 0 | Z76: 0 | AA76: 0 | AB76: 0 | AC76: 0 | AD76: 24012658
D79: Total Egr. de Explotación | E79: -4701534 | F79: 14025 | G79: 0 | H79: 276 | J79: -487575 | K79: -1232496 | L79: -338414 | M79: 0 | O79: -1218719 | P79: -1128058 | Q79: -1003907 | R79: -740424 | S79: 0 | T79: 0 | U79: 2391874 | V79: 0 | W79: -175747 | X79: 0 | Y79: 0 | Z79: 0 | AA79: -2866174 | AB79: 0 | AC79: 0 | AD79: -11486873
D81: RESULTADO NO OPERACIONAL | E81: -4701534 | F81: 14025 | G81: 0 | H81: 276 | J81: 23544388 | K81: -1240942 | L81: -338414 | M81: 0 | O81: -1218719 | P81: -1128058 | Q81: -1008008 | R81: -747182 | S81: 0 | T81: 0 | U81: 2391874 | V81: 0 | W81: -175747 | X81: 0 | Y81: 0 | Z81: 0 | AA81: -2866174 | AB81: 0 | AC81: 0 | AD81: 12525785
D83: Total Otros Gastos Fuera de Explot. | E83: 0 | F83: -198798 | G83: 0 | H83: -198798 | J83: -240703 | K83: -198798 | L83: -198798 | M83: 0 | O83: -198795 | P83: -198794 | Q83: -198794 | R83: -198794 | S83: 0 | T83: -2086868 | U83: 0 | V83: 0 | W83: 0 | X83: 0 | Y83: 0 | Z83: 0 | AA83: 0 | AB83: 0 | AC83: 0 | AD83: -3917940
D85: RESULTADO ANTES DEL IMPUESTO A LA RENTA | E85: -11610152 | F85: -3386273 | G85: -100547 | H85: -6805270 | J85: 17104059 | K85: -9861021 | L85: -9645058 | M85: -1437340 | O85: -4644098 | P85: -4687309 | Q85: -7022645 | R85: -6995483 | S85: 0 | T85: 1664206 | U85: 6677312 | V85: -554918 | W85: -512568 | X85: 0 | Y85: -1365803 | Z85: 0 | AA85: -2866174 | AB85: -1984002 | AC85: 0 | AD85: -48033084
E87: 0 | F87: 0 | G87: 0 | H87: 0 | J87: -623797 | K87: 0 | L87: 0 | M87: 0 | O87: 0 | P87: 0 | Q87: 0 | R87: 0 | S87: 0 | T87: 0 | U87: 0 | V87: 0 | W87: 0 | X87: 0 | Y87: 0 | Z87: 0 | AA87: 0 | AB87: 0 | AC87: 0 | AD87: -623797
D90: UTILIDAD O PERDIDA DEL EJERCICIO | E90: -11610152 | F90: -3386273 | G90: -100547 | H90: -6805270 | J90: 16480262 | K90: -9861021 | L90: -9645058 | M90: -1437340 | O90: -4644098 | P90: -4687309 | Q90: -7022645 | R90: -6995483 | S90: 0 | T90: 1664206 | U90: 6677312 | V90: -554918 | W90: -512568 | X90: 0 | Y90: -1365803 | Z90: 0 | AA90: -2866174 | AB90: -1984002 | AC90: 0 | AD90: -48656881

Sheet Hoja2
A1: 3.1.01.300
A2: 3.1.02.102
A3: 3.1.02.104
A4: 3.1.02.105
A5: 3.1.02.108
A6: 3.1.02.109
A7: 3.1.02.110
A8: 3.1.05.101
A9: 3.1.05.102
A10: 3.1.05.103
A11: 3.1.05.104
A12: 3.1.05.107
... A60: 3.2.13.109

Sheet Hoja3
